{"name":"Good Request","status":"passed","statusDetails":{"known":false,"muted":false,"flaky":false},"stage":"finished","description":"Good Request","steps":[{"name":"Verify API Good Request for Google_TestAPI2","status":"passed","stage":"finished","steps":[{"name":"Response Status is HTTP/1.1 200 OK\n Response Body {\"id\":4,\"token\":\"QpwL5tke4Pnpja7X4\"}","status":"passed","stage":"finished","steps":[],"attachments":[],"parameters":[{"name":"responseStatus","value":"HTTP/1.1 200 OK"},{"name":"responseBody","value":"{\"id\":4,\"token\":\"QpwL5tke4Pnpja7X4\"}"}],"start":1607959685845,"stop":1607959685860}],"attachments":[],"parameters":[{"name":"sheetName","value":"Google_TestAPI2"},{"name":"domain","value":"https://reqres.in/"},{"name":"requestMethod","value":"POST"},{"name":"parameterType","value":"JSON"},{"name":"header","value":"{Content-Type=application/json}"},{"name":"path","value":"/api/register"},{"name":"params","value":"{}"},{"name":"body","value":"{password=testqa, email=eve.holt@reqres.in}"},{"name":"expectedStatus","value":"200"},{"name":"paramsQuery","value":"{}"}],"start":1607959681841,"stop":1607959685860},{"name":"Verify API Good Request for Date_TestAPI1","status":"passed","stage":"finished","steps":[{"name":"Response Status is HTTP/1.1 200 OK\n Response Body {\"leap\":true}","status":"passed","stage":"finished","steps":[],"attachments":[],"parameters":[{"name":"responseStatus","value":"HTTP/1.1 200 OK"},{"name":"responseBody","value":"{\"leap\":true}"}],"start":1607959687027,"stop":1607959687027}],"attachments":[],"parameters":[{"name":"sheetName","value":"Date_TestAPI1"},{"name":"domain","value":"https://postman-echo.com"},{"name":"requestMethod","value":"GET"},{"name":"parameterType","value":"QueryParameter"},{"name":"header","value":"{Content-Type=application/json}"},{"name":"path","value":"/time/leap"},{"name":"params","value":"{}"},{"name":"body","value":"{}"},{"name":"expectedStatus","value":"200"},{"name":"paramsQuery","value":"{timestamp=2016-10-24}"}],"start":1607959685866,"stop":1607959687027},{"name":"Generating a Number Sequence, the lenght of number Sequence is a Random length between 1 and 5","status":"passed","stage":"finished","steps":[{"name":"Generating a single Random Number between 1 and 5","status":"passed","stage":"finished","steps":[],"attachments":[],"parameters":[{"name":"boundStart","value":"1"},{"name":"boundEnd","value":"5"}],"start":1607959687114,"stop":1607959687114},{"name":"Generating a Random number sequence of length - 2","status":"passed","stage":"finished","steps":[],"attachments":[],"parameters":[{"name":"numberSeqLength","value":"2"}],"start":1607959687118,"stop":1607959687118}],"attachments":[{"name":"SingleNumber_BetBounds","source":"b6eb8461-6868-4688-8e94-03cb38031cec-attachment"},{"name":"NumberSequence","source":"483c3425-97cd-4e5c-b33a-4983faf25e83-attachment"}],"parameters":[{"name":"boundStart","value":"1"},{"name":"boundEnd","value":"5"}],"start":1607959687114,"stop":1607959687120},{"name":"Verify API Good Request for Google_TestAPI3","status":"passed","stage":"finished","steps":[{"name":"Response Status is HTTP/1.1 200 OK\n Response Body {\"id\":4,\"token\":\"QpwL5tke4Pnpja7X4\"}","status":"passed","stage":"finished","steps":[],"attachments":[],"parameters":[{"name":"responseStatus","value":"HTTP/1.1 200 OK"},{"name":"responseBody","value":"{\"id\":4,\"token\":\"QpwL5tke4Pnpja7X4\"}"}],"start":1607959687811,"stop":1607959687811}],"attachments":[],"parameters":[{"name":"sheetName","value":"Google_TestAPI3"},{"name":"domain","value":"https://reqres.in/"},{"name":"requestMethod","value":"POST"},{"name":"parameterType","value":"NormalParameter"},{"name":"header","value":"{Content-Type=application/json}"},{"name":"path","value":"/api/register"},{"name":"params","value":"{}"},{"name":"body","value":"{email=eve.holt@reqres.in, password=83}"},{"name":"expectedStatus","value":"200"},{"name":"paramsQuery","value":"{}"}],"start":1607959687121,"stop":1607959687812},{"name":"Verify API Good Request for SPARTA_API","status":"passed","stage":"finished","steps":[{"name":"Response Status is HTTP/1.1 200 \n Response Body {\n  \"Z_YYKC_SALES_ORDER_CREATE_Response\": {\n    \"ETB_CONDITIONS\": {\n      \"item\": [\n        {\n          \"ITM_NUMBER\": \"000010\",\n          \"COND_ST_NO\": \"010\",\n          \"COND_COUNT\": \"01\",\n          \"COND_TYPE\": \"ZPR0\",\n          \"COND_VALUE\": \"278.710000000\",\n          \"CURRENCY\": \"BRL\",\n          \"COND_UNIT\": \"CS\",\n          \"COND_P_UNT\": \"1\",\n          \"CURR_ISO\": \"BRL\",\n          \"CD_UNT_ISO\": \"CS\",\n          \"REFOBJTYPE\": \"\",\n          \"REFOBJKEY\": \"\",\n          \"REFLOGSYS\": \"\",\n          \"APPLICATIO\": \"V\",\n          \"CONPRICDAT\": \"2020-12-14\",\n          \"CALCTYPCON\": \"C\",\n          \"CONBASEVAL\": \"1.000000000\",\n          \"CONEXCHRAT\": \"1.00000\",\n          \"NUMCONVERT\": \"1\",\n          \"DENOMINATO\": \"1\",\n          \"CONDTYPE\": \"\",\n          \"STAT_CON\": \"\",\n          \"SCALETYPE\": \"\",\n          \"ACCRUALS\": \"\",\n          \"CONINVOLST\": \"\",\n          \"CONDORIGIN\": \"A\",\n          \"GROUPCOND\": \"\",\n          \"COND_UPDAT\": \"\",\n          \"ACCESS_SEQ\": \"10\",\n          \"CONDCOUNT\": \"01\",\n          \"ROUNDOFFDI\": \"0.000000000\",\n          \"CONDVALUE\": \"278.710000000\",\n          \"CURRENCY_2\": \"BRL\",\n          \"CURR_ISO_2\": \"BRL\",\n          \"CONDCNTRL\": \"A\",\n          \"CONDISACTI\": \"Y\",\n          \"CONDCLASS\": \"B\",\n          \"FACTBASVAL\": \"0.0000000000000000E+00\",\n          \"SCALEBASIN\": \"\",\n          \"SCALBASVAL\": \"0.000000000\",\n          \"UNITMEASUR\": \"\",\n          \"ISO_UNIT\": \"\",\n          \"CURRENCKEY\": \"\",\n          \"CURRENISO\": \"\",\n          \"CONDINCOMP\": \"\",\n          \"CONDCONFIG\": \"\",\n          \"CONDCHAMAN\": \"\",\n          \"COND_NO\": \"0070387778\",\n          \"TAX_CODE\": \"\",\n          \"VARCOND\": \"\",\n          \"ACCOUNTKEY\": \"\",\n          \"ACCOUNT_KE\": \"\",\n          \"WT_WITHCD\": \"\",\n          \"STRUCTCOND\": \"\",\n          \"FACTCONBAS\": \"0.0000000000000000E+00\",\n          \"CONDCOINHD\": \"00\"\n        },\n        {\n          \"ITM_NUMBER\": \"000010\",\n          \"COND_ST_NO\": \"025\",\n          \"COND_COUNT\": \"01\",\n          \"COND_TYPE\": \"ZGRO\",\n          \"COND_VALUE\": \"278.710000000\",\n          \"CURRENCY\": \"BRL\",\n          \"COND_UNIT\": \"CS\",\n          \"COND_P_UNT\": \"1\",\n          \"CURR_ISO\": \"BRL\",\n          \"CD_UNT_ISO\": \"CS\",\n          \"REFOBJTYPE\": \"\",\n          \"REFOBJKEY\": \"\",\n          \"REFLOGSYS\": \"\",\n          \"APPLICATIO\": \"V\",\n          \"CONPRICDAT\": \"2020-12-14\",\n          \"CALCTYPCON\": \"C\",\n          \"CONBASEVAL\": \"1.000000000\",\n          \"CONEXCHRAT\": \"1.00000\",\n          \"NUMCONVERT\": \"1\",\n          \"DENOMINATO\": \"1\",\n          \"CONDTYPE\": \"\",\n          \"STAT_CON\": \"X\",\n          \"SCALETYPE\": \"\",\n          \"ACCRUALS\": \"\",\n          \"CONINVOLST\": \"\",\n          \"CONDORIGIN\": \"A\",\n          \"GROUPCOND\": \"\",\n          \"COND_UPDAT\": \"\",\n          \"ACCESS_SEQ\": \"00\",\n          \"CONDCOUNT\": \"00\",\n          \"ROUNDOFFDI\": \"0.000000000\",\n          \"CONDVALUE\": \"278.710000000\",\n          \"CURRENCY_2\": \"BRL\",\n          \"CURR_ISO_2\": \"BRL\",\n          \"CONDCNTRL\": \"A\",\n          \"CONDISACTI\": \"Y\",\n          \"CONDCLASS\": \"B\",\n          \"FACTBASVAL\": \"0.0000000000000000E+00\",\n          \"SCALEBASIN\": \"\",\n          \"SCALBASVAL\": \"0.000000000\",\n          \"UNITMEASUR\": \"\",\n          \"ISO_UNIT\": \"\",\n          \"CURRENCKEY\": \"\",\n          \"CURRENISO\": \"\",\n          \"CONDINCOMP\": \"\",\n          \"CONDCONFIG\": \"\",\n          \"CONDCHAMAN\": \"\",\n          \"COND_NO\": \"\",\n          \"TAX_CODE\": \"\",\n          \"VARCOND\": \"\",\n          \"ACCOUNTKEY\": \"\",\n          \"ACCOUNT_KE\": \"\",\n          \"WT_WITHCD\": \"\",\n          \"STRUCTCOND\": \"\",\n          \"FACTCONBAS\": \"0.0000000000000000E+00\",\n          \"CONDCOINHD\": \"00\"\n        },\n        {\n          \"ITM_NUMBER\": \"000010\",\n          \"COND_ST_NO\": \"028\",\n          \"COND_COUNT\": \"01\",\n          \"COND_TYPE\": \"YGRP\",\n          \"COND_VALUE\": \"118.330000000\",\n          \"CURRENCY\": \"BRL\",\n          \"COND_UNIT\": \"CS\",\n          \"COND_P_UNT\": \"1\",\n          \"CURR_ISO\": \"BRL\",\n          \"CD_UNT_ISO\": \"CS\",\n          \"REFOBJTYPE\": \"\",\n          \"REFOBJKEY\": \"\",\n          \"REFLOGSYS\": \"\",\n          \"APPLICATIO\": \"V\",\n          \"CONPRICDAT\": \"2020-12-14\",\n          \"CALCTYPCON\": \"C\",\n          \"CONBASEVAL\": \"1.000000000\",\n          \"CONEXCHRAT\": \"1.00000\",\n          \"NUMCONVERT\": \"1\",\n          \"DENOMINATO\": \"1\",\n          \"CONDTYPE\": \"\",\n          \"STAT_CON\": \"X\",\n          \"SCALETYPE\": \"\",\n          \"ACCRUALS\": \"\",\n          \"CONINVOLST\": \"\",\n          \"CONDORIGIN\": \"A\",\n          \"GROUPCOND\": \"\",\n          \"COND_UPDAT\": \"\",\n          \"ACCESS_SEQ\": \"30\",\n          \"CONDCOUNT\": \"01\",\n          \"ROUNDOFFDI\": \"0.000000000\",\n          \"CONDVALUE\": \"118.330000000\",\n          \"CURRENCY_2\": \"BRL\",\n          \"CURR_ISO_2\": \"BRL\",\n          \"CONDCNTRL\": \"A\",\n          \"CONDISACTI\": \"Y\",\n          \"CONDCLASS\": \"B\",\n          \"FACTBASVAL\": \"0.0000000000000000E+00\",\n          \"SCALEBASIN\": \"\",\n          \"SCALBASVAL\": \"0.000000000\",\n          \"UNITMEASUR\": \"\",\n          \"ISO_UNIT\": \"\",\n          \"CURRENCKEY\": \"\",\n          \"CURRENISO\": \"\",\n          \"CONDINCOMP\": \"\",\n          \"CONDCONFIG\": \"\",\n          \"CONDCHAMAN\": \"\",\n          \"COND_NO\": \"0069686765\",\n          \"TAX_CODE\": \"\",\n          \"VARCOND\": \"\",\n          \"ACCOUNTKEY\": \"\",\n          \"ACCOUNT_KE\": \"\",\n          \"WT_WITHCD\": \"\",\n          \"STRUCTCOND\": \"\",\n          \"FACTCONBAS\": \"0.0000000000000000E+00\",\n          \"CONDCOINHD\": \"00\"\n        },\n        {\n          \"ITM_NUMBER\": \"000010\",\n          \"COND_ST_NO\": \"035\",\n          \"COND_COUNT\": \"01\",\n          \"COND_TYPE\": \"ZE09\",\n          \"COND_VALUE\": \"0.000000000\",\n          \"CURRENCY\": \"\",\n          \"COND_UNIT\": \"\",\n          \"COND_P_UNT\": \"0\",\n          \"CURR_ISO\": \"\",\n          \"CD_UNT_ISO\": \"\",\n          \"REFOBJTYPE\": \"\",\n          \"REFOBJKEY\": \"\",\n          \"REFLOGSYS\": \"\",\n          \"APPLICATIO\": \"V\",\n          \"CONPRICDAT\": \"2020-12-14\",\n          \"CALCTYPCON\": \"A\",\n          \"CONBASEVAL\": \"118.330000000\",\n          \"CONEXCHRAT\": \"0.00000\",\n          \"NUMCONVERT\": \"0\",\n          \"DENOMINATO\": \"0\",\n          \"CONDTYPE\": \"\",\n          \"STAT_CON\": \"\",\n          \"SCALETYPE\": \"\",\n          \"ACCRUALS\": \"\",\n          \"CONINVOLST\": \"\",\n          \"CONDORIGIN\": \"A\",\n          \"GROUPCOND\": \"\",\n          \"COND_UPDAT\": \"X\",\n          \"ACCESS_SEQ\": \"00\",\n          \"CONDCOUNT\": \"00\",\n          \"ROUNDOFFDI\": \"0.000000000\",\n          \"CONDVALUE\": \"-160.380000000\",\n          \"CURRENCY_2\": \"BRL\",\n          \"CURR_ISO_2\": \"BRL\",\n          \"CONDCNTRL\": \"A\",\n          \"CONDISACTI\": \"Y\",\n          \"CONDCLASS\": \"A\",\n          \"FACTBASVAL\": \"0.0000000000000000E+00\",\n          \"SCALEBASIN\": \"\",\n          \"SCALBASVAL\": \"0.000000000\",\n          \"UNITMEASUR\": \"\",\n          \"ISO_UNIT\": \"\",\n          \"CURRENCKEY\": \"\",\n          \"CURRENISO\": \"\",\n          \"CONDINCOMP\": \"\",\n          \"CONDCONFIG\": \"\",\n          \"CONDCHAMAN\": \"\",\n          \"COND_NO\": \"\",\n          \"TAX_CODE\": \"\",\n          \"VARCOND\": \"\",\n          \"ACCOUNTKEY\": \"\",\n          \"ACCOUNT_KE\": \"\",\n          \"WT_WITHCD\": \"\",\n          \"STRUCTCOND\": \"\",\n          \"FACTCONBAS\": \"0.0000000000000000E+00\",\n          \"CONDCOINHD\": \"00\"\n        },\n        {\n          \"ITM_NUMBER\": \"000010\",\n          \"COND_ST_NO\": \"040\",\n          \"COND_COUNT\": \"01\",\n          \"COND_TYPE\": \"YC15\",\n          \"COND_VALUE\": \"0.000000000\",\n          \"CURRENCY\": \"BRL\",\n          \"COND_UNIT\": \"CS\",\n          \"COND_P_UNT\": \"1\",\n          \"CURR_ISO\": \"BRL\",\n          \"CD_UNT_ISO\": \"CS\",\n          \"REFOBJTYPE\": \"\",\n          \"REFOBJKEY\": \"\",\n          \"REFLOGSYS\": \"\",\n          \"APPLICATIO\": \"V\",\n          \"CONPRICDAT\": \"2020-12-14\",\n          \"CALCTYPCON\": \"C\",\n          \"CONBASEVAL\": \"1.000000000\",\n          \"CONEXCHRAT\": \"1.00000\",\n          \"NUMCONVERT\": \"1\",\n          \"DENOMINATO\": \"1\",\n          \"CONDTYPE\": \"Y\",\n          \"STAT_CON\": \"X\",\n          \"SCALETYPE\": \"\",\n          \"ACCRUALS\": \"\",\n          \"CONINVOLST\": \"\",\n          \"CONDORIGIN\": \"A\",\n          \"GROUPCOND\": \"\",\n          \"COND_UPDAT\": \"X\",\n          \"ACCESS_SEQ\": \"00\",\n          \"CONDCOUNT\": \"00\",\n          \"ROUNDOFFDI\": \"0.000000000\",\n          \"CONDVALUE\": \"0.000000000\",\n          \"CURRENCY_2\": \"BRL\",\n          \"CURR_ISO_2\": \"BRL\",\n          \"CONDCNTRL\": \"A\",\n          \"CONDISACTI\": \"X\",\n          \"CONDCLASS\": \"B\",\n          \"FACTBASVAL\": \"0.0000000000000000E+00\",\n          \"SCALEBASIN\": \"\",\n          \"SCALBASVAL\": \"0.000000000\",\n          \"UNITMEASUR\": \"\",\n          \"ISO_UNIT\": \"\",\n          \"CURRENCKEY\": \"\",\n          \"CURRENISO\": \"\",\n          \"CONDINCOMP\": \"\",\n          \"CONDCONFIG\": \"\",\n          \"CONDCHAMAN\": \"\",\n          \"COND_NO\": \"\",\n          \"TAX_CODE\": \"\",\n          \"VARCOND\": \"\",\n          \"ACCOUNTKEY\": \"\",\n          \"ACCOUNT_KE\": \"\",\n          \"WT_WITHCD\": \"\",\n          \"STRUCTCOND\": \"\",\n          \"FACTCONBAS\": \"0.0000000000000000E+00\",\n          \"CONDCOINHD\": \"00\"\n        },\n        {\n          \"ITM_NUMBER\": \"000010\",\n          \"COND_ST_NO\": \"045\",\n          \"COND_COUNT\": \"01\",\n          \"COND_TYPE\": \"ZE10\",\n          \"COND_VALUE\": \"0.000000000\",\n          \"CURRENCY\": \"\",\n          \"COND_UNIT\": \"\",\n          \"COND_P_UNT\": \"0\",\n          \"CURR_ISO\": \"\",\n          \"CD_UNT_ISO\": \"\",\n          \"REFOBJTYPE\": \"\",\n          \"REFOBJKEY\": \"\",\n          \"REFLOGSYS\": \"\",\n          \"APPLICATIO\": \"V\",\n          \"CONPRICDAT\": \"2020-12-14\",\n          \"CALCTYPCON\": \"A\",\n          \"CONBASEVAL\": \"-42.050000000\",\n          \"CONEXCHRAT\": \"0.00000\",\n          \"NUMCONVERT\": \"0\",\n          \"DENOMINATO\": \"0\",\n          \"CONDTYPE\": \"\",\n          \"STAT_CON\": \"\",\n          \"SCALETYPE\": \"\",\n          \"ACCRUALS\": \"\",\n          \"CONINVOLST\": \"\",\n          \"CONDORIGIN\": \"A\",\n          \"GROUPCOND\": \"\",\n          \"COND_UPDAT\": \"X\",\n          \"ACCESS_SEQ\": \"00\",\n          \"CONDCOUNT\": \"00\",\n          \"ROUNDOFFDI\": \"0.000000000\",\n          \"CONDVALUE\": \"0.000000000\",\n          \"CURRENCY_2\": \"BRL\",\n          \"CURR_ISO_2\": \"BRL\",\n          \"CONDCNTRL\": \"A\",\n          \"CONDISACTI\": \"Y\",\n          \"CONDCLASS\": \"A\",\n          \"FACTBASVAL\": \"0.0000000000000000E+00\",\n          \"SCALEBASIN\": \"\",\n          \"SCALBASVAL\": \"0.000000000\",\n          \"UNITMEASUR\": \"\",\n          \"ISO_UNIT\": \"\",\n          \"CURRENCKEY\": \"\",\n          \"CURRENISO\": \"\",\n          \"CONDINCOMP\": \"\",\n          \"CONDCONFIG\": \"\",\n          \"CONDCHAMAN\": \"\",\n          \"COND_NO\": \"\",\n          \"TAX_CODE\": \"\",\n          \"VARCOND\": \"\",\n          \"ACCOUNTKEY\": \"\",\n          \"ACCOUNT_KE\": \"\",\n          \"WT_WITHCD\": \"\",\n          \"STRUCTCOND\": \"\",\n          \"FACTCONBAS\": \"0.0000000000000000E+00\",\n          \"CONDCOINHD\": \"00\"\n        },\n        {\n          \"ITM_NUMBER\": \"000010\",\n          \"COND_ST_NO\": \"195\",\n          \"COND_COUNT\": \"01\",\n          \"COND_TYPE\": \"ZNIV\",\n          \"COND_VALUE\": \"118.330000000\",\n          \"CURRENCY\": \"BRL\",\n          \"COND_UNIT\": \"CS\",\n          \"COND_P_UNT\": \"1\",\n          \"CURR_ISO\": \"BRL\",\n          \"CD_UNT_ISO\": \"CS\",\n          \"REFOBJTYPE\": \"\",\n          \"REFOBJKEY\": \"\",\n          \"REFLOGSYS\": \"\",\n          \"APPLICATIO\": \"V\",\n          \"CONPRICDAT\": \"2020-12-14\",\n          \"CALCTYPCON\": \"C\",\n          \"CONBASEVAL\": \"1.000000000\",\n          \"CONEXCHRAT\": \"1.00000\",\n          \"NUMCONVERT\": \"1\",\n          \"DENOMINATO\": \"1\",\n          \"CONDTYPE\": \"\",\n          \"STAT_CON\": \"X\",\n          \"SCALETYPE\": \"\",\n          \"ACCRUALS\": \"\",\n          \"CONINVOLST\": \"\",\n          \"CONDORIGIN\": \"A\",\n          \"GROUPCOND\": \"\",\n          \"COND_UPDAT\": \"\",\n          \"ACCESS_SEQ\": \"00\",\n          \"CONDCOUNT\": \"00\",\n          \"ROUNDOFFDI\": \"0.000000000\",\n          \"CONDVALUE\": \"118.330000000\",\n          \"CURRENCY_2\": \"BRL\",\n          \"CURR_ISO_2\": \"BRL\",\n          \"CONDCNTRL\": \"A\",\n          \"CONDISACTI\": \"Y\",\n          \"CONDCLASS\": \"B\",\n          \"FACTBASVAL\": \"0.0000000000000000E+00\",\n          \"SCALEBASIN\": \"\",\n          \"SCALBASVAL\": \"0.000000000\",\n          \"UNITMEASUR\": \"\",\n          \"ISO_UNIT\": \"\",\n          \"CURRENCKEY\": \"\",\n          \"CURRENISO\": \"\",\n          \"CONDINCOMP\": \"\",\n          \"CONDCONFIG\": \"\",\n          \"CONDCHAMAN\": \"\",\n          \"COND_NO\": \"\",\n          \"TAX_CODE\": \"\",\n          \"VARCOND\": \"\",\n          \"ACCOUNTKEY\": \"\",\n          \"ACCOUNT_KE\": \"\",\n          \"WT_WITHCD\": \"\",\n          \"STRUCTCOND\": \"\",\n          \"FACTCONBAS\": \"0.0000000000000000E+00\",\n          \"CONDCOINHD\": \"00\"\n        },\n        {\n          \"ITM_NUMBER\": \"000010\",\n          \"COND_ST_NO\": \"199\",\n          \"COND_COUNT\": \"01\",\n          \"COND_TYPE\": \"DGTX\",\n          \"COND_VALUE\": \"100.000000000\",\n          \"CURRENCY\": \"\",\n          \"COND_UNIT\": \"\",\n          \"COND_P_UNT\": \"0\",\n          \"CURR_ISO\": \"\",\n          \"CD_UNT_ISO\": \"\",\n          \"REFOBJTYPE\": \"\",\n          \"REFOBJKEY\": \"\",\n          \"REFLOGSYS\": \"\",\n          \"APPLICATIO\": \"V\",\n          \"CONPRICDAT\": \"2020-12-14\",\n          \"CALCTYPCON\": \"A\",\n          \"CONBASEVAL\": \"10.000000000\",\n          \"CONEXCHRAT\": \"0.00000\",\n          \"NUMCONVERT\": \"0\",\n          \"DENOMINATO\": \"0\",\n          \"CONDTYPE\": \"D\",\n          \"STAT_CON\": \"X\",\n          \"SCALETYPE\": \"\",\n          \"ACCRUALS\": \"\",\n          \"CONINVOLST\": \"\",\n          \"CONDORIGIN\": \"A\",\n          \"GROUPCOND\": \"\",\n          \"COND_UPDAT\": \"\",\n          \"ACCESS_SEQ\": \"01\",\n          \"CONDCOUNT\": \"01\",\n          \"ROUNDOFFDI\": \"0.000000000\",\n          \"CONDVALUE\": \"10.000000000\",\n          \"CURRENCY_2\": \"BRL\",\n          \"CURR_ISO_2\": \"BRL\",\n          \"CONDCNTRL\": \"A\",\n          \"CONDISACTI\": \"Y\",\n          \"CONDCLASS\": \"D\",\n          \"FACTBASVAL\": \"0.0000000000000000E+00\",\n          \"SCALEBASIN\": \"\",\n          \"SCALBASVAL\": \"0.000000000\",\n          \"UNITMEASUR\": \"\",\n          \"ISO_UNIT\": \"\",\n          \"CURRENCKEY\": \"\",\n          \"CURRENISO\": \"\",\n          \"CONDINCOMP\": \"\",\n          \"CONDCONFIG\": \"\",\n          \"CONDCHAMAN\": \"\",\n          \"COND_NO\": \"0035482469\",\n          \"TAX_CODE\": \"SD\",\n          \"VARCOND\": \"\",\n          \"ACCOUNTKEY\": \"\",\n          \"ACCOUNT_KE\": \"\",\n          \"WT_WITHCD\": \"\",\n          \"STRUCTCOND\": \"\",\n          \"FACTCONBAS\": \"0.0000000000000000E+00\",\n          \"CONDCOINHD\": \"00\"\n        },\n        {\n          \"ITM_NUMBER\": \"000010\",\n          \"COND_ST_NO\": \"200\",\n          \"COND_COUNT\": \"01\",\n          \"COND_TYPE\": \"DICM\",\n          \"COND_VALUE\": \"100.000000000\",\n          \"CURRENCY\": \"\",\n          \"COND_UNIT\": \"\",\n          \"COND_P_UNT\": \"0\",\n          \"CURR_ISO\": \"\",\n          \"CD_UNT_ISO\": \"\",\n          \"REFOBJTYPE\": \"\",\n          \"REFOBJKEY\": \"\",\n          \"REFLOGSYS\": \"\",\n          \"APPLICATIO\": \"V\",\n          \"CONPRICDAT\": \"2020-12-14\",\n          \"CALCTYPCON\": \"A\",\n          \"CONBASEVAL\": \"10.000000000\",\n          \"CONEXCHRAT\": \"0.00000\",\n          \"NUMCONVERT\": \"0\",\n          \"DENOMINATO\": \"0\",\n          \"CONDTYPE\": \"D\",\n          \"STAT_CON\": \"X\",\n          \"SCALETYPE\": \"\",\n          \"ACCRUALS\": \"\",\n          \"CONINVOLST\": \"\",\n          \"CONDORIGIN\": \"A\",\n          \"GROUPCOND\": \"\",\n          \"COND_UPDAT\": \"\",\n          \"ACCESS_SEQ\": \"10\",\n          \"CONDCOUNT\": \"01\",\n          \"ROUNDOFFDI\": \"0.000000000\",\n          \"CONDVALUE\": \"10.000000000\",\n          \"CURRENCY_2\": \"BRL\",\n          \"CURR_ISO_2\": \"BRL\",\n          \"CONDCNTRL\": \"A\",\n          \"CONDISACTI\": \"Y\",\n          \"CONDCLASS\": \"D\",\n          \"FACTBASVAL\": \"0.0000000000000000E+00\",\n          \"SCALEBASIN\": \"\",\n          \"SCALBASVAL\": \"0.000000000\",\n          \"UNITMEASUR\": \"\",\n          \"ISO_UNIT\": \"\",\n          \"CURRENCKEY\": \"\",\n          \"CURRENISO\": \"\",\n          \"CONDINCOMP\": \"\",\n          \"CONDCONFIG\": \"\",\n          \"CONDCHAMAN\": \"\",\n          \"COND_NO\": \"0011142811\",\n          \"TAX_CODE\": \"SD\",\n          \"VARCOND\": \"\",\n          \"ACCOUNTKEY\": \"\",\n          \"ACCOUNT_KE\": \"\",\n          \"WT_WITHCD\": \"\",\n          \"STRUCTCOND\": \"\",\n          \"FACTCONBAS\": \"0.0000000000000000E+00\",\n          \"CONDCOINHD\": \"00\"\n        },\n        {\n          \"ITM_NUMBER\": \"000010\",\n          \"COND_ST_NO\": \"201\",\n          \"COND_COUNT\": \"01\",\n          \"COND_TYPE\": \"ICVA\",\n          \"COND_VALUE\": \"12.000000000\",\n          \"CURRENCY\": \"\",\n          \"COND_UNIT\": \"\",\n          \"COND_P_UNT\": \"0\",\n          \"CURR_ISO\": \"\",\n          \"CD_UNT_ISO\": \"\",\n          \"REFOBJTYPE\": \"\",\n          \"REFOBJKEY\": \"\",\n          \"REFLOGSYS\": \"\",\n          \"APPLICATIO\": \"V\",\n          \"CONPRICDAT\": \"2020-12-14\",\n          \"CALCTYPCON\": \"A\",\n          \"CONBASEVAL\": \"10.000000000\",\n          \"CONEXCHRAT\": \"0.00000\",\n          \"NUMCONVERT\": \"0\",\n          \"DENOMINATO\": \"0\",\n          \"CONDTYPE\": \"D\",\n          \"STAT_CON\": \"X\",\n          \"SCALETYPE\": \"\",\n          \"ACCRUALS\": \"\",\n          \"CONINVOLST\": \"\",\n          \"CONDORIGIN\": \"A\",\n          \"GROUPCOND\": \"\",\n          \"COND_UPDAT\": \"\",\n          \"ACCESS_SEQ\": \"87\",\n          \"CONDCOUNT\": \"01\",\n          \"ROUNDOFFDI\": \"0.000000000\",\n          \"CONDVALUE\": \"1.200000000\",\n          \"CURRENCY_2\": \"BRL\",\n          \"CURR_ISO_2\": \"BRL\",\n          \"CONDCNTRL\": \"A\",\n          \"CONDISACTI\": \"Y\",\n          \"CONDCLASS\": \"D\",\n          \"FACTBASVAL\": \"0.0000000000000000E+00\",\n          \"SCALEBASIN\": \"\",\n          \"SCALBASVAL\": \"0.000000000\",\n          \"UNITMEASUR\": \"\",\n          \"ISO_UNIT\": \"\",\n          \"CURRENCKEY\": \"\",\n          \"CURRENISO\": \"\",\n          \"CONDINCOMP\": \"\",\n          \"CONDCONFIG\": \"\",\n          \"CONDCHAMAN\": \"\",\n          \"COND_NO\": \"0034882128\",\n          \"TAX_CODE\": \"SD\",\n          \"VARCOND\": \"\",\n          \"ACCOUNTKEY\": \"\",\n          \"ACCOUNT_KE\": \"\",\n          \"WT_WITHCD\": \"\",\n          \"STRUCTCOND\": \"\",\n          \"FACTCONBAS\": \"0.0000000000000000E+00\",\n          \"CONDCOINHD\": \"00\"\n        },\n        {\n          \"ITM_NUMBER\": \"000010\",\n          \"COND_ST_NO\": \"202\",\n          \"COND_COUNT\": \"01\",\n          \"COND_TYPE\": \"ICBS\",\n          \"COND_VALUE\": \"100.000000000\",\n          \"CURRENCY\": \"\",\n          \"COND_UNIT\": \"\",\n          \"COND_P_UNT\": \"0\",\n          \"CURR_ISO\": \"\",\n          \"CD_UNT_ISO\": \"\",\n          \"REFOBJTYPE\": \"\",\n          \"REFOBJKEY\": \"\",\n          \"REFLOGSYS\": \"\",\n          \"APPLICATIO\": \"V\",\n          \"CONPRICDAT\": \"2020-12-14\",\n          \"CALCTYPCON\": \"A\",\n          \"CONBASEVAL\": \"10.000000000\",\n          \"CONEXCHRAT\": \"0.00000\",\n          \"NUMCONVERT\": \"0\",\n          \"DENOMINATO\": \"0\",\n          \"CONDTYPE\": \"D\",\n          \"STAT_CON\": \"X\",\n          \"SCALETYPE\": \"\",\n          \"ACCRUALS\": \"\",\n          \"CONINVOLST\": \"\",\n          \"CONDORIGIN\": \"A\",\n          \"GROUPCOND\": \"\",\n          \"COND_UPDAT\": \"\",\n          \"ACCESS_SEQ\": \"87\",\n          \"CONDCOUNT\": \"01\",\n          \"ROUNDOFFDI\": \"0.000000000\",\n          \"CONDVALUE\": \"10.000000000\",\n          \"CURRENCY_2\": \"BRL\",\n          \"CURR_ISO_2\": \"BRL\",\n          \"CONDCNTRL\": \"A\",\n          \"CONDISACTI\": \"Y\",\n          \"CONDCLASS\": \"D\",\n          \"FACTBASVAL\": \"0.0000000000000000E+00\",\n          \"SCALEBASIN\": \"\",\n          \"SCALBASVAL\": \"0.000000000\",\n          \"UNITMEASUR\": \"\",\n          \"ISO_UNIT\": \"\",\n          \"CURRENCKEY\": \"\",\n          \"CURRENISO\": \"\",\n          \"CONDINCOMP\": \"\",\n          \"CONDCONFIG\": \"\",\n          \"CONDCHAMAN\": \"\",\n          \"COND_NO\": \"0034882129\",\n          \"TAX_CODE\": \"SD\",\n          \"VARCOND\": \"\",\n          \"ACCOUNTKEY\": \"\",\n          \"ACCOUNT_KE\": \"\",\n          \"WT_WITHCD\": \"\",\n          \"STRUCTCOND\": \"\",\n          \"FACTCONBAS\": \"0.0000000000000000E+00\",\n          \"CONDCOINHD\": \"00\"\n        },\n        {\n          \"ITM_NUMBER\": \"000010\",\n          \"COND_ST_NO\": \"207\",\n          \"COND_COUNT\": \"01\",\n          \"COND_TYPE\": \"ISIC\",\n          \"COND_VALUE\": \"18.000000000\",\n          \"CURRENCY\": \"\",\n          \"COND_UNIT\": \"\",\n          \"COND_P_UNT\": \"0\",\n          \"CURR_ISO\": \"\",\n          \"CD_UNT_ISO\": \"\",\n          \"REFOBJTYPE\": \"\",\n          \"REFOBJKEY\": \"\",\n          \"REFLOGSYS\": \"\",\n          \"APPLICATIO\": \"V\",\n          \"CONPRICDAT\": \"2020-12-14\",\n          \"CALCTYPCON\": \"A\",\n          \"CONBASEVAL\": \"10.000000000\",\n          \"CONEXCHRAT\": \"0.00000\",\n          \"NUMCONVERT\": \"0\",\n          \"DENOMINATO\": \"0\",\n          \"CONDTYPE\": \"D\",\n          \"STAT_CON\": \"X\",\n          \"SCALETYPE\": \"\",\n          \"ACCRUALS\": \"\",\n          \"CONINVOLST\": \"\",\n          \"CONDORIGIN\": \"A\",\n          \"GROUPCOND\": \"\",\n          \"COND_UPDAT\": \"\",\n          \"ACCESS_SEQ\": \"53\",\n          \"CONDCOUNT\": \"01\",\n          \"ROUNDOFFDI\": \"0.000000000\",\n          \"CONDVALUE\": \"1.800000000\",\n          \"CURRENCY_2\": \"BRL\",\n          \"CURR_ISO_2\": \"BRL\",\n          \"CONDCNTRL\": \"A\",\n          \"CONDISACTI\": \"Y\",\n          \"CONDCLASS\": \"D\",\n          \"FACTBASVAL\": \"0.0000000000000000E+00\",\n          \"SCALEBASIN\": \"\",\n          \"SCALBASVAL\": \"0.000000000\",\n          \"UNITMEASUR\": \"\",\n          \"ISO_UNIT\": \"\",\n          \"CURRENCKEY\": \"\",\n          \"CURRENISO\": \"\",\n          \"CONDINCOMP\": \"\",\n          \"CONDCONFIG\": \"\",\n          \"CONDCHAMAN\": \"\",\n          \"COND_NO\": \"0035528182\",\n          \"TAX_CODE\": \"SD\",\n          \"VARCOND\": \"\",\n          \"ACCOUNTKEY\": \"\",\n          \"ACCOUNT_KE\": \"\",\n          \"WT_WITHCD\": \"\",\n          \"STRUCTCOND\": \"\",\n          \"FACTCONBAS\": \"0.0000000000000000E+00\",\n          \"CONDCOINHD\": \"00\"\n        },\n        {\n          \"ITM_NUMBER\": \"000010\",\n          \"COND_ST_NO\": \"211\",\n          \"COND_COUNT\": \"01\",\n          \"COND_TYPE\": \"ISIB\",\n          \"COND_VALUE\": \"100.000000000\",\n          \"CURRENCY\": \"\",\n          \"COND_UNIT\": \"\",\n          \"COND_P_UNT\": \"0\",\n          \"CURR_ISO\": \"\",\n          \"CD_UNT_ISO\": \"\",\n          \"REFOBJTYPE\": \"\",\n          \"REFOBJKEY\": \"\",\n          \"REFLOGSYS\": \"\",\n          \"APPLICATIO\": \"V\",\n          \"CONPRICDAT\": \"2020-12-14\",\n          \"CALCTYPCON\": \"A\",\n          \"CONBASEVAL\": \"10.000000000\",\n          \"CONEXCHRAT\": \"0.00000\",\n          \"NUMCONVERT\": \"0\",\n          \"DENOMINATO\": \"0\",\n          \"CONDTYPE\": \"D\",\n          \"STAT_CON\": \"X\",\n          \"SCALETYPE\": \"\",\n          \"ACCRUALS\": \"\",\n          \"CONINVOLST\": \"\",\n          \"CONDORIGIN\": \"A\",\n          \"GROUPCOND\": \"\",\n          \"COND_UPDAT\": \"\",\n          \"ACCESS_SEQ\": \"53\",\n          \"CONDCOUNT\": \"01\",\n          \"ROUNDOFFDI\": \"0.000000000\",\n          \"CONDVALUE\": \"10.000000000\",\n          \"CURRENCY_2\": \"BRL\",\n          \"CURR_ISO_2\": \"BRL\",\n          \"CONDCNTRL\": \"A\",\n          \"CONDISACTI\": \"Y\",\n          \"CONDCLASS\": \"D\",\n          \"FACTBASVAL\": \"0.0000000000000000E+00\",\n          \"SCALEBASIN\": \"\",\n          \"SCALBASVAL\": \"0.000000000\",\n          \"UNITMEASUR\": \"\",\n          \"ISO_UNIT\": \"\",\n          \"CURRENCKEY\": \"\",\n          \"CURRENISO\": \"\",\n          \"CONDINCOMP\": \"\",\n          \"CONDCONFIG\": \"\",\n          \"CONDCHAMAN\": \"\",\n          \"COND_NO\": \"0035528188\",\n          \"TAX_CODE\": \"SD\",\n          \"VARCOND\": \"\",\n          \"ACCOUNTKEY\": \"\",\n          \"ACCOUNT_KE\": \"\",\n          \"WT_WITHCD\": \"\",\n          \"STRUCTCOND\": \"\",\n          \"FACTCONBAS\": \"0.0000000000000000E+00\",\n          \"CONDCOINHD\": \"00\"\n        },\n        {\n          \"ITM_NUMBER\": \"000010\",\n          \"COND_ST_NO\": \"212\",\n          \"COND_COUNT\": \"01\",\n          \"COND_TYPE\": \"ISFR\",\n          \"COND_VALUE\": \"0.000000000\",\n          \"CURRENCY\": \"\",\n          \"COND_UNIT\": \"\",\n          \"COND_P_UNT\": \"0\",\n          \"CURR_ISO\": \"\",\n          \"CD_UNT_ISO\": \"\",\n          \"REFOBJTYPE\": \"\",\n          \"REFOBJKEY\": \"\",\n          \"REFLOGSYS\": \"\",\n          \"APPLICATIO\": \"V\",\n          \"CONPRICDAT\": \"2020-12-14\",\n          \"CALCTYPCON\": \"A\",\n          \"CONBASEVAL\": \"10.000000000\",\n          \"CONEXCHRAT\": \"0.00000\",\n          \"NUMCONVERT\": \"0\",\n          \"DENOMINATO\": \"0\",\n          \"CONDTYPE\": \"D\",\n          \"STAT_CON\": \"X\",\n          \"SCALETYPE\": \"\",\n          \"ACCRUALS\": \"\",\n          \"CONINVOLST\": \"\",\n          \"CONDORIGIN\": \"A\",\n          \"GROUPCOND\": \"\",\n          \"COND_UPDAT\": \"\",\n          \"ACCESS_SEQ\": \"53\",\n          \"CONDCOUNT\": \"01\",\n          \"ROUNDOFFDI\": \"0.000000000\",\n          \"CONDVALUE\": \"0.000000000\",\n          \"CURRENCY_2\": \"BRL\",\n          \"CURR_ISO_2\": \"BRL\",\n          \"CONDCNTRL\": \"A\",\n          \"CONDISACTI\": \"Y\",\n          \"CONDCLASS\": \"D\",\n          \"FACTBASVAL\": \"0.0000000000000000E+00\",\n          \"SCALEBASIN\": \"\",\n          \"SCALBASVAL\": \"0.000000000\",\n          \"UNITMEASUR\": \"\",\n          \"ISO_UNIT\": \"\",\n          \"CURRENCKEY\": \"\",\n          \"CURRENISO\": \"\",\n          \"CONDINCOMP\": \"\",\n          \"CONDCONFIG\": \"\",\n          \"CONDCHAMAN\": \"\",\n          \"COND_NO\": \"0035528189\",\n          \"TAX_CODE\": \"SD\",\n          \"VARCOND\": \"\",\n          \"ACCOUNTKEY\": \"\",\n          \"ACCOUNT_KE\": \"\",\n          \"WT_WITHCD\": \"\",\n          \"STRUCTCOND\": \"\",\n          \"FACTCONBAS\": \"0.0000000000000000E+00\",\n          \"CONDCOINHD\": \"00\"\n        },\n        {\n          \"ITM_NUMBER\": \"000010\",\n          \"COND_ST_NO\": \"213\",\n          \"COND_COUNT\": \"01\",\n          \"COND_TYPE\": \"ISFB\",\n          \"COND_VALUE\": \"0.000000000\",\n          \"CURRENCY\": \"\",\n          \"COND_UNIT\": \"\",\n          \"COND_P_UNT\": \"0\",\n          \"CURR_ISO\": \"\",\n          \"CD_UNT_ISO\": \"\",\n          \"REFOBJTYPE\": \"\",\n          \"REFOBJKEY\": \"\",\n          \"REFLOGSYS\": \"\",\n          \"APPLICATIO\": \"V\",\n          \"CONPRICDAT\": \"2020-12-14\",\n          \"CALCTYPCON\": \"A\",\n          \"CONBASEVAL\": \"10.000000000\",\n          \"CONEXCHRAT\": \"0.00000\",\n          \"NUMCONVERT\": \"0\",\n          \"DENOMINATO\": \"0\",\n          \"CONDTYPE\": \"D\",\n          \"STAT_CON\": \"X\",\n          \"SCALETYPE\": \"\",\n          \"ACCRUALS\": \"\",\n          \"CONINVOLST\": \"\",\n          \"CONDORIGIN\": \"A\",\n          \"GROUPCOND\": \"\",\n          \"COND_UPDAT\": \"\",\n          \"ACCESS_SEQ\": \"53\",\n          \"CONDCOUNT\": \"01\",\n          \"ROUNDOFFDI\": \"0.000000000\",\n          \"CONDVALUE\": \"0.000000000\",\n          \"CURRENCY_2\": \"BRL\",\n          \"CURR_ISO_2\": \"BRL\",\n          \"CONDCNTRL\": \"A\",\n          \"CONDISACTI\": \"Y\",\n          \"CONDCLASS\": \"D\",\n          \"FACTBASVAL\": \"0.0000000000000000E+00\",\n          \"SCALEBASIN\": \"\",\n          \"SCALBASVAL\": \"0.000000000\",\n          \"UNITMEASUR\": \"\",\n          \"ISO_UNIT\": \"\",\n          \"CURRENCKEY\": \"\",\n          \"CURRENISO\": \"\",\n          \"CONDINCOMP\": \"\",\n          \"CONDCONFIG\": \"\",\n          \"CONDCHAMAN\": \"\",\n          \"COND_NO\": \"0035528190\",\n          \"TAX_CODE\": \"SD\",\n          \"VARCOND\": \"\",\n          \"ACCOUNTKEY\": \"\",\n          \"ACCOUNT_KE\": \"\",\n          \"WT_WITHCD\": \"\",\n          \"STRUCTCOND\": \"\",\n          \"FACTCONBAS\": \"0.0000000000000000E+00\",\n          \"CONDCOINHD\": \"00\"\n        },\n        {\n          \"ITM_NUMBER\": \"000010\",\n          \"COND_ST_NO\": \"214\",\n          \"COND_COUNT\": \"01\",\n          \"COND_TYPE\": \"DINC\",\n          \"COND_VALUE\": \"100.000000000\",\n          \"CURRENCY\": \"\",\n          \"COND_UNIT\": \"\",\n          \"COND_P_UNT\": \"0\",\n          \"CURR_ISO\": \"\",\n          \"CD_UNT_ISO\": \"\",\n          \"REFOBJTYPE\": \"\",\n          \"REFOBJKEY\": \"\",\n          \"REFLOGSYS\": \"\",\n          \"APPLICATIO\": \"V\",\n          \"CONPRICDAT\": \"2020-12-14\",\n          \"CALCTYPCON\": \"A\",\n          \"CONBASEVAL\": \"10.000000000\",\n          \"CONEXCHRAT\": \"0.00000\",\n          \"NUMCONVERT\": \"0\",\n          \"DENOMINATO\": \"0\",\n          \"CONDTYPE\": \"1\",\n          \"STAT_CON\": \"X\",\n          \"SCALETYPE\": \"\",\n          \"ACCRUALS\": \"\",\n          \"CONINVOLST\": \"\",\n          \"CONDORIGIN\": \"A\",\n          \"GROUPCOND\": \"\",\n          \"COND_UPDAT\": \"\",\n          \"ACCESS_SEQ\": \"00\",\n          \"CONDCOUNT\": \"00\",\n          \"ROUNDOFFDI\": \"0.000000000\",\n          \"CONDVALUE\": \"10.000000000\",\n          \"CURRENCY_2\": \"BRL\",\n          \"CURR_ISO_2\": \"BRL\",\n          \"CONDCNTRL\": \"A\",\n          \"CONDISACTI\": \"Y\",\n          \"CONDCLASS\": \"A\",\n          \"FACTBASVAL\": \"0.0000000000000000E+00\",\n          \"SCALEBASIN\": \"\",\n          \"SCALBASVAL\": \"0.000000000\",\n          \"UNITMEASUR\": \"\",\n          \"ISO_UNIT\": \"\",\n          \"CURRENCKEY\": \"\",\n          \"CURRENISO\": \"\",\n          \"CONDINCOMP\": \"\",\n          \"CONDCONFIG\": \"\",\n          \"CONDCHAMAN\": \"\",\n          \"COND_NO\": \"\",\n          \"TAX_CODE\": \"\",\n          \"VARCOND\": \"\",\n          \"ACCOUNTKEY\": \"\",\n          \"ACCOUNT_KE\": \"\",\n          \"WT_WITHCD\": \"\",\n          \"STRUCTCOND\": \"\",\n          \"FACTCONBAS\": \"0.0000000000000000E+00\",\n          \"CONDCOINHD\": \"00\"\n        },\n        {\n          \"ITM_NUMBER\": \"000010\",\n          \"COND_ST_NO\": \"221\",\n          \"COND_COUNT\": \"01\",\n          \"COND_TYPE\": \"ICFR\",\n          \"COND_VALUE\": \"12.000000000\",\n          \"CURRENCY\": \"\",\n          \"COND_UNIT\": \"\",\n          \"COND_P_UNT\": \"0\",\n          \"CURR_ISO\": \"\",\n          \"CD_UNT_ISO\": \"\",\n          \"REFOBJTYPE\": \"\",\n          \"REFOBJKEY\": \"\",\n          \"REFLOGSYS\": \"\",\n          \"APPLICATIO\": \"V\",\n          \"CONPRICDAT\": \"2020-12-14\",\n          \"CALCTYPCON\": \"A\",\n          \"CONBASEVAL\": \"10.000000000\",\n          \"CONEXCHRAT\": \"0.00000\",\n          \"NUMCONVERT\": \"0\",\n          \"DENOMINATO\": \"0\",\n          \"CONDTYPE\": \"D\",\n          \"STAT_CON\": \"X\",\n          \"SCALETYPE\": \"\",\n          \"ACCRUALS\": \"\",\n          \"CONINVOLST\": \"\",\n          \"CONDORIGIN\": \"A\",\n          \"GROUPCOND\": \"\",\n          \"COND_UPDAT\": \"\",\n          \"ACCESS_SEQ\": \"98\",\n          \"CONDCOUNT\": \"01\",\n          \"ROUNDOFFDI\": \"0.000000000\",\n          \"CONDVALUE\": \"1.200000000\",\n          \"CURRENCY_2\": \"BRL\",\n          \"CURR_ISO_2\": \"BRL\",\n          \"CONDCNTRL\": \"A\",\n          \"CONDISACTI\": \"Y\",\n          \"CONDCLASS\": \"D\",\n          \"FACTBASVAL\": \"0.0000000000000000E+00\",\n          \"SCALEBASIN\": \"\",\n          \"SCALBASVAL\": \"0.000000000\",\n          \"UNITMEASUR\": \"\",\n          \"ISO_UNIT\": \"\",\n          \"CURRENCKEY\": \"\",\n          \"CURRENISO\": \"\",\n          \"CONDINCOMP\": \"\",\n          \"CONDCONFIG\": \"\",\n          \"CONDCHAMAN\": \"\",\n          \"COND_NO\": \"0035124175\",\n          \"TAX_CODE\": \"SD\",\n          \"VARCOND\": \"\",\n          \"ACCOUNTKEY\": \"\",\n          \"ACCOUNT_KE\": \"\",\n          \"WT_WITHCD\": \"\",\n          \"STRUCTCOND\": \"\",\n          \"FACTCONBAS\": \"0.0000000000000000E+00\",\n          \"CONDCOINHD\": \"00\"\n        },\n        {\n          \"ITM_NUMBER\": \"000010\",\n          \"COND_ST_NO\": \"240\",\n          \"COND_COUNT\": \"01\",\n          \"COND_TYPE\": \"DIPI\",\n          \"COND_VALUE\": \"100.000000000\",\n          \"CURRENCY\": \"\",\n          \"COND_UNIT\": \"\",\n          \"COND_P_UNT\": \"0\",\n          \"CURR_ISO\": \"\",\n          \"CD_UNT_ISO\": \"\",\n          \"REFOBJTYPE\": \"\",\n          \"REFOBJKEY\": \"\",\n          \"REFLOGSYS\": \"\",\n          \"APPLICATIO\": \"V\",\n          \"CONPRICDAT\": \"2020-12-14\",\n          \"CALCTYPCON\": \"A\",\n          \"CONBASEVAL\": \"10.000000000\",\n          \"CONEXCHRAT\": \"0.00000\",\n          \"NUMCONVERT\": \"0\",\n          \"DENOMINATO\": \"0\",\n          \"CONDTYPE\": \"D\",\n          \"STAT_CON\": \"X\",\n          \"SCALETYPE\": \"\",\n          \"ACCRUALS\": \"\",\n          \"CONINVOLST\": \"\",\n          \"CONDORIGIN\": \"A\",\n          \"GROUPCOND\": \"\",\n          \"COND_UPDAT\": \"\",\n          \"ACCESS_SEQ\": \"10\",\n          \"CONDCOUNT\": \"01\",\n          \"ROUNDOFFDI\": \"0.000000000\",\n          \"CONDVALUE\": \"10.000000000\",\n          \"CURRENCY_2\": \"BRL\",\n          \"CURR_ISO_2\": \"BRL\",\n          \"CONDCNTRL\": \"A\",\n          \"CONDISACTI\": \"Y\",\n          \"CONDCLASS\": \"D\",\n          \"FACTBASVAL\": \"0.0000000000000000E+00\",\n          \"SCALEBASIN\": \"\",\n          \"SCALBASVAL\": \"0.000000000\",\n          \"UNITMEASUR\": \"\",\n          \"ISO_UNIT\": \"\",\n          \"CURRENCKEY\": \"\",\n          \"CURRENISO\": \"\",\n          \"CONDINCOMP\": \"\",\n          \"CONDCONFIG\": \"\",\n          \"CONDCHAMAN\": \"\",\n          \"COND_NO\": \"0011149091\",\n          \"TAX_CODE\": \"SD\",\n          \"VARCOND\": \"\",\n          \"ACCOUNTKEY\": \"\",\n          \"ACCOUNT_KE\": \"\",\n          \"WT_WITHCD\": \"\",\n          \"STRUCTCOND\": \"\",\n          \"FACTCONBAS\": \"0.0000000000000000E+00\",\n          \"CONDCOINHD\": \"00\"\n        },\n        {\n          \"ITM_NUMBER\": \"000010\",\n          \"COND_ST_NO\": \"241\",\n          \"COND_COUNT\": \"01\",\n          \"COND_TYPE\": \"IPVA\",\n          \"COND_VALUE\": \"5.000000000\",\n          \"CURRENCY\": \"\",\n          \"COND_UNIT\": \"\",\n          \"COND_P_UNT\": \"0\",\n          \"CURR_ISO\": \"\",\n          \"CD_UNT_ISO\": \"\",\n          \"REFOBJTYPE\": \"\",\n          \"REFOBJKEY\": \"\",\n          \"REFLOGSYS\": \"\",\n          \"APPLICATIO\": \"V\",\n          \"CONPRICDAT\": \"2020-12-14\",\n          \"CALCTYPCON\": \"A\",\n          \"CONBASEVAL\": \"10.000000000\",\n          \"CONEXCHRAT\": \"0.00000\",\n          \"NUMCONVERT\": \"0\",\n          \"DENOMINATO\": \"0\",\n          \"CONDTYPE\": \"D\",\n          \"STAT_CON\": \"X\",\n          \"SCALETYPE\": \"\",\n          \"ACCRUALS\": \"\",\n          \"CONINVOLST\": \"\",\n          \"CONDORIGIN\": \"A\",\n          \"GROUPCOND\": \"\",\n          \"COND_UPDAT\": \"\",\n          \"ACCESS_SEQ\": \"79\",\n          \"CONDCOUNT\": \"01\",\n          \"ROUNDOFFDI\": \"0.000000000\",\n          \"CONDVALUE\": \"0.500000000\",\n          \"CURRENCY_2\": \"BRL\",\n          \"CURR_ISO_2\": \"BRL\",\n          \"CONDCNTRL\": \"A\",\n          \"CONDISACTI\": \"Y\",\n          \"CONDCLASS\": \"D\",\n          \"FACTBASVAL\": \"0.0000000000000000E+00\",\n          \"SCALEBASIN\": \"\",\n          \"SCALBASVAL\": \"0.000000000\",\n          \"UNITMEASUR\": \"\",\n          \"ISO_UNIT\": \"\",\n          \"CURRENCKEY\": \"\",\n          \"CURRENISO\": \"\",\n          \"CONDINCOMP\": \"\",\n          \"CONDCONFIG\": \"\",\n          \"CONDCHAMAN\": \"\",\n          \"COND_NO\": \"0043113081\",\n          \"TAX_CODE\": \"SD\",\n          \"VARCOND\": \"\",\n          \"ACCOUNTKEY\": \"\",\n          \"ACCOUNT_KE\": \"\",\n          \"WT_WITHCD\": \"\",\n          \"STRUCTCOND\": \"\",\n          \"FACTCONBAS\": \"0.0000000000000000E+00\",\n          \"CONDCOINHD\": \"00\"\n        },\n        {\n          \"ITM_NUMBER\": \"000010\",\n          \"COND_ST_NO\": \"242\",\n          \"COND_COUNT\": \"01\",\n          \"COND_TYPE\": \"IPBS\",\n          \"COND_VALUE\": \"100.000000000\",\n          \"CURRENCY\": \"\",\n          \"COND_UNIT\": \"\",\n          \"COND_P_UNT\": \"0\",\n          \"CURR_ISO\": \"\",\n          \"CD_UNT_ISO\": \"\",\n          \"REFOBJTYPE\": \"\",\n          \"REFOBJKEY\": \"\",\n          \"REFLOGSYS\": \"\",\n          \"APPLICATIO\": \"V\",\n          \"CONPRICDAT\": \"2020-12-14\",\n          \"CALCTYPCON\": \"A\",\n          \"CONBASEVAL\": \"10.000000000\",\n          \"CONEXCHRAT\": \"0.00000\",\n          \"NUMCONVERT\": \"0\",\n          \"DENOMINATO\": \"0\",\n          \"CONDTYPE\": \"D\",\n          \"STAT_CON\": \"X\",\n          \"SCALETYPE\": \"\",\n          \"ACCRUALS\": \"\",\n          \"CONINVOLST\": \"\",\n          \"CONDORIGIN\": \"A\",\n          \"GROUPCOND\": \"\",\n          \"COND_UPDAT\": \"\",\n          \"ACCESS_SEQ\": \"79\",\n          \"CONDCOUNT\": \"01\",\n          \"ROUNDOFFDI\": \"0.000000000\",\n          \"CONDVALUE\": \"10.000000000\",\n          \"CURRENCY_2\": \"BRL\",\n          \"CURR_ISO_2\": \"BRL\",\n          \"CONDCNTRL\": \"A\",\n          \"CONDISACTI\": \"Y\",\n          \"CONDCLASS\": \"D\",\n          \"FACTBASVAL\": \"0.0000000000000000E+00\",\n          \"SCALEBASIN\": \"\",\n          \"SCALBASVAL\": \"0.000000000\",\n          \"UNITMEASUR\": \"\",\n          \"ISO_UNIT\": \"\",\n          \"CURRENCKEY\": \"\",\n          \"CURRENISO\": \"\",\n          \"CONDINCOMP\": \"\",\n          \"CONDCONFIG\": \"\",\n          \"CONDCHAMAN\": \"\",\n          \"COND_NO\": \"0043113082\",\n          \"TAX_CODE\": \"SD\",\n          \"VARCOND\": \"\",\n          \"ACCOUNTKEY\": \"\",\n          \"ACCOUNT_KE\": \"\",\n          \"WT_WITHCD\": \"\",\n          \"STRUCTCOND\": \"\",\n          \"FACTCONBAS\": \"0.0000000000000000E+00\",\n          \"CONDCOINHD\": \"00\"\n        },\n        {\n          \"ITM_NUMBER\": \"000010\",\n          \"COND_ST_NO\": \"243\",\n          \"COND_COUNT\": \"01\",\n          \"COND_TYPE\": \"IPOB\",\n          \"COND_VALUE\": \"0.000000000\",\n          \"CURRENCY\": \"\",\n          \"COND_UNIT\": \"\",\n          \"COND_P_UNT\": \"0\",\n          \"CURR_ISO\": \"\",\n          \"CD_UNT_ISO\": \"\",\n          \"REFOBJTYPE\": \"\",\n          \"REFOBJKEY\": \"\",\n          \"REFLOGSYS\": \"\",\n          \"APPLICATIO\": \"V\",\n          \"CONPRICDAT\": \"2020-12-14\",\n          \"CALCTYPCON\": \"A\",\n          \"CONBASEVAL\": \"10.000000000\",\n          \"CONEXCHRAT\": \"0.00000\",\n          \"NUMCONVERT\": \"0\",\n          \"DENOMINATO\": \"0\",\n          \"CONDTYPE\": \"D\",\n          \"STAT_CON\": \"X\",\n          \"SCALETYPE\": \"\",\n          \"ACCRUALS\": \"\",\n          \"CONINVOLST\": \"\",\n          \"CONDORIGIN\": \"A\",\n          \"GROUPCOND\": \"\",\n          \"COND_UPDAT\": \"\",\n          \"ACCESS_SEQ\": \"79\",\n          \"CONDCOUNT\": \"01\",\n          \"ROUNDOFFDI\": \"0.000000000\",\n          \"CONDVALUE\": \"0.000000000\",\n          \"CURRENCY_2\": \"BRL\",\n          \"CURR_ISO_2\": \"BRL\",\n          \"CONDCNTRL\": \"A\",\n          \"CONDISACTI\": \"Y\",\n          \"CONDCLASS\": \"D\",\n          \"FACTBASVAL\": \"0.0000000000000000E+00\",\n          \"SCALEBASIN\": \"\",\n          \"SCALBASVAL\": \"0.000000000\",\n          \"UNITMEASUR\": \"\",\n          \"ISO_UNIT\": \"\",\n          \"CURRENCKEY\": \"\",\n          \"CURRENISO\": \"\",\n          \"CONDINCOMP\": \"\",\n          \"CONDCONFIG\": \"\",\n          \"CONDCHAMAN\": \"\",\n          \"COND_NO\": \"0043113083\",\n          \"TAX_CODE\": \"SD\",\n          \"VARCOND\": \"\",\n          \"ACCOUNTKEY\": \"\",\n          \"ACCOUNT_KE\": \"\",\n          \"WT_WITHCD\": \"\",\n          \"STRUCTCOND\": \"\",\n          \"FACTCONBAS\": \"0.0000000000000000E+00\",\n          \"CONDCOINHD\": \"00\"\n        },\n        {\n          \"ITM_NUMBER\": \"000010\",\n          \"COND_ST_NO\": \"246\",\n          \"COND_COUNT\": \"01\",\n          \"COND_TYPE\": \"IPLW\",\n          \"COND_VALUE\": \"100.000000000\",\n          \"CURRENCY\": \"\",\n          \"COND_UNIT\": \"\",\n          \"COND_P_UNT\": \"0\",\n          \"CURR_ISO\": \"\",\n          \"CD_UNT_ISO\": \"\",\n          \"REFOBJTYPE\": \"\",\n          \"REFOBJKEY\": \"\",\n          \"REFLOGSYS\": \"\",\n          \"APPLICATIO\": \"V\",\n          \"CONPRICDAT\": \"2020-12-14\",\n          \"CALCTYPCON\": \"A\",\n          \"CONBASEVAL\": \"10.000000000\",\n          \"CONEXCHRAT\": \"0.00000\",\n          \"NUMCONVERT\": \"0\",\n          \"DENOMINATO\": \"0\",\n          \"CONDTYPE\": \"D\",\n          \"STAT_CON\": \"X\",\n          \"SCALETYPE\": \"\",\n          \"ACCRUALS\": \"\",\n          \"CONINVOLST\": \"\",\n          \"CONDORIGIN\": \"A\",\n          \"GROUPCOND\": \"\",\n          \"COND_UPDAT\": \"\",\n          \"ACCESS_SEQ\": \"79\",\n          \"CONDCOUNT\": \"01\",\n          \"ROUNDOFFDI\": \"0.000000000\",\n          \"CONDVALUE\": \"10.000000000\",\n          \"CURRENCY_2\": \"BRL\",\n          \"CURR_ISO_2\": \"BRL\",\n          \"CONDCNTRL\": \"A\",\n          \"CONDISACTI\": \"Y\",\n          \"CONDCLASS\": \"D\",\n          \"FACTBASVAL\": \"0.0000000000000000E+00\",\n          \"SCALEBASIN\": \"\",\n          \"SCALBASVAL\": \"0.000000000\",\n          \"UNITMEASUR\": \"\",\n          \"ISO_UNIT\": \"\",\n          \"CURRENCKEY\": \"\",\n          \"CURRENISO\": \"\",\n          \"CONDINCOMP\": \"\",\n          \"CONDCONFIG\": \"\",\n          \"CONDCHAMAN\": \"\",\n          \"COND_NO\": \"0043113084\",\n          \"TAX_CODE\": \"SD\",\n          \"VARCOND\": \"\",\n          \"ACCOUNTKEY\": \"\",\n          \"ACCOUNT_KE\": \"\",\n          \"WT_WITHCD\": \"\",\n          \"STRUCTCOND\": \"\",\n          \"FACTCONBAS\": \"0.0000000000000000E+00\",\n          \"CONDCOINHD\": \"00\"\n        },\n        {\n          \"ITM_NUMBER\": \"000010\",\n          \"COND_ST_NO\": \"250\",\n          \"COND_COUNT\": \"01\",\n          \"COND_TYPE\": \"DCOF\",\n          \"COND_VALUE\": \"100.000000000\",\n          \"CURRENCY\": \"\",\n          \"COND_UNIT\": \"\",\n          \"COND_P_UNT\": \"0\",\n          \"CURR_ISO\": \"\",\n          \"CD_UNT_ISO\": \"\",\n          \"REFOBJTYPE\": \"\",\n          \"REFOBJKEY\": \"\",\n          \"REFLOGSYS\": \"\",\n          \"APPLICATIO\": \"V\",\n          \"CONPRICDAT\": \"2020-12-14\",\n          \"CALCTYPCON\": \"A\",\n          \"CONBASEVAL\": \"10.000000000\",\n          \"CONEXCHRAT\": \"0.00000\",\n          \"NUMCONVERT\": \"0\",\n          \"DENOMINATO\": \"0\",\n          \"CONDTYPE\": \"D\",\n          \"STAT_CON\": \"X\",\n          \"SCALETYPE\": \"\",\n          \"ACCRUALS\": \"\",\n          \"CONINVOLST\": \"\",\n          \"CONDORIGIN\": \"A\",\n          \"GROUPCOND\": \"\",\n          \"COND_UPDAT\": \"\",\n          \"ACCESS_SEQ\": \"10\",\n          \"CONDCOUNT\": \"01\",\n          \"ROUNDOFFDI\": \"0.000000000\",\n          \"CONDVALUE\": \"10.000000000\",\n          \"CURRENCY_2\": \"BRL\",\n          \"CURR_ISO_2\": \"BRL\",\n          \"CONDCNTRL\": \"A\",\n          \"CONDISACTI\": \"Y\",\n          \"CONDCLASS\": \"D\",\n          \"FACTBASVAL\": \"0.0000000000000000E+00\",\n          \"SCALEBASIN\": \"\",\n          \"SCALBASVAL\": \"0.000000000\",\n          \"UNITMEASUR\": \"\",\n          \"ISO_UNIT\": \"\",\n          \"CURRENCKEY\": \"\",\n          \"CURRENISO\": \"\",\n          \"CONDINCOMP\": \"\",\n          \"CONDCONFIG\": \"\",\n          \"CONDCHAMAN\": \"\",\n          \"COND_NO\": \"0011152508\",\n          \"TAX_CODE\": \"SD\",\n          \"VARCOND\": \"\",\n          \"ACCOUNTKEY\": \"\",\n          \"ACCOUNT_KE\": \"\",\n          \"WT_WITHCD\": \"\",\n          \"STRUCTCOND\": \"\",\n          \"FACTCONBAS\": \"0.0000000000000000E+00\",\n          \"CONDCOINHD\": \"00\"\n        },\n        {\n          \"ITM_NUMBER\": \"000010\",\n          \"COND_ST_NO\": \"251\",\n          \"COND_COUNT\": \"01\",\n          \"COND_TYPE\": \"BCO1\",\n          \"COND_VALUE\": \"7.600000000\",\n          \"CURRENCY\": \"\",\n          \"COND_UNIT\": \"\",\n          \"COND_P_UNT\": \"0\",\n          \"CURR_ISO\": \"\",\n          \"CD_UNT_ISO\": \"\",\n          \"REFOBJTYPE\": \"\",\n          \"REFOBJKEY\": \"\",\n          \"REFLOGSYS\": \"\",\n          \"APPLICATIO\": \"V\",\n          \"CONPRICDAT\": \"2020-12-14\",\n          \"CALCTYPCON\": \"A\",\n          \"CONBASEVAL\": \"10.000000000\",\n          \"CONEXCHRAT\": \"0.00000\",\n          \"NUMCONVERT\": \"0\",\n          \"DENOMINATO\": \"0\",\n          \"CONDTYPE\": \"D\",\n          \"STAT_CON\": \"X\",\n          \"SCALETYPE\": \"\",\n          \"ACCRUALS\": \"\",\n          \"CONINVOLST\": \"\",\n          \"CONDORIGIN\": \"A\",\n          \"GROUPCOND\": \"\",\n          \"COND_UPDAT\": \"\",\n          \"ACCESS_SEQ\": \"89\",\n          \"CONDCOUNT\": \"01\",\n          \"ROUNDOFFDI\": \"0.000000000\",\n          \"CONDVALUE\": \"0.760000000\",\n          \"CURRENCY_2\": \"BRL\",\n          \"CURR_ISO_2\": \"BRL\",\n          \"CONDCNTRL\": \"A\",\n          \"CONDISACTI\": \"Y\",\n          \"CONDCLASS\": \"D\",\n          \"FACTBASVAL\": \"0.0000000000000000E+00\",\n          \"SCALEBASIN\": \"\",\n          \"SCALBASVAL\": \"0.000000000\",\n          \"UNITMEASUR\": \"\",\n          \"ISO_UNIT\": \"\",\n          \"CURRENCKEY\": \"\",\n          \"CURRENISO\": \"\",\n          \"CONDINCOMP\": \"\",\n          \"CONDCONFIG\": \"\",\n          \"CONDCHAMAN\": \"\",\n          \"COND_NO\": \"0023891241\",\n          \"TAX_CODE\": \"SD\",\n          \"VARCOND\": \"\",\n          \"ACCOUNTKEY\": \"\",\n          \"ACCOUNT_KE\": \"\",\n          \"WT_WITHCD\": \"\",\n          \"STRUCTCOND\": \"\",\n          \"FACTCONBAS\": \"0.0000000000000000E+00\",\n          \"CONDCOINHD\": \"00\"\n        },\n        {\n          \"ITM_NUMBER\": \"000010\",\n          \"COND_ST_NO\": \"252\",\n          \"COND_COUNT\": \"01\",\n          \"COND_TYPE\": \"BCO2\",\n          \"COND_VALUE\": \"100.000000000\",\n          \"CURRENCY\": \"\",\n          \"COND_UNIT\": \"\",\n          \"COND_P_UNT\": \"0\",\n          \"CURR_ISO\": \"\",\n          \"CD_UNT_ISO\": \"\",\n          \"REFOBJTYPE\": \"\",\n          \"REFOBJKEY\": \"\",\n          \"REFLOGSYS\": \"\",\n          \"APPLICATIO\": \"V\",\n          \"CONPRICDAT\": \"2020-12-14\",\n          \"CALCTYPCON\": \"A\",\n          \"CONBASEVAL\": \"10.000000000\",\n          \"CONEXCHRAT\": \"0.00000\",\n          \"NUMCONVERT\": \"0\",\n          \"DENOMINATO\": \"0\",\n          \"CONDTYPE\": \"D\",\n          \"STAT_CON\": \"X\",\n          \"SCALETYPE\": \"\",\n          \"ACCRUALS\": \"\",\n          \"CONINVOLST\": \"\",\n          \"CONDORIGIN\": \"A\",\n          \"GROUPCOND\": \"\",\n          \"COND_UPDAT\": \"\",\n          \"ACCESS_SEQ\": \"89\",\n          \"CONDCOUNT\": \"01\",\n          \"ROUNDOFFDI\": \"0.000000000\",\n          \"CONDVALUE\": \"10.000000000\",\n          \"CURRENCY_2\": \"BRL\",\n          \"CURR_ISO_2\": \"BRL\",\n          \"CONDCNTRL\": \"A\",\n          \"CONDISACTI\": \"Y\",\n          \"CONDCLASS\": \"D\",\n          \"FACTBASVAL\": \"0.0000000000000000E+00\",\n          \"SCALEBASIN\": \"\",\n          \"SCALBASVAL\": \"0.000000000\",\n          \"UNITMEASUR\": \"\",\n          \"ISO_UNIT\": \"\",\n          \"CURRENCKEY\": \"\",\n          \"CURRENISO\": \"\",\n          \"CONDINCOMP\": \"\",\n          \"CONDCONFIG\": \"\",\n          \"CONDCHAMAN\": \"\",\n          \"COND_NO\": \"0023891242\",\n          \"TAX_CODE\": \"SD\",\n          \"VARCOND\": \"\",\n          \"ACCOUNTKEY\": \"\",\n          \"ACCOUNT_KE\": \"\",\n          \"WT_WITHCD\": \"\",\n          \"STRUCTCOND\": \"\",\n          \"FACTCONBAS\": \"0.0000000000000000E+00\",\n          \"CONDCOINHD\": \"00\"\n        },\n        {\n          \"ITM_NUMBER\": \"000010\",\n          \"COND_ST_NO\": \"255\",\n          \"COND_COUNT\": \"01\",\n          \"COND_TYPE\": \"DPIS\",\n          \"COND_VALUE\": \"100.000000000\",\n          \"CURRENCY\": \"\",\n          \"COND_UNIT\": \"\",\n          \"COND_P_UNT\": \"0\",\n          \"CURR_ISO\": \"\",\n          \"CD_UNT_ISO\": \"\",\n          \"REFOBJTYPE\": \"\",\n          \"REFOBJKEY\": \"\",\n          \"REFLOGSYS\": \"\",\n          \"APPLICATIO\": \"V\",\n          \"CONPRICDAT\": \"2020-12-14\",\n          \"CALCTYPCON\": \"A\",\n          \"CONBASEVAL\": \"10.000000000\",\n          \"CONEXCHRAT\": \"0.00000\",\n          \"NUMCONVERT\": \"0\",\n          \"DENOMINATO\": \"0\",\n          \"CONDTYPE\": \"D\",\n          \"STAT_CON\": \"X\",\n          \"SCALETYPE\": \"\",\n          \"ACCRUALS\": \"\",\n          \"CONINVOLST\": \"\",\n          \"CONDORIGIN\": \"A\",\n          \"GROUPCOND\": \"\",\n          \"COND_UPDAT\": \"\",\n          \"ACCESS_SEQ\": \"10\",\n          \"CONDCOUNT\": \"01\",\n          \"ROUNDOFFDI\": \"0.000000000\",\n          \"CONDVALUE\": \"10.000000000\",\n          \"CURRENCY_2\": \"BRL\",\n          \"CURR_ISO_2\": \"BRL\",\n          \"CONDCNTRL\": \"A\",\n          \"CONDISACTI\": \"Y\",\n          \"CONDCLASS\": \"D\",\n          \"FACTBASVAL\": \"0.0000000000000000E+00\",\n          \"SCALEBASIN\": \"\",\n          \"SCALBASVAL\": \"0.000000000\",\n          \"UNITMEASUR\": \"\",\n          \"ISO_UNIT\": \"\",\n          \"CURRENCKEY\": \"\",\n          \"CURRENISO\": \"\",\n          \"CONDINCOMP\": \"\",\n          \"CONDCONFIG\": \"\",\n          \"CONDCHAMAN\": \"\",\n          \"COND_NO\": \"0011153563\",\n          \"TAX_CODE\": \"SD\",\n          \"VARCOND\": \"\",\n          \"ACCOUNTKEY\": \"\",\n          \"ACCOUNT_KE\": \"\",\n          \"WT_WITHCD\": \"\",\n          \"STRUCTCOND\": \"\",\n          \"FACTCONBAS\": \"0.0000000000000000E+00\",\n          \"CONDCOINHD\": \"00\"\n        },\n        {\n          \"ITM_NUMBER\": \"000010\",\n          \"COND_ST_NO\": \"256\",\n          \"COND_COUNT\": \"01\",\n          \"COND_TYPE\": \"BPI1\",\n          \"COND_VALUE\": \"1.650000000\",\n          \"CURRENCY\": \"\",\n          \"COND_UNIT\": \"\",\n          \"COND_P_UNT\": \"0\",\n          \"CURR_ISO\": \"\",\n          \"CD_UNT_ISO\": \"\",\n          \"REFOBJTYPE\": \"\",\n          \"REFOBJKEY\": \"\",\n          \"REFLOGSYS\": \"\",\n          \"APPLICATIO\": \"V\",\n          \"CONPRICDAT\": \"2020-12-14\",\n          \"CALCTYPCON\": \"A\",\n          \"CONBASEVAL\": \"10.000000000\",\n          \"CONEXCHRAT\": \"0.00000\",\n          \"NUMCONVERT\": \"0\",\n          \"DENOMINATO\": \"0\",\n          \"CONDTYPE\": \"D\",\n          \"STAT_CON\": \"X\",\n          \"SCALETYPE\": \"\",\n          \"ACCRUALS\": \"\",\n          \"CONINVOLST\": \"\",\n          \"CONDORIGIN\": \"A\",\n          \"GROUPCOND\": \"\",\n          \"COND_UPDAT\": \"\",\n          \"ACCESS_SEQ\": \"89\",\n          \"CONDCOUNT\": \"01\",\n          \"ROUNDOFFDI\": \"0.000000000\",\n          \"CONDVALUE\": \"0.170000000\",\n          \"CURRENCY_2\": \"BRL\",\n          \"CURR_ISO_2\": \"BRL\",\n          \"CONDCNTRL\": \"A\",\n          \"CONDISACTI\": \"Y\",\n          \"CONDCLASS\": \"D\",\n          \"FACTBASVAL\": \"0.0000000000000000E+00\",\n          \"SCALEBASIN\": \"\",\n          \"SCALBASVAL\": \"0.000000000\",\n          \"UNITMEASUR\": \"\",\n          \"ISO_UNIT\": \"\",\n          \"CURRENCKEY\": \"\",\n          \"CURRENISO\": \"\",\n          \"CONDINCOMP\": \"\",\n          \"CONDCONFIG\": \"\",\n          \"CONDCHAMAN\": \"\",\n          \"COND_NO\": \"0023924157\",\n          \"TAX_CODE\": \"SD\",\n          \"VARCOND\": \"\",\n          \"ACCOUNTKEY\": \"\",\n          \"ACCOUNT_KE\": \"\",\n          \"WT_WITHCD\": \"\",\n          \"STRUCTCOND\": \"\",\n          \"FACTCONBAS\": \"0.0000000000000000E+00\",\n          \"CONDCOINHD\": \"00\"\n        },\n        {\n          \"ITM_NUMBER\": \"000010\",\n          \"COND_ST_NO\": \"257\",\n          \"COND_COUNT\": \"01\",\n          \"COND_TYPE\": \"BPI2\",\n          \"COND_VALUE\": \"100.000000000\",\n          \"CURRENCY\": \"\",\n          \"COND_UNIT\": \"\",\n          \"COND_P_UNT\": \"0\",\n          \"CURR_ISO\": \"\",\n          \"CD_UNT_ISO\": \"\",\n          \"REFOBJTYPE\": \"\",\n          \"REFOBJKEY\": \"\",\n          \"REFLOGSYS\": \"\",\n          \"APPLICATIO\": \"V\",\n          \"CONPRICDAT\": \"2020-12-14\",\n          \"CALCTYPCON\": \"A\",\n          \"CONBASEVAL\": \"10.000000000\",\n          \"CONEXCHRAT\": \"0.00000\",\n          \"NUMCONVERT\": \"0\",\n          \"DENOMINATO\": \"0\",\n          \"CONDTYPE\": \"D\",\n          \"STAT_CON\": \"X\",\n          \"SCALETYPE\": \"\",\n          \"ACCRUALS\": \"\",\n          \"CONINVOLST\": \"\",\n          \"CONDORIGIN\": \"A\",\n          \"GROUPCOND\": \"\",\n          \"COND_UPDAT\": \"\",\n          \"ACCESS_SEQ\": \"89\",\n          \"CONDCOUNT\": \"01\",\n          \"ROUNDOFFDI\": \"0.000000000\",\n          \"CONDVALUE\": \"10.000000000\",\n          \"CURRENCY_2\": \"BRL\",\n          \"CURR_ISO_2\": \"BRL\",\n          \"CONDCNTRL\": \"A\",\n          \"CONDISACTI\": \"Y\",\n          \"CONDCLASS\": \"D\",\n          \"FACTBASVAL\": \"0.0000000000000000E+00\",\n          \"SCALEBASIN\": \"\",\n          \"SCALBASVAL\": \"0.000000000\",\n          \"UNITMEASUR\": \"\",\n          \"ISO_UNIT\": \"\",\n          \"CURRENCKEY\": \"\",\n          \"CURRENISO\": \"\",\n          \"CONDINCOMP\": \"\",\n          \"CONDCONFIG\": \"\",\n          \"CONDCHAMAN\": \"\",\n          \"COND_NO\": \"0023924158\",\n          \"TAX_CODE\": \"SD\",\n          \"VARCOND\": \"\",\n          \"ACCOUNTKEY\": \"\",\n          \"ACCOUNT_KE\": \"\",\n          \"WT_WITHCD\": \"\",\n          \"STRUCTCOND\": \"\",\n          \"FACTCONBAS\": \"0.0000000000000000E+00\",\n          \"CONDCOINHD\": \"00\"\n        },\n        {\n          \"ITM_NUMBER\": \"000010\",\n          \"COND_ST_NO\": \"280\",\n          \"COND_COUNT\": \"01\",\n          \"COND_TYPE\": \"DSUB\",\n          \"COND_VALUE\": \"100.000000000\",\n          \"CURRENCY\": \"\",\n          \"COND_UNIT\": \"\",\n          \"COND_P_UNT\": \"0\",\n          \"CURR_ISO\": \"\",\n          \"CD_UNT_ISO\": \"\",\n          \"REFOBJTYPE\": \"\",\n          \"REFOBJKEY\": \"\",\n          \"REFLOGSYS\": \"\",\n          \"APPLICATIO\": \"V\",\n          \"CONPRICDAT\": \"2020-12-14\",\n          \"CALCTYPCON\": \"A\",\n          \"CONBASEVAL\": \"10.000000000\",\n          \"CONEXCHRAT\": \"0.00000\",\n          \"NUMCONVERT\": \"0\",\n          \"DENOMINATO\": \"0\",\n          \"CONDTYPE\": \"D\",\n          \"STAT_CON\": \"X\",\n          \"SCALETYPE\": \"\",\n          \"ACCRUALS\": \"\",\n          \"CONINVOLST\": \"\",\n          \"CONDORIGIN\": \"A\",\n          \"GROUPCOND\": \"\",\n          \"COND_UPDAT\": \"\",\n          \"ACCESS_SEQ\": \"10\",\n          \"CONDCOUNT\": \"01\",\n          \"ROUNDOFFDI\": \"0.000000000\",\n          \"CONDVALUE\": \"10.000000000\",\n          \"CURRENCY_2\": \"BRL\",\n          \"CURR_ISO_2\": \"BRL\",\n          \"CONDCNTRL\": \"A\",\n          \"CONDISACTI\": \"Y\",\n          \"CONDCLASS\": \"D\",\n          \"FACTBASVAL\": \"0.0000000000000000E+00\",\n          \"SCALEBASIN\": \"\",\n          \"SCALBASVAL\": \"0.000000000\",\n          \"UNITMEASUR\": \"\",\n          \"ISO_UNIT\": \"\",\n          \"CURRENCKEY\": \"\",\n          \"CURRENISO\": \"\",\n          \"CONDINCOMP\": \"\",\n          \"CONDCONFIG\": \"\",\n          \"CONDCHAMAN\": \"\",\n          \"COND_NO\": \"0011208403\",\n          \"TAX_CODE\": \"SD\",\n          \"VARCOND\": \"\",\n          \"ACCOUNTKEY\": \"\",\n          \"ACCOUNT_KE\": \"\",\n          \"WT_WITHCD\": \"\",\n          \"STRUCTCOND\": \"\",\n          \"FACTCONBAS\": \"0.0000000000000000E+00\",\n          \"CONDCOINHD\": \"00\"\n        },\n        {\n          \"ITM_NUMBER\": \"000010\",\n          \"COND_ST_NO\": \"300\",\n          \"COND_COUNT\": \"01\",\n          \"COND_TYPE\": \"ICMI\",\n          \"COND_VALUE\": \"164.690000000\",\n          \"CURRENCY\": \"BRL\",\n          \"COND_UNIT\": \"CS\",\n          \"COND_P_UNT\": \"1\",\n          \"CURR_ISO\": \"BRL\",\n          \"CD_UNT_ISO\": \"CS\",\n          \"REFOBJTYPE\": \"\",\n          \"REFOBJKEY\": \"\",\n          \"REFLOGSYS\": \"\",\n          \"APPLICATIO\": \"V\",\n          \"CONPRICDAT\": \"2020-12-14\",\n          \"CALCTYPCON\": \"C\",\n          \"CONBASEVAL\": \"1.000000000\",\n          \"CONEXCHRAT\": \"1.00000\",\n          \"NUMCONVERT\": \"1\",\n          \"DENOMINATO\": \"1\",\n          \"CONDTYPE\": \"\",\n          \"STAT_CON\": \"\",\n          \"SCALETYPE\": \"\",\n          \"ACCRUALS\": \"\",\n          \"CONINVOLST\": \"\",\n          \"CONDORIGIN\": \"A\",\n          \"GROUPCOND\": \"\",\n          \"COND_UPDAT\": \"\",\n          \"ACCESS_SEQ\": \"00\",\n          \"CONDCOUNT\": \"00\",\n          \"ROUNDOFFDI\": \"0.000000000\",\n          \"CONDVALUE\": \"164.690000000\",\n          \"CURRENCY_2\": \"BRL\",\n          \"CURR_ISO_2\": \"BRL\",\n          \"CONDCNTRL\": \"A\",\n          \"CONDISACTI\": \"\",\n          \"CONDCLASS\": \"B\",\n          \"FACTBASVAL\": \"0.0000000000000000E+00\",\n          \"SCALEBASIN\": \"\",\n          \"SCALBASVAL\": \"0.000000000\",\n          \"UNITMEASUR\": \"\",\n          \"ISO_UNIT\": \"\",\n          \"CURRENCKEY\": \"\",\n          \"CURRENISO\": \"\",\n          \"CONDINCOMP\": \"\",\n          \"CONDCONFIG\": \"\",\n          \"CONDCHAMAN\": \"\",\n          \"COND_NO\": \"\",\n          \"TAX_CODE\": \"\",\n          \"VARCOND\": \"\",\n          \"ACCOUNTKEY\": \"\",\n          \"ACCOUNT_KE\": \"\",\n          \"WT_WITHCD\": \"\",\n          \"STRUCTCOND\": \"\",\n          \"FACTCONBAS\": \"0.0000000000000000E+00\",\n          \"CONDCOINHD\": \"00\"\n        },\n        {\n          \"ITM_NUMBER\": \"000010\",\n          \"COND_ST_NO\": \"305\",\n          \"COND_COUNT\": \"01\",\n          \"COND_TYPE\": \"ZICI\",\n          \"COND_VALUE\": \"164.690000000\",\n          \"CURRENCY\": \"BRL\",\n          \"COND_UNIT\": \"CS\",\n          \"COND_P_UNT\": \"1\",\n          \"CURR_ISO\": \"BRL\",\n          \"CD_UNT_ISO\": \"CS\",\n          \"REFOBJTYPE\": \"\",\n          \"REFOBJKEY\": \"\",\n          \"REFLOGSYS\": \"\",\n          \"APPLICATIO\": \"V\",\n          \"CONPRICDAT\": \"2020-12-14\",\n          \"CALCTYPCON\": \"C\",\n          \"CONBASEVAL\": \"1.000000000\",\n          \"CONEXCHRAT\": \"1.00000\",\n          \"NUMCONVERT\": \"1\",\n          \"DENOMINATO\": \"1\",\n          \"CONDTYPE\": \"\",\n          \"STAT_CON\": \"X\",\n          \"SCALETYPE\": \"\",\n          \"ACCRUALS\": \"\",\n          \"CONINVOLST\": \"\",\n          \"CONDORIGIN\": \"A\",\n          \"GROUPCOND\": \"\",\n          \"COND_UPDAT\": \"\",\n          \"ACCESS_SEQ\": \"00\",\n          \"CONDCOUNT\": \"00\",\n          \"ROUNDOFFDI\": \"0.000000000\",\n          \"CONDVALUE\": \"164.690000000\",\n          \"CURRENCY_2\": \"BRL\",\n          \"CURR_ISO_2\": \"BRL\",\n          \"CONDCNTRL\": \"A\",\n          \"CONDISACTI\": \"\",\n          \"CONDCLASS\": \"B\",\n          \"FACTBASVAL\": \"0.0000000000000000E+00\",\n          \"SCALEBASIN\": \"\",\n          \"SCALBASVAL\": \"0.000000000\",\n          \"UNITMEASUR\": \"\",\n          \"ISO_UNIT\": \"\",\n          \"CURRENCKEY\": \"\",\n          \"CURRENISO\": \"\",\n          \"CONDINCOMP\": \"\",\n          \"CONDCONFIG\": \"\",\n          \"CONDCHAMAN\": \"\",\n          \"COND_NO\": \"\",\n          \"TAX_CODE\": \"\",\n          \"VARCOND\": \"\",\n          \"ACCOUNTKEY\": \"\",\n          \"ACCOUNT_KE\": \"\",\n          \"WT_WITHCD\": \"\",\n          \"STRUCTCOND\": \"\",\n          \"FACTCONBAS\": \"0.0000000000000000E+00\",\n          \"CONDCOINHD\": \"00\"\n        },\n        {\n          \"ITM_NUMBER\": \"000010\",\n          \"COND_ST_NO\": \"310\",\n          \"COND_COUNT\": \"01\",\n          \"COND_TYPE\": \"ZICD\",\n          \"COND_VALUE\": \"-100.000000000\",\n          \"CURRENCY\": \"\",\n          \"COND_UNIT\": \"\",\n          \"COND_P_UNT\": \"0\",\n          \"CURR_ISO\": \"\",\n          \"CD_UNT_ISO\": \"\",\n          \"REFOBJTYPE\": \"\",\n          \"REFOBJKEY\": \"\",\n          \"REFLOGSYS\": \"\",\n          \"APPLICATIO\": \"V\",\n          \"CONPRICDAT\": \"2020-12-14\",\n          \"CALCTYPCON\": \"A\",\n          \"CONBASEVAL\": \"164.690000000\",\n          \"CONEXCHRAT\": \"0.00000\",\n          \"NUMCONVERT\": \"0\",\n          \"DENOMINATO\": \"0\",\n          \"CONDTYPE\": \"D\",\n          \"STAT_CON\": \"\",\n          \"SCALETYPE\": \"\",\n          \"ACCRUALS\": \"\",\n          \"CONINVOLST\": \"\",\n          \"CONDORIGIN\": \"A\",\n          \"GROUPCOND\": \"\",\n          \"COND_UPDAT\": \"\",\n          \"ACCESS_SEQ\": \"01\",\n          \"CONDCOUNT\": \"01\",\n          \"ROUNDOFFDI\": \"0.000000000\",\n          \"CONDVALUE\": \"0.000000000\",\n          \"CURRENCY_2\": \"BRL\",\n          \"CURR_ISO_2\": \"BRL\",\n          \"CONDCNTRL\": \"A\",\n          \"CONDISACTI\": \"\",\n          \"CONDCLASS\": \"A\",\n          \"FACTBASVAL\": \"0.0000000000000000E+00\",\n          \"SCALEBASIN\": \"\",\n          \"SCALBASVAL\": \"0.000000000\",\n          \"UNITMEASUR\": \"\",\n          \"ISO_UNIT\": \"\",\n          \"CURRENCKEY\": \"\",\n          \"CURRENISO\": \"\",\n          \"CONDINCOMP\": \"\",\n          \"CONDCONFIG\": \"\",\n          \"CONDCHAMAN\": \"\",\n          \"COND_NO\": \"0011863741\",\n          \"TAX_CODE\": \"\",\n          \"VARCOND\": \"\",\n          \"ACCOUNTKEY\": \"\",\n          \"ACCOUNT_KE\": \"\",\n          \"WT_WITHCD\": \"\",\n          \"STRUCTCOND\": \"\",\n          \"FACTCONBAS\": \"0.0000000000000000E+00\",\n          \"CONDCOINHD\": \"00\"\n        },\n        {\n          \"ITM_NUMBER\": \"000010\",\n          \"COND_ST_NO\": \"340\",\n          \"COND_COUNT\": \"01\",\n          \"COND_TYPE\": \"Z060\",\n          \"COND_VALUE\": \"0.000000000\",\n          \"CURRENCY\": \"\",\n          \"COND_UNIT\": \"\",\n          \"COND_P_UNT\": \"0\",\n          \"CURR_ISO\": \"\",\n          \"CD_UNT_ISO\": \"\",\n          \"REFOBJTYPE\": \"\",\n          \"REFOBJKEY\": \"\",\n          \"REFLOGSYS\": \"\",\n          \"APPLICATIO\": \"V\",\n          \"CONPRICDAT\": \"2020-12-14\",\n          \"CALCTYPCON\": \"A\",\n          \"CONBASEVAL\": \"164.690000000\",\n          \"CONEXCHRAT\": \"0.00000\",\n          \"NUMCONVERT\": \"0\",\n          \"DENOMINATO\": \"0\",\n          \"CONDTYPE\": \"\",\n          \"STAT_CON\": \"\",\n          \"SCALETYPE\": \"\",\n          \"ACCRUALS\": \"\",\n          \"CONINVOLST\": \"\",\n          \"CONDORIGIN\": \"A\",\n          \"GROUPCOND\": \"\",\n          \"COND_UPDAT\": \"\",\n          \"ACCESS_SEQ\": \"15\",\n          \"CONDCOUNT\": \"01\",\n          \"ROUNDOFFDI\": \"0.000000000\",\n          \"CONDVALUE\": \"0.000000000\",\n          \"CURRENCY_2\": \"BRL\",\n          \"CURR_ISO_2\": \"BRL\",\n          \"CONDCNTRL\": \"A\",\n          \"CONDISACTI\": \"\",\n          \"CONDCLASS\": \"A\",\n          \"FACTBASVAL\": \"0.0000000000000000E+00\",\n          \"SCALEBASIN\": \"B\",\n          \"SCALBASVAL\": \"164.690000000\",\n          \"UNITMEASUR\": \"\",\n          \"ISO_UNIT\": \"\",\n          \"CURRENCKEY\": \"BRL\",\n          \"CURRENISO\": \"BRL\",\n          \"CONDINCOMP\": \"\",\n          \"CONDCONFIG\": \"\",\n          \"CONDCHAMAN\": \"\",\n          \"COND_NO\": \"0000741815\",\n          \"TAX_CODE\": \"\",\n          \"VARCOND\": \"\",\n          \"ACCOUNTKEY\": \"\",\n          \"ACCOUNT_KE\": \"\",\n          \"WT_WITHCD\": \"\",\n          \"STRUCTCOND\": \"\",\n          \"FACTCONBAS\": \"0.0000000000000000E+00\",\n          \"CONDCOINHD\": \"00\"\n        },\n        {\n          \"ITM_NUMBER\": \"000010\",\n          \"COND_ST_NO\": \"600\",\n          \"COND_COUNT\": \"01\",\n          \"COND_TYPE\": \"IBRX\",\n          \"COND_VALUE\": \"100.000000000\",\n          \"CURRENCY\": \"\",\n          \"COND_UNIT\": \"\",\n          \"COND_P_UNT\": \"0\",\n          \"CURR_ISO\": \"\",\n          \"CD_UNT_ISO\": \"\",\n          \"REFOBJTYPE\": \"\",\n          \"REFOBJKEY\": \"\",\n          \"REFLOGSYS\": \"\",\n          \"APPLICATIO\": \"V\",\n          \"CONPRICDAT\": \"2020-12-14\",\n          \"CALCTYPCON\": \"A\",\n          \"CONBASEVAL\": \"164.690000000\",\n          \"CONEXCHRAT\": \"0.00000\",\n          \"NUMCONVERT\": \"0\",\n          \"DENOMINATO\": \"0\",\n          \"CONDTYPE\": \"1\",\n          \"STAT_CON\": \"X\",\n          \"SCALETYPE\": \"\",\n          \"ACCRUALS\": \"\",\n          \"CONINVOLST\": \"\",\n          \"CONDORIGIN\": \"A\",\n          \"GROUPCOND\": \"\",\n          \"COND_UPDAT\": \"\",\n          \"ACCESS_SEQ\": \"01\",\n          \"CONDCOUNT\": \"01\",\n          \"ROUNDOFFDI\": \"0.000000000\",\n          \"CONDVALUE\": \"164.690000000\",\n          \"CURRENCY_2\": \"BRL\",\n          \"CURR_ISO_2\": \"BRL\",\n          \"CONDCNTRL\": \"A\",\n          \"CONDISACTI\": \"\",\n          \"CONDCLASS\": \"D\",\n          \"FACTBASVAL\": \"0.0000000000000000E+00\",\n          \"SCALEBASIN\": \"\",\n          \"SCALBASVAL\": \"0.000000000\",\n          \"UNITMEASUR\": \"\",\n          \"ISO_UNIT\": \"\",\n          \"CURRENCKEY\": \"\",\n          \"CURRENISO\": \"\",\n          \"CONDINCOMP\": \"\",\n          \"CONDCONFIG\": \"\",\n          \"CONDCHAMAN\": \"\",\n          \"COND_NO\": \"0035482469\",\n          \"TAX_CODE\": \"SD\",\n          \"VARCOND\": \"\",\n          \"ACCOUNTKEY\": \"\",\n          \"ACCOUNT_KE\": \"\",\n          \"WT_WITHCD\": \"\",\n          \"STRUCTCOND\": \"\",\n          \"FACTCONBAS\": \"0.0000000000000000E+00\",\n          \"CONDCOINHD\": \"00\"\n        },\n        {\n          \"ITM_NUMBER\": \"000010\",\n          \"COND_ST_NO\": \"610\",\n          \"COND_COUNT\": \"01\",\n          \"COND_TYPE\": \"BX10\",\n          \"COND_VALUE\": \"0.000000000\",\n          \"CURRENCY\": \"BRL\",\n          \"COND_UNIT\": \"\",\n          \"COND_P_UNT\": \"0\",\n          \"CURR_ISO\": \"BRL\",\n          \"CD_UNT_ISO\": \"\",\n          \"REFOBJTYPE\": \"\",\n          \"REFOBJKEY\": \"\",\n          \"REFLOGSYS\": \"\",\n          \"APPLICATIO\": \"V\",\n          \"CONPRICDAT\": \"2020-12-14\",\n          \"CALCTYPCON\": \"B\",\n          \"CONBASEVAL\": \"329.380000000\",\n          \"CONEXCHRAT\": \"1.00000\",\n          \"NUMCONVERT\": \"0\",\n          \"DENOMINATO\": \"0\",\n          \"CONDTYPE\": \"1\",\n          \"STAT_CON\": \"X\",\n          \"SCALETYPE\": \"\",\n          \"ACCRUALS\": \"\",\n          \"CONINVOLST\": \"\",\n          \"CONDORIGIN\": \"A\",\n          \"GROUPCOND\": \"\",\n          \"COND_UPDAT\": \"\",\n          \"ACCESS_SEQ\": \"00\",\n          \"CONDCOUNT\": \"00\",\n          \"ROUNDOFFDI\": \"0.000000000\",\n          \"CONDVALUE\": \"172.920000000\",\n          \"CURRENCY_2\": \"BRL\",\n          \"CURR_ISO_2\": \"BRL\",\n          \"CONDCNTRL\": \"A\",\n          \"CONDISACTI\": \"\",\n          \"CONDCLASS\": \"A\",\n          \"FACTBASVAL\": \"0.0000000000000000E+00\",\n          \"SCALEBASIN\": \"\",\n          \"SCALBASVAL\": \"0.000000000\",\n          \"UNITMEASUR\": \"\",\n          \"ISO_UNIT\": \"\",\n          \"CURRENCKEY\": \"\",\n          \"CURRENISO\": \"\",\n          \"CONDINCOMP\": \"\",\n          \"CONDCONFIG\": \"\",\n          \"CONDCHAMAN\": \"\",\n          \"COND_NO\": \"\",\n          \"TAX_CODE\": \"\",\n          \"VARCOND\": \"\",\n          \"ACCOUNTKEY\": \"\",\n          \"ACCOUNT_KE\": \"\",\n          \"WT_WITHCD\": \"\",\n          \"STRUCTCOND\": \"\",\n          \"FACTCONBAS\": \"0.0000000000000000E+00\",\n          \"CONDCOINHD\": \"00\"\n        },\n        {\n          \"ITM_NUMBER\": \"000010\",\n          \"COND_ST_NO\": \"612\",\n          \"COND_COUNT\": \"01\",\n          \"COND_TYPE\": \"BX11\",\n          \"COND_VALUE\": \"0.000000000\",\n          \"CURRENCY\": \"BRL\",\n          \"COND_UNIT\": \"\",\n          \"COND_P_UNT\": \"0\",\n          \"CURR_ISO\": \"BRL\",\n          \"CD_UNT_ISO\": \"\",\n          \"REFOBJTYPE\": \"\",\n          \"REFOBJKEY\": \"\",\n          \"REFLOGSYS\": \"\",\n          \"APPLICATIO\": \"V\",\n          \"CONPRICDAT\": \"2020-12-14\",\n          \"CALCTYPCON\": \"B\",\n          \"CONBASEVAL\": \"502.300000000\",\n          \"CONEXCHRAT\": \"1.00000\",\n          \"NUMCONVERT\": \"0\",\n          \"DENOMINATO\": \"0\",\n          \"CONDTYPE\": \"1\",\n          \"STAT_CON\": \"X\",\n          \"SCALETYPE\": \"\",\n          \"ACCRUALS\": \"\",\n          \"CONINVOLST\": \"\",\n          \"CONDORIGIN\": \"A\",\n          \"GROUPCOND\": \"\",\n          \"COND_UPDAT\": \"\",\n          \"ACCESS_SEQ\": \"00\",\n          \"CONDCOUNT\": \"00\",\n          \"ROUNDOFFDI\": \"0.000000000\",\n          \"CONDVALUE\": \"0.000000000\",\n          \"CURRENCY_2\": \"BRL\",\n          \"CURR_ISO_2\": \"BRL\",\n          \"CONDCNTRL\": \"A\",\n          \"CONDISACTI\": \"\",\n          \"CONDCLASS\": \"A\",\n          \"FACTBASVAL\": \"0.0000000000000000E+00\",\n          \"SCALEBASIN\": \"\",\n          \"SCALBASVAL\": \"0.000000000\",\n          \"UNITMEASUR\": \"\",\n          \"ISO_UNIT\": \"\",\n          \"CURRENCKEY\": \"\",\n          \"CURRENISO\": \"\",\n          \"CONDINCOMP\": \"\",\n          \"CONDCONFIG\": \"\",\n          \"CONDCHAMAN\": \"\",\n          \"COND_NO\": \"\",\n          \"TAX_CODE\": \"\",\n          \"VARCOND\": \"\",\n          \"ACCOUNTKEY\": \"\",\n          \"ACCOUNT_KE\": \"\",\n          \"WT_WITHCD\": \"\",\n          \"STRUCTCOND\": \"\",\n          \"FACTCONBAS\": \"0.0000000000000000E+00\",\n          \"CONDCOINHD\": \"00\"\n        },\n        {\n          \"ITM_NUMBER\": \"000010\",\n          \"COND_ST_NO\": \"614\",\n          \"COND_COUNT\": \"01\",\n          \"COND_TYPE\": \"BX12\",\n          \"COND_VALUE\": \"0.000000000\",\n          \"CURRENCY\": \"BRL\",\n          \"COND_UNIT\": \"\",\n          \"COND_P_UNT\": \"0\",\n          \"CURR_ISO\": \"BRL\",\n          \"CD_UNT_ISO\": \"\",\n          \"REFOBJTYPE\": \"\",\n          \"REFOBJKEY\": \"\",\n          \"REFLOGSYS\": \"\",\n          \"APPLICATIO\": \"V\",\n          \"CONPRICDAT\": \"2020-12-14\",\n          \"CALCTYPCON\": \"B\",\n          \"CONBASEVAL\": \"502.300000000\",\n          \"CONEXCHRAT\": \"1.00000\",\n          \"NUMCONVERT\": \"0\",\n          \"DENOMINATO\": \"0\",\n          \"CONDTYPE\": \"1\",\n          \"STAT_CON\": \"X\",\n          \"SCALETYPE\": \"\",\n          \"ACCRUALS\": \"\",\n          \"CONINVOLST\": \"\",\n          \"CONDORIGIN\": \"A\",\n          \"GROUPCOND\": \"\",\n          \"COND_UPDAT\": \"\",\n          \"ACCESS_SEQ\": \"00\",\n          \"CONDCOUNT\": \"00\",\n          \"ROUNDOFFDI\": \"0.000000000\",\n          \"CONDVALUE\": \"0.000000000\",\n          \"CURRENCY_2\": \"BRL\",\n          \"CURR_ISO_2\": \"BRL\",\n          \"CONDCNTRL\": \"A\",\n          \"CONDISACTI\": \"\",\n          \"CONDCLASS\": \"A\",\n          \"FACTBASVAL\": \"0.0000000000000000E+00\",\n          \"SCALEBASIN\": \"\",\n          \"SCALBASVAL\": \"0.000000000\",\n          \"UNITMEASUR\": \"\",\n          \"ISO_UNIT\": \"\",\n          \"CURRENCKEY\": \"\",\n          \"CURRENISO\": \"\",\n          \"CONDINCOMP\": \"\",\n          \"CONDCONFIG\": \"\",\n          \"CONDCHAMAN\": \"\",\n          \"COND_NO\": \"\",\n          \"TAX_CODE\": \"\",\n          \"VARCOND\": \"\",\n          \"ACCOUNTKEY\": \"\",\n          \"ACCOUNT_KE\": \"\",\n          \"WT_WITHCD\": \"\",\n          \"STRUCTCOND\": \"\",\n          \"FACTCONBAS\": \"0.0000000000000000E+00\",\n          \"CONDCOINHD\": \"00\"\n        },\n        {\n          \"ITM_NUMBER\": \"000010\",\n          \"COND_ST_NO\": \"616\",\n          \"COND_COUNT\": \"01\",\n          \"COND_TYPE\": \"BX13\",\n          \"COND_VALUE\": \"12.000000000\",\n          \"CURRENCY\": \"\",\n          \"COND_UNIT\": \"\",\n          \"COND_P_UNT\": \"0\",\n          \"CURR_ISO\": \"\",\n          \"CD_UNT_ISO\": \"\",\n          \"REFOBJTYPE\": \"\",\n          \"REFOBJKEY\": \"\",\n          \"REFLOGSYS\": \"\",\n          \"APPLICATIO\": \"V\",\n          \"CONPRICDAT\": \"2020-12-14\",\n          \"CALCTYPCON\": \"A\",\n          \"CONBASEVAL\": \"172.920000000\",\n          \"CONEXCHRAT\": \"0.00000\",\n          \"NUMCONVERT\": \"0\",\n          \"DENOMINATO\": \"0\",\n          \"CONDTYPE\": \"D\",\n          \"STAT_CON\": \"\",\n          \"SCALETYPE\": \"\",\n          \"ACCRUALS\": \"\",\n          \"CONINVOLST\": \"\",\n          \"CONDORIGIN\": \"A\",\n          \"GROUPCOND\": \"\",\n          \"COND_UPDAT\": \"\",\n          \"ACCESS_SEQ\": \"01\",\n          \"CONDCOUNT\": \"01\",\n          \"ROUNDOFFDI\": \"0.000000000\",\n          \"CONDVALUE\": \"20.750000000\",\n          \"CURRENCY_2\": \"BRL\",\n          \"CURR_ISO_2\": \"BRL\",\n          \"CONDCNTRL\": \"A\",\n          \"CONDISACTI\": \"\",\n          \"CONDCLASS\": \"D\",\n          \"FACTBASVAL\": \"0.0000000000000000E+00\",\n          \"SCALEBASIN\": \"\",\n          \"SCALBASVAL\": \"0.000000000\",\n          \"UNITMEASUR\": \"\",\n          \"ISO_UNIT\": \"\",\n          \"CURRENCKEY\": \"\",\n          \"CURRENISO\": \"\",\n          \"CONDINCOMP\": \"\",\n          \"CONDCONFIG\": \"\",\n          \"CONDCHAMAN\": \"\",\n          \"COND_NO\": \"0035482469\",\n          \"TAX_CODE\": \"SD\",\n          \"VARCOND\": \"\",\n          \"ACCOUNTKEY\": \"\",\n          \"ACCOUNT_KE\": \"\",\n          \"WT_WITHCD\": \"\",\n          \"STRUCTCOND\": \"\",\n          \"FACTCONBAS\": \"0.0000000000000000E+00\",\n          \"CONDCOINHD\": \"00\"\n        },\n        {\n          \"ITM_NUMBER\": \"000010\",\n          \"COND_ST_NO\": \"617\",\n          \"COND_COUNT\": \"01\",\n          \"COND_TYPE\": \"BXZF\",\n          \"COND_VALUE\": \"0.000000000\",\n          \"CURRENCY\": \"\",\n          \"COND_UNIT\": \"\",\n          \"COND_P_UNT\": \"0\",\n          \"CURR_ISO\": \"\",\n          \"CD_UNT_ISO\": \"\",\n          \"REFOBJTYPE\": \"\",\n          \"REFOBJKEY\": \"\",\n          \"REFLOGSYS\": \"\",\n          \"APPLICATIO\": \"V\",\n          \"CONPRICDAT\": \"2020-12-14\",\n          \"CALCTYPCON\": \"A\",\n          \"CONBASEVAL\": \"0.000000000\",\n          \"CONEXCHRAT\": \"0.00000\",\n          \"NUMCONVERT\": \"0\",\n          \"DENOMINATO\": \"0\",\n          \"CONDTYPE\": \"D\",\n          \"STAT_CON\": \"\",\n          \"SCALETYPE\": \"\",\n          \"ACCRUALS\": \"\",\n          \"CONINVOLST\": \"\",\n          \"CONDORIGIN\": \"A\",\n          \"GROUPCOND\": \"\",\n          \"COND_UPDAT\": \"\",\n          \"ACCESS_SEQ\": \"01\",\n          \"CONDCOUNT\": \"01\",\n          \"ROUNDOFFDI\": \"0.000000000\",\n          \"CONDVALUE\": \"0.000000000\",\n          \"CURRENCY_2\": \"BRL\",\n          \"CURR_ISO_2\": \"BRL\",\n          \"CONDCNTRL\": \"A\",\n          \"CONDISACTI\": \"\",\n          \"CONDCLASS\": \"D\",\n          \"FACTBASVAL\": \"0.0000000000000000E+00\",\n          \"SCALEBASIN\": \"\",\n          \"SCALBASVAL\": \"0.000000000\",\n          \"UNITMEASUR\": \"\",\n          \"ISO_UNIT\": \"\",\n          \"CURRENCKEY\": \"\",\n          \"CURRENISO\": \"\",\n          \"CONDINCOMP\": \"\",\n          \"CONDCONFIG\": \"\",\n          \"CONDCHAMAN\": \"\",\n          \"COND_NO\": \"0035482469\",\n          \"TAX_CODE\": \"SD\",\n          \"VARCOND\": \"\",\n          \"ACCOUNTKEY\": \"\",\n          \"ACCOUNT_KE\": \"\",\n          \"WT_WITHCD\": \"\",\n          \"STRUCTCOND\": \"\",\n          \"FACTCONBAS\": \"0.0000000000000000E+00\",\n          \"CONDCOINHD\": \"00\"\n        },\n        {\n          \"ITM_NUMBER\": \"000010\",\n          \"COND_ST_NO\": \"618\",\n          \"COND_COUNT\": \"01\",\n          \"COND_TYPE\": \"BX14\",\n          \"COND_VALUE\": \"0.000000000\",\n          \"CURRENCY\": \"BRL\",\n          \"COND_UNIT\": \"\",\n          \"COND_P_UNT\": \"0\",\n          \"CURR_ISO\": \"BRL\",\n          \"CD_UNT_ISO\": \"\",\n          \"REFOBJTYPE\": \"\",\n          \"REFOBJKEY\": \"\",\n          \"REFLOGSYS\": \"\",\n          \"APPLICATIO\": \"V\",\n          \"CONPRICDAT\": \"2020-12-14\",\n          \"CALCTYPCON\": \"B\",\n          \"CONBASEVAL\": \"523.050000000\",\n          \"CONEXCHRAT\": \"1.00000\",\n          \"NUMCONVERT\": \"0\",\n          \"DENOMINATO\": \"0\",\n          \"CONDTYPE\": \"1\",\n          \"STAT_CON\": \"X\",\n          \"SCALETYPE\": \"\",\n          \"ACCRUALS\": \"\",\n          \"CONINVOLST\": \"\",\n          \"CONDORIGIN\": \"A\",\n          \"GROUPCOND\": \"\",\n          \"COND_UPDAT\": \"\",\n          \"ACCESS_SEQ\": \"00\",\n          \"CONDCOUNT\": \"00\",\n          \"ROUNDOFFDI\": \"0.000000000\",\n          \"CONDVALUE\": \"0.000000000\",\n          \"CURRENCY_2\": \"BRL\",\n          \"CURR_ISO_2\": \"BRL\",\n          \"CONDCNTRL\": \"A\",\n          \"CONDISACTI\": \"\",\n          \"CONDCLASS\": \"A\",\n          \"FACTBASVAL\": \"0.0000000000000000E+00\",\n          \"SCALEBASIN\": \"\",\n          \"SCALBASVAL\": \"0.000000000\",\n          \"UNITMEASUR\": \"\",\n          \"ISO_UNIT\": \"\",\n          \"CURRENCKEY\": \"\",\n          \"CURRENISO\": \"\",\n          \"CONDINCOMP\": \"\",\n          \"CONDCONFIG\": \"\",\n          \"CONDCHAMAN\": \"\",\n          \"COND_NO\": \"\",\n          \"TAX_CODE\": \"\",\n          \"VARCOND\": \"\",\n          \"ACCOUNTKEY\": \"\",\n          \"ACCOUNT_KE\": \"\",\n          \"WT_WITHCD\": \"\",\n          \"STRUCTCOND\": \"\",\n          \"FACTCONBAS\": \"0.0000000000000000E+00\",\n          \"CONDCOINHD\": \"00\"\n        },\n        {\n          \"ITM_NUMBER\": \"000010\",\n          \"COND_ST_NO\": \"620\",\n          \"COND_COUNT\": \"01\",\n          \"COND_TYPE\": \"BX15\",\n          \"COND_VALUE\": \"100.000000000\",\n          \"CURRENCY\": \"\",\n          \"COND_UNIT\": \"\",\n          \"COND_P_UNT\": \"0\",\n          \"CURR_ISO\": \"\",\n          \"CD_UNT_ISO\": \"\",\n          \"REFOBJTYPE\": \"\",\n          \"REFOBJKEY\": \"\",\n          \"REFLOGSYS\": \"\",\n          \"APPLICATIO\": \"V\",\n          \"CONPRICDAT\": \"2020-12-14\",\n          \"CALCTYPCON\": \"A\",\n          \"CONBASEVAL\": \"523.050000000\",\n          \"CONEXCHRAT\": \"0.00000\",\n          \"NUMCONVERT\": \"0\",\n          \"DENOMINATO\": \"0\",\n          \"CONDTYPE\": \"D\",\n          \"STAT_CON\": \"X\",\n          \"SCALETYPE\": \"\",\n          \"ACCRUALS\": \"\",\n          \"CONINVOLST\": \"\",\n          \"CONDORIGIN\": \"A\",\n          \"GROUPCOND\": \"\",\n          \"COND_UPDAT\": \"\",\n          \"ACCESS_SEQ\": \"01\",\n          \"CONDCOUNT\": \"01\",\n          \"ROUNDOFFDI\": \"0.000000000\",\n          \"CONDVALUE\": \"0.000000000\",\n          \"CURRENCY_2\": \"BRL\",\n          \"CURR_ISO_2\": \"BRL\",\n          \"CONDCNTRL\": \"A\",\n          \"CONDISACTI\": \"\",\n          \"CONDCLASS\": \"D\",\n          \"FACTBASVAL\": \"0.0000000000000000E+00\",\n          \"SCALEBASIN\": \"\",\n          \"SCALBASVAL\": \"0.000000000\",\n          \"UNITMEASUR\": \"\",\n          \"ISO_UNIT\": \"\",\n          \"CURRENCKEY\": \"\",\n          \"CURRENISO\": \"\",\n          \"CONDINCOMP\": \"\",\n          \"CONDCONFIG\": \"\",\n          \"CONDCHAMAN\": \"\",\n          \"COND_NO\": \"0035482469\",\n          \"TAX_CODE\": \"SD\",\n          \"VARCOND\": \"\",\n          \"ACCOUNTKEY\": \"\",\n          \"ACCOUNT_KE\": \"\",\n          \"WT_WITHCD\": \"\",\n          \"STRUCTCOND\": \"\",\n          \"FACTCONBAS\": \"0.0000000000000000E+00\",\n          \"CONDCOINHD\": \"00\"\n        },\n        {\n          \"ITM_NUMBER\": \"000010\",\n          \"COND_ST_NO\": \"622\",\n          \"COND_COUNT\": \"01\",\n          \"COND_TYPE\": \"BX16\",\n          \"COND_VALUE\": \"0.000000000\",\n          \"CURRENCY\": \"BRL\",\n          \"COND_UNIT\": \"\",\n          \"COND_P_UNT\": \"0\",\n          \"CURR_ISO\": \"BRL\",\n          \"CD_UNT_ISO\": \"\",\n          \"REFOBJTYPE\": \"\",\n          \"REFOBJKEY\": \"\",\n          \"REFLOGSYS\": \"\",\n          \"APPLICATIO\": \"V\",\n          \"CONPRICDAT\": \"2020-12-14\",\n          \"CALCTYPCON\": \"B\",\n          \"CONBASEVAL\": \"523.050000000\",\n          \"CONEXCHRAT\": \"1.00000\",\n          \"NUMCONVERT\": \"0\",\n          \"DENOMINATO\": \"0\",\n          \"CONDTYPE\": \"1\",\n          \"STAT_CON\": \"X\",\n          \"SCALETYPE\": \"\",\n          \"ACCRUALS\": \"\",\n          \"CONINVOLST\": \"\",\n          \"CONDORIGIN\": \"A\",\n          \"GROUPCOND\": \"\",\n          \"COND_UPDAT\": \"\",\n          \"ACCESS_SEQ\": \"00\",\n          \"CONDCOUNT\": \"00\",\n          \"ROUNDOFFDI\": \"0.000000000\",\n          \"CONDVALUE\": \"120.000000000\",\n          \"CURRENCY_2\": \"BRL\",\n          \"CURR_ISO_2\": \"BRL\",\n          \"CONDCNTRL\": \"A\",\n          \"CONDISACTI\": \"\",\n          \"CONDCLASS\": \"A\",\n          \"FACTBASVAL\": \"0.0000000000000000E+00\",\n          \"SCALEBASIN\": \"\",\n          \"SCALBASVAL\": \"0.000000000\",\n          \"UNITMEASUR\": \"\",\n          \"ISO_UNIT\": \"\",\n          \"CURRENCKEY\": \"\",\n          \"CURRENISO\": \"\",\n          \"CONDINCOMP\": \"\",\n          \"CONDCONFIG\": \"\",\n          \"CONDCHAMAN\": \"\",\n          \"COND_NO\": \"\",\n          \"TAX_CODE\": \"\",\n          \"VARCOND\": \"\",\n          \"ACCOUNTKEY\": \"\",\n          \"ACCOUNT_KE\": \"\",\n          \"WT_WITHCD\": \"\",\n          \"STRUCTCOND\": \"\",\n          \"FACTCONBAS\": \"0.0000000000000000E+00\",\n          \"CONDCOINHD\": \"00\"\n        },\n        {\n          \"ITM_NUMBER\": \"000010\",\n          \"COND_ST_NO\": \"623\",\n          \"COND_COUNT\": \"01\",\n          \"COND_TYPE\": \"BX17\",\n          \"COND_VALUE\": \"-100.000000000\",\n          \"CURRENCY\": \"\",\n          \"COND_UNIT\": \"\",\n          \"COND_P_UNT\": \"0\",\n          \"CURR_ISO\": \"\",\n          \"CD_UNT_ISO\": \"\",\n          \"REFOBJTYPE\": \"\",\n          \"REFOBJKEY\": \"\",\n          \"REFLOGSYS\": \"\",\n          \"APPLICATIO\": \"V\",\n          \"CONPRICDAT\": \"2020-12-14\",\n          \"CALCTYPCON\": \"A\",\n          \"CONBASEVAL\": \"20.750000000\",\n          \"CONEXCHRAT\": \"0.00000\",\n          \"NUMCONVERT\": \"0\",\n          \"DENOMINATO\": \"0\",\n          \"CONDTYPE\": \"\",\n          \"STAT_CON\": \"\",\n          \"SCALETYPE\": \"\",\n          \"ACCRUALS\": \"\",\n          \"CONINVOLST\": \"\",\n          \"CONDORIGIN\": \"A\",\n          \"GROUPCOND\": \"\",\n          \"COND_UPDAT\": \"\",\n          \"ACCESS_SEQ\": \"01\",\n          \"CONDCOUNT\": \"01\",\n          \"ROUNDOFFDI\": \"0.000000000\",\n          \"CONDVALUE\": \"-20.750000000\",\n          \"CURRENCY_2\": \"BRL\",\n          \"CURR_ISO_2\": \"BRL\",\n          \"CONDCNTRL\": \"A\",\n          \"CONDISACTI\": \"\",\n          \"CONDCLASS\": \"A\",\n          \"FACTBASVAL\": \"0.0000000000000000E+00\",\n          \"SCALEBASIN\": \"\",\n          \"SCALBASVAL\": \"0.000000000\",\n          \"UNITMEASUR\": \"\",\n          \"ISO_UNIT\": \"\",\n          \"CURRENCKEY\": \"\",\n          \"CURRENISO\": \"\",\n          \"CONDINCOMP\": \"\",\n          \"CONDCONFIG\": \"\",\n          \"CONDCHAMAN\": \"\",\n          \"COND_NO\": \"0011401268\",\n          \"TAX_CODE\": \"\",\n          \"VARCOND\": \"\",\n          \"ACCOUNTKEY\": \"\",\n          \"ACCOUNT_KE\": \"\",\n          \"WT_WITHCD\": \"\",\n          \"STRUCTCOND\": \"\",\n          \"FACTCONBAS\": \"0.0000000000000000E+00\",\n          \"CONDCOINHD\": \"00\"\n        },\n        {\n          \"ITM_NUMBER\": \"000010\",\n          \"COND_ST_NO\": \"624\",\n          \"COND_COUNT\": \"01\",\n          \"COND_TYPE\": \"BX20\",\n          \"COND_VALUE\": \"0.000000000\",\n          \"CURRENCY\": \"BRL\",\n          \"COND_UNIT\": \"\",\n          \"COND_P_UNT\": \"0\",\n          \"CURR_ISO\": \"BRL\",\n          \"CD_UNT_ISO\": \"\",\n          \"REFOBJTYPE\": \"\",\n          \"REFOBJKEY\": \"\",\n          \"REFLOGSYS\": \"\",\n          \"APPLICATIO\": \"V\",\n          \"CONPRICDAT\": \"2020-12-14\",\n          \"CALCTYPCON\": \"B\",\n          \"CONBASEVAL\": \"622.300000000\",\n          \"CONEXCHRAT\": \"1.00000\",\n          \"NUMCONVERT\": \"0\",\n          \"DENOMINATO\": \"0\",\n          \"CONDTYPE\": \"1\",\n          \"STAT_CON\": \"X\",\n          \"SCALETYPE\": \"\",\n          \"ACCRUALS\": \"\",\n          \"CONINVOLST\": \"\",\n          \"CONDORIGIN\": \"A\",\n          \"GROUPCOND\": \"\",\n          \"COND_UPDAT\": \"\",\n          \"ACCESS_SEQ\": \"00\",\n          \"CONDCOUNT\": \"00\",\n          \"ROUNDOFFDI\": \"0.000000000\",\n          \"CONDVALUE\": \"164.690000000\",\n          \"CURRENCY_2\": \"BRL\",\n          \"CURR_ISO_2\": \"BRL\",\n          \"CONDCNTRL\": \"A\",\n          \"CONDISACTI\": \"\",\n          \"CONDCLASS\": \"A\",\n          \"FACTBASVAL\": \"0.0000000000000000E+00\",\n          \"SCALEBASIN\": \"\",\n          \"SCALBASVAL\": \"0.000000000\",\n          \"UNITMEASUR\": \"\",\n          \"ISO_UNIT\": \"\",\n          \"CURRENCKEY\": \"\",\n          \"CURRENISO\": \"\",\n          \"CONDINCOMP\": \"\",\n          \"CONDCONFIG\": \"\",\n          \"CONDCHAMAN\": \"\",\n          \"COND_NO\": \"\",\n          \"TAX_CODE\": \"\",\n          \"VARCOND\": \"\",\n          \"ACCOUNTKEY\": \"\",\n          \"ACCOUNT_KE\": \"\",\n          \"WT_WITHCD\": \"\",\n          \"STRUCTCOND\": \"\",\n          \"FACTCONBAS\": \"0.0000000000000000E+00\",\n          \"CONDCOINHD\": \"00\"\n        },\n        {\n          \"ITM_NUMBER\": \"000010\",\n          \"COND_ST_NO\": \"626\",\n          \"COND_COUNT\": \"01\",\n          \"COND_TYPE\": \"BX21\",\n          \"COND_VALUE\": \"0.000000000\",\n          \"CURRENCY\": \"BRL\",\n          \"COND_UNIT\": \"\",\n          \"COND_P_UNT\": \"0\",\n          \"CURR_ISO\": \"BRL\",\n          \"CD_UNT_ISO\": \"\",\n          \"REFOBJTYPE\": \"\",\n          \"REFOBJKEY\": \"\",\n          \"REFLOGSYS\": \"\",\n          \"APPLICATIO\": \"V\",\n          \"CONPRICDAT\": \"2020-12-14\",\n          \"CALCTYPCON\": \"B\",\n          \"CONBASEVAL\": \"786.990000000\",\n          \"CONEXCHRAT\": \"1.00000\",\n          \"NUMCONVERT\": \"0\",\n          \"DENOMINATO\": \"0\",\n          \"CONDTYPE\": \"1\",\n          \"STAT_CON\": \"X\",\n          \"SCALETYPE\": \"\",\n          \"ACCRUALS\": \"\",\n          \"CONINVOLST\": \"\",\n          \"CONDORIGIN\": \"A\",\n          \"GROUPCOND\": \"\",\n          \"COND_UPDAT\": \"\",\n          \"ACCESS_SEQ\": \"00\",\n          \"CONDCOUNT\": \"00\",\n          \"ROUNDOFFDI\": \"0.000000000\",\n          \"CONDVALUE\": \"0.000000000\",\n          \"CURRENCY_2\": \"BRL\",\n          \"CURR_ISO_2\": \"BRL\",\n          \"CONDCNTRL\": \"A\",\n          \"CONDISACTI\": \"\",\n          \"CONDCLASS\": \"A\",\n          \"FACTBASVAL\": \"0.0000000000000000E+00\",\n          \"SCALEBASIN\": \"\",\n          \"SCALBASVAL\": \"0.000000000\",\n          \"UNITMEASUR\": \"\",\n          \"ISO_UNIT\": \"\",\n          \"CURRENCKEY\": \"\",\n          \"CURRENISO\": \"\",\n          \"CONDINCOMP\": \"\",\n          \"CONDCONFIG\": \"\",\n          \"CONDCHAMAN\": \"\",\n          \"COND_NO\": \"\",\n          \"TAX_CODE\": \"\",\n          \"VARCOND\": \"\",\n          \"ACCOUNTKEY\": \"\",\n          \"ACCOUNT_KE\": \"\",\n          \"WT_WITHCD\": \"\",\n          \"STRUCTCOND\": \"\",\n          \"FACTCONBAS\": \"0.0000000000000000E+00\",\n          \"CONDCOINHD\": \"00\"\n        },\n        {\n          \"ITM_NUMBER\": \"000010\",\n          \"COND_ST_NO\": \"628\",\n          \"COND_COUNT\": \"01\",\n          \"COND_TYPE\": \"BX22\",\n          \"COND_VALUE\": \"0.000000000\",\n          \"CURRENCY\": \"BRL\",\n          \"COND_UNIT\": \"\",\n          \"COND_P_UNT\": \"0\",\n          \"CURR_ISO\": \"BRL\",\n          \"CD_UNT_ISO\": \"\",\n          \"REFOBJTYPE\": \"\",\n          \"REFOBJKEY\": \"\",\n          \"REFLOGSYS\": \"\",\n          \"APPLICATIO\": \"V\",\n          \"CONPRICDAT\": \"2020-12-14\",\n          \"CALCTYPCON\": \"B\",\n          \"CONBASEVAL\": \"786.990000000\",\n          \"CONEXCHRAT\": \"1.00000\",\n          \"NUMCONVERT\": \"0\",\n          \"DENOMINATO\": \"0\",\n          \"CONDTYPE\": \"1\",\n          \"STAT_CON\": \"X\",\n          \"SCALETYPE\": \"\",\n          \"ACCRUALS\": \"\",\n          \"CONINVOLST\": \"\",\n          \"CONDORIGIN\": \"A\",\n          \"GROUPCOND\": \"\",\n          \"COND_UPDAT\": \"\",\n          \"ACCESS_SEQ\": \"00\",\n          \"CONDCOUNT\": \"00\",\n          \"ROUNDOFFDI\": \"0.000000000\",\n          \"CONDVALUE\": \"0.000000000\",\n          \"CURRENCY_2\": \"BRL\",\n          \"CURR_ISO_2\": \"BRL\",\n          \"CONDCNTRL\": \"A\",\n          \"CONDISACTI\": \"\",\n          \"CONDCLASS\": \"A\",\n          \"FACTBASVAL\": \"0.0000000000000000E+00\",\n          \"SCALEBASIN\": \"\",\n          \"SCALBASVAL\": \"0.000000000\",\n          \"UNITMEASUR\": \"\",\n          \"ISO_UNIT\": \"\",\n          \"CURRENCKEY\": \"\",\n          \"CURRENISO\": \"\",\n          \"CONDINCOMP\": \"\",\n          \"CONDCONFIG\": \"\",\n          \"CONDCHAMAN\": \"\",\n          \"COND_NO\": \"\",\n          \"TAX_CODE\": \"\",\n          \"VARCOND\": \"\",\n          \"ACCOUNTKEY\": \"\",\n          \"ACCOUNT_KE\": \"\",\n          \"WT_WITHCD\": \"\",\n          \"STRUCTCOND\": \"\",\n          \"FACTCONBAS\": \"0.0000000000000000E+00\",\n          \"CONDCOINHD\": \"00\"\n        },\n        {\n          \"ITM_NUMBER\": \"000010\",\n          \"COND_ST_NO\": \"630\",\n          \"COND_COUNT\": \"01\",\n          \"COND_TYPE\": \"BX23\",\n          \"COND_VALUE\": \"100.000000000\",\n          \"CURRENCY\": \"\",\n          \"COND_UNIT\": \"\",\n          \"COND_P_UNT\": \"0\",\n          \"CURR_ISO\": \"\",\n          \"CD_UNT_ISO\": \"\",\n          \"REFOBJTYPE\": \"\",\n          \"REFOBJKEY\": \"\",\n          \"REFLOGSYS\": \"\",\n          \"APPLICATIO\": \"V\",\n          \"CONPRICDAT\": \"2020-12-14\",\n          \"CALCTYPCON\": \"A\",\n          \"CONBASEVAL\": \"786.990000000\",\n          \"CONEXCHRAT\": \"0.00000\",\n          \"NUMCONVERT\": \"0\",\n          \"DENOMINATO\": \"0\",\n          \"CONDTYPE\": \"D\",\n          \"STAT_CON\": \"\",\n          \"SCALETYPE\": \"\",\n          \"ACCRUALS\": \"\",\n          \"CONINVOLST\": \"\",\n          \"CONDORIGIN\": \"A\",\n          \"GROUPCOND\": \"\",\n          \"COND_UPDAT\": \"\",\n          \"ACCESS_SEQ\": \"01\",\n          \"CONDCOUNT\": \"01\",\n          \"ROUNDOFFDI\": \"0.000000000\",\n          \"CONDVALUE\": \"8.230000000\",\n          \"CURRENCY_2\": \"BRL\",\n          \"CURR_ISO_2\": \"BRL\",\n          \"CONDCNTRL\": \"A\",\n          \"CONDISACTI\": \"\",\n          \"CONDCLASS\": \"D\",\n          \"FACTBASVAL\": \"0.0000000000000000E+00\",\n          \"SCALEBASIN\": \"\",\n          \"SCALBASVAL\": \"0.000000000\",\n          \"UNITMEASUR\": \"\",\n          \"ISO_UNIT\": \"\",\n          \"CURRENCKEY\": \"\",\n          \"CURRENISO\": \"\",\n          \"CONDINCOMP\": \"\",\n          \"CONDCONFIG\": \"\",\n          \"CONDCHAMAN\": \"\",\n          \"COND_NO\": \"0035482469\",\n          \"TAX_CODE\": \"SD\",\n          \"VARCOND\": \"\",\n          \"ACCOUNTKEY\": \"\",\n          \"ACCOUNT_KE\": \"\",\n          \"WT_WITHCD\": \"\",\n          \"STRUCTCOND\": \"\",\n          \"FACTCONBAS\": \"0.0000000000000000E+00\",\n          \"CONDCOINHD\": \"00\"\n        },\n        {\n          \"ITM_NUMBER\": \"000010\",\n          \"COND_ST_NO\": \"632\",\n          \"COND_COUNT\": \"01\",\n          \"COND_TYPE\": \"BX24\",\n          \"COND_VALUE\": \"0.000000000\",\n          \"CURRENCY\": \"BRL\",\n          \"COND_UNIT\": \"\",\n          \"COND_P_UNT\": \"0\",\n          \"CURR_ISO\": \"BRL\",\n          \"CD_UNT_ISO\": \"\",\n          \"REFOBJTYPE\": \"\",\n          \"REFOBJKEY\": \"\",\n          \"REFLOGSYS\": \"\",\n          \"APPLICATIO\": \"V\",\n          \"CONPRICDAT\": \"2020-12-14\",\n          \"CALCTYPCON\": \"B\",\n          \"CONBASEVAL\": \"795.220000000\",\n          \"CONEXCHRAT\": \"1.00000\",\n          \"NUMCONVERT\": \"0\",\n          \"DENOMINATO\": \"0\",\n          \"CONDTYPE\": \"1\",\n          \"STAT_CON\": \"X\",\n          \"SCALETYPE\": \"\",\n          \"ACCRUALS\": \"\",\n          \"CONINVOLST\": \"\",\n          \"CONDORIGIN\": \"A\",\n          \"GROUPCOND\": \"\",\n          \"COND_UPDAT\": \"\",\n          \"ACCESS_SEQ\": \"00\",\n          \"CONDCOUNT\": \"00\",\n          \"ROUNDOFFDI\": \"0.000000000\",\n          \"CONDVALUE\": \"0.000000000\",\n          \"CURRENCY_2\": \"BRL\",\n          \"CURR_ISO_2\": \"BRL\",\n          \"CONDCNTRL\": \"A\",\n          \"CONDISACTI\": \"\",\n          \"CONDCLASS\": \"A\",\n          \"FACTBASVAL\": \"0.0000000000000000E+00\",\n          \"SCALEBASIN\": \"\",\n          \"SCALBASVAL\": \"0.000000000\",\n          \"UNITMEASUR\": \"\",\n          \"ISO_UNIT\": \"\",\n          \"CURRENCKEY\": \"\",\n          \"CURRENISO\": \"\",\n          \"CONDINCOMP\": \"\",\n          \"CONDCONFIG\": \"\",\n          \"CONDCHAMAN\": \"\",\n          \"COND_NO\": \"\",\n          \"TAX_CODE\": \"\",\n          \"VARCOND\": \"\",\n          \"ACCOUNTKEY\": \"\",\n          \"ACCOUNT_KE\": \"\",\n          \"WT_WITHCD\": \"\",\n          \"STRUCTCOND\": \"\",\n          \"FACTCONBAS\": \"0.0000000000000000E+00\",\n          \"CONDCOINHD\": \"00\"\n        },\n        {\n          \"ITM_NUMBER\": \"000010\",\n          \"COND_ST_NO\": \"634\",\n          \"COND_COUNT\": \"01\",\n          \"COND_TYPE\": \"BX25\",\n          \"COND_VALUE\": \"-100.000000000\",\n          \"CURRENCY\": \"\",\n          \"COND_UNIT\": \"\",\n          \"COND_P_UNT\": \"0\",\n          \"CURR_ISO\": \"\",\n          \"CD_UNT_ISO\": \"\",\n          \"REFOBJTYPE\": \"\",\n          \"REFOBJKEY\": \"\",\n          \"REFLOGSYS\": \"\",\n          \"APPLICATIO\": \"V\",\n          \"CONPRICDAT\": \"2020-12-14\",\n          \"CALCTYPCON\": \"A\",\n          \"CONBASEVAL\": \"8.230000000\",\n          \"CONEXCHRAT\": \"0.00000\",\n          \"NUMCONVERT\": \"0\",\n          \"DENOMINATO\": \"0\",\n          \"CONDTYPE\": \"\",\n          \"STAT_CON\": \"\",\n          \"SCALETYPE\": \"\",\n          \"ACCRUALS\": \"\",\n          \"CONINVOLST\": \"\",\n          \"CONDORIGIN\": \"A\",\n          \"GROUPCOND\": \"\",\n          \"COND_UPDAT\": \"\",\n          \"ACCESS_SEQ\": \"01\",\n          \"CONDCOUNT\": \"01\",\n          \"ROUNDOFFDI\": \"0.000000000\",\n          \"CONDVALUE\": \"-8.230000000\",\n          \"CURRENCY_2\": \"BRL\",\n          \"CURR_ISO_2\": \"BRL\",\n          \"CONDCNTRL\": \"A\",\n          \"CONDISACTI\": \"\",\n          \"CONDCLASS\": \"A\",\n          \"FACTBASVAL\": \"0.0000000000000000E+00\",\n          \"SCALEBASIN\": \"\",\n          \"SCALBASVAL\": \"0.000000000\",\n          \"UNITMEASUR\": \"\",\n          \"ISO_UNIT\": \"\",\n          \"CURRENCKEY\": \"\",\n          \"CURRENISO\": \"\",\n          \"CONDINCOMP\": \"\",\n          \"CONDCONFIG\": \"\",\n          \"CONDCHAMAN\": \"\",\n          \"COND_NO\": \"0000006853\",\n          \"TAX_CODE\": \"\",\n          \"VARCOND\": \"\",\n          \"ACCOUNTKEY\": \"\",\n          \"ACCOUNT_KE\": \"\",\n          \"WT_WITHCD\": \"\",\n          \"STRUCTCOND\": \"\",\n          \"FACTCONBAS\": \"0.0000000000000000E+00\",\n          \"CONDCOINHD\": \"00\"\n        },\n        {\n          \"ITM_NUMBER\": \"000010\",\n          \"COND_ST_NO\": \"636\",\n          \"COND_COUNT\": \"01\",\n          \"COND_TYPE\": \"BX40\",\n          \"COND_VALUE\": \"0.000000000\",\n          \"CURRENCY\": \"BRL\",\n          \"COND_UNIT\": \"\",\n          \"COND_P_UNT\": \"0\",\n          \"CURR_ISO\": \"BRL\",\n          \"CD_UNT_ISO\": \"\",\n          \"REFOBJTYPE\": \"\",\n          \"REFOBJKEY\": \"\",\n          \"REFLOGSYS\": \"\",\n          \"APPLICATIO\": \"V\",\n          \"CONPRICDAT\": \"2020-12-14\",\n          \"CALCTYPCON\": \"B\",\n          \"CONBASEVAL\": \"786.990000000\",\n          \"CONEXCHRAT\": \"1.00000\",\n          \"NUMCONVERT\": \"0\",\n          \"DENOMINATO\": \"0\",\n          \"CONDTYPE\": \"1\",\n          \"STAT_CON\": \"X\",\n          \"SCALETYPE\": \"\",\n          \"ACCRUALS\": \"\",\n          \"CONINVOLST\": \"\",\n          \"CONDORIGIN\": \"A\",\n          \"GROUPCOND\": \"\",\n          \"COND_UPDAT\": \"\",\n          \"ACCESS_SEQ\": \"00\",\n          \"CONDCOUNT\": \"00\",\n          \"ROUNDOFFDI\": \"0.000000000\",\n          \"CONDVALUE\": \"0.000000000\",\n          \"CURRENCY_2\": \"BRL\",\n          \"CURR_ISO_2\": \"BRL\",\n          \"CONDCNTRL\": \"A\",\n          \"CONDISACTI\": \"\",\n          \"CONDCLASS\": \"A\",\n          \"FACTBASVAL\": \"0.0000000000000000E+00\",\n          \"SCALEBASIN\": \"\",\n          \"SCALBASVAL\": \"0.000000000\",\n          \"UNITMEASUR\": \"\",\n          \"ISO_UNIT\": \"\",\n          \"CURRENCKEY\": \"\",\n          \"CURRENISO\": \"\",\n          \"CONDINCOMP\": \"\",\n          \"CONDCONFIG\": \"\",\n          \"CONDCHAMAN\": \"\",\n          \"COND_NO\": \"\",\n          \"TAX_CODE\": \"\",\n          \"VARCOND\": \"\",\n          \"ACCOUNTKEY\": \"\",\n          \"ACCOUNT_KE\": \"\",\n          \"WT_WITHCD\": \"\",\n          \"STRUCTCOND\": \"\",\n          \"FACTCONBAS\": \"0.0000000000000000E+00\",\n          \"CONDCOINHD\": \"00\"\n        },\n        {\n          \"ITM_NUMBER\": \"000010\",\n          \"COND_ST_NO\": \"638\",\n          \"COND_COUNT\": \"01\",\n          \"COND_TYPE\": \"BX41\",\n          \"COND_VALUE\": \"100.000000000\",\n          \"CURRENCY\": \"\",\n          \"COND_UNIT\": \"\",\n          \"COND_P_UNT\": \"0\",\n          \"CURR_ISO\": \"\",\n          \"CD_UNT_ISO\": \"\",\n          \"REFOBJTYPE\": \"\",\n          \"REFOBJKEY\": \"\",\n          \"REFLOGSYS\": \"\",\n          \"APPLICATIO\": \"V\",\n          \"CONPRICDAT\": \"2020-12-14\",\n          \"CALCTYPCON\": \"A\",\n          \"CONBASEVAL\": \"786.990000000\",\n          \"CONEXCHRAT\": \"0.00000\",\n          \"NUMCONVERT\": \"0\",\n          \"DENOMINATO\": \"0\",\n          \"CONDTYPE\": \"D\",\n          \"STAT_CON\": \"\",\n          \"SCALETYPE\": \"\",\n          \"ACCRUALS\": \"\",\n          \"CONINVOLST\": \"\",\n          \"CONDORIGIN\": \"A\",\n          \"GROUPCOND\": \"\",\n          \"COND_UPDAT\": \"\",\n          \"ACCESS_SEQ\": \"01\",\n          \"CONDCOUNT\": \"01\",\n          \"ROUNDOFFDI\": \"0.000000000\",\n          \"CONDVALUE\": \"0.000000000\",\n          \"CURRENCY_2\": \"BRL\",\n          \"CURR_ISO_2\": \"BRL\",\n          \"CONDCNTRL\": \"A\",\n          \"CONDISACTI\": \"\",\n          \"CONDCLASS\": \"D\",\n          \"FACTBASVAL\": \"0.0000000000000000E+00\",\n          \"SCALEBASIN\": \"\",\n          \"SCALBASVAL\": \"0.000000000\",\n          \"UNITMEASUR\": \"\",\n          \"ISO_UNIT\": \"\",\n          \"CURRENCKEY\": \"\",\n          \"CURRENISO\": \"\",\n          \"CONDINCOMP\": \"\",\n          \"CONDCONFIG\": \"\",\n          \"CONDCHAMAN\": \"\",\n          \"COND_NO\": \"0035482469\",\n          \"TAX_CODE\": \"SD\",\n          \"VARCOND\": \"\",\n          \"ACCOUNTKEY\": \"\",\n          \"ACCOUNT_KE\": \"\",\n          \"WT_WITHCD\": \"\",\n          \"STRUCTCOND\": \"\",\n          \"FACTCONBAS\": \"0.0000000000000000E+00\",\n          \"CONDCOINHD\": \"00\"\n        },\n        {\n          \"ITM_NUMBER\": \"000010\",\n          \"COND_ST_NO\": \"640\",\n          \"COND_COUNT\": \"01\",\n          \"COND_TYPE\": \"BX42\",\n          \"COND_VALUE\": \"0.000000000\",\n          \"CURRENCY\": \"BRL\",\n          \"COND_UNIT\": \"\",\n          \"COND_P_UNT\": \"0\",\n          \"CURR_ISO\": \"BRL\",\n          \"CD_UNT_ISO\": \"\",\n          \"REFOBJTYPE\": \"\",\n          \"REFOBJKEY\": \"\",\n          \"REFLOGSYS\": \"\",\n          \"APPLICATIO\": \"V\",\n          \"CONPRICDAT\": \"2020-12-14\",\n          \"CALCTYPCON\": \"B\",\n          \"CONBASEVAL\": \"786.990000000\",\n          \"CONEXCHRAT\": \"1.00000\",\n          \"NUMCONVERT\": \"0\",\n          \"DENOMINATO\": \"0\",\n          \"CONDTYPE\": \"1\",\n          \"STAT_CON\": \"X\",\n          \"SCALETYPE\": \"\",\n          \"ACCRUALS\": \"\",\n          \"CONINVOLST\": \"\",\n          \"CONDORIGIN\": \"A\",\n          \"GROUPCOND\": \"\",\n          \"COND_UPDAT\": \"\",\n          \"ACCESS_SEQ\": \"00\",\n          \"CONDCOUNT\": \"00\",\n          \"ROUNDOFFDI\": \"0.000000000\",\n          \"CONDVALUE\": \"0.000000000\",\n          \"CURRENCY_2\": \"BRL\",\n          \"CURR_ISO_2\": \"BRL\",\n          \"CONDCNTRL\": \"A\",\n          \"CONDISACTI\": \"\",\n          \"CONDCLASS\": \"A\",\n          \"FACTBASVAL\": \"0.0000000000000000E+00\",\n          \"SCALEBASIN\": \"\",\n          \"SCALBASVAL\": \"0.000000000\",\n          \"UNITMEASUR\": \"\",\n          \"ISO_UNIT\": \"\",\n          \"CURRENCKEY\": \"\",\n          \"CURRENISO\": \"\",\n          \"CONDINCOMP\": \"\",\n          \"CONDCONFIG\": \"\",\n          \"CONDCHAMAN\": \"\",\n          \"COND_NO\": \"\",\n          \"TAX_CODE\": \"\",\n          \"VARCOND\": \"\",\n          \"ACCOUNTKEY\": \"\",\n          \"ACCOUNT_KE\": \"\",\n          \"WT_WITHCD\": \"\",\n          \"STRUCTCOND\": \"\",\n          \"FACTCONBAS\": \"0.0000000000000000E+00\",\n          \"CONDCOINHD\": \"00\"\n        },\n        {\n          \"ITM_NUMBER\": \"000010\",\n          \"COND_ST_NO\": \"642\",\n          \"COND_COUNT\": \"01\",\n          \"COND_TYPE\": \"BX43\",\n          \"COND_VALUE\": \"100.000000000\",\n          \"CURRENCY\": \"\",\n          \"COND_UNIT\": \"\",\n          \"COND_P_UNT\": \"0\",\n          \"CURR_ISO\": \"\",\n          \"CD_UNT_ISO\": \"\",\n          \"REFOBJTYPE\": \"\",\n          \"REFOBJKEY\": \"\",\n          \"REFLOGSYS\": \"\",\n          \"APPLICATIO\": \"V\",\n          \"CONPRICDAT\": \"2020-12-14\",\n          \"CALCTYPCON\": \"A\",\n          \"CONBASEVAL\": \"786.990000000\",\n          \"CONEXCHRAT\": \"0.00000\",\n          \"NUMCONVERT\": \"0\",\n          \"DENOMINATO\": \"0\",\n          \"CONDTYPE\": \"D\",\n          \"STAT_CON\": \"X\",\n          \"SCALETYPE\": \"\",\n          \"ACCRUALS\": \"\",\n          \"CONINVOLST\": \"\",\n          \"CONDORIGIN\": \"A\",\n          \"GROUPCOND\": \"\",\n          \"COND_UPDAT\": \"\",\n          \"ACCESS_SEQ\": \"01\",\n          \"CONDCOUNT\": \"01\",\n          \"ROUNDOFFDI\": \"0.000000000\",\n          \"CONDVALUE\": \"0.000000000\",\n          \"CURRENCY_2\": \"BRL\",\n          \"CURR_ISO_2\": \"BRL\",\n          \"CONDCNTRL\": \"A\",\n          \"CONDISACTI\": \"\",\n          \"CONDCLASS\": \"D\",\n          \"FACTBASVAL\": \"0.0000000000000000E+00\",\n          \"SCALEBASIN\": \"\",\n          \"SCALBASVAL\": \"0.000000000\",\n          \"UNITMEASUR\": \"\",\n          \"ISO_UNIT\": \"\",\n          \"CURRENCKEY\": \"\",\n          \"CURRENISO\": \"\",\n          \"CONDINCOMP\": \"\",\n          \"CONDCONFIG\": \"\",\n          \"CONDCHAMAN\": \"\",\n          \"COND_NO\": \"0035482469\",\n          \"TAX_CODE\": \"SD\",\n          \"VARCOND\": \"\",\n          \"ACCOUNTKEY\": \"\",\n          \"ACCOUNT_KE\": \"\",\n          \"WT_WITHCD\": \"\",\n          \"STRUCTCOND\": \"\",\n          \"FACTCONBAS\": \"0.0000000000000000E+00\",\n          \"CONDCOINHD\": \"00\"\n        },\n        {\n          \"ITM_NUMBER\": \"000010\",\n          \"COND_ST_NO\": \"644\",\n          \"COND_COUNT\": \"01\",\n          \"COND_TYPE\": \"BX44\",\n          \"COND_VALUE\": \"0.000000000\",\n          \"CURRENCY\": \"BRL\",\n          \"COND_UNIT\": \"\",\n          \"COND_P_UNT\": \"0\",\n          \"CURR_ISO\": \"BRL\",\n          \"CD_UNT_ISO\": \"\",\n          \"REFOBJTYPE\": \"\",\n          \"REFOBJKEY\": \"\",\n          \"REFLOGSYS\": \"\",\n          \"APPLICATIO\": \"V\",\n          \"CONPRICDAT\": \"2020-12-14\",\n          \"CALCTYPCON\": \"B\",\n          \"CONBASEVAL\": \"786.990000000\",\n          \"CONEXCHRAT\": \"1.00000\",\n          \"NUMCONVERT\": \"0\",\n          \"DENOMINATO\": \"0\",\n          \"CONDTYPE\": \"1\",\n          \"STAT_CON\": \"X\",\n          \"SCALETYPE\": \"\",\n          \"ACCRUALS\": \"\",\n          \"CONINVOLST\": \"\",\n          \"CONDORIGIN\": \"A\",\n          \"GROUPCOND\": \"\",\n          \"COND_UPDAT\": \"\",\n          \"ACCESS_SEQ\": \"00\",\n          \"CONDCOUNT\": \"00\",\n          \"ROUNDOFFDI\": \"0.000000000\",\n          \"CONDVALUE\": \"180.000000000\",\n          \"CURRENCY_2\": \"BRL\",\n          \"CURR_ISO_2\": \"BRL\",\n          \"CONDCNTRL\": \"A\",\n          \"CONDISACTI\": \"\",\n          \"CONDCLASS\": \"A\",\n          \"FACTBASVAL\": \"0.0000000000000000E+00\",\n          \"SCALEBASIN\": \"\",\n          \"SCALBASVAL\": \"0.000000000\",\n          \"UNITMEASUR\": \"\",\n          \"ISO_UNIT\": \"\",\n          \"CURRENCKEY\": \"\",\n          \"CURRENISO\": \"\",\n          \"CONDINCOMP\": \"\",\n          \"CONDCONFIG\": \"\",\n          \"CONDCHAMAN\": \"\",\n          \"COND_NO\": \"\",\n          \"TAX_CODE\": \"\",\n          \"VARCOND\": \"\",\n          \"ACCOUNTKEY\": \"\",\n          \"ACCOUNT_KE\": \"\",\n          \"WT_WITHCD\": \"\",\n          \"STRUCTCOND\": \"\",\n          \"FACTCONBAS\": \"0.0000000000000000E+00\",\n          \"CONDCOINHD\": \"00\"\n        },\n        {\n          \"ITM_NUMBER\": \"000010\",\n          \"COND_ST_NO\": \"645\",\n          \"COND_COUNT\": \"01\",\n          \"COND_TYPE\": \"BX45\",\n          \"COND_VALUE\": \"0.000000000\",\n          \"CURRENCY\": \"BRL\",\n          \"COND_UNIT\": \"\",\n          \"COND_P_UNT\": \"0\",\n          \"CURR_ISO\": \"BRL\",\n          \"CD_UNT_ISO\": \"\",\n          \"REFOBJTYPE\": \"\",\n          \"REFOBJKEY\": \"\",\n          \"REFLOGSYS\": \"\",\n          \"APPLICATIO\": \"V\",\n          \"CONPRICDAT\": \"2020-12-14\",\n          \"CALCTYPCON\": \"B\",\n          \"CONBASEVAL\": \"966.990000000\",\n          \"CONEXCHRAT\": \"1.00000\",\n          \"NUMCONVERT\": \"0\",\n          \"DENOMINATO\": \"0\",\n          \"CONDTYPE\": \"1\",\n          \"STAT_CON\": \"X\",\n          \"SCALETYPE\": \"\",\n          \"ACCRUALS\": \"\",\n          \"CONINVOLST\": \"\",\n          \"CONDORIGIN\": \"A\",\n          \"GROUPCOND\": \"\",\n          \"COND_UPDAT\": \"\",\n          \"ACCESS_SEQ\": \"00\",\n          \"CONDCOUNT\": \"00\",\n          \"ROUNDOFFDI\": \"0.000000000\",\n          \"CONDVALUE\": \"0.000000000\",\n          \"CURRENCY_2\": \"BRL\",\n          \"CURR_ISO_2\": \"BRL\",\n          \"CONDCNTRL\": \"A\",\n          \"CONDISACTI\": \"\",\n          \"CONDCLASS\": \"A\",\n          \"FACTBASVAL\": \"0.0000000000000000E+00\",\n          \"SCALEBASIN\": \"\",\n          \"SCALBASVAL\": \"0.000000000\",\n          \"UNITMEASUR\": \"\",\n          \"ISO_UNIT\": \"\",\n          \"CURRENCKEY\": \"\",\n          \"CURRENISO\": \"\",\n          \"CONDINCOMP\": \"\",\n          \"CONDCONFIG\": \"\",\n          \"CONDCHAMAN\": \"\",\n          \"COND_NO\": \"\",\n          \"TAX_CODE\": \"\",\n          \"VARCOND\": \"\",\n          \"ACCOUNTKEY\": \"\",\n          \"ACCOUNT_KE\": \"\",\n          \"WT_WITHCD\": \"\",\n          \"STRUCTCOND\": \"\",\n          \"FACTCONBAS\": \"0.0000000000000000E+00\",\n          \"CONDCOINHD\": \"00\"\n        },\n        {\n          \"ITM_NUMBER\": \"000010\",\n          \"COND_ST_NO\": \"646\",\n          \"COND_COUNT\": \"01\",\n          \"COND_TYPE\": \"BX46\",\n          \"COND_VALUE\": \"0.000000000\",\n          \"CURRENCY\": \"BRL\",\n          \"COND_UNIT\": \"\",\n          \"COND_P_UNT\": \"0\",\n          \"CURR_ISO\": \"BRL\",\n          \"CD_UNT_ISO\": \"\",\n          \"REFOBJTYPE\": \"\",\n          \"REFOBJKEY\": \"\",\n          \"REFLOGSYS\": \"\",\n          \"APPLICATIO\": \"V\",\n          \"CONPRICDAT\": \"2020-12-14\",\n          \"CALCTYPCON\": \"B\",\n          \"CONBASEVAL\": \"966.990000000\",\n          \"CONEXCHRAT\": \"1.00000\",\n          \"NUMCONVERT\": \"0\",\n          \"DENOMINATO\": \"0\",\n          \"CONDTYPE\": \"1\",\n          \"STAT_CON\": \"X\",\n          \"SCALETYPE\": \"\",\n          \"ACCRUALS\": \"\",\n          \"CONINVOLST\": \"\",\n          \"CONDORIGIN\": \"A\",\n          \"GROUPCOND\": \"\",\n          \"COND_UPDAT\": \"\",\n          \"ACCESS_SEQ\": \"00\",\n          \"CONDCOUNT\": \"00\",\n          \"ROUNDOFFDI\": \"0.000000000\",\n          \"CONDVALUE\": \"0.000000000\",\n          \"CURRENCY_2\": \"BRL\",\n          \"CURR_ISO_2\": \"BRL\",\n          \"CONDCNTRL\": \"A\",\n          \"CONDISACTI\": \"\",\n          \"CONDCLASS\": \"A\",\n          \"FACTBASVAL\": \"0.0000000000000000E+00\",\n          \"SCALEBASIN\": \"\",\n          \"SCALBASVAL\": \"0.000000000\",\n          \"UNITMEASUR\": \"\",\n          \"ISO_UNIT\": \"\",\n          \"CURRENCKEY\": \"\",\n          \"CURRENISO\": \"\",\n          \"CONDINCOMP\": \"\",\n          \"CONDCONFIG\": \"\",\n          \"CONDCHAMAN\": \"\",\n          \"COND_NO\": \"\",\n          \"TAX_CODE\": \"\",\n          \"VARCOND\": \"\",\n          \"ACCOUNTKEY\": \"\",\n          \"ACCOUNT_KE\": \"\",\n          \"WT_WITHCD\": \"\",\n          \"STRUCTCOND\": \"\",\n          \"FACTCONBAS\": \"0.0000000000000000E+00\",\n          \"CONDCOINHD\": \"00\"\n        },\n        {\n          \"ITM_NUMBER\": \"000010\",\n          \"COND_ST_NO\": \"650\",\n          \"COND_COUNT\": \"01\",\n          \"COND_TYPE\": \"BXPA\",\n          \"COND_VALUE\": \"0.000000000\",\n          \"CURRENCY\": \"BRL\",\n          \"COND_UNIT\": \"\",\n          \"COND_P_UNT\": \"0\",\n          \"CURR_ISO\": \"BRL\",\n          \"CD_UNT_ISO\": \"\",\n          \"REFOBJTYPE\": \"\",\n          \"REFOBJKEY\": \"\",\n          \"REFLOGSYS\": \"\",\n          \"APPLICATIO\": \"V\",\n          \"CONPRICDAT\": \"2020-12-14\",\n          \"CALCTYPCON\": \"B\",\n          \"CONBASEVAL\": \"966.990000000\",\n          \"CONEXCHRAT\": \"1.00000\",\n          \"NUMCONVERT\": \"0\",\n          \"DENOMINATO\": \"0\",\n          \"CONDTYPE\": \"1\",\n          \"STAT_CON\": \"\",\n          \"SCALETYPE\": \"\",\n          \"ACCRUALS\": \"\",\n          \"CONINVOLST\": \"\",\n          \"CONDORIGIN\": \"A\",\n          \"GROUPCOND\": \"\",\n          \"COND_UPDAT\": \"\",\n          \"ACCESS_SEQ\": \"00\",\n          \"CONDCOUNT\": \"00\",\n          \"ROUNDOFFDI\": \"0.000000000\",\n          \"CONDVALUE\": \"0.000000000\",\n          \"CURRENCY_2\": \"BRL\",\n          \"CURR_ISO_2\": \"BRL\",\n          \"CONDCNTRL\": \"A\",\n          \"CONDISACTI\": \"\",\n          \"CONDCLASS\": \"A\",\n          \"FACTBASVAL\": \"0.0000000000000000E+00\",\n          \"SCALEBASIN\": \"\",\n          \"SCALBASVAL\": \"0.000000000\",\n          \"UNITMEASUR\": \"\",\n          \"ISO_UNIT\": \"\",\n          \"CURRENCKEY\": \"\",\n          \"CURRENISO\": \"\",\n          \"CONDINCOMP\": \"\",\n          \"CONDCONFIG\": \"\",\n          \"CONDCHAMAN\": \"\",\n          \"COND_NO\": \"\",\n          \"TAX_CODE\": \"\",\n          \"VARCOND\": \"\",\n          \"ACCOUNTKEY\": \"\",\n          \"ACCOUNT_KE\": \"\",\n          \"WT_WITHCD\": \"\",\n          \"STRUCTCOND\": \"\",\n          \"FACTCONBAS\": \"0.0000000000000000E+00\",\n          \"CONDCOINHD\": \"00\"\n        },\n        {\n          \"ITM_NUMBER\": \"000010\",\n          \"COND_ST_NO\": \"666\",\n          \"COND_COUNT\": \"01\",\n          \"COND_TYPE\": \"BX70\",\n          \"COND_VALUE\": \"0.000000000\",\n          \"CURRENCY\": \"BRL\",\n          \"COND_UNIT\": \"\",\n          \"COND_P_UNT\": \"0\",\n          \"CURR_ISO\": \"BRL\",\n          \"CD_UNT_ISO\": \"\",\n          \"REFOBJTYPE\": \"\",\n          \"REFOBJKEY\": \"\",\n          \"REFLOGSYS\": \"\",\n          \"APPLICATIO\": \"V\",\n          \"CONPRICDAT\": \"2020-12-14\",\n          \"CALCTYPCON\": \"B\",\n          \"CONBASEVAL\": \"966.990000000\",\n          \"CONEXCHRAT\": \"1.00000\",\n          \"NUMCONVERT\": \"0\",\n          \"DENOMINATO\": \"0\",\n          \"CONDTYPE\": \"1\",\n          \"STAT_CON\": \"X\",\n          \"SCALETYPE\": \"\",\n          \"ACCRUALS\": \"\",\n          \"CONINVOLST\": \"\",\n          \"CONDORIGIN\": \"A\",\n          \"GROUPCOND\": \"\",\n          \"COND_UPDAT\": \"\",\n          \"ACCESS_SEQ\": \"00\",\n          \"CONDCOUNT\": \"00\",\n          \"ROUNDOFFDI\": \"0.000000000\",\n          \"CONDVALUE\": \"164.690000000\",\n          \"CURRENCY_2\": \"BRL\",\n          \"CURR_ISO_2\": \"BRL\",\n          \"CONDCNTRL\": \"A\",\n          \"CONDISACTI\": \"\",\n          \"CONDCLASS\": \"A\",\n          \"FACTBASVAL\": \"0.0000000000000000E+00\",\n          \"SCALEBASIN\": \"\",\n          \"SCALBASVAL\": \"0.000000000\",\n          \"UNITMEASUR\": \"\",\n          \"ISO_UNIT\": \"\",\n          \"CURRENCKEY\": \"\",\n          \"CURRENISO\": \"\",\n          \"CONDINCOMP\": \"\",\n          \"CONDCONFIG\": \"\",\n          \"CONDCHAMAN\": \"\",\n          \"COND_NO\": \"\",\n          \"TAX_CODE\": \"\",\n          \"VARCOND\": \"\",\n          \"ACCOUNTKEY\": \"\",\n          \"ACCOUNT_KE\": \"\",\n          \"WT_WITHCD\": \"\",\n          \"STRUCTCOND\": \"\",\n          \"FACTCONBAS\": \"0.0000000000000000E+00\",\n          \"CONDCOINHD\": \"00\"\n        },\n        {\n          \"ITM_NUMBER\": \"000010\",\n          \"COND_ST_NO\": \"667\",\n          \"COND_COUNT\": \"01\",\n          \"COND_TYPE\": \"BX71\",\n          \"COND_VALUE\": \"0.000000000\",\n          \"CURRENCY\": \"BRL\",\n          \"COND_UNIT\": \"\",\n          \"COND_P_UNT\": \"0\",\n          \"CURR_ISO\": \"BRL\",\n          \"CD_UNT_ISO\": \"\",\n          \"REFOBJTYPE\": \"\",\n          \"REFOBJKEY\": \"\",\n          \"REFLOGSYS\": \"\",\n          \"APPLICATIO\": \"V\",\n          \"CONPRICDAT\": \"2020-12-14\",\n          \"CALCTYPCON\": \"B\",\n          \"CONBASEVAL\": \"1131.680000000\",\n          \"CONEXCHRAT\": \"1.00000\",\n          \"NUMCONVERT\": \"0\",\n          \"DENOMINATO\": \"0\",\n          \"CONDTYPE\": \"1\",\n          \"STAT_CON\": \"X\",\n          \"SCALETYPE\": \"\",\n          \"ACCRUALS\": \"\",\n          \"CONINVOLST\": \"\",\n          \"CONDORIGIN\": \"A\",\n          \"GROUPCOND\": \"\",\n          \"COND_UPDAT\": \"\",\n          \"ACCESS_SEQ\": \"00\",\n          \"CONDCOUNT\": \"00\",\n          \"ROUNDOFFDI\": \"0.000000000\",\n          \"CONDVALUE\": \"0.000000000\",\n          \"CURRENCY_2\": \"BRL\",\n          \"CURR_ISO_2\": \"BRL\",\n          \"CONDCNTRL\": \"A\",\n          \"CONDISACTI\": \"\",\n          \"CONDCLASS\": \"A\",\n          \"FACTBASVAL\": \"0.0000000000000000E+00\",\n          \"SCALEBASIN\": \"\",\n          \"SCALBASVAL\": \"0.000000000\",\n          \"UNITMEASUR\": \"\",\n          \"ISO_UNIT\": \"\",\n          \"CURRENCKEY\": \"\",\n          \"CURRENISO\": \"\",\n          \"CONDINCOMP\": \"\",\n          \"CONDCONFIG\": \"\",\n          \"CONDCHAMAN\": \"\",\n          \"COND_NO\": \"\",\n          \"TAX_CODE\": \"\",\n          \"VARCOND\": \"\",\n          \"ACCOUNTKEY\": \"\",\n          \"ACCOUNT_KE\": \"\",\n          \"WT_WITHCD\": \"\",\n          \"STRUCTCOND\": \"\",\n          \"FACTCONBAS\": \"0.0000000000000000E+00\",\n          \"CONDCOINHD\": \"00\"\n        },\n        {\n          \"ITM_NUMBER\": \"000010\",\n          \"COND_ST_NO\": \"668\",\n          \"COND_COUNT\": \"01\",\n          \"COND_TYPE\": \"BX72\",\n          \"COND_VALUE\": \"100.000000000\",\n          \"CURRENCY\": \"\",\n          \"COND_UNIT\": \"\",\n          \"COND_P_UNT\": \"0\",\n          \"CURR_ISO\": \"\",\n          \"CD_UNT_ISO\": \"\",\n          \"REFOBJTYPE\": \"\",\n          \"REFOBJKEY\": \"\",\n          \"REFLOGSYS\": \"\",\n          \"APPLICATIO\": \"V\",\n          \"CONPRICDAT\": \"2020-12-14\",\n          \"CALCTYPCON\": \"A\",\n          \"CONBASEVAL\": \"1131.680000000\",\n          \"CONEXCHRAT\": \"0.00000\",\n          \"NUMCONVERT\": \"0\",\n          \"DENOMINATO\": \"0\",\n          \"CONDTYPE\": \"D\",\n          \"STAT_CON\": \"\",\n          \"SCALETYPE\": \"\",\n          \"ACCRUALS\": \"\",\n          \"CONINVOLST\": \"\",\n          \"CONDORIGIN\": \"A\",\n          \"GROUPCOND\": \"\",\n          \"COND_UPDAT\": \"\",\n          \"ACCESS_SEQ\": \"01\",\n          \"CONDCOUNT\": \"01\",\n          \"ROUNDOFFDI\": \"0.000000000\",\n          \"CONDVALUE\": \"12.520000000\",\n          \"CURRENCY_2\": \"BRL\",\n          \"CURR_ISO_2\": \"BRL\",\n          \"CONDCNTRL\": \"A\",\n          \"CONDISACTI\": \"\",\n          \"CONDCLASS\": \"D\",\n          \"FACTBASVAL\": \"0.0000000000000000E+00\",\n          \"SCALEBASIN\": \"\",\n          \"SCALBASVAL\": \"0.000000000\",\n          \"UNITMEASUR\": \"\",\n          \"ISO_UNIT\": \"\",\n          \"CURRENCKEY\": \"\",\n          \"CURRENISO\": \"\",\n          \"CONDINCOMP\": \"\",\n          \"CONDCONFIG\": \"\",\n          \"CONDCHAMAN\": \"\",\n          \"COND_NO\": \"0035482469\",\n          \"TAX_CODE\": \"SD\",\n          \"VARCOND\": \"\",\n          \"ACCOUNTKEY\": \"\",\n          \"ACCOUNT_KE\": \"\",\n          \"WT_WITHCD\": \"\",\n          \"STRUCTCOND\": \"\",\n          \"FACTCONBAS\": \"0.0000000000000000E+00\",\n          \"CONDCOINHD\": \"00\"\n        },\n        {\n          \"ITM_NUMBER\": \"000010\",\n          \"COND_ST_NO\": \"669\",\n          \"COND_COUNT\": \"01\",\n          \"COND_TYPE\": \"BX7P\",\n          \"COND_VALUE\": \"0.000000000\",\n          \"CURRENCY\": \"BRL\",\n          \"COND_UNIT\": \"\",\n          \"COND_P_UNT\": \"0\",\n          \"CURR_ISO\": \"BRL\",\n          \"CD_UNT_ISO\": \"\",\n          \"REFOBJTYPE\": \"\",\n          \"REFOBJKEY\": \"\",\n          \"REFLOGSYS\": \"\",\n          \"APPLICATIO\": \"V\",\n          \"CONPRICDAT\": \"2020-12-14\",\n          \"CALCTYPCON\": \"B\",\n          \"CONBASEVAL\": \"1144.200000000\",\n          \"CONEXCHRAT\": \"1.00000\",\n          \"NUMCONVERT\": \"0\",\n          \"DENOMINATO\": \"0\",\n          \"CONDTYPE\": \"1\",\n          \"STAT_CON\": \"X\",\n          \"SCALETYPE\": \"\",\n          \"ACCRUALS\": \"\",\n          \"CONINVOLST\": \"\",\n          \"CONDORIGIN\": \"A\",\n          \"GROUPCOND\": \"\",\n          \"COND_UPDAT\": \"\",\n          \"ACCESS_SEQ\": \"00\",\n          \"CONDCOUNT\": \"00\",\n          \"ROUNDOFFDI\": \"0.000000000\",\n          \"CONDVALUE\": \"0.000000000\",\n          \"CURRENCY_2\": \"BRL\",\n          \"CURR_ISO_2\": \"BRL\",\n          \"CONDCNTRL\": \"A\",\n          \"CONDISACTI\": \"\",\n          \"CONDCLASS\": \"A\",\n          \"FACTBASVAL\": \"0.0000000000000000E+00\",\n          \"SCALEBASIN\": \"\",\n          \"SCALBASVAL\": \"0.000000000\",\n          \"UNITMEASUR\": \"\",\n          \"ISO_UNIT\": \"\",\n          \"CURRENCKEY\": \"\",\n          \"CURRENISO\": \"\",\n          \"CONDINCOMP\": \"\",\n          \"CONDCONFIG\": \"\",\n          \"CONDCHAMAN\": \"\",\n          \"COND_NO\": \"\",\n          \"TAX_CODE\": \"\",\n          \"VARCOND\": \"\",\n          \"ACCOUNTKEY\": \"\",\n          \"ACCOUNT_KE\": \"\",\n          \"WT_WITHCD\": \"\",\n          \"STRUCTCOND\": \"\",\n          \"FACTCONBAS\": \"0.0000000000000000E+00\",\n          \"CONDCOINHD\": \"00\"\n        },\n        {\n          \"ITM_NUMBER\": \"000010\",\n          \"COND_ST_NO\": \"672\",\n          \"COND_COUNT\": \"01\",\n          \"COND_TYPE\": \"BX7O\",\n          \"COND_VALUE\": \"-100.000000000\",\n          \"CURRENCY\": \"\",\n          \"COND_UNIT\": \"\",\n          \"COND_P_UNT\": \"0\",\n          \"CURR_ISO\": \"\",\n          \"CD_UNT_ISO\": \"\",\n          \"REFOBJTYPE\": \"\",\n          \"REFOBJKEY\": \"\",\n          \"REFLOGSYS\": \"\",\n          \"APPLICATIO\": \"V\",\n          \"CONPRICDAT\": \"2020-12-14\",\n          \"CALCTYPCON\": \"A\",\n          \"CONBASEVAL\": \"12.520000000\",\n          \"CONEXCHRAT\": \"0.00000\",\n          \"NUMCONVERT\": \"0\",\n          \"DENOMINATO\": \"0\",\n          \"CONDTYPE\": \"\",\n          \"STAT_CON\": \"\",\n          \"SCALETYPE\": \"\",\n          \"ACCRUALS\": \"\",\n          \"CONINVOLST\": \"\",\n          \"CONDORIGIN\": \"A\",\n          \"GROUPCOND\": \"\",\n          \"COND_UPDAT\": \"\",\n          \"ACCESS_SEQ\": \"01\",\n          \"CONDCOUNT\": \"01\",\n          \"ROUNDOFFDI\": \"0.000000000\",\n          \"CONDVALUE\": \"-12.520000000\",\n          \"CURRENCY_2\": \"BRL\",\n          \"CURR_ISO_2\": \"BRL\",\n          \"CONDCNTRL\": \"A\",\n          \"CONDISACTI\": \"\",\n          \"CONDCLASS\": \"A\",\n          \"FACTBASVAL\": \"0.0000000000000000E+00\",\n          \"SCALEBASIN\": \"\",\n          \"SCALBASVAL\": \"0.000000000\",\n          \"UNITMEASUR\": \"\",\n          \"ISO_UNIT\": \"\",\n          \"CURRENCKEY\": \"\",\n          \"CURRENISO\": \"\",\n          \"CONDINCOMP\": \"\",\n          \"CONDCONFIG\": \"\",\n          \"CONDCHAMAN\": \"\",\n          \"COND_NO\": \"0000006853\",\n          \"TAX_CODE\": \"\",\n          \"VARCOND\": \"\",\n          \"ACCOUNTKEY\": \"\",\n          \"ACCOUNT_KE\": \"\",\n          \"WT_WITHCD\": \"\",\n          \"STRUCTCOND\": \"\",\n          \"FACTCONBAS\": \"0.0000000000000000E+00\",\n          \"CONDCOINHD\": \"00\"\n        },\n        {\n          \"ITM_NUMBER\": \"000010\",\n          \"COND_ST_NO\": \"675\",\n          \"COND_COUNT\": \"01\",\n          \"COND_TYPE\": \"BX80\",\n          \"COND_VALUE\": \"0.000000000\",\n          \"CURRENCY\": \"BRL\",\n          \"COND_UNIT\": \"\",\n          \"COND_P_UNT\": \"0\",\n          \"CURR_ISO\": \"BRL\",\n          \"CD_UNT_ISO\": \"\",\n          \"REFOBJTYPE\": \"\",\n          \"REFOBJKEY\": \"\",\n          \"REFLOGSYS\": \"\",\n          \"APPLICATIO\": \"V\",\n          \"CONPRICDAT\": \"2020-12-14\",\n          \"CALCTYPCON\": \"B\",\n          \"CONBASEVAL\": \"1131.680000000\",\n          \"CONEXCHRAT\": \"1.00000\",\n          \"NUMCONVERT\": \"0\",\n          \"DENOMINATO\": \"0\",\n          \"CONDTYPE\": \"1\",\n          \"STAT_CON\": \"X\",\n          \"SCALETYPE\": \"\",\n          \"ACCRUALS\": \"\",\n          \"CONINVOLST\": \"\",\n          \"CONDORIGIN\": \"A\",\n          \"GROUPCOND\": \"\",\n          \"COND_UPDAT\": \"\",\n          \"ACCESS_SEQ\": \"00\",\n          \"CONDCOUNT\": \"00\",\n          \"ROUNDOFFDI\": \"0.000000000\",\n          \"CONDVALUE\": \"164.690000000\",\n          \"CURRENCY_2\": \"BRL\",\n          \"CURR_ISO_2\": \"BRL\",\n          \"CONDCNTRL\": \"A\",\n          \"CONDISACTI\": \"\",\n          \"CONDCLASS\": \"A\",\n          \"FACTBASVAL\": \"0.0000000000000000E+00\",\n          \"SCALEBASIN\": \"\",\n          \"SCALBASVAL\": \"0.000000000\",\n          \"UNITMEASUR\": \"\",\n          \"ISO_UNIT\": \"\",\n          \"CURRENCKEY\": \"\",\n          \"CURRENISO\": \"\",\n          \"CONDINCOMP\": \"\",\n          \"CONDCONFIG\": \"\",\n          \"CONDCHAMAN\": \"\",\n          \"COND_NO\": \"\",\n          \"TAX_CODE\": \"\",\n          \"VARCOND\": \"\",\n          \"ACCOUNTKEY\": \"\",\n          \"ACCOUNT_KE\": \"\",\n          \"WT_WITHCD\": \"\",\n          \"STRUCTCOND\": \"\",\n          \"FACTCONBAS\": \"0.0000000000000000E+00\",\n          \"CONDCOINHD\": \"00\"\n        },\n        {\n          \"ITM_NUMBER\": \"000010\",\n          \"COND_ST_NO\": \"677\",\n          \"COND_COUNT\": \"01\",\n          \"COND_TYPE\": \"BX81\",\n          \"COND_VALUE\": \"0.000000000\",\n          \"CURRENCY\": \"BRL\",\n          \"COND_UNIT\": \"\",\n          \"COND_P_UNT\": \"0\",\n          \"CURR_ISO\": \"BRL\",\n          \"CD_UNT_ISO\": \"\",\n          \"REFOBJTYPE\": \"\",\n          \"REFOBJKEY\": \"\",\n          \"REFLOGSYS\": \"\",\n          \"APPLICATIO\": \"V\",\n          \"CONPRICDAT\": \"2020-12-14\",\n          \"CALCTYPCON\": \"B\",\n          \"CONBASEVAL\": \"1296.370000000\",\n          \"CONEXCHRAT\": \"1.00000\",\n          \"NUMCONVERT\": \"0\",\n          \"DENOMINATO\": \"0\",\n          \"CONDTYPE\": \"1\",\n          \"STAT_CON\": \"X\",\n          \"SCALETYPE\": \"\",\n          \"ACCRUALS\": \"\",\n          \"CONINVOLST\": \"\",\n          \"CONDORIGIN\": \"A\",\n          \"GROUPCOND\": \"\",\n          \"COND_UPDAT\": \"\",\n          \"ACCESS_SEQ\": \"00\",\n          \"CONDCOUNT\": \"00\",\n          \"ROUNDOFFDI\": \"0.000000000\",\n          \"CONDVALUE\": \"0.000000000\",\n          \"CURRENCY_2\": \"BRL\",\n          \"CURR_ISO_2\": \"BRL\",\n          \"CONDCNTRL\": \"A\",\n          \"CONDISACTI\": \"\",\n          \"CONDCLASS\": \"A\",\n          \"FACTBASVAL\": \"0.0000000000000000E+00\",\n          \"SCALEBASIN\": \"\",\n          \"SCALBASVAL\": \"0.000000000\",\n          \"UNITMEASUR\": \"\",\n          \"ISO_UNIT\": \"\",\n          \"CURRENCKEY\": \"\",\n          \"CURRENISO\": \"\",\n          \"CONDINCOMP\": \"\",\n          \"CONDCONFIG\": \"\",\n          \"CONDCHAMAN\": \"\",\n          \"COND_NO\": \"\",\n          \"TAX_CODE\": \"\",\n          \"VARCOND\": \"\",\n          \"ACCOUNTKEY\": \"\",\n          \"ACCOUNT_KE\": \"\",\n          \"WT_WITHCD\": \"\",\n          \"STRUCTCOND\": \"\",\n          \"FACTCONBAS\": \"0.0000000000000000E+00\",\n          \"CONDCOINHD\": \"00\"\n        },\n        {\n          \"ITM_NUMBER\": \"000010\",\n          \"COND_ST_NO\": \"679\",\n          \"COND_COUNT\": \"01\",\n          \"COND_TYPE\": \"BX82\",\n          \"COND_VALUE\": \"100.000000000\",\n          \"CURRENCY\": \"\",\n          \"COND_UNIT\": \"\",\n          \"COND_P_UNT\": \"0\",\n          \"CURR_ISO\": \"\",\n          \"CD_UNT_ISO\": \"\",\n          \"REFOBJTYPE\": \"\",\n          \"REFOBJKEY\": \"\",\n          \"REFLOGSYS\": \"\",\n          \"APPLICATIO\": \"V\",\n          \"CONPRICDAT\": \"2020-12-14\",\n          \"CALCTYPCON\": \"A\",\n          \"CONBASEVAL\": \"1296.370000000\",\n          \"CONEXCHRAT\": \"0.00000\",\n          \"NUMCONVERT\": \"0\",\n          \"DENOMINATO\": \"0\",\n          \"CONDTYPE\": \"D\",\n          \"STAT_CON\": \"\",\n          \"SCALETYPE\": \"\",\n          \"ACCRUALS\": \"\",\n          \"CONINVOLST\": \"\",\n          \"CONDORIGIN\": \"A\",\n          \"GROUPCOND\": \"\",\n          \"COND_UPDAT\": \"\",\n          \"ACCESS_SEQ\": \"01\",\n          \"CONDCOUNT\": \"01\",\n          \"ROUNDOFFDI\": \"0.000000000\",\n          \"CONDVALUE\": \"2.720000000\",\n          \"CURRENCY_2\": \"BRL\",\n          \"CURR_ISO_2\": \"BRL\",\n          \"CONDCNTRL\": \"A\",\n          \"CONDISACTI\": \"\",\n          \"CONDCLASS\": \"D\",\n          \"FACTBASVAL\": \"0.0000000000000000E+00\",\n          \"SCALEBASIN\": \"\",\n          \"SCALBASVAL\": \"0.000000000\",\n          \"UNITMEASUR\": \"\",\n          \"ISO_UNIT\": \"\",\n          \"CURRENCKEY\": \"\",\n          \"CURRENISO\": \"\",\n          \"CONDINCOMP\": \"\",\n          \"CONDCONFIG\": \"\",\n          \"CONDCHAMAN\": \"\",\n          \"COND_NO\": \"0035482469\",\n          \"TAX_CODE\": \"SD\",\n          \"VARCOND\": \"\",\n          \"ACCOUNTKEY\": \"\",\n          \"ACCOUNT_KE\": \"\",\n          \"WT_WITHCD\": \"\",\n          \"STRUCTCOND\": \"\",\n          \"FACTCONBAS\": \"0.0000000000000000E+00\",\n          \"CONDCOINHD\": \"00\"\n        },\n        {\n          \"ITM_NUMBER\": \"000010\",\n          \"COND_ST_NO\": \"680\",\n          \"COND_COUNT\": \"01\",\n          \"COND_TYPE\": \"BX8P\",\n          \"COND_VALUE\": \"0.000000000\",\n          \"CURRENCY\": \"BRL\",\n          \"COND_UNIT\": \"\",\n          \"COND_P_UNT\": \"0\",\n          \"CURR_ISO\": \"BRL\",\n          \"CD_UNT_ISO\": \"\",\n          \"REFOBJTYPE\": \"\",\n          \"REFOBJKEY\": \"\",\n          \"REFLOGSYS\": \"\",\n          \"APPLICATIO\": \"V\",\n          \"CONPRICDAT\": \"2020-12-14\",\n          \"CALCTYPCON\": \"B\",\n          \"CONBASEVAL\": \"1299.090000000\",\n          \"CONEXCHRAT\": \"1.00000\",\n          \"NUMCONVERT\": \"0\",\n          \"DENOMINATO\": \"0\",\n          \"CONDTYPE\": \"1\",\n          \"STAT_CON\": \"\",\n          \"SCALETYPE\": \"\",\n          \"ACCRUALS\": \"\",\n          \"CONINVOLST\": \"\",\n          \"CONDORIGIN\": \"A\",\n          \"GROUPCOND\": \"\",\n          \"COND_UPDAT\": \"\",\n          \"ACCESS_SEQ\": \"00\",\n          \"CONDCOUNT\": \"00\",\n          \"ROUNDOFFDI\": \"0.000000000\",\n          \"CONDVALUE\": \"0.000000000\",\n          \"CURRENCY_2\": \"BRL\",\n          \"CURR_ISO_2\": \"BRL\",\n          \"CONDCNTRL\": \"A\",\n          \"CONDISACTI\": \"\",\n          \"CONDCLASS\": \"A\",\n          \"FACTBASVAL\": \"0.0000000000000000E+00\",\n          \"SCALEBASIN\": \"\",\n          \"SCALBASVAL\": \"0.000000000\",\n          \"UNITMEASUR\": \"\",\n          \"ISO_UNIT\": \"\",\n          \"CURRENCKEY\": \"\",\n          \"CURRENISO\": \"\",\n          \"CONDINCOMP\": \"\",\n          \"CONDCONFIG\": \"\",\n          \"CONDCHAMAN\": \"\",\n          \"COND_NO\": \"\",\n          \"TAX_CODE\": \"\",\n          \"VARCOND\": \"\",\n          \"ACCOUNTKEY\": \"\",\n          \"ACCOUNT_KE\": \"\",\n          \"WT_WITHCD\": \"\",\n          \"STRUCTCOND\": \"\",\n          \"FACTCONBAS\": \"0.0000000000000000E+00\",\n          \"CONDCOINHD\": \"00\"\n        },\n        {\n          \"ITM_NUMBER\": \"000010\",\n          \"COND_ST_NO\": \"683\",\n          \"COND_COUNT\": \"01\",\n          \"COND_TYPE\": \"BX8O\",\n          \"COND_VALUE\": \"-100.000000000\",\n          \"CURRENCY\": \"\",\n          \"COND_UNIT\": \"\",\n          \"COND_P_UNT\": \"0\",\n          \"CURR_ISO\": \"\",\n          \"CD_UNT_ISO\": \"\",\n          \"REFOBJTYPE\": \"\",\n          \"REFOBJKEY\": \"\",\n          \"REFLOGSYS\": \"\",\n          \"APPLICATIO\": \"V\",\n          \"CONPRICDAT\": \"2020-12-14\",\n          \"CALCTYPCON\": \"A\",\n          \"CONBASEVAL\": \"2.720000000\",\n          \"CONEXCHRAT\": \"0.00000\",\n          \"NUMCONVERT\": \"0\",\n          \"DENOMINATO\": \"0\",\n          \"CONDTYPE\": \"\",\n          \"STAT_CON\": \"\",\n          \"SCALETYPE\": \"\",\n          \"ACCRUALS\": \"\",\n          \"CONINVOLST\": \"\",\n          \"CONDORIGIN\": \"A\",\n          \"GROUPCOND\": \"\",\n          \"COND_UPDAT\": \"\",\n          \"ACCESS_SEQ\": \"01\",\n          \"CONDCOUNT\": \"01\",\n          \"ROUNDOFFDI\": \"0.000000000\",\n          \"CONDVALUE\": \"-2.720000000\",\n          \"CURRENCY_2\": \"BRL\",\n          \"CURR_ISO_2\": \"BRL\",\n          \"CONDCNTRL\": \"A\",\n          \"CONDISACTI\": \"\",\n          \"CONDCLASS\": \"A\",\n          \"FACTBASVAL\": \"0.0000000000000000E+00\",\n          \"SCALEBASIN\": \"\",\n          \"SCALBASVAL\": \"0.000000000\",\n          \"UNITMEASUR\": \"\",\n          \"ISO_UNIT\": \"\",\n          \"CURRENCKEY\": \"\",\n          \"CURRENISO\": \"\",\n          \"CONDINCOMP\": \"\",\n          \"CONDCONFIG\": \"\",\n          \"CONDCHAMAN\": \"\",\n          \"COND_NO\": \"0000006853\",\n          \"TAX_CODE\": \"\",\n          \"VARCOND\": \"\",\n          \"ACCOUNTKEY\": \"\",\n          \"ACCOUNT_KE\": \"\",\n          \"WT_WITHCD\": \"\",\n          \"STRUCTCOND\": \"\",\n          \"FACTCONBAS\": \"0.0000000000000000E+00\",\n          \"CONDCOINHD\": \"00\"\n        },\n        {\n          \"ITM_NUMBER\": \"000010\",\n          \"COND_ST_NO\": \"702\",\n          \"COND_COUNT\": \"01\",\n          \"COND_TYPE\": \"IPI3\",\n          \"COND_VALUE\": \"100.000000000\",\n          \"CURRENCY\": \"\",\n          \"COND_UNIT\": \"\",\n          \"COND_P_UNT\": \"0\",\n          \"CURR_ISO\": \"\",\n          \"CD_UNT_ISO\": \"\",\n          \"REFOBJTYPE\": \"\",\n          \"REFOBJKEY\": \"\",\n          \"REFLOGSYS\": \"\",\n          \"APPLICATIO\": \"TX\",\n          \"CONPRICDAT\": \"2020-12-14\",\n          \"CALCTYPCON\": \"A\",\n          \"CONBASEVAL\": \"0.000000000\",\n          \"CONEXCHRAT\": \"0.00000\",\n          \"NUMCONVERT\": \"0\",\n          \"DENOMINATO\": \"0\",\n          \"CONDTYPE\": \"1\",\n          \"STAT_CON\": \"\",\n          \"SCALETYPE\": \"\",\n          \"ACCRUALS\": \"\",\n          \"CONINVOLST\": \"\",\n          \"CONDORIGIN\": \"A\",\n          \"GROUPCOND\": \"\",\n          \"COND_UPDAT\": \"\",\n          \"ACCESS_SEQ\": \"10\",\n          \"CONDCOUNT\": \"01\",\n          \"ROUNDOFFDI\": \"0.000000000\",\n          \"CONDVALUE\": \"0.000000000\",\n          \"CURRENCY_2\": \"BRL\",\n          \"CURR_ISO_2\": \"BRL\",\n          \"CONDCNTRL\": \"A\",\n          \"CONDISACTI\": \"\",\n          \"CONDCLASS\": \"D\",\n          \"FACTBASVAL\": \"0.0000000000000000E+00\",\n          \"SCALEBASIN\": \"\",\n          \"SCALBASVAL\": \"0.000000000\",\n          \"UNITMEASUR\": \"\",\n          \"ISO_UNIT\": \"\",\n          \"CURRENCKEY\": \"\",\n          \"CURRENISO\": \"\",\n          \"CONDINCOMP\": \"\",\n          \"CONDCONFIG\": \"\",\n          \"CONDCHAMAN\": \"\",\n          \"COND_NO\": \"0000006899\",\n          \"TAX_CODE\": \"SD\",\n          \"VARCOND\": \"\",\n          \"ACCOUNTKEY\": \"\",\n          \"ACCOUNT_KE\": \"\",\n          \"WT_WITHCD\": \"\",\n          \"STRUCTCOND\": \"\",\n          \"FACTCONBAS\": \"0.0000000000000000E+00\",\n          \"CONDCOINHD\": \"00\"\n        },\n        {\n          \"ITM_NUMBER\": \"000010\",\n          \"COND_ST_NO\": \"704\",\n          \"COND_COUNT\": \"01\",\n          \"COND_TYPE\": \"ICM3\",\n          \"COND_VALUE\": \"100.000000000\",\n          \"CURRENCY\": \"\",\n          \"COND_UNIT\": \"\",\n          \"COND_P_UNT\": \"0\",\n          \"CURR_ISO\": \"\",\n          \"CD_UNT_ISO\": \"\",\n          \"REFOBJTYPE\": \"\",\n          \"REFOBJKEY\": \"\",\n          \"REFLOGSYS\": \"\",\n          \"APPLICATIO\": \"TX\",\n          \"CONPRICDAT\": \"2020-12-14\",\n          \"CALCTYPCON\": \"A\",\n          \"CONBASEVAL\": \"0.000000000\",\n          \"CONEXCHRAT\": \"0.00000\",\n          \"NUMCONVERT\": \"0\",\n          \"DENOMINATO\": \"0\",\n          \"CONDTYPE\": \"1\",\n          \"STAT_CON\": \"\",\n          \"SCALETYPE\": \"\",\n          \"ACCRUALS\": \"\",\n          \"CONINVOLST\": \"\",\n          \"CONDORIGIN\": \"A\",\n          \"GROUPCOND\": \"\",\n          \"COND_UPDAT\": \"\",\n          \"ACCESS_SEQ\": \"10\",\n          \"CONDCOUNT\": \"01\",\n          \"ROUNDOFFDI\": \"0.000000000\",\n          \"CONDVALUE\": \"0.000000000\",\n          \"CURRENCY_2\": \"BRL\",\n          \"CURR_ISO_2\": \"BRL\",\n          \"CONDCNTRL\": \"A\",\n          \"CONDISACTI\": \"\",\n          \"CONDCLASS\": \"D\",\n          \"FACTBASVAL\": \"0.0000000000000000E+00\",\n          \"SCALEBASIN\": \"\",\n          \"SCALBASVAL\": \"0.000000000\",\n          \"UNITMEASUR\": \"\",\n          \"ISO_UNIT\": \"\",\n          \"CURRENCKEY\": \"\",\n          \"CURRENISO\": \"\",\n          \"CONDINCOMP\": \"\",\n          \"CONDCONFIG\": \"\",\n          \"CONDCHAMAN\": \"\",\n          \"COND_NO\": \"0000006900\",\n          \"TAX_CODE\": \"SD\",\n          \"VARCOND\": \"\",\n          \"ACCOUNTKEY\": \"\",\n          \"ACCOUNT_KE\": \"\",\n          \"WT_WITHCD\": \"\",\n          \"STRUCTCOND\": \"\",\n          \"FACTCONBAS\": \"0.0000000000000000E+00\",\n          \"CONDCOINHD\": \"00\"\n        },\n        {\n          \"ITM_NUMBER\": \"000010\",\n          \"COND_ST_NO\": \"706\",\n          \"COND_COUNT\": \"01\",\n          \"COND_TYPE\": \"ICS3\",\n          \"COND_VALUE\": \"100.000000000\",\n          \"CURRENCY\": \"\",\n          \"COND_UNIT\": \"\",\n          \"COND_P_UNT\": \"0\",\n          \"CURR_ISO\": \"\",\n          \"CD_UNT_ISO\": \"\",\n          \"REFOBJTYPE\": \"\",\n          \"REFOBJKEY\": \"\",\n          \"REFLOGSYS\": \"\",\n          \"APPLICATIO\": \"TX\",\n          \"CONPRICDAT\": \"2020-12-14\",\n          \"CALCTYPCON\": \"A\",\n          \"CONBASEVAL\": \"0.000000000\",\n          \"CONEXCHRAT\": \"0.00000\",\n          \"NUMCONVERT\": \"0\",\n          \"DENOMINATO\": \"0\",\n          \"CONDTYPE\": \"1\",\n          \"STAT_CON\": \"\",\n          \"SCALETYPE\": \"\",\n          \"ACCRUALS\": \"\",\n          \"CONINVOLST\": \"\",\n          \"CONDORIGIN\": \"A\",\n          \"GROUPCOND\": \"\",\n          \"COND_UPDAT\": \"\",\n          \"ACCESS_SEQ\": \"10\",\n          \"CONDCOUNT\": \"01\",\n          \"ROUNDOFFDI\": \"0.000000000\",\n          \"CONDVALUE\": \"0.000000000\",\n          \"CURRENCY_2\": \"BRL\",\n          \"CURR_ISO_2\": \"BRL\",\n          \"CONDCNTRL\": \"A\",\n          \"CONDISACTI\": \"\",\n          \"CONDCLASS\": \"D\",\n          \"FACTBASVAL\": \"0.0000000000000000E+00\",\n          \"SCALEBASIN\": \"\",\n          \"SCALBASVAL\": \"0.000000000\",\n          \"UNITMEASUR\": \"\",\n          \"ISO_UNIT\": \"\",\n          \"CURRENCKEY\": \"\",\n          \"CURRENISO\": \"\",\n          \"CONDINCOMP\": \"\",\n          \"CONDCONFIG\": \"\",\n          \"CONDCHAMAN\": \"\",\n          \"COND_NO\": \"0000006901\",\n          \"TAX_CODE\": \"SD\",\n          \"VARCOND\": \"\",\n          \"ACCOUNTKEY\": \"\",\n          \"ACCOUNT_KE\": \"\",\n          \"WT_WITHCD\": \"\",\n          \"STRUCTCOND\": \"\",\n          \"FACTCONBAS\": \"0.0000000000000000E+00\",\n          \"CONDCOINHD\": \"00\"\n        },\n        {\n          \"ITM_NUMBER\": \"000010\",\n          \"COND_ST_NO\": \"770\",\n          \"COND_COUNT\": \"01\",\n          \"COND_TYPE\": \"VPRS\",\n          \"COND_VALUE\": \"45.400000000\",\n          \"CURRENCY\": \"BRL\",\n          \"COND_UNIT\": \"CS\",\n          \"COND_P_UNT\": \"1\",\n          \"CURR_ISO\": \"BRL\",\n          \"CD_UNT_ISO\": \"CS\",\n          \"REFOBJTYPE\": \"\",\n          \"REFOBJKEY\": \"\",\n          \"REFLOGSYS\": \"\",\n          \"APPLICATIO\": \"V\",\n          \"CONPRICDAT\": \"2020-12-14\",\n          \"CALCTYPCON\": \"C\",\n          \"CONBASEVAL\": \"1.000000000\",\n          \"CONEXCHRAT\": \"1.00000\",\n          \"NUMCONVERT\": \"1\",\n          \"DENOMINATO\": \"1\",\n          \"CONDTYPE\": \"G\",\n          \"STAT_CON\": \"X\",\n          \"SCALETYPE\": \"\",\n          \"ACCRUALS\": \"\",\n          \"CONINVOLST\": \"\",\n          \"CONDORIGIN\": \"A\",\n          \"GROUPCOND\": \"\",\n          \"COND_UPDAT\": \"\",\n          \"ACCESS_SEQ\": \"00\",\n          \"CONDCOUNT\": \"00\",\n          \"ROUNDOFFDI\": \"0.000000000\",\n          \"CONDVALUE\": \"45.400000000\",\n          \"CURRENCY_2\": \"BRL\",\n          \"CURR_ISO_2\": \"BRL\",\n          \"CONDCNTRL\": \"A\",\n          \"CONDISACTI\": \"\",\n          \"CONDCLASS\": \"B\",\n          \"FACTBASVAL\": \"0.0000000000000000E+00\",\n          \"SCALEBASIN\": \"\",\n          \"SCALBASVAL\": \"0.000000000\",\n          \"UNITMEASUR\": \"\",\n          \"ISO_UNIT\": \"\",\n          \"CURRENCKEY\": \"\",\n          \"CURRENISO\": \"\",\n          \"CONDINCOMP\": \"\",\n          \"CONDCONFIG\": \"\",\n          \"CONDCHAMAN\": \"\",\n          \"COND_NO\": \"\",\n          \"TAX_CODE\": \"\",\n          \"VARCOND\": \"\",\n          \"ACCOUNTKEY\": \"\",\n          \"ACCOUNT_KE\": \"\",\n          \"WT_WITHCD\": \"\",\n          \"STRUCTCOND\": \"\",\n          \"FACTCONBAS\": \"0.0000000000000000E+00\",\n          \"CONDCOINHD\": \"00\"\n        },\n        {\n          \"ITM_NUMBER\": \"000010\",\n          \"COND_ST_NO\": \"780\",\n          \"COND_COUNT\": \"01\",\n          \"COND_TYPE\": \"BX9M\",\n          \"COND_VALUE\": \"0.000000000\",\n          \"CURRENCY\": \"BRL\",\n          \"COND_UNIT\": \"\",\n          \"COND_P_UNT\": \"0\",\n          \"CURR_ISO\": \"BRL\",\n          \"CD_UNT_ISO\": \"\",\n          \"REFOBJTYPE\": \"\",\n          \"REFOBJKEY\": \"\",\n          \"REFLOGSYS\": \"\",\n          \"APPLICATIO\": \"V\",\n          \"CONPRICDAT\": \"2020-12-14\",\n          \"CALCTYPCON\": \"B\",\n          \"CONBASEVAL\": \"45.400000000\",\n          \"CONEXCHRAT\": \"1.00000\",\n          \"NUMCONVERT\": \"0\",\n          \"DENOMINATO\": \"0\",\n          \"CONDTYPE\": \"1\",\n          \"STAT_CON\": \"X\",\n          \"SCALETYPE\": \"\",\n          \"ACCRUALS\": \"\",\n          \"CONINVOLST\": \"\",\n          \"CONDORIGIN\": \"A\",\n          \"GROUPCOND\": \"\",\n          \"COND_UPDAT\": \"\",\n          \"ACCESS_SEQ\": \"00\",\n          \"CONDCOUNT\": \"00\",\n          \"ROUNDOFFDI\": \"0.000000000\",\n          \"CONDVALUE\": \"0.000000000\",\n          \"CURRENCY_2\": \"BRL\",\n          \"CURR_ISO_2\": \"BRL\",\n          \"CONDCNTRL\": \"A\",\n          \"CONDISACTI\": \"\",\n          \"CONDCLASS\": \"A\",\n          \"FACTBASVAL\": \"0.0000000000000000E+00\",\n          \"SCALEBASIN\": \"\",\n          \"SCALBASVAL\": \"0.000000000\",\n          \"UNITMEASUR\": \"\",\n          \"ISO_UNIT\": \"\",\n          \"CURRENCKEY\": \"\",\n          \"CURRENISO\": \"\",\n          \"CONDINCOMP\": \"\",\n          \"CONDCONFIG\": \"\",\n          \"CONDCHAMAN\": \"\",\n          \"COND_NO\": \"\",\n          \"TAX_CODE\": \"\",\n          \"VARCOND\": \"\",\n          \"ACCOUNTKEY\": \"\",\n          \"ACCOUNT_KE\": \"\",\n          \"WT_WITHCD\": \"\",\n          \"STRUCTCOND\": \"\",\n          \"FACTCONBAS\": \"0.0000000000000000E+00\",\n          \"CONDCOINHD\": \"00\"\n        },\n        {\n          \"ITM_NUMBER\": \"000010\",\n          \"COND_ST_NO\": \"780\",\n          \"COND_COUNT\": \"02\",\n          \"COND_TYPE\": \"BX9L\",\n          \"COND_VALUE\": \"0.000000000\",\n          \"CURRENCY\": \"BRL\",\n          \"COND_UNIT\": \"\",\n          \"COND_P_UNT\": \"0\",\n          \"CURR_ISO\": \"BRL\",\n          \"CD_UNT_ISO\": \"\",\n          \"REFOBJTYPE\": \"\",\n          \"REFOBJKEY\": \"\",\n          \"REFLOGSYS\": \"\",\n          \"APPLICATIO\": \"V\",\n          \"CONPRICDAT\": \"2020-12-14\",\n          \"CALCTYPCON\": \"B\",\n          \"CONBASEVAL\": \"45.400000000\",\n          \"CONEXCHRAT\": \"1.00000\",\n          \"NUMCONVERT\": \"0\",\n          \"DENOMINATO\": \"0\",\n          \"CONDTYPE\": \"1\",\n          \"STAT_CON\": \"X\",\n          \"SCALETYPE\": \"\",\n          \"ACCRUALS\": \"\",\n          \"CONINVOLST\": \"\",\n          \"CONDORIGIN\": \"A\",\n          \"GROUPCOND\": \"\",\n          \"COND_UPDAT\": \"\",\n          \"ACCESS_SEQ\": \"00\",\n          \"CONDCOUNT\": \"00\",\n          \"ROUNDOFFDI\": \"0.000000000\",\n          \"CONDVALUE\": \"0.000000000\",\n          \"CURRENCY_2\": \"BRL\",\n          \"CURR_ISO_2\": \"BRL\",\n          \"CONDCNTRL\": \"A\",\n          \"CONDISACTI\": \"\",\n          \"CONDCLASS\": \"A\",\n          \"FACTBASVAL\": \"0.0000000000000000E+00\",\n          \"SCALEBASIN\": \"\",\n          \"SCALBASVAL\": \"0.000000000\",\n          \"UNITMEASUR\": \"\",\n          \"ISO_UNIT\": \"\",\n          \"CURRENCKEY\": \"\",\n          \"CURRENISO\": \"\",\n          \"CONDINCOMP\": \"\",\n          \"CONDCONFIG\": \"\",\n          \"CONDCHAMAN\": \"\",\n          \"COND_NO\": \"\",\n          \"TAX_CODE\": \"\",\n          \"VARCOND\": \"\",\n          \"ACCOUNTKEY\": \"\",\n          \"ACCOUNT_KE\": \"\",\n          \"WT_WITHCD\": \"\",\n          \"STRUCTCOND\": \"\",\n          \"FACTCONBAS\": \"0.0000000000000000E+00\",\n          \"CONDCOINHD\": \"00\"\n        },\n        {\n          \"ITM_NUMBER\": \"000010\",\n          \"COND_ST_NO\": \"780\",\n          \"COND_COUNT\": \"03\",\n          \"COND_TYPE\": \"BX9H\",\n          \"COND_VALUE\": \"0.000000000\",\n          \"CURRENCY\": \"BRL\",\n          \"COND_UNIT\": \"\",\n          \"COND_P_UNT\": \"0\",\n          \"CURR_ISO\": \"BRL\",\n          \"CD_UNT_ISO\": \"\",\n          \"REFOBJTYPE\": \"\",\n          \"REFOBJKEY\": \"\",\n          \"REFLOGSYS\": \"\",\n          \"APPLICATIO\": \"V\",\n          \"CONPRICDAT\": \"2020-12-14\",\n          \"CALCTYPCON\": \"B\",\n          \"CONBASEVAL\": \"45.400000000\",\n          \"CONEXCHRAT\": \"1.00000\",\n          \"NUMCONVERT\": \"0\",\n          \"DENOMINATO\": \"0\",\n          \"CONDTYPE\": \"1\",\n          \"STAT_CON\": \"X\",\n          \"SCALETYPE\": \"\",\n          \"ACCRUALS\": \"\",\n          \"CONINVOLST\": \"\",\n          \"CONDORIGIN\": \"A\",\n          \"GROUPCOND\": \"\",\n          \"COND_UPDAT\": \"\",\n          \"ACCESS_SEQ\": \"00\",\n          \"CONDCOUNT\": \"00\",\n          \"ROUNDOFFDI\": \"0.000000000\",\n          \"CONDVALUE\": \"0.000000000\",\n          \"CURRENCY_2\": \"BRL\",\n          \"CURR_ISO_2\": \"BRL\",\n          \"CONDCNTRL\": \"A\",\n          \"CONDISACTI\": \"\",\n          \"CONDCLASS\": \"A\",\n          \"FACTBASVAL\": \"0.0000000000000000E+00\",\n          \"SCALEBASIN\": \"\",\n          \"SCALBASVAL\": \"0.000000000\",\n          \"UNITMEASUR\": \"\",\n          \"ISO_UNIT\": \"\",\n          \"CURRENCKEY\": \"\",\n          \"CURRENISO\": \"\",\n          \"CONDINCOMP\": \"\",\n          \"CONDCONFIG\": \"\",\n          \"CONDCHAMAN\": \"\",\n          \"COND_NO\": \"\",\n          \"TAX_CODE\": \"\",\n          \"VARCOND\": \"\",\n          \"ACCOUNTKEY\": \"\",\n          \"ACCOUNT_KE\": \"\",\n          \"WT_WITHCD\": \"\",\n          \"STRUCTCOND\": \"\",\n          \"FACTCONBAS\": \"0.0000000000000000E+00\",\n          \"CONDCOINHD\": \"00\"\n        },\n        {\n          \"ITM_NUMBER\": \"000010\",\n          \"COND_ST_NO\": \"780\",\n          \"COND_COUNT\": \"04\",\n          \"COND_TYPE\": \"BX90\",\n          \"COND_VALUE\": \"0.000000000\",\n          \"CURRENCY\": \"BRL\",\n          \"COND_UNIT\": \"\",\n          \"COND_P_UNT\": \"0\",\n          \"CURR_ISO\": \"BRL\",\n          \"CD_UNT_ISO\": \"\",\n          \"REFOBJTYPE\": \"\",\n          \"REFOBJKEY\": \"\",\n          \"REFLOGSYS\": \"\",\n          \"APPLICATIO\": \"V\",\n          \"CONPRICDAT\": \"2020-12-14\",\n          \"CALCTYPCON\": \"B\",\n          \"CONBASEVAL\": \"45.400000000\",\n          \"CONEXCHRAT\": \"1.00000\",\n          \"NUMCONVERT\": \"0\",\n          \"DENOMINATO\": \"0\",\n          \"CONDTYPE\": \"1\",\n          \"STAT_CON\": \"X\",\n          \"SCALETYPE\": \"\",\n          \"ACCRUALS\": \"\",\n          \"CONINVOLST\": \"\",\n          \"CONDORIGIN\": \"A\",\n          \"GROUPCOND\": \"\",\n          \"COND_UPDAT\": \"\",\n          \"ACCESS_SEQ\": \"00\",\n          \"CONDCOUNT\": \"00\",\n          \"ROUNDOFFDI\": \"0.000000000\",\n          \"CONDVALUE\": \"0.000000000\",\n          \"CURRENCY_2\": \"BRL\",\n          \"CURR_ISO_2\": \"BRL\",\n          \"CONDCNTRL\": \"A\",\n          \"CONDISACTI\": \"\",\n          \"CONDCLASS\": \"A\",\n          \"FACTBASVAL\": \"0.0000000000000000E+00\",\n          \"SCALEBASIN\": \"\",\n          \"SCALBASVAL\": \"0.000000000\",\n          \"UNITMEASUR\": \"\",\n          \"ISO_UNIT\": \"\",\n          \"CURRENCKEY\": \"\",\n          \"CURRENISO\": \"\",\n          \"CONDINCOMP\": \"\",\n          \"CONDCONFIG\": \"\",\n          \"CONDCHAMAN\": \"\",\n          \"COND_NO\": \"\",\n          \"TAX_CODE\": \"\",\n          \"VARCOND\": \"\",\n          \"ACCOUNTKEY\": \"\",\n          \"ACCOUNT_KE\": \"\",\n          \"WT_WITHCD\": \"\",\n          \"STRUCTCOND\": \"\",\n          \"FACTCONBAS\": \"0.0000000000000000E+00\",\n          \"CONDCOINHD\": \"00\"\n        },\n        {\n          \"ITM_NUMBER\": \"000010\",\n          \"COND_ST_NO\": \"780\",\n          \"COND_COUNT\": \"05\",\n          \"COND_TYPE\": \"BX9A\",\n          \"COND_VALUE\": \"0.000000000\",\n          \"CURRENCY\": \"BRL\",\n          \"COND_UNIT\": \"\",\n          \"COND_P_UNT\": \"0\",\n          \"CURR_ISO\": \"BRL\",\n          \"CD_UNT_ISO\": \"\",\n          \"REFOBJTYPE\": \"\",\n          \"REFOBJKEY\": \"\",\n          \"REFLOGSYS\": \"\",\n          \"APPLICATIO\": \"V\",\n          \"CONPRICDAT\": \"2020-12-14\",\n          \"CALCTYPCON\": \"B\",\n          \"CONBASEVAL\": \"45.400000000\",\n          \"CONEXCHRAT\": \"1.00000\",\n          \"NUMCONVERT\": \"0\",\n          \"DENOMINATO\": \"0\",\n          \"CONDTYPE\": \"1\",\n          \"STAT_CON\": \"X\",\n          \"SCALETYPE\": \"\",\n          \"ACCRUALS\": \"\",\n          \"CONINVOLST\": \"\",\n          \"CONDORIGIN\": \"A\",\n          \"GROUPCOND\": \"\",\n          \"COND_UPDAT\": \"\",\n          \"ACCESS_SEQ\": \"00\",\n          \"CONDCOUNT\": \"00\",\n          \"ROUNDOFFDI\": \"0.000000000\",\n          \"CONDVALUE\": \"172.920000000\",\n          \"CURRENCY_2\": \"BRL\",\n          \"CURR_ISO_2\": \"BRL\",\n          \"CONDCNTRL\": \"A\",\n          \"CONDISACTI\": \"\",\n          \"CONDCLASS\": \"A\",\n          \"FACTBASVAL\": \"0.0000000000000000E+00\",\n          \"SCALEBASIN\": \"\",\n          \"SCALBASVAL\": \"0.000000000\",\n          \"UNITMEASUR\": \"\",\n          \"ISO_UNIT\": \"\",\n          \"CURRENCKEY\": \"\",\n          \"CURRENISO\": \"\",\n          \"CONDINCOMP\": \"\",\n          \"CONDCONFIG\": \"\",\n          \"CONDCHAMAN\": \"\",\n          \"COND_NO\": \"\",\n          \"TAX_CODE\": \"\",\n          \"VARCOND\": \"\",\n          \"ACCOUNTKEY\": \"\",\n          \"ACCOUNT_KE\": \"\",\n          \"WT_WITHCD\": \"\",\n          \"STRUCTCOND\": \"\",\n          \"FACTCONBAS\": \"0.0000000000000000E+00\",\n          \"CONDCOINHD\": \"00\"\n        },\n        {\n          \"ITM_NUMBER\": \"000010\",\n          \"COND_ST_NO\": \"781\",\n          \"COND_COUNT\": \"01\",\n          \"COND_TYPE\": \"BX92\",\n          \"COND_VALUE\": \"0.000000000\",\n          \"CURRENCY\": \"BRL\",\n          \"COND_UNIT\": \"\",\n          \"COND_P_UNT\": \"0\",\n          \"CURR_ISO\": \"BRL\",\n          \"CD_UNT_ISO\": \"\",\n          \"REFOBJTYPE\": \"\",\n          \"REFOBJKEY\": \"\",\n          \"REFLOGSYS\": \"\",\n          \"APPLICATIO\": \"V\",\n          \"CONPRICDAT\": \"2020-12-14\",\n          \"CALCTYPCON\": \"B\",\n          \"CONBASEVAL\": \"218.320000000\",\n          \"CONEXCHRAT\": \"1.00000\",\n          \"NUMCONVERT\": \"0\",\n          \"DENOMINATO\": \"0\",\n          \"CONDTYPE\": \"1\",\n          \"STAT_CON\": \"X\",\n          \"SCALETYPE\": \"\",\n          \"ACCRUALS\": \"\",\n          \"CONINVOLST\": \"\",\n          \"CONDORIGIN\": \"A\",\n          \"GROUPCOND\": \"\",\n          \"COND_UPDAT\": \"\",\n          \"ACCESS_SEQ\": \"00\",\n          \"CONDCOUNT\": \"00\",\n          \"ROUNDOFFDI\": \"0.000000000\",\n          \"CONDVALUE\": \"180.000000000\",\n          \"CURRENCY_2\": \"BRL\",\n          \"CURR_ISO_2\": \"BRL\",\n          \"CONDCNTRL\": \"A\",\n          \"CONDISACTI\": \"\",\n          \"CONDCLASS\": \"A\",\n          \"FACTBASVAL\": \"0.0000000000000000E+00\",\n          \"SCALEBASIN\": \"\",\n          \"SCALBASVAL\": \"0.000000000\",\n          \"UNITMEASUR\": \"\",\n          \"ISO_UNIT\": \"\",\n          \"CURRENCKEY\": \"\",\n          \"CURRENISO\": \"\",\n          \"CONDINCOMP\": \"\",\n          \"CONDCONFIG\": \"\",\n          \"CONDCHAMAN\": \"\",\n          \"COND_NO\": \"\",\n          \"TAX_CODE\": \"\",\n          \"VARCOND\": \"\",\n          \"ACCOUNTKEY\": \"\",\n          \"ACCOUNT_KE\": \"\",\n          \"WT_WITHCD\": \"\",\n          \"STRUCTCOND\": \"\",\n          \"FACTCONBAS\": \"0.0000000000000000E+00\",\n          \"CONDCOINHD\": \"00\"\n        },\n        {\n          \"ITM_NUMBER\": \"000010\",\n          \"COND_ST_NO\": \"782\",\n          \"COND_COUNT\": \"01\",\n          \"COND_TYPE\": \"BX94\",\n          \"COND_VALUE\": \"100.000000000\",\n          \"CURRENCY\": \"\",\n          \"COND_UNIT\": \"\",\n          \"COND_P_UNT\": \"0\",\n          \"CURR_ISO\": \"\",\n          \"CD_UNT_ISO\": \"\",\n          \"REFOBJTYPE\": \"\",\n          \"REFOBJKEY\": \"\",\n          \"REFLOGSYS\": \"\",\n          \"APPLICATIO\": \"V\",\n          \"CONPRICDAT\": \"2020-12-14\",\n          \"CALCTYPCON\": \"A\",\n          \"CONBASEVAL\": \"398.320000000\",\n          \"CONEXCHRAT\": \"0.00000\",\n          \"NUMCONVERT\": \"0\",\n          \"DENOMINATO\": \"0\",\n          \"CONDTYPE\": \"D\",\n          \"STAT_CON\": \"\",\n          \"SCALETYPE\": \"\",\n          \"ACCRUALS\": \"\",\n          \"CONINVOLST\": \"\",\n          \"CONDORIGIN\": \"A\",\n          \"GROUPCOND\": \"\",\n          \"COND_UPDAT\": \"\",\n          \"ACCESS_SEQ\": \"01\",\n          \"CONDCOUNT\": \"01\",\n          \"ROUNDOFFDI\": \"0.000000000\",\n          \"CONDVALUE\": \"0.000000000\",\n          \"CURRENCY_2\": \"BRL\",\n          \"CURR_ISO_2\": \"BRL\",\n          \"CONDCNTRL\": \"A\",\n          \"CONDISACTI\": \"\",\n          \"CONDCLASS\": \"D\",\n          \"FACTBASVAL\": \"0.0000000000000000E+00\",\n          \"SCALEBASIN\": \"\",\n          \"SCALBASVAL\": \"0.000000000\",\n          \"UNITMEASUR\": \"\",\n          \"ISO_UNIT\": \"\",\n          \"CURRENCKEY\": \"\",\n          \"CURRENISO\": \"\",\n          \"CONDINCOMP\": \"\",\n          \"CONDCONFIG\": \"\",\n          \"CONDCHAMAN\": \"\",\n          \"COND_NO\": \"0035482469\",\n          \"TAX_CODE\": \"SD\",\n          \"VARCOND\": \"\",\n          \"ACCOUNTKEY\": \"\",\n          \"ACCOUNT_KE\": \"\",\n          \"WT_WITHCD\": \"\",\n          \"STRUCTCOND\": \"\",\n          \"FACTCONBAS\": \"0.0000000000000000E+00\",\n          \"CONDCOINHD\": \"00\"\n        },\n        {\n          \"ITM_NUMBER\": \"000010\",\n          \"COND_ST_NO\": \"783\",\n          \"COND_COUNT\": \"01\",\n          \"COND_TYPE\": \"BX91\",\n          \"COND_VALUE\": \"0.000000000\",\n          \"CURRENCY\": \"BRL\",\n          \"COND_UNIT\": \"\",\n          \"COND_P_UNT\": \"0\",\n          \"CURR_ISO\": \"BRL\",\n          \"CD_UNT_ISO\": \"\",\n          \"REFOBJTYPE\": \"\",\n          \"REFOBJKEY\": \"\",\n          \"REFLOGSYS\": \"\",\n          \"APPLICATIO\": \"V\",\n          \"CONPRICDAT\": \"2020-12-14\",\n          \"CALCTYPCON\": \"B\",\n          \"CONBASEVAL\": \"398.320000000\",\n          \"CONEXCHRAT\": \"1.00000\",\n          \"NUMCONVERT\": \"0\",\n          \"DENOMINATO\": \"0\",\n          \"CONDTYPE\": \"1\",\n          \"STAT_CON\": \"X\",\n          \"SCALETYPE\": \"\",\n          \"ACCRUALS\": \"\",\n          \"CONINVOLST\": \"\",\n          \"CONDORIGIN\": \"A\",\n          \"GROUPCOND\": \"\",\n          \"COND_UPDAT\": \"\",\n          \"ACCESS_SEQ\": \"00\",\n          \"CONDCOUNT\": \"00\",\n          \"ROUNDOFFDI\": \"0.000000000\",\n          \"CONDVALUE\": \"172.920000000\",\n          \"CURRENCY_2\": \"BRL\",\n          \"CURR_ISO_2\": \"BRL\",\n          \"CONDCNTRL\": \"A\",\n          \"CONDISACTI\": \"\",\n          \"CONDCLASS\": \"A\",\n          \"FACTBASVAL\": \"0.0000000000000000E+00\",\n          \"SCALEBASIN\": \"\",\n          \"SCALBASVAL\": \"0.000000000\",\n          \"UNITMEASUR\": \"\",\n          \"ISO_UNIT\": \"\",\n          \"CURRENCKEY\": \"\",\n          \"CURRENISO\": \"\",\n          \"CONDINCOMP\": \"\",\n          \"CONDCONFIG\": \"\",\n          \"CONDCHAMAN\": \"\",\n          \"COND_NO\": \"\",\n          \"TAX_CODE\": \"\",\n          \"VARCOND\": \"\",\n          \"ACCOUNTKEY\": \"\",\n          \"ACCOUNT_KE\": \"\",\n          \"WT_WITHCD\": \"\",\n          \"STRUCTCOND\": \"\",\n          \"FACTCONBAS\": \"0.0000000000000000E+00\",\n          \"CONDCOINHD\": \"00\"\n        },\n        {\n          \"ITM_NUMBER\": \"000010\",\n          \"COND_ST_NO\": \"783\",\n          \"COND_COUNT\": \"02\",\n          \"COND_TYPE\": \"BX9B\",\n          \"COND_VALUE\": \"0.000000000\",\n          \"CURRENCY\": \"BRL\",\n          \"COND_UNIT\": \"\",\n          \"COND_P_UNT\": \"0\",\n          \"CURR_ISO\": \"BRL\",\n          \"CD_UNT_ISO\": \"\",\n          \"REFOBJTYPE\": \"\",\n          \"REFOBJKEY\": \"\",\n          \"REFLOGSYS\": \"\",\n          \"APPLICATIO\": \"V\",\n          \"CONPRICDAT\": \"2020-12-14\",\n          \"CALCTYPCON\": \"B\",\n          \"CONBASEVAL\": \"571.240000000\",\n          \"CONEXCHRAT\": \"1.00000\",\n          \"NUMCONVERT\": \"0\",\n          \"DENOMINATO\": \"0\",\n          \"CONDTYPE\": \"1\",\n          \"STAT_CON\": \"X\",\n          \"SCALETYPE\": \"\",\n          \"ACCRUALS\": \"\",\n          \"CONINVOLST\": \"\",\n          \"CONDORIGIN\": \"A\",\n          \"GROUPCOND\": \"\",\n          \"COND_UPDAT\": \"\",\n          \"ACCESS_SEQ\": \"00\",\n          \"CONDCOUNT\": \"00\",\n          \"ROUNDOFFDI\": \"0.000000000\",\n          \"CONDVALUE\": \"0.000000000\",\n          \"CURRENCY_2\": \"BRL\",\n          \"CURR_ISO_2\": \"BRL\",\n          \"CONDCNTRL\": \"A\",\n          \"CONDISACTI\": \"\",\n          \"CONDCLASS\": \"A\",\n          \"FACTBASVAL\": \"0.0000000000000000E+00\",\n          \"SCALEBASIN\": \"\",\n          \"SCALBASVAL\": \"0.000000000\",\n          \"UNITMEASUR\": \"\",\n          \"ISO_UNIT\": \"\",\n          \"CURRENCKEY\": \"\",\n          \"CURRENISO\": \"\",\n          \"CONDINCOMP\": \"\",\n          \"CONDCONFIG\": \"\",\n          \"CONDCHAMAN\": \"\",\n          \"COND_NO\": \"\",\n          \"TAX_CODE\": \"\",\n          \"VARCOND\": \"\",\n          \"ACCOUNTKEY\": \"\",\n          \"ACCOUNT_KE\": \"\",\n          \"WT_WITHCD\": \"\",\n          \"STRUCTCOND\": \"\",\n          \"FACTCONBAS\": \"0.0000000000000000E+00\",\n          \"CONDCOINHD\": \"00\"\n        },\n        {\n          \"ITM_NUMBER\": \"000010\",\n          \"COND_ST_NO\": \"784\",\n          \"COND_COUNT\": \"01\",\n          \"COND_TYPE\": \"BX93\",\n          \"COND_VALUE\": \"0.000000000\",\n          \"CURRENCY\": \"BRL\",\n          \"COND_UNIT\": \"\",\n          \"COND_P_UNT\": \"0\",\n          \"CURR_ISO\": \"BRL\",\n          \"CD_UNT_ISO\": \"\",\n          \"REFOBJTYPE\": \"\",\n          \"REFOBJKEY\": \"\",\n          \"REFLOGSYS\": \"\",\n          \"APPLICATIO\": \"V\",\n          \"CONPRICDAT\": \"2020-12-14\",\n          \"CALCTYPCON\": \"B\",\n          \"CONBASEVAL\": \"571.240000000\",\n          \"CONEXCHRAT\": \"1.00000\",\n          \"NUMCONVERT\": \"0\",\n          \"DENOMINATO\": \"0\",\n          \"CONDTYPE\": \"1\",\n          \"STAT_CON\": \"X\",\n          \"SCALETYPE\": \"\",\n          \"ACCRUALS\": \"\",\n          \"CONINVOLST\": \"\",\n          \"CONDORIGIN\": \"A\",\n          \"GROUPCOND\": \"\",\n          \"COND_UPDAT\": \"\",\n          \"ACCESS_SEQ\": \"00\",\n          \"CONDCOUNT\": \"00\",\n          \"ROUNDOFFDI\": \"0.000000000\",\n          \"CONDVALUE\": \"180.000000000\",\n          \"CURRENCY_2\": \"BRL\",\n          \"CURR_ISO_2\": \"BRL\",\n          \"CONDCNTRL\": \"A\",\n          \"CONDISACTI\": \"\",\n          \"CONDCLASS\": \"A\",\n          \"FACTBASVAL\": \"0.0000000000000000E+00\",\n          \"SCALEBASIN\": \"\",\n          \"SCALBASVAL\": \"0.000000000\",\n          \"UNITMEASUR\": \"\",\n          \"ISO_UNIT\": \"\",\n          \"CURRENCKEY\": \"\",\n          \"CURRENISO\": \"\",\n          \"CONDINCOMP\": \"\",\n          \"CONDCONFIG\": \"\",\n          \"CONDCHAMAN\": \"\",\n          \"COND_NO\": \"\",\n          \"TAX_CODE\": \"\",\n          \"VARCOND\": \"\",\n          \"ACCOUNTKEY\": \"\",\n          \"ACCOUNT_KE\": \"\",\n          \"WT_WITHCD\": \"\",\n          \"STRUCTCOND\": \"\",\n          \"FACTCONBAS\": \"0.0000000000000000E+00\",\n          \"CONDCOINHD\": \"00\"\n        },\n        {\n          \"ITM_NUMBER\": \"000010\",\n          \"COND_ST_NO\": \"786\",\n          \"COND_COUNT\": \"01\",\n          \"COND_TYPE\": \"BX95\",\n          \"COND_VALUE\": \"100.000000000\",\n          \"CURRENCY\": \"\",\n          \"COND_UNIT\": \"\",\n          \"COND_P_UNT\": \"0\",\n          \"CURR_ISO\": \"\",\n          \"CD_UNT_ISO\": \"\",\n          \"REFOBJTYPE\": \"\",\n          \"REFOBJKEY\": \"\",\n          \"REFLOGSYS\": \"\",\n          \"APPLICATIO\": \"V\",\n          \"CONPRICDAT\": \"2020-12-14\",\n          \"CALCTYPCON\": \"A\",\n          \"CONBASEVAL\": \"751.240000000\",\n          \"CONEXCHRAT\": \"0.00000\",\n          \"NUMCONVERT\": \"0\",\n          \"DENOMINATO\": \"0\",\n          \"CONDTYPE\": \"D\",\n          \"STAT_CON\": \"\",\n          \"SCALETYPE\": \"\",\n          \"ACCRUALS\": \"\",\n          \"CONINVOLST\": \"\",\n          \"CONDORIGIN\": \"A\",\n          \"GROUPCOND\": \"\",\n          \"COND_UPDAT\": \"\",\n          \"ACCESS_SEQ\": \"01\",\n          \"CONDCOUNT\": \"01\",\n          \"ROUNDOFFDI\": \"0.000000000\",\n          \"CONDVALUE\": \"10.380000000\",\n          \"CURRENCY_2\": \"BRL\",\n          \"CURR_ISO_2\": \"BRL\",\n          \"CONDCNTRL\": \"A\",\n          \"CONDISACTI\": \"\",\n          \"CONDCLASS\": \"D\",\n          \"FACTBASVAL\": \"0.0000000000000000E+00\",\n          \"SCALEBASIN\": \"\",\n          \"SCALBASVAL\": \"0.000000000\",\n          \"UNITMEASUR\": \"\",\n          \"ISO_UNIT\": \"\",\n          \"CURRENCKEY\": \"\",\n          \"CURRENISO\": \"\",\n          \"CONDINCOMP\": \"\",\n          \"CONDCONFIG\": \"\",\n          \"CONDCHAMAN\": \"\",\n          \"COND_NO\": \"0035482469\",\n          \"TAX_CODE\": \"SD\",\n          \"VARCOND\": \"\",\n          \"ACCOUNTKEY\": \"\",\n          \"ACCOUNT_KE\": \"\",\n          \"WT_WITHCD\": \"\",\n          \"STRUCTCOND\": \"\",\n          \"FACTCONBAS\": \"0.0000000000000000E+00\",\n          \"CONDCOINHD\": \"00\"\n        },\n        {\n          \"ITM_NUMBER\": \"000010\",\n          \"COND_ST_NO\": \"787\",\n          \"COND_COUNT\": \"01\",\n          \"COND_TYPE\": \"BX98\",\n          \"COND_VALUE\": \"0.000000000\",\n          \"CURRENCY\": \"BRL\",\n          \"COND_UNIT\": \"\",\n          \"COND_P_UNT\": \"0\",\n          \"CURR_ISO\": \"BRL\",\n          \"CD_UNT_ISO\": \"\",\n          \"REFOBJTYPE\": \"\",\n          \"REFOBJKEY\": \"\",\n          \"REFLOGSYS\": \"\",\n          \"APPLICATIO\": \"V\",\n          \"CONPRICDAT\": \"2020-12-14\",\n          \"CALCTYPCON\": \"B\",\n          \"CONBASEVAL\": \"761.620000000\",\n          \"CONEXCHRAT\": \"1.00000\",\n          \"NUMCONVERT\": \"0\",\n          \"DENOMINATO\": \"0\",\n          \"CONDTYPE\": \"1\",\n          \"STAT_CON\": \"X\",\n          \"SCALETYPE\": \"\",\n          \"ACCRUALS\": \"\",\n          \"CONINVOLST\": \"\",\n          \"CONDORIGIN\": \"A\",\n          \"GROUPCOND\": \"\",\n          \"COND_UPDAT\": \"\",\n          \"ACCESS_SEQ\": \"00\",\n          \"CONDCOUNT\": \"00\",\n          \"ROUNDOFFDI\": \"0.000000000\",\n          \"CONDVALUE\": \"0.000000000\",\n          \"CURRENCY_2\": \"BRL\",\n          \"CURR_ISO_2\": \"BRL\",\n          \"CONDCNTRL\": \"A\",\n          \"CONDISACTI\": \"\",\n          \"CONDCLASS\": \"A\",\n          \"FACTBASVAL\": \"0.0000000000000000E+00\",\n          \"SCALEBASIN\": \"\",\n          \"SCALBASVAL\": \"0.000000000\",\n          \"UNITMEASUR\": \"\",\n          \"ISO_UNIT\": \"\",\n          \"CURRENCKEY\": \"\",\n          \"CURRENISO\": \"\",\n          \"CONDINCOMP\": \"\",\n          \"CONDCONFIG\": \"\",\n          \"CONDCHAMAN\": \"\",\n          \"COND_NO\": \"\",\n          \"TAX_CODE\": \"\",\n          \"VARCOND\": \"\",\n          \"ACCOUNTKEY\": \"\",\n          \"ACCOUNT_KE\": \"\",\n          \"WT_WITHCD\": \"\",\n          \"STRUCTCOND\": \"\",\n          \"FACTCONBAS\": \"0.0000000000000000E+00\",\n          \"CONDCOINHD\": \"00\"\n        },\n        {\n          \"ITM_NUMBER\": \"000010\",\n          \"COND_ST_NO\": \"787\",\n          \"COND_COUNT\": \"02\",\n          \"COND_TYPE\": \"BX9C\",\n          \"COND_VALUE\": \"0.000000000\",\n          \"CURRENCY\": \"BRL\",\n          \"COND_UNIT\": \"\",\n          \"COND_P_UNT\": \"0\",\n          \"CURR_ISO\": \"BRL\",\n          \"CD_UNT_ISO\": \"\",\n          \"REFOBJTYPE\": \"\",\n          \"REFOBJKEY\": \"\",\n          \"REFLOGSYS\": \"\",\n          \"APPLICATIO\": \"V\",\n          \"CONPRICDAT\": \"2020-12-14\",\n          \"CALCTYPCON\": \"B\",\n          \"CONBASEVAL\": \"761.620000000\",\n          \"CONEXCHRAT\": \"1.00000\",\n          \"NUMCONVERT\": \"0\",\n          \"DENOMINATO\": \"0\",\n          \"CONDTYPE\": \"1\",\n          \"STAT_CON\": \"X\",\n          \"SCALETYPE\": \"\",\n          \"ACCRUALS\": \"\",\n          \"CONINVOLST\": \"\",\n          \"CONDORIGIN\": \"A\",\n          \"GROUPCOND\": \"\",\n          \"COND_UPDAT\": \"\",\n          \"ACCESS_SEQ\": \"00\",\n          \"CONDCOUNT\": \"00\",\n          \"ROUNDOFFDI\": \"0.000000000\",\n          \"CONDVALUE\": \"172.920000000\",\n          \"CURRENCY_2\": \"BRL\",\n          \"CURR_ISO_2\": \"BRL\",\n          \"CONDCNTRL\": \"A\",\n          \"CONDISACTI\": \"\",\n          \"CONDCLASS\": \"A\",\n          \"FACTBASVAL\": \"0.0000000000000000E+00\",\n          \"SCALEBASIN\": \"\",\n          \"SCALBASVAL\": \"0.000000000\",\n          \"UNITMEASUR\": \"\",\n          \"ISO_UNIT\": \"\",\n          \"CURRENCKEY\": \"\",\n          \"CURRENISO\": \"\",\n          \"CONDINCOMP\": \"\",\n          \"CONDCONFIG\": \"\",\n          \"CONDCHAMAN\": \"\",\n          \"COND_NO\": \"\",\n          \"TAX_CODE\": \"\",\n          \"VARCOND\": \"\",\n          \"ACCOUNTKEY\": \"\",\n          \"ACCOUNT_KE\": \"\",\n          \"WT_WITHCD\": \"\",\n          \"STRUCTCOND\": \"\",\n          \"FACTCONBAS\": \"0.0000000000000000E+00\",\n          \"CONDCOINHD\": \"00\"\n        },\n        {\n          \"ITM_NUMBER\": \"000010\",\n          \"COND_ST_NO\": \"788\",\n          \"COND_COUNT\": \"01\",\n          \"COND_TYPE\": \"BX97\",\n          \"COND_VALUE\": \"0.000000000\",\n          \"CURRENCY\": \"BRL\",\n          \"COND_UNIT\": \"\",\n          \"COND_P_UNT\": \"0\",\n          \"CURR_ISO\": \"BRL\",\n          \"CD_UNT_ISO\": \"\",\n          \"REFOBJTYPE\": \"\",\n          \"REFOBJKEY\": \"\",\n          \"REFLOGSYS\": \"\",\n          \"APPLICATIO\": \"V\",\n          \"CONPRICDAT\": \"2020-12-14\",\n          \"CALCTYPCON\": \"B\",\n          \"CONBASEVAL\": \"934.540000000\",\n          \"CONEXCHRAT\": \"1.00000\",\n          \"NUMCONVERT\": \"0\",\n          \"DENOMINATO\": \"0\",\n          \"CONDTYPE\": \"1\",\n          \"STAT_CON\": \"X\",\n          \"SCALETYPE\": \"\",\n          \"ACCRUALS\": \"\",\n          \"CONINVOLST\": \"\",\n          \"CONDORIGIN\": \"A\",\n          \"GROUPCOND\": \"\",\n          \"COND_UPDAT\": \"\",\n          \"ACCESS_SEQ\": \"00\",\n          \"CONDCOUNT\": \"00\",\n          \"ROUNDOFFDI\": \"0.000000000\",\n          \"CONDVALUE\": \"0.000000000\",\n          \"CURRENCY_2\": \"BRL\",\n          \"CURR_ISO_2\": \"BRL\",\n          \"CONDCNTRL\": \"A\",\n          \"CONDISACTI\": \"\",\n          \"CONDCLASS\": \"A\",\n          \"FACTBASVAL\": \"0.0000000000000000E+00\",\n          \"SCALEBASIN\": \"\",\n          \"SCALBASVAL\": \"0.000000000\",\n          \"UNITMEASUR\": \"\",\n          \"ISO_UNIT\": \"\",\n          \"CURRENCKEY\": \"\",\n          \"CURRENISO\": \"\",\n          \"CONDINCOMP\": \"\",\n          \"CONDCONFIG\": \"\",\n          \"CONDCHAMAN\": \"\",\n          \"COND_NO\": \"\",\n          \"TAX_CODE\": \"\",\n          \"VARCOND\": \"\",\n          \"ACCOUNTKEY\": \"\",\n          \"ACCOUNT_KE\": \"\",\n          \"WT_WITHCD\": \"\",\n          \"STRUCTCOND\": \"\",\n          \"FACTCONBAS\": \"0.0000000000000000E+00\",\n          \"CONDCOINHD\": \"00\"\n        },\n        {\n          \"ITM_NUMBER\": \"000010\",\n          \"COND_ST_NO\": \"789\",\n          \"COND_COUNT\": \"01\",\n          \"COND_TYPE\": \"BX96\",\n          \"COND_VALUE\": \"100.000000000\",\n          \"CURRENCY\": \"\",\n          \"COND_UNIT\": \"\",\n          \"COND_P_UNT\": \"0\",\n          \"CURR_ISO\": \"\",\n          \"CD_UNT_ISO\": \"\",\n          \"REFOBJTYPE\": \"\",\n          \"REFOBJKEY\": \"\",\n          \"REFLOGSYS\": \"\",\n          \"APPLICATIO\": \"V\",\n          \"CONPRICDAT\": \"2020-12-14\",\n          \"CALCTYPCON\": \"A\",\n          \"CONBASEVAL\": \"934.540000000\",\n          \"CONEXCHRAT\": \"0.00000\",\n          \"NUMCONVERT\": \"0\",\n          \"DENOMINATO\": \"0\",\n          \"CONDTYPE\": \"D\",\n          \"STAT_CON\": \"\",\n          \"SCALETYPE\": \"\",\n          \"ACCRUALS\": \"\",\n          \"CONINVOLST\": \"\",\n          \"CONDORIGIN\": \"A\",\n          \"GROUPCOND\": \"\",\n          \"COND_UPDAT\": \"\",\n          \"ACCESS_SEQ\": \"01\",\n          \"CONDCOUNT\": \"01\",\n          \"ROUNDOFFDI\": \"0.000000000\",\n          \"CONDVALUE\": \"0.000000000\",\n          \"CURRENCY_2\": \"BRL\",\n          \"CURR_ISO_2\": \"BRL\",\n          \"CONDCNTRL\": \"A\",\n          \"CONDISACTI\": \"\",\n          \"CONDCLASS\": \"D\",\n          \"FACTBASVAL\": \"0.0000000000000000E+00\",\n          \"SCALEBASIN\": \"\",\n          \"SCALBASVAL\": \"0.000000000\",\n          \"UNITMEASUR\": \"\",\n          \"ISO_UNIT\": \"\",\n          \"CURRENCKEY\": \"\",\n          \"CURRENISO\": \"\",\n          \"CONDINCOMP\": \"\",\n          \"CONDCONFIG\": \"\",\n          \"CONDCHAMAN\": \"\",\n          \"COND_NO\": \"0035482469\",\n          \"TAX_CODE\": \"SD\",\n          \"VARCOND\": \"\",\n          \"ACCOUNTKEY\": \"\",\n          \"ACCOUNT_KE\": \"\",\n          \"WT_WITHCD\": \"\",\n          \"STRUCTCOND\": \"\",\n          \"FACTCONBAS\": \"0.0000000000000000E+00\",\n          \"CONDCOINHD\": \"00\"\n        },\n        {\n          \"ITM_NUMBER\": \"000010\",\n          \"COND_ST_NO\": \"789\",\n          \"COND_COUNT\": \"02\",\n          \"COND_TYPE\": \"BX9I\",\n          \"COND_VALUE\": \"100.000000000\",\n          \"CURRENCY\": \"\",\n          \"COND_UNIT\": \"\",\n          \"COND_P_UNT\": \"0\",\n          \"CURR_ISO\": \"\",\n          \"CD_UNT_ISO\": \"\",\n          \"REFOBJTYPE\": \"\",\n          \"REFOBJKEY\": \"\",\n          \"REFLOGSYS\": \"\",\n          \"APPLICATIO\": \"V\",\n          \"CONPRICDAT\": \"2020-12-14\",\n          \"CALCTYPCON\": \"A\",\n          \"CONBASEVAL\": \"934.540000000\",\n          \"CONEXCHRAT\": \"0.00000\",\n          \"NUMCONVERT\": \"0\",\n          \"DENOMINATO\": \"0\",\n          \"CONDTYPE\": \"D\",\n          \"STAT_CON\": \"\",\n          \"SCALETYPE\": \"\",\n          \"ACCRUALS\": \"\",\n          \"CONINVOLST\": \"\",\n          \"CONDORIGIN\": \"A\",\n          \"GROUPCOND\": \"\",\n          \"COND_UPDAT\": \"\",\n          \"ACCESS_SEQ\": \"01\",\n          \"CONDCOUNT\": \"01\",\n          \"ROUNDOFFDI\": \"0.000000000\",\n          \"CONDVALUE\": \"0.000000000\",\n          \"CURRENCY_2\": \"BRL\",\n          \"CURR_ISO_2\": \"BRL\",\n          \"CONDCNTRL\": \"A\",\n          \"CONDISACTI\": \"\",\n          \"CONDCLASS\": \"D\",\n          \"FACTBASVAL\": \"0.0000000000000000E+00\",\n          \"SCALEBASIN\": \"\",\n          \"SCALBASVAL\": \"0.000000000\",\n          \"UNITMEASUR\": \"\",\n          \"ISO_UNIT\": \"\",\n          \"CURRENCKEY\": \"\",\n          \"CURRENISO\": \"\",\n          \"CONDINCOMP\": \"\",\n          \"CONDCONFIG\": \"\",\n          \"CONDCHAMAN\": \"\",\n          \"COND_NO\": \"0035482469\",\n          \"TAX_CODE\": \"SD\",\n          \"VARCOND\": \"\",\n          \"ACCOUNTKEY\": \"\",\n          \"ACCOUNT_KE\": \"\",\n          \"WT_WITHCD\": \"\",\n          \"STRUCTCOND\": \"\",\n          \"FACTCONBAS\": \"0.0000000000000000E+00\",\n          \"CONDCOINHD\": \"00\"\n        },\n        {\n          \"ITM_NUMBER\": \"000010\",\n          \"COND_ST_NO\": \"790\",\n          \"COND_COUNT\": \"01\",\n          \"COND_TYPE\": \"BX9O\",\n          \"COND_VALUE\": \"-100.000000000\",\n          \"CURRENCY\": \"\",\n          \"COND_UNIT\": \"\",\n          \"COND_P_UNT\": \"0\",\n          \"CURR_ISO\": \"\",\n          \"CD_UNT_ISO\": \"\",\n          \"REFOBJTYPE\": \"\",\n          \"REFOBJKEY\": \"\",\n          \"REFLOGSYS\": \"\",\n          \"APPLICATIO\": \"V\",\n          \"CONPRICDAT\": \"2020-12-14\",\n          \"CALCTYPCON\": \"A\",\n          \"CONBASEVAL\": \"0.000000000\",\n          \"CONEXCHRAT\": \"0.00000\",\n          \"NUMCONVERT\": \"0\",\n          \"DENOMINATO\": \"0\",\n          \"CONDTYPE\": \"H\",\n          \"STAT_CON\": \"\",\n          \"SCALETYPE\": \"\",\n          \"ACCRUALS\": \"\",\n          \"CONINVOLST\": \"\",\n          \"CONDORIGIN\": \"A\",\n          \"GROUPCOND\": \"\",\n          \"COND_UPDAT\": \"\",\n          \"ACCESS_SEQ\": \"01\",\n          \"CONDCOUNT\": \"01\",\n          \"ROUNDOFFDI\": \"0.000000000\",\n          \"CONDVALUE\": \"0.000000000\",\n          \"CURRENCY_2\": \"BRL\",\n          \"CURR_ISO_2\": \"BRL\",\n          \"CONDCNTRL\": \"A\",\n          \"CONDISACTI\": \"\",\n          \"CONDCLASS\": \"A\",\n          \"FACTBASVAL\": \"0.0000000000000000E+00\",\n          \"SCALEBASIN\": \"\",\n          \"SCALBASVAL\": \"0.000000000\",\n          \"UNITMEASUR\": \"\",\n          \"ISO_UNIT\": \"\",\n          \"CURRENCKEY\": \"\",\n          \"CURRENISO\": \"\",\n          \"CONDINCOMP\": \"\",\n          \"CONDCONFIG\": \"\",\n          \"CONDCHAMAN\": \"\",\n          \"COND_NO\": \"0035054234\",\n          \"TAX_CODE\": \"\",\n          \"VARCOND\": \"\",\n          \"ACCOUNTKEY\": \"\",\n          \"ACCOUNT_KE\": \"\",\n          \"WT_WITHCD\": \"\",\n          \"STRUCTCOND\": \"\",\n          \"FACTCONBAS\": \"0.0000000000000000E+00\",\n          \"CONDCOINHD\": \"00\"\n        },\n        {\n          \"ITM_NUMBER\": \"000010\",\n          \"COND_ST_NO\": \"790\",\n          \"COND_COUNT\": \"02\",\n          \"COND_TYPE\": \"BX9P\",\n          \"COND_VALUE\": \"-100.000000000\",\n          \"CURRENCY\": \"\",\n          \"COND_UNIT\": \"\",\n          \"COND_P_UNT\": \"0\",\n          \"CURR_ISO\": \"\",\n          \"CD_UNT_ISO\": \"\",\n          \"REFOBJTYPE\": \"\",\n          \"REFOBJKEY\": \"\",\n          \"REFLOGSYS\": \"\",\n          \"APPLICATIO\": \"V\",\n          \"CONPRICDAT\": \"2020-12-14\",\n          \"CALCTYPCON\": \"A\",\n          \"CONBASEVAL\": \"0.000000000\",\n          \"CONEXCHRAT\": \"0.00000\",\n          \"NUMCONVERT\": \"0\",\n          \"DENOMINATO\": \"0\",\n          \"CONDTYPE\": \"H\",\n          \"STAT_CON\": \"\",\n          \"SCALETYPE\": \"\",\n          \"ACCRUALS\": \"\",\n          \"CONINVOLST\": \"\",\n          \"CONDORIGIN\": \"A\",\n          \"GROUPCOND\": \"\",\n          \"COND_UPDAT\": \"\",\n          \"ACCESS_SEQ\": \"01\",\n          \"CONDCOUNT\": \"01\",\n          \"ROUNDOFFDI\": \"0.000000000\",\n          \"CONDVALUE\": \"0.000000000\",\n          \"CURRENCY_2\": \"BRL\",\n          \"CURR_ISO_2\": \"BRL\",\n          \"CONDCNTRL\": \"A\",\n          \"CONDISACTI\": \"\",\n          \"CONDCLASS\": \"A\",\n          \"FACTBASVAL\": \"0.0000000000000000E+00\",\n          \"SCALEBASIN\": \"\",\n          \"SCALBASVAL\": \"0.000000000\",\n          \"UNITMEASUR\": \"\",\n          \"ISO_UNIT\": \"\",\n          \"CURRENCKEY\": \"\",\n          \"CURRENISO\": \"\",\n          \"CONDINCOMP\": \"\",\n          \"CONDCONFIG\": \"\",\n          \"CONDCHAMAN\": \"\",\n          \"COND_NO\": \"0035054235\",\n          \"TAX_CODE\": \"\",\n          \"VARCOND\": \"\",\n          \"ACCOUNTKEY\": \"\",\n          \"ACCOUNT_KE\": \"\",\n          \"WT_WITHCD\": \"\",\n          \"STRUCTCOND\": \"\",\n          \"FACTCONBAS\": \"0.0000000000000000E+00\",\n          \"CONDCOINHD\": \"00\"\n        },\n        {\n          \"ITM_NUMBER\": \"000010\",\n          \"COND_ST_NO\": \"790\",\n          \"COND_COUNT\": \"03\",\n          \"COND_TYPE\": \"BX9D\",\n          \"COND_VALUE\": \"-100.000000000\",\n          \"CURRENCY\": \"\",\n          \"COND_UNIT\": \"\",\n          \"COND_P_UNT\": \"0\",\n          \"CURR_ISO\": \"\",\n          \"CD_UNT_ISO\": \"\",\n          \"REFOBJTYPE\": \"\",\n          \"REFOBJKEY\": \"\",\n          \"REFLOGSYS\": \"\",\n          \"APPLICATIO\": \"V\",\n          \"CONPRICDAT\": \"2020-12-14\",\n          \"CALCTYPCON\": \"A\",\n          \"CONBASEVAL\": \"10.380000000\",\n          \"CONEXCHRAT\": \"0.00000\",\n          \"NUMCONVERT\": \"0\",\n          \"DENOMINATO\": \"0\",\n          \"CONDTYPE\": \"H\",\n          \"STAT_CON\": \"\",\n          \"SCALETYPE\": \"\",\n          \"ACCRUALS\": \"\",\n          \"CONINVOLST\": \"\",\n          \"CONDORIGIN\": \"A\",\n          \"GROUPCOND\": \"\",\n          \"COND_UPDAT\": \"\",\n          \"ACCESS_SEQ\": \"01\",\n          \"CONDCOUNT\": \"01\",\n          \"ROUNDOFFDI\": \"0.000000000\",\n          \"CONDVALUE\": \"-10.380000000\",\n          \"CURRENCY_2\": \"BRL\",\n          \"CURR_ISO_2\": \"BRL\",\n          \"CONDCNTRL\": \"A\",\n          \"CONDISACTI\": \"\",\n          \"CONDCLASS\": \"A\",\n          \"FACTBASVAL\": \"0.0000000000000000E+00\",\n          \"SCALEBASIN\": \"\",\n          \"SCALBASVAL\": \"0.000000000\",\n          \"UNITMEASUR\": \"\",\n          \"ISO_UNIT\": \"\",\n          \"CURRENCKEY\": \"\",\n          \"CURRENISO\": \"\",\n          \"CONDINCOMP\": \"\",\n          \"CONDCONFIG\": \"\",\n          \"CONDCHAMAN\": \"\",\n          \"COND_NO\": \"0035054236\",\n          \"TAX_CODE\": \"\",\n          \"VARCOND\": \"\",\n          \"ACCOUNTKEY\": \"\",\n          \"ACCOUNT_KE\": \"\",\n          \"WT_WITHCD\": \"\",\n          \"STRUCTCOND\": \"\",\n          \"FACTCONBAS\": \"0.0000000000000000E+00\",\n          \"CONDCOINHD\": \"00\"\n        },\n        {\n          \"ITM_NUMBER\": \"000010\",\n          \"COND_ST_NO\": \"791\",\n          \"COND_COUNT\": \"01\",\n          \"COND_TYPE\": \"BX4B\",\n          \"COND_VALUE\": \"0.000000000\",\n          \"CURRENCY\": \"BRL\",\n          \"COND_UNIT\": \"\",\n          \"COND_P_UNT\": \"0\",\n          \"CURR_ISO\": \"BRL\",\n          \"CD_UNT_ISO\": \"\",\n          \"REFOBJTYPE\": \"\",\n          \"REFOBJKEY\": \"\",\n          \"REFLOGSYS\": \"\",\n          \"APPLICATIO\": \"V\",\n          \"CONPRICDAT\": \"2020-12-14\",\n          \"CALCTYPCON\": \"B\",\n          \"CONBASEVAL\": \"924.160000000\",\n          \"CONEXCHRAT\": \"1.00000\",\n          \"NUMCONVERT\": \"0\",\n          \"DENOMINATO\": \"0\",\n          \"CONDTYPE\": \"1\",\n          \"STAT_CON\": \"X\",\n          \"SCALETYPE\": \"\",\n          \"ACCRUALS\": \"\",\n          \"CONINVOLST\": \"\",\n          \"CONDORIGIN\": \"A\",\n          \"GROUPCOND\": \"\",\n          \"COND_UPDAT\": \"\",\n          \"ACCESS_SEQ\": \"00\",\n          \"CONDCOUNT\": \"00\",\n          \"ROUNDOFFDI\": \"0.000000000\",\n          \"CONDVALUE\": \"0.000000000\",\n          \"CURRENCY_2\": \"BRL\",\n          \"CURR_ISO_2\": \"BRL\",\n          \"CONDCNTRL\": \"A\",\n          \"CONDISACTI\": \"\",\n          \"CONDCLASS\": \"A\",\n          \"FACTBASVAL\": \"0.0000000000000000E+00\",\n          \"SCALEBASIN\": \"\",\n          \"SCALBASVAL\": \"0.000000000\",\n          \"UNITMEASUR\": \"\",\n          \"ISO_UNIT\": \"\",\n          \"CURRENCKEY\": \"\",\n          \"CURRENISO\": \"\",\n          \"CONDINCOMP\": \"\",\n          \"CONDCONFIG\": \"\",\n          \"CONDCHAMAN\": \"\",\n          \"COND_NO\": \"\",\n          \"TAX_CODE\": \"\",\n          \"VARCOND\": \"\",\n          \"ACCOUNTKEY\": \"\",\n          \"ACCOUNT_KE\": \"\",\n          \"WT_WITHCD\": \"\",\n          \"STRUCTCOND\": \"\",\n          \"FACTCONBAS\": \"0.0000000000000000E+00\",\n          \"CONDCOINHD\": \"00\"\n        },\n        {\n          \"ITM_NUMBER\": \"000010\",\n          \"COND_ST_NO\": \"792\",\n          \"COND_COUNT\": \"01\",\n          \"COND_TYPE\": \"BX4C\",\n          \"COND_VALUE\": \"0.000000000\",\n          \"CURRENCY\": \"BRL\",\n          \"COND_UNIT\": \"\",\n          \"COND_P_UNT\": \"0\",\n          \"CURR_ISO\": \"BRL\",\n          \"CD_UNT_ISO\": \"\",\n          \"REFOBJTYPE\": \"\",\n          \"REFOBJKEY\": \"\",\n          \"REFLOGSYS\": \"\",\n          \"APPLICATIO\": \"V\",\n          \"CONPRICDAT\": \"2020-12-14\",\n          \"CALCTYPCON\": \"B\",\n          \"CONBASEVAL\": \"924.160000000\",\n          \"CONEXCHRAT\": \"1.00000\",\n          \"NUMCONVERT\": \"0\",\n          \"DENOMINATO\": \"0\",\n          \"CONDTYPE\": \"1\",\n          \"STAT_CON\": \"X\",\n          \"SCALETYPE\": \"\",\n          \"ACCRUALS\": \"\",\n          \"CONINVOLST\": \"\",\n          \"CONDORIGIN\": \"A\",\n          \"GROUPCOND\": \"\",\n          \"COND_UPDAT\": \"\",\n          \"ACCESS_SEQ\": \"00\",\n          \"CONDCOUNT\": \"00\",\n          \"ROUNDOFFDI\": \"0.000000000\",\n          \"CONDVALUE\": \"0.000000000\",\n          \"CURRENCY_2\": \"BRL\",\n          \"CURR_ISO_2\": \"BRL\",\n          \"CONDCNTRL\": \"A\",\n          \"CONDISACTI\": \"\",\n          \"CONDCLASS\": \"A\",\n          \"FACTBASVAL\": \"0.0000000000000000E+00\",\n          \"SCALEBASIN\": \"\",\n          \"SCALBASVAL\": \"0.000000000\",\n          \"UNITMEASUR\": \"\",\n          \"ISO_UNIT\": \"\",\n          \"CURRENCKEY\": \"\",\n          \"CURRENISO\": \"\",\n          \"CONDINCOMP\": \"\",\n          \"CONDCONFIG\": \"\",\n          \"CONDCHAMAN\": \"\",\n          \"COND_NO\": \"\",\n          \"TAX_CODE\": \"\",\n          \"VARCOND\": \"\",\n          \"ACCOUNTKEY\": \"\",\n          \"ACCOUNT_KE\": \"\",\n          \"WT_WITHCD\": \"\",\n          \"STRUCTCOND\": \"\",\n          \"FACTCONBAS\": \"0.0000000000000000E+00\",\n          \"CONDCOINHD\": \"00\"\n        },\n        {\n          \"ITM_NUMBER\": \"000010\",\n          \"COND_ST_NO\": \"793\",\n          \"COND_COUNT\": \"01\",\n          \"COND_TYPE\": \"BX4A\",\n          \"COND_VALUE\": \"100.000000000\",\n          \"CURRENCY\": \"\",\n          \"COND_UNIT\": \"\",\n          \"COND_P_UNT\": \"0\",\n          \"CURR_ISO\": \"\",\n          \"CD_UNT_ISO\": \"\",\n          \"REFOBJTYPE\": \"\",\n          \"REFOBJKEY\": \"\",\n          \"REFLOGSYS\": \"\",\n          \"APPLICATIO\": \"V\",\n          \"CONPRICDAT\": \"2020-12-14\",\n          \"CALCTYPCON\": \"A\",\n          \"CONBASEVAL\": \"924.160000000\",\n          \"CONEXCHRAT\": \"0.00000\",\n          \"NUMCONVERT\": \"0\",\n          \"DENOMINATO\": \"0\",\n          \"CONDTYPE\": \"D\",\n          \"STAT_CON\": \"\",\n          \"SCALETYPE\": \"\",\n          \"ACCRUALS\": \"\",\n          \"CONINVOLST\": \"\",\n          \"CONDORIGIN\": \"A\",\n          \"GROUPCOND\": \"\",\n          \"COND_UPDAT\": \"\",\n          \"ACCESS_SEQ\": \"01\",\n          \"CONDCOUNT\": \"01\",\n          \"ROUNDOFFDI\": \"0.000000000\",\n          \"CONDVALUE\": \"0.000000000\",\n          \"CURRENCY_2\": \"BRL\",\n          \"CURR_ISO_2\": \"BRL\",\n          \"CONDCNTRL\": \"A\",\n          \"CONDISACTI\": \"\",\n          \"CONDCLASS\": \"D\",\n          \"FACTBASVAL\": \"0.0000000000000000E+00\",\n          \"SCALEBASIN\": \"\",\n          \"SCALBASVAL\": \"0.000000000\",\n          \"UNITMEASUR\": \"\",\n          \"ISO_UNIT\": \"\",\n          \"CURRENCKEY\": \"\",\n          \"CURRENISO\": \"\",\n          \"CONDINCOMP\": \"\",\n          \"CONDCONFIG\": \"\",\n          \"CONDCHAMAN\": \"\",\n          \"COND_NO\": \"0035482469\",\n          \"TAX_CODE\": \"SD\",\n          \"VARCOND\": \"\",\n          \"ACCOUNTKEY\": \"\",\n          \"ACCOUNT_KE\": \"\",\n          \"WT_WITHCD\": \"\",\n          \"STRUCTCOND\": \"\",\n          \"FACTCONBAS\": \"0.0000000000000000E+00\",\n          \"CONDCOINHD\": \"00\"\n        },\n        {\n          \"ITM_NUMBER\": \"000010\",\n          \"COND_ST_NO\": \"880\",\n          \"COND_COUNT\": \"01\",\n          \"COND_TYPE\": \"ZBDC\",\n          \"COND_VALUE\": \"100.000000000\",\n          \"CURRENCY\": \"\",\n          \"COND_UNIT\": \"\",\n          \"COND_P_UNT\": \"0\",\n          \"CURR_ISO\": \"\",\n          \"CD_UNT_ISO\": \"\",\n          \"REFOBJTYPE\": \"\",\n          \"REFOBJKEY\": \"\",\n          \"REFLOGSYS\": \"\",\n          \"APPLICATIO\": \"V\",\n          \"CONPRICDAT\": \"2020-12-14\",\n          \"CALCTYPCON\": \"A\",\n          \"CONBASEVAL\": \"0.000000000\",\n          \"CONEXCHRAT\": \"0.00000\",\n          \"NUMCONVERT\": \"0\",\n          \"DENOMINATO\": \"0\",\n          \"CONDTYPE\": \"\",\n          \"STAT_CON\": \"\",\n          \"SCALETYPE\": \"\",\n          \"ACCRUALS\": \"\",\n          \"CONINVOLST\": \"\",\n          \"CONDORIGIN\": \"A\",\n          \"GROUPCOND\": \"\",\n          \"COND_UPDAT\": \"\",\n          \"ACCESS_SEQ\": \"10\",\n          \"CONDCOUNT\": \"01\",\n          \"ROUNDOFFDI\": \"0.000000000\",\n          \"CONDVALUE\": \"0.000000000\",\n          \"CURRENCY_2\": \"BRL\",\n          \"CURR_ISO_2\": \"BRL\",\n          \"CONDCNTRL\": \"A\",\n          \"CONDISACTI\": \"\",\n          \"CONDCLASS\": \"A\",\n          \"FACTBASVAL\": \"0.0000000000000000E+00\",\n          \"SCALEBASIN\": \"\",\n          \"SCALBASVAL\": \"0.000000000\",\n          \"UNITMEASUR\": \"\",\n          \"ISO_UNIT\": \"\",\n          \"CURRENCKEY\": \"\",\n          \"CURRENISO\": \"\",\n          \"CONDINCOMP\": \"\",\n          \"CONDCONFIG\": \"\",\n          \"CONDCHAMAN\": \"\",\n          \"COND_NO\": \"0011028355\",\n          \"TAX_CODE\": \"\",\n          \"VARCOND\": \"\",\n          \"ACCOUNTKEY\": \"\",\n          \"ACCOUNT_KE\": \"\",\n          \"WT_WITHCD\": \"\",\n          \"STRUCTCOND\": \"\",\n          \"FACTCONBAS\": \"0.0000000000000000E+00\",\n          \"CONDCOINHD\": \"00\"\n        },\n        {\n          \"ITM_NUMBER\": \"000010\",\n          \"COND_ST_NO\": \"880\",\n          \"COND_COUNT\": \"03\",\n          \"COND_TYPE\": \"ZBD4\",\n          \"COND_VALUE\": \"100.000000000\",\n          \"CURRENCY\": \"\",\n          \"COND_UNIT\": \"\",\n          \"COND_P_UNT\": \"0\",\n          \"CURR_ISO\": \"\",\n          \"CD_UNT_ISO\": \"\",\n          \"REFOBJTYPE\": \"\",\n          \"REFOBJKEY\": \"\",\n          \"REFLOGSYS\": \"\",\n          \"APPLICATIO\": \"V\",\n          \"CONPRICDAT\": \"2020-12-14\",\n          \"CALCTYPCON\": \"A\",\n          \"CONBASEVAL\": \"0.000000000\",\n          \"CONEXCHRAT\": \"0.00000\",\n          \"NUMCONVERT\": \"0\",\n          \"DENOMINATO\": \"0\",\n          \"CONDTYPE\": \"\",\n          \"STAT_CON\": \"\",\n          \"SCALETYPE\": \"\",\n          \"ACCRUALS\": \"\",\n          \"CONINVOLST\": \"\",\n          \"CONDORIGIN\": \"A\",\n          \"GROUPCOND\": \"\",\n          \"COND_UPDAT\": \"\",\n          \"ACCESS_SEQ\": \"10\",\n          \"CONDCOUNT\": \"01\",\n          \"ROUNDOFFDI\": \"0.000000000\",\n          \"CONDVALUE\": \"0.000000000\",\n          \"CURRENCY_2\": \"BRL\",\n          \"CURR_ISO_2\": \"BRL\",\n          \"CONDCNTRL\": \"A\",\n          \"CONDISACTI\": \"\",\n          \"CONDCLASS\": \"A\",\n          \"FACTBASVAL\": \"0.0000000000000000E+00\",\n          \"SCALEBASIN\": \"\",\n          \"SCALBASVAL\": \"0.000000000\",\n          \"UNITMEASUR\": \"\",\n          \"ISO_UNIT\": \"\",\n          \"CURRENCKEY\": \"\",\n          \"CURRENISO\": \"\",\n          \"CONDINCOMP\": \"\",\n          \"CONDCONFIG\": \"\",\n          \"CONDCHAMAN\": \"\",\n          \"COND_NO\": \"0011028355\",\n          \"TAX_CODE\": \"\",\n          \"VARCOND\": \"\",\n          \"ACCOUNTKEY\": \"\",\n          \"ACCOUNT_KE\": \"\",\n          \"WT_WITHCD\": \"\",\n          \"STRUCTCOND\": \"\",\n          \"FACTCONBAS\": \"0.0000000000000000E+00\",\n          \"CONDCOINHD\": \"00\"\n        },\n        {\n          \"ITM_NUMBER\": \"000010\",\n          \"COND_ST_NO\": \"880\",\n          \"COND_COUNT\": \"04\",\n          \"COND_TYPE\": \"ZBDS\",\n          \"COND_VALUE\": \"100.000000000\",\n          \"CURRENCY\": \"\",\n          \"COND_UNIT\": \"\",\n          \"COND_P_UNT\": \"0\",\n          \"CURR_ISO\": \"\",\n          \"CD_UNT_ISO\": \"\",\n          \"REFOBJTYPE\": \"\",\n          \"REFOBJKEY\": \"\",\n          \"REFLOGSYS\": \"\",\n          \"APPLICATIO\": \"V\",\n          \"CONPRICDAT\": \"2020-12-14\",\n          \"CALCTYPCON\": \"A\",\n          \"CONBASEVAL\": \"0.000000000\",\n          \"CONEXCHRAT\": \"0.00000\",\n          \"NUMCONVERT\": \"0\",\n          \"DENOMINATO\": \"0\",\n          \"CONDTYPE\": \"\",\n          \"STAT_CON\": \"\",\n          \"SCALETYPE\": \"\",\n          \"ACCRUALS\": \"\",\n          \"CONINVOLST\": \"\",\n          \"CONDORIGIN\": \"A\",\n          \"GROUPCOND\": \"\",\n          \"COND_UPDAT\": \"\",\n          \"ACCESS_SEQ\": \"10\",\n          \"CONDCOUNT\": \"01\",\n          \"ROUNDOFFDI\": \"0.000000000\",\n          \"CONDVALUE\": \"0.000000000\",\n          \"CURRENCY_2\": \"BRL\",\n          \"CURR_ISO_2\": \"BRL\",\n          \"CONDCNTRL\": \"A\",\n          \"CONDISACTI\": \"\",\n          \"CONDCLASS\": \"A\",\n          \"FACTBASVAL\": \"0.0000000000000000E+00\",\n          \"SCALEBASIN\": \"\",\n          \"SCALBASVAL\": \"0.000000000\",\n          \"UNITMEASUR\": \"\",\n          \"ISO_UNIT\": \"\",\n          \"CURRENCKEY\": \"\",\n          \"CURRENISO\": \"\",\n          \"CONDINCOMP\": \"\",\n          \"CONDCONFIG\": \"\",\n          \"CONDCHAMAN\": \"\",\n          \"COND_NO\": \"0011028355\",\n          \"TAX_CODE\": \"\",\n          \"VARCOND\": \"\",\n          \"ACCOUNTKEY\": \"\",\n          \"ACCOUNT_KE\": \"\",\n          \"WT_WITHCD\": \"\",\n          \"STRUCTCOND\": \"\",\n          \"FACTCONBAS\": \"0.0000000000000000E+00\",\n          \"CONDCOINHD\": \"00\"\n        },\n        {\n          \"ITM_NUMBER\": \"000010\",\n          \"COND_ST_NO\": \"880\",\n          \"COND_COUNT\": \"05\",\n          \"COND_TYPE\": \"ZBD5\",\n          \"COND_VALUE\": \"100.000000000\",\n          \"CURRENCY\": \"\",\n          \"COND_UNIT\": \"\",\n          \"COND_P_UNT\": \"0\",\n          \"CURR_ISO\": \"\",\n          \"CD_UNT_ISO\": \"\",\n          \"REFOBJTYPE\": \"\",\n          \"REFOBJKEY\": \"\",\n          \"REFLOGSYS\": \"\",\n          \"APPLICATIO\": \"V\",\n          \"CONPRICDAT\": \"2020-12-14\",\n          \"CALCTYPCON\": \"A\",\n          \"CONBASEVAL\": \"0.000000000\",\n          \"CONEXCHRAT\": \"0.00000\",\n          \"NUMCONVERT\": \"0\",\n          \"DENOMINATO\": \"0\",\n          \"CONDTYPE\": \"\",\n          \"STAT_CON\": \"\",\n          \"SCALETYPE\": \"\",\n          \"ACCRUALS\": \"\",\n          \"CONINVOLST\": \"\",\n          \"CONDORIGIN\": \"A\",\n          \"GROUPCOND\": \"\",\n          \"COND_UPDAT\": \"\",\n          \"ACCESS_SEQ\": \"10\",\n          \"CONDCOUNT\": \"01\",\n          \"ROUNDOFFDI\": \"0.000000000\",\n          \"CONDVALUE\": \"0.000000000\",\n          \"CURRENCY_2\": \"BRL\",\n          \"CURR_ISO_2\": \"BRL\",\n          \"CONDCNTRL\": \"A\",\n          \"CONDISACTI\": \"\",\n          \"CONDCLASS\": \"A\",\n          \"FACTBASVAL\": \"0.0000000000000000E+00\",\n          \"SCALEBASIN\": \"\",\n          \"SCALBASVAL\": \"0.000000000\",\n          \"UNITMEASUR\": \"\",\n          \"ISO_UNIT\": \"\",\n          \"CURRENCKEY\": \"\",\n          \"CURRENISO\": \"\",\n          \"CONDINCOMP\": \"\",\n          \"CONDCONFIG\": \"\",\n          \"CONDCHAMAN\": \"\",\n          \"COND_NO\": \"0011028355\",\n          \"TAX_CODE\": \"\",\n          \"VARCOND\": \"\",\n          \"ACCOUNTKEY\": \"\",\n          \"ACCOUNT_KE\": \"\",\n          \"WT_WITHCD\": \"\",\n          \"STRUCTCOND\": \"\",\n          \"FACTCONBAS\": \"0.0000000000000000E+00\",\n          \"CONDCOINHD\": \"00\"\n        },\n        {\n          \"ITM_NUMBER\": \"000010\",\n          \"COND_ST_NO\": \"880\",\n          \"COND_COUNT\": \"06\",\n          \"COND_TYPE\": \"ZBD6\",\n          \"COND_VALUE\": \"100.000000000\",\n          \"CURRENCY\": \"\",\n          \"COND_UNIT\": \"\",\n          \"COND_P_UNT\": \"0\",\n          \"CURR_ISO\": \"\",\n          \"CD_UNT_ISO\": \"\",\n          \"REFOBJTYPE\": \"\",\n          \"REFOBJKEY\": \"\",\n          \"REFLOGSYS\": \"\",\n          \"APPLICATIO\": \"V\",\n          \"CONPRICDAT\": \"2020-12-14\",\n          \"CALCTYPCON\": \"A\",\n          \"CONBASEVAL\": \"0.000000000\",\n          \"CONEXCHRAT\": \"0.00000\",\n          \"NUMCONVERT\": \"0\",\n          \"DENOMINATO\": \"0\",\n          \"CONDTYPE\": \"\",\n          \"STAT_CON\": \"\",\n          \"SCALETYPE\": \"\",\n          \"ACCRUALS\": \"\",\n          \"CONINVOLST\": \"\",\n          \"CONDORIGIN\": \"A\",\n          \"GROUPCOND\": \"\",\n          \"COND_UPDAT\": \"\",\n          \"ACCESS_SEQ\": \"10\",\n          \"CONDCOUNT\": \"01\",\n          \"ROUNDOFFDI\": \"0.000000000\",\n          \"CONDVALUE\": \"0.000000000\",\n          \"CURRENCY_2\": \"BRL\",\n          \"CURR_ISO_2\": \"BRL\",\n          \"CONDCNTRL\": \"A\",\n          \"CONDISACTI\": \"\",\n          \"CONDCLASS\": \"A\",\n          \"FACTBASVAL\": \"0.0000000000000000E+00\",\n          \"SCALEBASIN\": \"\",\n          \"SCALBASVAL\": \"0.000000000\",\n          \"UNITMEASUR\": \"\",\n          \"ISO_UNIT\": \"\",\n          \"CURRENCKEY\": \"\",\n          \"CURRENISO\": \"\",\n          \"CONDINCOMP\": \"\",\n          \"CONDCONFIG\": \"\",\n          \"CONDCHAMAN\": \"\",\n          \"COND_NO\": \"0011028355\",\n          \"TAX_CODE\": \"\",\n          \"VARCOND\": \"\",\n          \"ACCOUNTKEY\": \"\",\n          \"ACCOUNT_KE\": \"\",\n          \"WT_WITHCD\": \"\",\n          \"STRUCTCOND\": \"\",\n          \"FACTCONBAS\": \"0.0000000000000000E+00\",\n          \"CONDCOINHD\": \"00\"\n        },\n        {\n          \"ITM_NUMBER\": \"000010\",\n          \"COND_ST_NO\": \"880\",\n          \"COND_COUNT\": \"07\",\n          \"COND_TYPE\": \"ZBDA\",\n          \"COND_VALUE\": \"100.000000000\",\n          \"CURRENCY\": \"\",\n          \"COND_UNIT\": \"\",\n          \"COND_P_UNT\": \"0\",\n          \"CURR_ISO\": \"\",\n          \"CD_UNT_ISO\": \"\",\n          \"REFOBJTYPE\": \"\",\n          \"REFOBJKEY\": \"\",\n          \"REFLOGSYS\": \"\",\n          \"APPLICATIO\": \"V\",\n          \"CONPRICDAT\": \"2020-12-14\",\n          \"CALCTYPCON\": \"A\",\n          \"CONBASEVAL\": \"0.000000000\",\n          \"CONEXCHRAT\": \"0.00000\",\n          \"NUMCONVERT\": \"0\",\n          \"DENOMINATO\": \"0\",\n          \"CONDTYPE\": \"\",\n          \"STAT_CON\": \"\",\n          \"SCALETYPE\": \"\",\n          \"ACCRUALS\": \"\",\n          \"CONINVOLST\": \"\",\n          \"CONDORIGIN\": \"A\",\n          \"GROUPCOND\": \"\",\n          \"COND_UPDAT\": \"\",\n          \"ACCESS_SEQ\": \"10\",\n          \"CONDCOUNT\": \"01\",\n          \"ROUNDOFFDI\": \"0.000000000\",\n          \"CONDVALUE\": \"0.000000000\",\n          \"CURRENCY_2\": \"BRL\",\n          \"CURR_ISO_2\": \"BRL\",\n          \"CONDCNTRL\": \"A\",\n          \"CONDISACTI\": \"\",\n          \"CONDCLASS\": \"A\",\n          \"FACTBASVAL\": \"0.0000000000000000E+00\",\n          \"SCALEBASIN\": \"\",\n          \"SCALBASVAL\": \"0.000000000\",\n          \"UNITMEASUR\": \"\",\n          \"ISO_UNIT\": \"\",\n          \"CURRENCKEY\": \"\",\n          \"CURRENISO\": \"\",\n          \"CONDINCOMP\": \"\",\n          \"CONDCONFIG\": \"\",\n          \"CONDCHAMAN\": \"\",\n          \"COND_NO\": \"0011028355\",\n          \"TAX_CODE\": \"\",\n          \"VARCOND\": \"\",\n          \"ACCOUNTKEY\": \"\",\n          \"ACCOUNT_KE\": \"\",\n          \"WT_WITHCD\": \"\",\n          \"STRUCTCOND\": \"\",\n          \"FACTCONBAS\": \"0.0000000000000000E+00\",\n          \"CONDCOINHD\": \"00\"\n        },\n        {\n          \"ITM_NUMBER\": \"000010\",\n          \"COND_ST_NO\": \"880\",\n          \"COND_COUNT\": \"08\",\n          \"COND_TYPE\": \"ZBD8\",\n          \"COND_VALUE\": \"100.000000000\",\n          \"CURRENCY\": \"\",\n          \"COND_UNIT\": \"\",\n          \"COND_P_UNT\": \"0\",\n          \"CURR_ISO\": \"\",\n          \"CD_UNT_ISO\": \"\",\n          \"REFOBJTYPE\": \"\",\n          \"REFOBJKEY\": \"\",\n          \"REFLOGSYS\": \"\",\n          \"APPLICATIO\": \"V\",\n          \"CONPRICDAT\": \"2020-12-14\",\n          \"CALCTYPCON\": \"A\",\n          \"CONBASEVAL\": \"0.000000000\",\n          \"CONEXCHRAT\": \"0.00000\",\n          \"NUMCONVERT\": \"0\",\n          \"DENOMINATO\": \"0\",\n          \"CONDTYPE\": \"\",\n          \"STAT_CON\": \"\",\n          \"SCALETYPE\": \"\",\n          \"ACCRUALS\": \"\",\n          \"CONINVOLST\": \"\",\n          \"CONDORIGIN\": \"A\",\n          \"GROUPCOND\": \"\",\n          \"COND_UPDAT\": \"\",\n          \"ACCESS_SEQ\": \"10\",\n          \"CONDCOUNT\": \"01\",\n          \"ROUNDOFFDI\": \"0.000000000\",\n          \"CONDVALUE\": \"0.000000000\",\n          \"CURRENCY_2\": \"BRL\",\n          \"CURR_ISO_2\": \"BRL\",\n          \"CONDCNTRL\": \"A\",\n          \"CONDISACTI\": \"\",\n          \"CONDCLASS\": \"A\",\n          \"FACTBASVAL\": \"0.0000000000000000E+00\",\n          \"SCALEBASIN\": \"\",\n          \"SCALBASVAL\": \"0.000000000\",\n          \"UNITMEASUR\": \"\",\n          \"ISO_UNIT\": \"\",\n          \"CURRENCKEY\": \"\",\n          \"CURRENISO\": \"\",\n          \"CONDINCOMP\": \"\",\n          \"CONDCONFIG\": \"\",\n          \"CONDCHAMAN\": \"\",\n          \"COND_NO\": \"0011028355\",\n          \"TAX_CODE\": \"\",\n          \"VARCOND\": \"\",\n          \"ACCOUNTKEY\": \"\",\n          \"ACCOUNT_KE\": \"\",\n          \"WT_WITHCD\": \"\",\n          \"STRUCTCOND\": \"\",\n          \"FACTCONBAS\": \"0.0000000000000000E+00\",\n          \"CONDCOINHD\": \"00\"\n        },\n        {\n          \"ITM_NUMBER\": \"000010\",\n          \"COND_ST_NO\": \"880\",\n          \"COND_COUNT\": \"09\",\n          \"COND_TYPE\": \"ZBDB\",\n          \"COND_VALUE\": \"100.000000000\",\n          \"CURRENCY\": \"\",\n          \"COND_UNIT\": \"\",\n          \"COND_P_UNT\": \"0\",\n          \"CURR_ISO\": \"\",\n          \"CD_UNT_ISO\": \"\",\n          \"REFOBJTYPE\": \"\",\n          \"REFOBJKEY\": \"\",\n          \"REFLOGSYS\": \"\",\n          \"APPLICATIO\": \"V\",\n          \"CONPRICDAT\": \"2020-12-14\",\n          \"CALCTYPCON\": \"A\",\n          \"CONBASEVAL\": \"0.000000000\",\n          \"CONEXCHRAT\": \"0.00000\",\n          \"NUMCONVERT\": \"0\",\n          \"DENOMINATO\": \"0\",\n          \"CONDTYPE\": \"\",\n          \"STAT_CON\": \"\",\n          \"SCALETYPE\": \"\",\n          \"ACCRUALS\": \"\",\n          \"CONINVOLST\": \"\",\n          \"CONDORIGIN\": \"A\",\n          \"GROUPCOND\": \"\",\n          \"COND_UPDAT\": \"\",\n          \"ACCESS_SEQ\": \"10\",\n          \"CONDCOUNT\": \"01\",\n          \"ROUNDOFFDI\": \"0.000000000\",\n          \"CONDVALUE\": \"0.000000000\",\n          \"CURRENCY_2\": \"BRL\",\n          \"CURR_ISO_2\": \"BRL\",\n          \"CONDCNTRL\": \"A\",\n          \"CONDISACTI\": \"\",\n          \"CONDCLASS\": \"A\",\n          \"FACTBASVAL\": \"0.0000000000000000E+00\",\n          \"SCALEBASIN\": \"\",\n          \"SCALBASVAL\": \"0.000000000\",\n          \"UNITMEASUR\": \"\",\n          \"ISO_UNIT\": \"\",\n          \"CURRENCKEY\": \"\",\n          \"CURRENISO\": \"\",\n          \"CONDINCOMP\": \"\",\n          \"CONDCONFIG\": \"\",\n          \"CONDCHAMAN\": \"\",\n          \"COND_NO\": \"0011028355\",\n          \"TAX_CODE\": \"\",\n          \"VARCOND\": \"\",\n          \"ACCOUNTKEY\": \"\",\n          \"ACCOUNT_KE\": \"\",\n          \"WT_WITHCD\": \"\",\n          \"STRUCTCOND\": \"\",\n          \"FACTCONBAS\": \"0.0000000000000000E+00\",\n          \"CONDCOINHD\": \"00\"\n        },\n        {\n          \"ITM_NUMBER\": \"000010\",\n          \"COND_ST_NO\": \"885\",\n          \"COND_COUNT\": \"01\",\n          \"COND_TYPE\": \"ZBDI\",\n          \"COND_VALUE\": \"-100.000000000\",\n          \"CURRENCY\": \"\",\n          \"COND_UNIT\": \"\",\n          \"COND_P_UNT\": \"0\",\n          \"CURR_ISO\": \"\",\n          \"CD_UNT_ISO\": \"\",\n          \"REFOBJTYPE\": \"\",\n          \"REFOBJKEY\": \"\",\n          \"REFLOGSYS\": \"\",\n          \"APPLICATIO\": \"V\",\n          \"CONPRICDAT\": \"2020-12-14\",\n          \"CALCTYPCON\": \"A\",\n          \"CONBASEVAL\": \"-160.380000000\",\n          \"CONEXCHRAT\": \"0.00000\",\n          \"NUMCONVERT\": \"0\",\n          \"DENOMINATO\": \"0\",\n          \"CONDTYPE\": \"\",\n          \"STAT_CON\": \"\",\n          \"SCALETYPE\": \"\",\n          \"ACCRUALS\": \"\",\n          \"CONINVOLST\": \"\",\n          \"CONDORIGIN\": \"A\",\n          \"GROUPCOND\": \"\",\n          \"COND_UPDAT\": \"\",\n          \"ACCESS_SEQ\": \"10\",\n          \"CONDCOUNT\": \"01\",\n          \"ROUNDOFFDI\": \"0.000000000\",\n          \"CONDVALUE\": \"160.380000000\",\n          \"CURRENCY_2\": \"BRL\",\n          \"CURR_ISO_2\": \"BRL\",\n          \"CONDCNTRL\": \"A\",\n          \"CONDISACTI\": \"\",\n          \"CONDCLASS\": \"A\",\n          \"FACTBASVAL\": \"0.0000000000000000E+00\",\n          \"SCALEBASIN\": \"\",\n          \"SCALBASVAL\": \"0.000000000\",\n          \"UNITMEASUR\": \"\",\n          \"ISO_UNIT\": \"\",\n          \"CURRENCKEY\": \"\",\n          \"CURRENISO\": \"\",\n          \"CONDINCOMP\": \"\",\n          \"CONDCONFIG\": \"\",\n          \"CONDCHAMAN\": \"\",\n          \"COND_NO\": \"0000716933\",\n          \"TAX_CODE\": \"\",\n          \"VARCOND\": \"\",\n          \"ACCOUNTKEY\": \"\",\n          \"ACCOUNT_KE\": \"\",\n          \"WT_WITHCD\": \"\",\n          \"STRUCTCOND\": \"\",\n          \"FACTCONBAS\": \"0.0000000000000000E+00\",\n          \"CONDCOINHD\": \"00\"\n        },\n        {\n          \"ITM_NUMBER\": \"000010\",\n          \"COND_ST_NO\": \"890\",\n          \"COND_COUNT\": \"01\",\n          \"COND_TYPE\": \"ZBIP\",\n          \"COND_VALUE\": \"-100.000000000\",\n          \"CURRENCY\": \"\",\n          \"COND_UNIT\": \"\",\n          \"COND_P_UNT\": \"0\",\n          \"CURR_ISO\": \"\",\n          \"CD_UNT_ISO\": \"\",\n          \"REFOBJTYPE\": \"\",\n          \"REFOBJKEY\": \"\",\n          \"REFLOGSYS\": \"\",\n          \"APPLICATIO\": \"V\",\n          \"CONPRICDAT\": \"2020-12-14\",\n          \"CALCTYPCON\": \"A\",\n          \"CONBASEVAL\": \"-8.230000000\",\n          \"CONEXCHRAT\": \"0.00000\",\n          \"NUMCONVERT\": \"0\",\n          \"DENOMINATO\": \"0\",\n          \"CONDTYPE\": \"\",\n          \"STAT_CON\": \"\",\n          \"SCALETYPE\": \"\",\n          \"ACCRUALS\": \"\",\n          \"CONINVOLST\": \"\",\n          \"CONDORIGIN\": \"A\",\n          \"GROUPCOND\": \"\",\n          \"COND_UPDAT\": \"\",\n          \"ACCESS_SEQ\": \"10\",\n          \"CONDCOUNT\": \"01\",\n          \"ROUNDOFFDI\": \"0.000000000\",\n          \"CONDVALUE\": \"8.230000000\",\n          \"CURRENCY_2\": \"BRL\",\n          \"CURR_ISO_2\": \"BRL\",\n          \"CONDCNTRL\": \"A\",\n          \"CONDISACTI\": \"\",\n          \"CONDCLASS\": \"A\",\n          \"FACTBASVAL\": \"0.0000000000000000E+00\",\n          \"SCALEBASIN\": \"\",\n          \"SCALBASVAL\": \"0.000000000\",\n          \"UNITMEASUR\": \"\",\n          \"ISO_UNIT\": \"\",\n          \"CURRENCKEY\": \"\",\n          \"CURRENISO\": \"\",\n          \"CONDINCOMP\": \"\",\n          \"CONDCONFIG\": \"\",\n          \"CONDCHAMAN\": \"\",\n          \"COND_NO\": \"0000716933\",\n          \"TAX_CODE\": \"\",\n          \"VARCOND\": \"\",\n          \"ACCOUNTKEY\": \"\",\n          \"ACCOUNT_KE\": \"\",\n          \"WT_WITHCD\": \"\",\n          \"STRUCTCOND\": \"\",\n          \"FACTCONBAS\": \"0.0000000000000000E+00\",\n          \"CONDCOINHD\": \"00\"\n        },\n        {\n          \"ITM_NUMBER\": \"000010\",\n          \"COND_ST_NO\": \"894\",\n          \"COND_COUNT\": \"01\",\n          \"COND_TYPE\": \"ZBTB\",\n          \"COND_VALUE\": \"0.000000000\",\n          \"CURRENCY\": \"BRL\",\n          \"COND_UNIT\": \"\",\n          \"COND_P_UNT\": \"0\",\n          \"CURR_ISO\": \"BRL\",\n          \"CD_UNT_ISO\": \"\",\n          \"REFOBJTYPE\": \"\",\n          \"REFOBJKEY\": \"\",\n          \"REFLOGSYS\": \"\",\n          \"APPLICATIO\": \"V\",\n          \"CONPRICDAT\": \"2020-12-14\",\n          \"CALCTYPCON\": \"B\",\n          \"CONBASEVAL\": \"0.000000000\",\n          \"CONEXCHRAT\": \"1.00000\",\n          \"NUMCONVERT\": \"0\",\n          \"DENOMINATO\": \"0\",\n          \"CONDTYPE\": \"\",\n          \"STAT_CON\": \"X\",\n          \"SCALETYPE\": \"\",\n          \"ACCRUALS\": \"\",\n          \"CONINVOLST\": \"\",\n          \"CONDORIGIN\": \"A\",\n          \"GROUPCOND\": \"\",\n          \"COND_UPDAT\": \"\",\n          \"ACCESS_SEQ\": \"00\",\n          \"CONDCOUNT\": \"00\",\n          \"ROUNDOFFDI\": \"0.000000000\",\n          \"CONDVALUE\": \"128.700000000\",\n          \"CURRENCY_2\": \"BRL\",\n          \"CURR_ISO_2\": \"BRL\",\n          \"CONDCNTRL\": \"A\",\n          \"CONDISACTI\": \"\",\n          \"CONDCLASS\": \"A\",\n          \"FACTBASVAL\": \"0.0000000000000000E+00\",\n          \"SCALEBASIN\": \"\",\n          \"SCALBASVAL\": \"0.000000000\",\n          \"UNITMEASUR\": \"\",\n          \"ISO_UNIT\": \"\",\n          \"CURRENCKEY\": \"\",\n          \"CURRENISO\": \"\",\n          \"CONDINCOMP\": \"\",\n          \"CONDCONFIG\": \"\",\n          \"CONDCHAMAN\": \"\",\n          \"COND_NO\": \"\",\n          \"TAX_CODE\": \"\",\n          \"VARCOND\": \"\",\n          \"ACCOUNTKEY\": \"\",\n          \"ACCOUNT_KE\": \"\",\n          \"WT_WITHCD\": \"\",\n          \"STRUCTCOND\": \"\",\n          \"FACTCONBAS\": \"0.0000000000000000E+00\",\n          \"CONDCOINHD\": \"00\"\n        },\n        {\n          \"ITM_NUMBER\": \"000010\",\n          \"COND_ST_NO\": \"896\",\n          \"COND_COUNT\": \"01\",\n          \"COND_TYPE\": \"ZBTR\",\n          \"COND_VALUE\": \"-100.000000000\",\n          \"CURRENCY\": \"\",\n          \"COND_UNIT\": \"\",\n          \"COND_P_UNT\": \"0\",\n          \"CURR_ISO\": \"\",\n          \"CD_UNT_ISO\": \"\",\n          \"REFOBJTYPE\": \"\",\n          \"REFOBJKEY\": \"\",\n          \"REFLOGSYS\": \"\",\n          \"APPLICATIO\": \"V\",\n          \"CONPRICDAT\": \"2020-12-14\",\n          \"CALCTYPCON\": \"A\",\n          \"CONBASEVAL\": \"128.700000000\",\n          \"CONEXCHRAT\": \"0.00000\",\n          \"NUMCONVERT\": \"0\",\n          \"DENOMINATO\": \"0\",\n          \"CONDTYPE\": \"\",\n          \"STAT_CON\": \"X\",\n          \"SCALETYPE\": \"\",\n          \"ACCRUALS\": \"\",\n          \"CONINVOLST\": \"\",\n          \"CONDORIGIN\": \"A\",\n          \"GROUPCOND\": \"\",\n          \"COND_UPDAT\": \"\",\n          \"ACCESS_SEQ\": \"10\",\n          \"CONDCOUNT\": \"01\",\n          \"ROUNDOFFDI\": \"0.000000000\",\n          \"CONDVALUE\": \"-128.700000000\",\n          \"CURRENCY_2\": \"BRL\",\n          \"CURR_ISO_2\": \"BRL\",\n          \"CONDCNTRL\": \"A\",\n          \"CONDISACTI\": \"\",\n          \"CONDCLASS\": \"A\",\n          \"FACTBASVAL\": \"0.0000000000000000E+00\",\n          \"SCALEBASIN\": \"\",\n          \"SCALBASVAL\": \"0.000000000\",\n          \"UNITMEASUR\": \"\",\n          \"ISO_UNIT\": \"\",\n          \"CURRENCKEY\": \"\",\n          \"CURRENISO\": \"\",\n          \"CONDINCOMP\": \"\",\n          \"CONDCONFIG\": \"\",\n          \"CONDCHAMAN\": \"\",\n          \"COND_NO\": \"0000716933\",\n          \"TAX_CODE\": \"\",\n          \"VARCOND\": \"\",\n          \"ACCOUNTKEY\": \"\",\n          \"ACCOUNT_KE\": \"\",\n          \"WT_WITHCD\": \"\",\n          \"STRUCTCOND\": \"\",\n          \"FACTCONBAS\": \"0.0000000000000000E+00\",\n          \"CONDCOINHD\": \"00\"\n        },\n        {\n          \"ITM_NUMBER\": \"000010\",\n          \"COND_ST_NO\": \"904\",\n          \"COND_COUNT\": \"01\",\n          \"COND_TYPE\": \"ZTOT\",\n          \"COND_VALUE\": \"172.920000000\",\n          \"CURRENCY\": \"BRL\",\n          \"COND_UNIT\": \"CS\",\n          \"COND_P_UNT\": \"1\",\n          \"CURR_ISO\": \"BRL\",\n          \"CD_UNT_ISO\": \"CS\",\n          \"REFOBJTYPE\": \"\",\n          \"REFOBJKEY\": \"\",\n          \"REFLOGSYS\": \"\",\n          \"APPLICATIO\": \"V\",\n          \"CONPRICDAT\": \"2020-12-14\",\n          \"CALCTYPCON\": \"C\",\n          \"CONBASEVAL\": \"1.000000000\",\n          \"CONEXCHRAT\": \"1.00000\",\n          \"NUMCONVERT\": \"1\",\n          \"DENOMINATO\": \"1\",\n          \"CONDTYPE\": \"\",\n          \"STAT_CON\": \"X\",\n          \"SCALETYPE\": \"\",\n          \"ACCRUALS\": \"\",\n          \"CONINVOLST\": \"\",\n          \"CONDORIGIN\": \"A\",\n          \"GROUPCOND\": \"\",\n          \"COND_UPDAT\": \"\",\n          \"ACCESS_SEQ\": \"00\",\n          \"CONDCOUNT\": \"00\",\n          \"ROUNDOFFDI\": \"0.000000000\",\n          \"CONDVALUE\": \"172.920000000\",\n          \"CURRENCY_2\": \"BRL\",\n          \"CURR_ISO_2\": \"BRL\",\n          \"CONDCNTRL\": \"A\",\n          \"CONDISACTI\": \"\",\n          \"CONDCLASS\": \"B\",\n          \"FACTBASVAL\": \"0.0000000000000000E+00\",\n          \"SCALEBASIN\": \"\",\n          \"SCALBASVAL\": \"0.000000000\",\n          \"UNITMEASUR\": \"\",\n          \"ISO_UNIT\": \"\",\n          \"CURRENCKEY\": \"\",\n          \"CURRENISO\": \"\",\n          \"CONDINCOMP\": \"\",\n          \"CONDCONFIG\": \"\",\n          \"CONDCHAMAN\": \"\",\n          \"COND_NO\": \"\",\n          \"TAX_CODE\": \"\",\n          \"VARCOND\": \"\",\n          \"ACCOUNTKEY\": \"\",\n          \"ACCOUNT_KE\": \"\",\n          \"WT_WITHCD\": \"\",\n          \"STRUCTCOND\": \"\",\n          \"FACTCONBAS\": \"0.0000000000000000E+00\",\n          \"CONDCOINHD\": \"00\"\n        },\n        {\n          \"ITM_NUMBER\": \"000010\",\n          \"COND_ST_NO\": \"977\",\n          \"COND_COUNT\": \"01\",\n          \"COND_TYPE\": \"ZVC2\",\n          \"COND_VALUE\": \"-100.000000000\",\n          \"CURRENCY\": \"\",\n          \"COND_UNIT\": \"\",\n          \"COND_P_UNT\": \"0\",\n          \"CURR_ISO\": \"\",\n          \"CD_UNT_ISO\": \"\",\n          \"REFOBJTYPE\": \"\",\n          \"REFOBJKEY\": \"\",\n          \"REFLOGSYS\": \"\",\n          \"APPLICATIO\": \"V\",\n          \"CONPRICDAT\": \"2020-12-14\",\n          \"CALCTYPCON\": \"A\",\n          \"CONBASEVAL\": \"0.000000000\",\n          \"CONEXCHRAT\": \"0.00000\",\n          \"NUMCONVERT\": \"0\",\n          \"DENOMINATO\": \"0\",\n          \"CONDTYPE\": \"\",\n          \"STAT_CON\": \"\",\n          \"SCALETYPE\": \"\",\n          \"ACCRUALS\": \"\",\n          \"CONINVOLST\": \"\",\n          \"CONDORIGIN\": \"A\",\n          \"GROUPCOND\": \"\",\n          \"COND_UPDAT\": \"\",\n          \"ACCESS_SEQ\": \"10\",\n          \"CONDCOUNT\": \"01\",\n          \"ROUNDOFFDI\": \"0.000000000\",\n          \"CONDVALUE\": \"0.000000000\",\n          \"CURRENCY_2\": \"BRL\",\n          \"CURR_ISO_2\": \"BRL\",\n          \"CONDCNTRL\": \"A\",\n          \"CONDISACTI\": \"\",\n          \"CONDCLASS\": \"E\",\n          \"FACTBASVAL\": \"0.0000000000000000E+00\",\n          \"SCALEBASIN\": \"\",\n          \"SCALBASVAL\": \"0.000000000\",\n          \"UNITMEASUR\": \"\",\n          \"ISO_UNIT\": \"\",\n          \"CURRENCKEY\": \"\",\n          \"CURRENISO\": \"\",\n          \"CONDINCOMP\": \"\",\n          \"CONDCONFIG\": \"\",\n          \"CONDCHAMAN\": \"\",\n          \"COND_NO\": \"0000716941\",\n          \"TAX_CODE\": \"\",\n          \"VARCOND\": \"\",\n          \"ACCOUNTKEY\": \"\",\n          \"ACCOUNT_KE\": \"\",\n          \"WT_WITHCD\": \"\",\n          \"STRUCTCOND\": \"\",\n          \"FACTCONBAS\": \"0.0000000000000000E+00\",\n          \"CONDCOINHD\": \"00\"\n        },\n        {\n          \"ITM_NUMBER\": \"000010\",\n          \"COND_ST_NO\": \"979\",\n          \"COND_COUNT\": \"01\",\n          \"COND_TYPE\": \"ZVC4\",\n          \"COND_VALUE\": \"-100.000000000\",\n          \"CURRENCY\": \"\",\n          \"COND_UNIT\": \"\",\n          \"COND_P_UNT\": \"0\",\n          \"CURR_ISO\": \"\",\n          \"CD_UNT_ISO\": \"\",\n          \"REFOBJTYPE\": \"\",\n          \"REFOBJKEY\": \"\",\n          \"REFLOGSYS\": \"\",\n          \"APPLICATIO\": \"V\",\n          \"CONPRICDAT\": \"2020-12-14\",\n          \"CALCTYPCON\": \"A\",\n          \"CONBASEVAL\": \"0.000000000\",\n          \"CONEXCHRAT\": \"0.00000\",\n          \"NUMCONVERT\": \"0\",\n          \"DENOMINATO\": \"0\",\n          \"CONDTYPE\": \"\",\n          \"STAT_CON\": \"\",\n          \"SCALETYPE\": \"\",\n          \"ACCRUALS\": \"\",\n          \"CONINVOLST\": \"\",\n          \"CONDORIGIN\": \"A\",\n          \"GROUPCOND\": \"\",\n          \"COND_UPDAT\": \"\",\n          \"ACCESS_SEQ\": \"10\",\n          \"CONDCOUNT\": \"01\",\n          \"ROUNDOFFDI\": \"0.000000000\",\n          \"CONDVALUE\": \"0.000000000\",\n          \"CURRENCY_2\": \"BRL\",\n          \"CURR_ISO_2\": \"BRL\",\n          \"CONDCNTRL\": \"A\",\n          \"CONDISACTI\": \"\",\n          \"CONDCLASS\": \"E\",\n          \"FACTBASVAL\": \"0.0000000000000000E+00\",\n          \"SCALEBASIN\": \"\",\n          \"SCALBASVAL\": \"0.000000000\",\n          \"UNITMEASUR\": \"\",\n          \"ISO_UNIT\": \"\",\n          \"CURRENCKEY\": \"\",\n          \"CURRENISO\": \"\",\n          \"CONDINCOMP\": \"\",\n          \"CONDCONFIG\": \"\",\n          \"CONDCHAMAN\": \"\",\n          \"COND_NO\": \"0000716945\",\n          \"TAX_CODE\": \"\",\n          \"VARCOND\": \"\",\n          \"ACCOUNTKEY\": \"\",\n          \"ACCOUNT_KE\": \"\",\n          \"WT_WITHCD\": \"\",\n          \"STRUCTCOND\": \"\",\n          \"FACTCONBAS\": \"0.0000000000000000E+00\",\n          \"CONDCOINHD\": \"00\"\n        }\n      ]\n    },\n    \"ETB_EXTENSION\": {\n      \"item\": [\n        \n      ]\n    },\n    \"ETB_INCOMPLETE_LOG\": {\n      \"item\": [\n        {\n          \"DOC_NUMBER\": \"\",\n          \"ITM_NUMBER\": \"000000\",\n          \"SCHED_LINE\": \"0000\",\n          \"PARTN_ROLE\": \"\",\n          \"TABLE_NAME\": \"VBKD\",\n          \"FIELD_NAME\": \"BSTDK\",\n          \"FIELD_TEXT\": \"Purchase order date\"\n        },\n        {\n          \"DOC_NUMBER\": \"\",\n          \"ITM_NUMBER\": \"000000\",\n          \"SCHED_LINE\": \"0000\",\n          \"PARTN_ROLE\": \"\",\n          \"TABLE_NAME\": \"VBKD\",\n          \"FIELD_NAME\": \"BSTKD\",\n          \"FIELD_TEXT\": \"PO number\"\n        }\n      ]\n    },\n    \"ETB_ITEMS\": {\n      \"item\": [\n        {\n          \"OPERATION\": \"\",\n          \"DOC_NUMBER\": \"\",\n          \"ITM_NUMBER\": \"000010\",\n          \"MATERIAL\": \"000000000030197119\",\n          \"MAT_ENTRD\": \"000000000030197119\",\n          \"PR_REF_MAT\": \"\",\n          \"BATCH\": \"\",\n          \"MATL_GROUP\": \"048\",\n          \"SHORT_TEXT\": \"KCP SCOTT SPRAY ANTISSEPTICO 300ML 6X1\",\n          \"ITEM_CATEG\": \"ZTBN\",\n          \"ITEM_TYPE\": \"\",\n          \"REL_FOR_DE\": \"\",\n          \"REL_FOR_BI\": \"H\",\n          \"HG_LV_ITEM\": \"000000\",\n          \"ALTERN_ITM\": \"000000\",\n          \"REA_FOR_RE\": \"\",\n          \"PROD_HIER\": \"28004002001001\",\n          \"OUT_AGR_TA\": \"0.000000000\",\n          \"TARGET_QTY\": \"0.000\",\n          \"TARGET_QU\": \"CS\",\n          \"T_UNIT_ISO\": \"CS\",\n          \"TARG_QTY_N\": \"1\",\n          \"TARG_QTY_D\": \"1\",\n          \"BASE_UOM\": \"CS\",\n          \"T_BAS_UNIT\": \"CS\",\n          \"SCALE_QUAN\": \"0.000\",\n          \"ROUND_DLV\": \"0.000\",\n          \"RECON_DATE\": \"0000-00-00\",\n          \"MAX_DEVIAT\": \"0.000\",\n          \"PO_ITM_NO\": \"\",\n          \"CUST_MAT22\": \"\",\n          \"MAX_DEV_PE\": \"0\",\n          \"MAX_DEV_DA\": \"0\",\n          \"REPAIR_PRO\": \"\",\n          \"DLVSCHEDUS\": \"\",\n          \"DLV_GROUP\": \"000\",\n          \"FIXED_QUAN\": \"\",\n          \"DELI_UNLIM\": \"\",\n          \"OVER_DLV_T\": \"0.0\",\n          \"UNDER_DLV\": \"0.0\",\n          \"BILL_BLOCK\": \"\",\n          \"REPLACE_PT\": \"\",\n          \"METH_BILL\": \"\",\n          \"DIVISION\": \"02\",\n          \"BUS_AREA\": \"\",\n          \"NET_VALUE\": \"118.320000000\",\n          \"CURRENCY\": \"BRL\",\n          \"CURREN_ISO\": \"BRL\",\n          \"MAX_PL_DLV\": \"1\",\n          \"PART_DLV\": \"B\",\n          \"BTCH_SPLIT\": \"\",\n          \"REQ_QTY\": \"1.000\",\n          \"CUM_REQ_DE\": \"1.000\",\n          \"CUM_CF_QTY\": \"0.000\",\n          \"CUM_CON_QU\": \"0.000\",\n          \"SALES_UNIT\": \"CS\",\n          \"ISOCODUNIT\": \"CS\",\n          \"SALES_QTY1\": \"1\",\n          \"SALES_QTY2\": \"1\",\n          \"GROSS_WEIG\": \"1.797\",\n          \"NET_WEIGHT\": \"1.572\",\n          \"UNIT_OF_WT\": \"KG\",\n          \"UNIT_WTISO\": \"KGM\",\n          \"VOLUME\": \"5.736\",\n          \"VOLUMEUNIT\": \"CDM\",\n          \"VOLUNITISO\": \"DMQ\",\n          \"CAU_VBELN\": \"\",\n          \"CAU_POSNR\": \"000000\",\n          \"REF_DOC\": \"\",\n          \"POSNR_VOR\": \"000000\",\n          \"OBJ_COPY\": \"\",\n          \"UPDAT_FLAG\": \"\",\n          \"END_RULE\": \"\",\n          \"DLV_PRIO\": \"02\",\n          \"PLANT\": \"7026\",\n          \"STGE_LOC\": \"\",\n          \"SHIP_POINT\": \"BR27\",\n          \"ROUTE\": \"BRK120\",\n          \"KEY_ST\": \"\",\n          \"DATE_ST\": \"0000-00-00\",\n          \"NBR_ST\": \"\",\n          \"STPOS_VBAP\": \"0\",\n          \"ORDER_PROB\": \"100\",\n          \"CREAT_DATE\": \"2020-12-14\",\n          \"CREATED_BY\": \"APISALES0001\",\n          \"REC_TIME\": \"15:28:08\",\n          \"TAX_CLASS1\": \"1\",\n          \"TAX_CLASS2\": \"\",\n          \"TAX_CLASS3\": \"\",\n          \"TAX_CLASS4\": \"\",\n          \"TAX_CLASS5\": \"\",\n          \"TAX_CLASS6\": \"\",\n          \"TAX_CLASS7\": \"\",\n          \"TAX_CLASS8\": \"\",\n          \"TAX_CLASS9\": \"\",\n          \"FIX_SP_DAY\": \"0.00\",\n          \"VAR_SP_DAY\": \"0.00\",\n          \"PREC_DOC\": \"\",\n          \"NET_PRICE\": \"118.320000000\",\n          \"COND_P_UNT\": \"1\",\n          \"COND_UNIT\": \"CS\",\n          \"CONISOUNIT\": \"CS\",\n          \"RETOURE\": \"\",\n          \"CASH_DISC\": \"\",\n          \"AVAILCHECK\": \"Z2\",\n          \"SUM_REQUIR\": \"A\",\n          \"MAT_PR_GRP\": \"\",\n          \"ACCT_ASSGT\": \"M1\",\n          \"REBATE_GRP\": \"\",\n          \"COMM_GROUP\": \"\",\n          \"EUR_ART_NR\": \"\",\n          \"PRICE_OK\": \"X\",\n          \"VAL_TYPE\": \"\",\n          \"SEP_VALUAT\": \"\",\n          \"BATCH_MGMT\": \"\",\n          \"IND_BTCH\": \"\",\n          \"MIN_DELY\": \"0.000\",\n          \"UPDATE_GRP\": \"000001\",\n          \"COST_DOC_C\": \"45.400000000\",\n          \"SUBTOT_PP1\": \"128.710000000\",\n          \"SUBTOT_PP2\": \"0.000000000\",\n          \"SUBTOT_PP3\": \"0.000000000\",\n          \"SUBTOT_PP4\": \"0.000000000\",\n          \"SUBTOT_PP5\": \"128.700000000\",\n          \"SUBTOT_PP6\": \"0.000000000\",\n          \"EXCH_RATE\": \"5.02614\",\n          \"CH_ON\": \"0000-00-00\",\n          \"EAN_UPC\": \"17891172001298\",\n          \"FIX_DATE\": \"\",\n          \"PROFIT_CTR\": \"P141200005\",\n          \"PRC_GROUP1\": \"\",\n          \"PRC_GROUP2\": \"\",\n          \"PRC_GROUP3\": \"\",\n          \"PRC_GROUP4\": \"\",\n          \"PRC_GROUP5\": \"\",\n          \"COMPON_QTY\": \"0.000\",\n          \"SUBSTREASO\": \"\",\n          \"SPEC_STOCK\": \"\",\n          \"ALLOC_INDI\": \"1\",\n          \"PROFIT_SEG\": \"0732969666\",\n          \"WBS_ELEM\": \"00000000\",\n          \"ORDERID\": \"\",\n          \"PLNG_MATL\": \"\",\n          \"PLNG_PLANT\": \"\",\n          \"BASE_UNIT\": \"\",\n          \"ISOBASUNIT\": \"\",\n          \"CONV_FACT\": \"0.0000000000000000E+00\",\n          \"ACCTASSCAT\": \"\",\n          \"CONSUMPT\": \"\",\n          \"BOMEXPLNO\": \"\",\n          \"OBJ_NR_IT\": \"\",\n          \"RES_ANAL\": \"\",\n          \"REQMTSTYP\": \"KSV\",\n          \"CREDPRICIT\": \"172.920000000\",\n          \"PARTRELID\": \"\",\n          \"ACTCREDID\": \"X\",\n          \"CR_EXCHRAT\": \"1.00000\",\n          \"CONFIG\": \"000000000000000000\",\n          \"CHCLASS_IN\": \"000000000000000000\",\n          \"STAT_PRICE\": \"\",\n          \"COND_UPDAT\": \"X\",\n          \"SERNO_PROF\": \"\",\n          \"NO_OF_SERI\": \"0\",\n          \"NOGRPOSTED\": \"\",\n          \"MAT_GRP_SM\": \"\",\n          \"MAN_PR_CH\": \"\",\n          \"DOC_CAT_SD\": \"\",\n          \"MATDETERID\": \"\",\n          \"ITUSAGEID\": \"\",\n          \"COSTESTNR\": \"000000000000\",\n          \"CSTG_VRNT\": \"\",\n          \"BOMITEMNR\": \"\",\n          \"STAT_VAL\": \"\",\n          \"STAT_DATE\": \"0000-00-00\",\n          \"BUS_TRANST\": \"\",\n          \"PREF_INDIC\": \"\",\n          \"NRCONDREC\": \"\",\n          \"INTCLASSNR\": \"0000000000\",\n          \"BATCH_EXIT\": \"000\",\n          \"BOM_CATEGO\": \"\",\n          \"BOM_IT_NR\": \"00000000\",\n          \"COUNTER\": \"00000000\",\n          \"INCONSCONF\": \"\",\n          \"OVERH_KEY\": \"\",\n          \"CSTG_SHEET\": \"\",\n          \"CSTG_VRNT1\": \"\",\n          \"PROD_ALLOC\": \"\",\n          \"PRICE_REF\": \"\",\n          \"MATPRICGRP\": \"\",\n          \"MATFRGTGRP\": \"\",\n          \"PLANDLVSCH\": \"\",\n          \"SEQUENCENO\": \"\",\n          \"CREDPRIC\": \"1.7291999999999999E+02\",\n          \"PAY_GUARAN\": \"\",\n          \"GURANTEED\": \"0.0000000000000000E+00\",\n          \"CFOP_CODE\": \"\",\n          \"TAXLAWICMS\": \"IC0\",\n          \"TAXLAWIPI\": \"IP0\",\n          \"SD_TAXCODE\": \"C4\",\n          \"VALCONTRNR\": \"\",\n          \"VALCONTRIT\": \"000000\",\n          \"ASSORT_MOD\": \"\",\n          \"VALSPECSTO\": \"\",\n          \"MATGRHIE1\": \"\",\n          \"MATGRHIE2\": \"\",\n          \"PROMOTION\": \"\",\n          \"SALES_DEAL\": \"\",\n          \"FLGLEADUNI\": \"\",\n          \"FREE_GOODS\": \"\",\n          \"VALID_OBJ\": \"\",\n          \"TAX_AMOUNT\": \"54.600000000\",\n          \"MRP_AREA\": \"7026\",\n          \"CUST_MAT35\": \"\",\n          \"CR_EXCHRAT_V\": \"0.00000\",\n          \"EXCHRATEST_V\": \"0.00000\",\n          \"ITM_TYPE_USAGE\": \"\",\n          \"CFOP_LONG\": \"6108AA\",\n          \"GROSS_VAL\": \"0.000000000\",\n          \"LOG_SYSTEM_OWN\": \"QL3400\",\n          \"TAXLAWISS\": \"\",\n          \"TAXLAWCOFINS\": \"C01\",\n          \"TAXLAWPIS\": \"P01\"\n        }\n      ]\n    },\n    \"ETB_RETURN\": {\n      \"item\": [\n        {\n          \"TYPE\": \"S\",\n          \"ID\": \"V4\",\n          \"NUMBER\": \"233\",\n          \"MESSAGE\": \"SALES_HEADER_IN has been processed successfully\",\n          \"LOG_NO\": \"\",\n          \"LOG_MSG_NO\": \"000000\",\n          \"MESSAGE_V1\": \"VBAKKOM\",\n          \"MESSAGE_V2\": \"14.12.2020\",\n          \"MESSAGE_V3\": \"15:28:08\",\n          \"MESSAGE_V4\": \"\",\n          \"PARAMETER\": \"SALES_HEADER_IN\",\n          \"ROW\": \"0\",\n          \"FIELD\": \"\",\n          \"SYSTEM\": \"QL3400\"\n        },\n        {\n          \"TYPE\": \"S\",\n          \"ID\": \"V4\",\n          \"NUMBER\": \"233\",\n          \"MESSAGE\": \"SALES_ITEM_IN has been processed successfully\",\n          \"LOG_NO\": \"\",\n          \"LOG_MSG_NO\": \"000000\",\n          \"MESSAGE_V1\": \"VBAPKOM\",\n          \"MESSAGE_V2\": \"000010\",\n          \"MESSAGE_V3\": \"\",\n          \"MESSAGE_V4\": \"\",\n          \"PARAMETER\": \"SALES_ITEM_IN\",\n          \"ROW\": \"1\",\n          \"FIELD\": \"\",\n          \"SYSTEM\": \"QL3400\"\n        },\n        {\n          \"TYPE\": \"W\",\n          \"ID\": \"V1\",\n          \"NUMBER\": \"555\",\n          \"MESSAGE\": \"The sales document is not yet complete: Edit data\",\n          \"LOG_NO\": \"\",\n          \"LOG_MSG_NO\": \"000000\",\n          \"MESSAGE_V1\": \"VBAPKOM\",\n          \"MESSAGE_V2\": \"000010\",\n          \"MESSAGE_V3\": \"\",\n          \"MESSAGE_V4\": \"\",\n          \"PARAMETER\": \"VBUVKOM\",\n          \"ROW\": \"0\",\n          \"FIELD\": \"\",\n          \"SYSTEM\": \"QL3400\"\n        }\n      ]\n    },\n    \"EWA_SALES_HEADER_OUT\": {\n      \"OPERATION\": \"\",\n      \"DOC_NUMBER\": \"\",\n      \"REC_DATE\": \"2020-12-14\",\n      \"REC_TIME\": \"15:28:08\",\n      \"CREATED_BY\": \"APISALES0001\",\n      \"QT_VALID_F\": \"0000-00-00\",\n      \"QT_VALID_T\": \"0000-00-00\",\n      \"DOC_DATE\": \"2020-12-14\",\n      \"SD_DOC_CAT\": \"C\",\n      \"TRAN_GROUP\": \"0\",\n      \"DOC_TYPE\": \"ZSMP\",\n      \"ORD_REASON\": \"\",\n      \"WAR_DATE\": \"0000-00-00\",\n      \"SD_COL_NUM\": \"\",\n      \"DLV_BLOCK\": \"\",\n      \"BILL_BLOCK\": \"\",\n      \"NET_VAL_HD\": \"118.320000000\",\n      \"CURRENCY\": \"BRL\",\n      \"CURREN_ISO\": \"BRL\",\n      \"SALES_ORG\": \"7024\",\n      \"DISTR_CHAN\": \"50\",\n      \"DIVISION\": \"02\",\n      \"SALES_GRP\": \"BMF\",\n      \"SALES_OFF\": \"BR70\",\n      \"BUS_AREA\": \"\",\n      \"CT_AREA\": \"\",\n      \"CT_VALID_F\": \"0000-00-00\",\n      \"CT_VALID_T\": \"0000-00-00\",\n      \"CONDITIONS\": \"\",\n      \"REQ_DATE_H\": \"2020-12-22\",\n      \"DATE_TYPE\": \"1\",\n      \"COMPL_DLV\": \"X\",\n      \"DOC_CLASS\": \"\",\n      \"DOC_INDIC\": \"\",\n      \"SD_PRIC_PR\": \"ZBRABV\",\n      \"SHIP_COND\": \"10\",\n      \"ORDBILLTYP\": \"ZF2B\",\n      \"ORD_PROBAB\": \"100\",\n      \"SEAR_PRPR\": \"\",\n      \"PURCH_NO\": \"\",\n      \"PO_METHOD\": \"\",\n      \"PURCH_DATE\": \"0000-00-00\",\n      \"PO_SUPPLEM\": \"\",\n      \"REF_1\": \"\",\n      \"ORDERER_NA\": \"\",\n      \"TELEPHONE\": \"(45) 2102-7500\",\n      \"DUN_COUNT\": \"0\",\n      \"DUN_DATE\": \"0000-00-00\",\n      \"SOLD_TO\": \"0042026019\",\n      \"COSTCENTER\": \"\",\n      \"UPDATE_GRP\": \"\",\n      \"STAT_CURR\": \"USD\",\n      \"ISOSTATCUR\": \"USD\",\n      \"CH_ON\": \"0000-00-00\",\n      \"CUST_GRP1\": \"10\",\n      \"CUST_GRP2\": \"101\",\n      \"CUST_GRP3\": \"\",\n      \"CUST_GRP4\": \"02\",\n      \"CUST_GRP5\": \"B3H\",\n      \"AGREE_COND\": \"\",\n      \"CO_AREA\": \"LA01\",\n      \"WBS_ELEM\": \"00000000\",\n      \"EXCHG_RATE\": \"\",\n      \"C_CTR_AREA\": \"BR02\",\n      \"CRED_ACCNT\": \"0042026019\",\n      \"CRED_GROUP\": \"\",\n      \"REPR_GROUP\": \"\",\n      \"RISK_CATEG\": \"C\",\n      \"CURR_CRED\": \"BRL\",\n      \"ISOCURRCRE\": \"BRL\",\n      \"REL_DAT_DD\": \"0000-00-00\",\n      \"NEXT_CHDAT\": \"0000-00-00\",\n      \"NEXT_DATE\": \"2020-12-14\",\n      \"REL_CREDIT\": \"0.000000000\",\n      \"HI_TYPE_PR\": \"A\",\n      \"DLVSCHEDUS\": \"\",\n      \"PLAN_DLV\": \"\",\n      \"REF_DOC\": \"\",\n      \"OB_JNR_HD\": \"\",\n      \"COMP_CODE\": \"0545\",\n      \"ALT_TAX_CL\": \"\",\n      \"TAX_CLASS2\": \"\",\n      \"TAX_CLASS3\": \"\",\n      \"TAX_CLASS4\": \"\",\n      \"TAX_CLASS5\": \"\",\n      \"TAX_CLASS6\": \"\",\n      \"TAX_CLASS7\": \"\",\n      \"TAX_CLASS8\": \"\",\n      \"TAX_CLASS9\": \"\",\n      \"REF_DOC_L\": \"\",\n      \"ASS_NUMBER\": \"\",\n      \"DOC_CAT_SD\": \"\",\n      \"KALSM_CH\": \"\",\n      \"ACC_PERIOD\": \"00\",\n      \"ORDERID\": \"\",\n      \"NOTIF_NO\": \"\",\n      \"MASTER_CON\": \"\",\n      \"REF_PROC\": \"\",\n      \"CHECK_PART\": \"\",\n      \"PICK_UP_DA\": \"0000-00-00\",\n      \"PICK_UP_T1\": \"00:00:00\",\n      \"PICK_UP_T2\": \"00:00:00\",\n      \"NUM_PAY_CA\": \"\",\n      \"LINE_TIME\": \"00:00:00\",\n      \"TAX_DEST_CT\": \"\",\n      \"ISOTAXDEST\": \"\",\n      \"TAX_DEPART\": \"\",\n      \"ISOTAXDEPA\": \"\",\n      \"EU_TRIANG\": \"\",\n      \"MAST_CONTR\": \"\",\n      \"CML_QTY_DA\": \"0000-00-00\",\n      \"MS_DATE\": \"0000-00-00\",\n      \"VERSION\": \"\",\n      \"REF_DOC_L_LONG\": \"\",\n      \"CRM_GUID\": \"\"\n    },\n    \"EWA_SALES_HEADER_STATUS\": {\n      \"OPERATION\": \"\",\n      \"SD_DOC\": \"\",\n      \"REFDOCHDST\": \"\",\n      \"TOTREFSTAT\": \"\",\n      \"CONFIRSTAT\": \"A\",\n      \"DELIV_STAT\": \"A\",\n      \"DLV_STAT_H\": \"A\",\n      \"TOTGOODSMV\": \"\",\n      \"BILLSTATUS\": \"\",\n      \"BILLINGSTA\": \"\",\n      \"ACCOUNTSTA\": \"\",\n      \"OVERALLREJ\": \"A\",\n      \"PRC_STAT_H\": \"B\",\n      \"OVERALLPIC\": \"\",\n      \"OVERALL_WM\": \"\",\n      \"TOTINCOMPL\": \"C\",\n      \"TOTINCOMIT\": \"C\",\n      \"TOTINCOMBI\": \"C\",\n      \"GENINCOMHD\": \"A\",\n      \"HDIMCOMDEL\": \"C\",\n      \"HDINCOMBIL\": \"C\",\n      \"DOCIMCOMPR\": \"C\",\n      \"SD_DOC_CAT\": \"C\",\n      \"SDDOCOBJ\": \"A\",\n      \"CH_ON\": \"0000-00-00\",\n      \"BILTOTSTAT\": \"\",\n      \"INVOICSTAT\": \"\",\n      \"CUSTRESHD1\": \"\",\n      \"CUSTRESHD2\": \"\",\n      \"CUSTRESHD3\": \"\",\n      \"CUSTRESHD4\": \"\",\n      \"CUSTRESHD5\": \"\",\n      \"CUSTRESIT1\": \"\",\n      \"CUSTRESIT2\": \"\",\n      \"CUSTRESIT3\": \"\",\n      \"CUSTRESIT4\": \"\",\n      \"CUSTRESIT5\": \"\",\n      \"TOTSTATIT\": \"\",\n      \"STATSTACLC\": \"\",\n      \"STATDYNCLC\": \"B\",\n      \"STATCREDCH\": \"\",\n      \"STATCRECH1\": \"\",\n      \"STATCRECH2\": \"\",\n      \"STATCRECH3\": \"\",\n      \"STATCRECH4\": \"\",\n      \"STATCRECH5\": \"\",\n      \"STATCRECH6\": \"\",\n      \"STATCRECH7\": \"\",\n      \"STATCRECH8\": \"\",\n      \"STATCRECH9\": \"\",\n      \"STATCRECHA\": \"\",\n      \"STATCRECHB\": \"B\",\n      \"STATCRECHC\": \"\",\n      \"TOTSTATCCH\": \"B\",\n      \"TRNSPLANST\": \"\",\n      \"QUITTSTAT\": \"\",\n      \"CONFIRMSTA\": \"\",\n      \"SAPRELEASE\": \"740\",\n      \"TOTINCOMI\": \"\",\n      \"TOTINCOMI1\": \"\",\n      \"TOTINCOMI2\": \"\",\n      \"HDINCOMPL\": \"\",\n      \"HDINCOMPL1\": \"\",\n      \"HDINCOMPL2\": \"\",\n      \"HDINCOMPL3\": \"\",\n      \"CREDCHECK\": \"\",\n      \"DELAYSTAT\": \"\",\n      \"SHIPPUNIT\": \"\",\n      \"DISTRISTAT\": \"\",\n      \"REVDETSTAT\": \"\",\n      \"INDIDOCACH\": \"\",\n      \"TOBILBLOST\": \"\",\n      \"TODELBLOST\": \"\",\n      \"TOBLOCKSTA\": \"C\",\n      \"LEBHEADSTA\": \"\",\n      \"FMSTATUS\": \"\"\n    },\n    \"EW_SALESDOCUMENT\": \"\",\n    \"ETB_SCALES\": {\n      \"item\": [\n        \n      ]\n    },\n    \"ETB_BUSINESS_EX\": {\n      \"item\": [\n        \n      ]\n    }\n  }\n}","status":"passed","stage":"finished","steps":[],"attachments":[],"parameters":[{"name":"responseStatus","value":"HTTP/1.1 200 "},{"name":"responseBody","value":"{\n  \"Z_YYKC_SALES_ORDER_CREATE_Response\": {\n    \"ETB_CONDITIONS\": {\n      \"item\": [\n        {\n          \"ITM_NUMBER\": \"000010\",\n          \"COND_ST_NO\": \"010\",\n          \"COND_COUNT\": \"01\",\n          \"COND_TYPE\": \"ZPR0\",\n          \"COND_VALUE\": \"278.710000000\",\n          \"CURRENCY\": \"BRL\",\n          \"COND_UNIT\": \"CS\",\n          \"COND_P_UNT\": \"1\",\n          \"CURR_ISO\": \"BRL\",\n          \"CD_UNT_ISO\": \"CS\",\n          \"REFOBJTYPE\": \"\",\n          \"REFOBJKEY\": \"\",\n          \"REFLOGSYS\": \"\",\n          \"APPLICATIO\": \"V\",\n          \"CONPRICDAT\": \"2020-12-14\",\n          \"CALCTYPCON\": \"C\",\n          \"CONBASEVAL\": \"1.000000000\",\n          \"CONEXCHRAT\": \"1.00000\",\n          \"NUMCONVERT\": \"1\",\n          \"DENOMINATO\": \"1\",\n          \"CONDTYPE\": \"\",\n          \"STAT_CON\": \"\",\n          \"SCALETYPE\": \"\",\n          \"ACCRUALS\": \"\",\n          \"CONINVOLST\": \"\",\n          \"CONDORIGIN\": \"A\",\n          \"GROUPCOND\": \"\",\n          \"COND_UPDAT\": \"\",\n          \"ACCESS_SEQ\": \"10\",\n          \"CONDCOUNT\": \"01\",\n          \"ROUNDOFFDI\": \"0.000000000\",\n          \"CONDVALUE\": \"278.710000000\",\n          \"CURRENCY_2\": \"BRL\",\n          \"CURR_ISO_2\": \"BRL\",\n          \"CONDCNTRL\": \"A\",\n          \"CONDISACTI\": \"Y\",\n          \"CONDCLASS\": \"B\",\n          \"FACTBASVAL\": \"0.0000000000000000E+00\",\n          \"SCALEBASIN\": \"\",\n          \"SCALBASVAL\": \"0.000000000\",\n          \"UNITMEASUR\": \"\",\n          \"ISO_UNIT\": \"\",\n          \"CURRENCKEY\": \"\",\n          \"CURRENISO\": \"\",\n          \"CONDINCOMP\": \"\",\n          \"CONDCONFIG\": \"\",\n          \"CONDCHAMAN\": \"\",\n          \"COND_NO\": \"0070387778\",\n          \"TAX_CODE\": \"\",\n          \"VARCOND\": \"\",\n          \"ACCOUNTKEY\": \"\",\n          \"ACCOUNT_KE\": \"\",\n          \"WT_WITHCD\": \"\",\n          \"STRUCTCOND\": \"\",\n          \"FACTCONBAS\": \"0.0000000000000000E+00\",\n          \"CONDCOINHD\": \"00\"\n        },\n        {\n          \"ITM_NUMBER\": \"000010\",\n          \"COND_ST_NO\": \"025\",\n          \"COND_COUNT\": \"01\",\n          \"COND_TYPE\": \"ZGRO\",\n          \"COND_VALUE\": \"278.710000000\",\n          \"CURRENCY\": \"BRL\",\n          \"COND_UNIT\": \"CS\",\n          \"COND_P_UNT\": \"1\",\n          \"CURR_ISO\": \"BRL\",\n          \"CD_UNT_ISO\": \"CS\",\n          \"REFOBJTYPE\": \"\",\n          \"REFOBJKEY\": \"\",\n          \"REFLOGSYS\": \"\",\n          \"APPLICATIO\": \"V\",\n          \"CONPRICDAT\": \"2020-12-14\",\n          \"CALCTYPCON\": \"C\",\n          \"CONBASEVAL\": \"1.000000000\",\n          \"CONEXCHRAT\": \"1.00000\",\n          \"NUMCONVERT\": \"1\",\n          \"DENOMINATO\": \"1\",\n          \"CONDTYPE\": \"\",\n          \"STAT_CON\": \"X\",\n          \"SCALETYPE\": \"\",\n          \"ACCRUALS\": \"\",\n          \"CONINVOLST\": \"\",\n          \"CONDORIGIN\": \"A\",\n          \"GROUPCOND\": \"\",\n          \"COND_UPDAT\": \"\",\n          \"ACCESS_SEQ\": \"00\",\n          \"CONDCOUNT\": \"00\",\n          \"ROUNDOFFDI\": \"0.000000000\",\n          \"CONDVALUE\": \"278.710000000\",\n          \"CURRENCY_2\": \"BRL\",\n          \"CURR_ISO_2\": \"BRL\",\n          \"CONDCNTRL\": \"A\",\n          \"CONDISACTI\": \"Y\",\n          \"CONDCLASS\": \"B\",\n          \"FACTBASVAL\": \"0.0000000000000000E+00\",\n          \"SCALEBASIN\": \"\",\n          \"SCALBASVAL\": \"0.000000000\",\n          \"UNITMEASUR\": \"\",\n          \"ISO_UNIT\": \"\",\n          \"CURRENCKEY\": \"\",\n          \"CURRENISO\": \"\",\n          \"CONDINCOMP\": \"\",\n          \"CONDCONFIG\": \"\",\n          \"CONDCHAMAN\": \"\",\n          \"COND_NO\": \"\",\n          \"TAX_CODE\": \"\",\n          \"VARCOND\": \"\",\n          \"ACCOUNTKEY\": \"\",\n          \"ACCOUNT_KE\": \"\",\n          \"WT_WITHCD\": \"\",\n          \"STRUCTCOND\": \"\",\n          \"FACTCONBAS\": \"0.0000000000000000E+00\",\n          \"CONDCOINHD\": \"00\"\n        },\n        {\n          \"ITM_NUMBER\": \"000010\",\n          \"COND_ST_NO\": \"028\",\n          \"COND_COUNT\": \"01\",\n          \"COND_TYPE\": \"YGRP\",\n          \"COND_VALUE\": \"118.330000000\",\n          \"CURRENCY\": \"BRL\",\n          \"COND_UNIT\": \"CS\",\n          \"COND_P_UNT\": \"1\",\n          \"CURR_ISO\": \"BRL\",\n          \"CD_UNT_ISO\": \"CS\",\n          \"REFOBJTYPE\": \"\",\n          \"REFOBJKEY\": \"\",\n          \"REFLOGSYS\": \"\",\n          \"APPLICATIO\": \"V\",\n          \"CONPRICDAT\": \"2020-12-14\",\n          \"CALCTYPCON\": \"C\",\n          \"CONBASEVAL\": \"1.000000000\",\n          \"CONEXCHRAT\": \"1.00000\",\n          \"NUMCONVERT\": \"1\",\n          \"DENOMINATO\": \"1\",\n          \"CONDTYPE\": \"\",\n          \"STAT_CON\": \"X\",\n          \"SCALETYPE\": \"\",\n          \"ACCRUALS\": \"\",\n          \"CONINVOLST\": \"\",\n          \"CONDORIGIN\": \"A\",\n          \"GROUPCOND\": \"\",\n          \"COND_UPDAT\": \"\",\n          \"ACCESS_SEQ\": \"30\",\n          \"CONDCOUNT\": \"01\",\n          \"ROUNDOFFDI\": \"0.000000000\",\n          \"CONDVALUE\": \"118.330000000\",\n          \"CURRENCY_2\": \"BRL\",\n          \"CURR_ISO_2\": \"BRL\",\n          \"CONDCNTRL\": \"A\",\n          \"CONDISACTI\": \"Y\",\n          \"CONDCLASS\": \"B\",\n          \"FACTBASVAL\": \"0.0000000000000000E+00\",\n          \"SCALEBASIN\": \"\",\n          \"SCALBASVAL\": \"0.000000000\",\n          \"UNITMEASUR\": \"\",\n          \"ISO_UNIT\": \"\",\n          \"CURRENCKEY\": \"\",\n          \"CURRENISO\": \"\",\n          \"CONDINCOMP\": \"\",\n          \"CONDCONFIG\": \"\",\n          \"CONDCHAMAN\": \"\",\n          \"COND_NO\": \"0069686765\",\n          \"TAX_CODE\": \"\",\n          \"VARCOND\": \"\",\n          \"ACCOUNTKEY\": \"\",\n          \"ACCOUNT_KE\": \"\",\n          \"WT_WITHCD\": \"\",\n          \"STRUCTCOND\": \"\",\n          \"FACTCONBAS\": \"0.0000000000000000E+00\",\n          \"CONDCOINHD\": \"00\"\n        },\n        {\n          \"ITM_NUMBER\": \"000010\",\n          \"COND_ST_NO\": \"035\",\n          \"COND_COUNT\": \"01\",\n          \"COND_TYPE\": \"ZE09\",\n          \"COND_VALUE\": \"0.000000000\",\n          \"CURRENCY\": \"\",\n          \"COND_UNIT\": \"\",\n          \"COND_P_UNT\": \"0\",\n          \"CURR_ISO\": \"\",\n          \"CD_UNT_ISO\": \"\",\n          \"REFOBJTYPE\": \"\",\n          \"REFOBJKEY\": \"\",\n          \"REFLOGSYS\": \"\",\n          \"APPLICATIO\": \"V\",\n          \"CONPRICDAT\": \"2020-12-14\",\n          \"CALCTYPCON\": \"A\",\n          \"CONBASEVAL\": \"118.330000000\",\n          \"CONEXCHRAT\": \"0.00000\",\n          \"NUMCONVERT\": \"0\",\n          \"DENOMINATO\": \"0\",\n          \"CONDTYPE\": \"\",\n          \"STAT_CON\": \"\",\n          \"SCALETYPE\": \"\",\n          \"ACCRUALS\": \"\",\n          \"CONINVOLST\": \"\",\n          \"CONDORIGIN\": \"A\",\n          \"GROUPCOND\": \"\",\n          \"COND_UPDAT\": \"X\",\n          \"ACCESS_SEQ\": \"00\",\n          \"CONDCOUNT\": \"00\",\n          \"ROUNDOFFDI\": \"0.000000000\",\n          \"CONDVALUE\": \"-160.380000000\",\n          \"CURRENCY_2\": \"BRL\",\n          \"CURR_ISO_2\": \"BRL\",\n          \"CONDCNTRL\": \"A\",\n          \"CONDISACTI\": \"Y\",\n          \"CONDCLASS\": \"A\",\n          \"FACTBASVAL\": \"0.0000000000000000E+00\",\n          \"SCALEBASIN\": \"\",\n          \"SCALBASVAL\": \"0.000000000\",\n          \"UNITMEASUR\": \"\",\n          \"ISO_UNIT\": \"\",\n          \"CURRENCKEY\": \"\",\n          \"CURRENISO\": \"\",\n          \"CONDINCOMP\": \"\",\n          \"CONDCONFIG\": \"\",\n          \"CONDCHAMAN\": \"\",\n          \"COND_NO\": \"\",\n          \"TAX_CODE\": \"\",\n          \"VARCOND\": \"\",\n          \"ACCOUNTKEY\": \"\",\n          \"ACCOUNT_KE\": \"\",\n          \"WT_WITHCD\": \"\",\n          \"STRUCTCOND\": \"\",\n          \"FACTCONBAS\": \"0.0000000000000000E+00\",\n          \"CONDCOINHD\": \"00\"\n        },\n        {\n          \"ITM_NUMBER\": \"000010\",\n          \"COND_ST_NO\": \"040\",\n          \"COND_COUNT\": \"01\",\n          \"COND_TYPE\": \"YC15\",\n          \"COND_VALUE\": \"0.000000000\",\n          \"CURRENCY\": \"BRL\",\n          \"COND_UNIT\": \"CS\",\n          \"COND_P_UNT\": \"1\",\n          \"CURR_ISO\": \"BRL\",\n          \"CD_UNT_ISO\": \"CS\",\n          \"REFOBJTYPE\": \"\",\n          \"REFOBJKEY\": \"\",\n          \"REFLOGSYS\": \"\",\n          \"APPLICATIO\": \"V\",\n          \"CONPRICDAT\": \"2020-12-14\",\n          \"CALCTYPCON\": \"C\",\n          \"CONBASEVAL\": \"1.000000000\",\n          \"CONEXCHRAT\": \"1.00000\",\n          \"NUMCONVERT\": \"1\",\n          \"DENOMINATO\": \"1\",\n          \"CONDTYPE\": \"Y\",\n          \"STAT_CON\": \"X\",\n          \"SCALETYPE\": \"\",\n          \"ACCRUALS\": \"\",\n          \"CONINVOLST\": \"\",\n          \"CONDORIGIN\": \"A\",\n          \"GROUPCOND\": \"\",\n          \"COND_UPDAT\": \"X\",\n          \"ACCESS_SEQ\": \"00\",\n          \"CONDCOUNT\": \"00\",\n          \"ROUNDOFFDI\": \"0.000000000\",\n          \"CONDVALUE\": \"0.000000000\",\n          \"CURRENCY_2\": \"BRL\",\n          \"CURR_ISO_2\": \"BRL\",\n          \"CONDCNTRL\": \"A\",\n          \"CONDISACTI\": \"X\",\n          \"CONDCLASS\": \"B\",\n          \"FACTBASVAL\": \"0.0000000000000000E+00\",\n          \"SCALEBASIN\": \"\",\n          \"SCALBASVAL\": \"0.000000000\",\n          \"UNITMEASUR\": \"\",\n          \"ISO_UNIT\": \"\",\n          \"CURRENCKEY\": \"\",\n          \"CURRENISO\": \"\",\n          \"CONDINCOMP\": \"\",\n          \"CONDCONFIG\": \"\",\n          \"CONDCHAMAN\": \"\",\n          \"COND_NO\": \"\",\n          \"TAX_CODE\": \"\",\n          \"VARCOND\": \"\",\n          \"ACCOUNTKEY\": \"\",\n          \"ACCOUNT_KE\": \"\",\n          \"WT_WITHCD\": \"\",\n          \"STRUCTCOND\": \"\",\n          \"FACTCONBAS\": \"0.0000000000000000E+00\",\n          \"CONDCOINHD\": \"00\"\n        },\n        {\n          \"ITM_NUMBER\": \"000010\",\n          \"COND_ST_NO\": \"045\",\n          \"COND_COUNT\": \"01\",\n          \"COND_TYPE\": \"ZE10\",\n          \"COND_VALUE\": \"0.000000000\",\n          \"CURRENCY\": \"\",\n          \"COND_UNIT\": \"\",\n          \"COND_P_UNT\": \"0\",\n          \"CURR_ISO\": \"\",\n          \"CD_UNT_ISO\": \"\",\n          \"REFOBJTYPE\": \"\",\n          \"REFOBJKEY\": \"\",\n          \"REFLOGSYS\": \"\",\n          \"APPLICATIO\": \"V\",\n          \"CONPRICDAT\": \"2020-12-14\",\n          \"CALCTYPCON\": \"A\",\n          \"CONBASEVAL\": \"-42.050000000\",\n          \"CONEXCHRAT\": \"0.00000\",\n          \"NUMCONVERT\": \"0\",\n          \"DENOMINATO\": \"0\",\n          \"CONDTYPE\": \"\",\n          \"STAT_CON\": \"\",\n          \"SCALETYPE\": \"\",\n          \"ACCRUALS\": \"\",\n          \"CONINVOLST\": \"\",\n          \"CONDORIGIN\": \"A\",\n          \"GROUPCOND\": \"\",\n          \"COND_UPDAT\": \"X\",\n          \"ACCESS_SEQ\": \"00\",\n          \"CONDCOUNT\": \"00\",\n          \"ROUNDOFFDI\": \"0.000000000\",\n          \"CONDVALUE\": \"0.000000000\",\n          \"CURRENCY_2\": \"BRL\",\n          \"CURR_ISO_2\": \"BRL\",\n          \"CONDCNTRL\": \"A\",\n          \"CONDISACTI\": \"Y\",\n          \"CONDCLASS\": \"A\",\n          \"FACTBASVAL\": \"0.0000000000000000E+00\",\n          \"SCALEBASIN\": \"\",\n          \"SCALBASVAL\": \"0.000000000\",\n          \"UNITMEASUR\": \"\",\n          \"ISO_UNIT\": \"\",\n          \"CURRENCKEY\": \"\",\n          \"CURRENISO\": \"\",\n          \"CONDINCOMP\": \"\",\n          \"CONDCONFIG\": \"\",\n          \"CONDCHAMAN\": \"\",\n          \"COND_NO\": \"\",\n          \"TAX_CODE\": \"\",\n          \"VARCOND\": \"\",\n          \"ACCOUNTKEY\": \"\",\n          \"ACCOUNT_KE\": \"\",\n          \"WT_WITHCD\": \"\",\n          \"STRUCTCOND\": \"\",\n          \"FACTCONBAS\": \"0.0000000000000000E+00\",\n          \"CONDCOINHD\": \"00\"\n        },\n        {\n          \"ITM_NUMBER\": \"000010\",\n          \"COND_ST_NO\": \"195\",\n          \"COND_COUNT\": \"01\",\n          \"COND_TYPE\": \"ZNIV\",\n          \"COND_VALUE\": \"118.330000000\",\n          \"CURRENCY\": \"BRL\",\n          \"COND_UNIT\": \"CS\",\n          \"COND_P_UNT\": \"1\",\n          \"CURR_ISO\": \"BRL\",\n          \"CD_UNT_ISO\": \"CS\",\n          \"REFOBJTYPE\": \"\",\n          \"REFOBJKEY\": \"\",\n          \"REFLOGSYS\": \"\",\n          \"APPLICATIO\": \"V\",\n          \"CONPRICDAT\": \"2020-12-14\",\n          \"CALCTYPCON\": \"C\",\n          \"CONBASEVAL\": \"1.000000000\",\n          \"CONEXCHRAT\": \"1.00000\",\n          \"NUMCONVERT\": \"1\",\n          \"DENOMINATO\": \"1\",\n          \"CONDTYPE\": \"\",\n          \"STAT_CON\": \"X\",\n          \"SCALETYPE\": \"\",\n          \"ACCRUALS\": \"\",\n          \"CONINVOLST\": \"\",\n          \"CONDORIGIN\": \"A\",\n          \"GROUPCOND\": \"\",\n          \"COND_UPDAT\": \"\",\n          \"ACCESS_SEQ\": \"00\",\n          \"CONDCOUNT\": \"00\",\n          \"ROUNDOFFDI\": \"0.000000000\",\n          \"CONDVALUE\": \"118.330000000\",\n          \"CURRENCY_2\": \"BRL\",\n          \"CURR_ISO_2\": \"BRL\",\n          \"CONDCNTRL\": \"A\",\n          \"CONDISACTI\": \"Y\",\n          \"CONDCLASS\": \"B\",\n          \"FACTBASVAL\": \"0.0000000000000000E+00\",\n          \"SCALEBASIN\": \"\",\n          \"SCALBASVAL\": \"0.000000000\",\n          \"UNITMEASUR\": \"\",\n          \"ISO_UNIT\": \"\",\n          \"CURRENCKEY\": \"\",\n          \"CURRENISO\": \"\",\n          \"CONDINCOMP\": \"\",\n          \"CONDCONFIG\": \"\",\n          \"CONDCHAMAN\": \"\",\n          \"COND_NO\": \"\",\n          \"TAX_CODE\": \"\",\n          \"VARCOND\": \"\",\n          \"ACCOUNTKEY\": \"\",\n          \"ACCOUNT_KE\": \"\",\n          \"WT_WITHCD\": \"\",\n          \"STRUCTCOND\": \"\",\n          \"FACTCONBAS\": \"0.0000000000000000E+00\",\n          \"CONDCOINHD\": \"00\"\n        },\n        {\n          \"ITM_NUMBER\": \"000010\",\n          \"COND_ST_NO\": \"199\",\n          \"COND_COUNT\": \"01\",\n          \"COND_TYPE\": \"DGTX\",\n          \"COND_VALUE\": \"100.000000000\",\n          \"CURRENCY\": \"\",\n          \"COND_UNIT\": \"\",\n          \"COND_P_UNT\": \"0\",\n          \"CURR_ISO\": \"\",\n          \"CD_UNT_ISO\": \"\",\n          \"REFOBJTYPE\": \"\",\n          \"REFOBJKEY\": \"\",\n          \"REFLOGSYS\": \"\",\n          \"APPLICATIO\": \"V\",\n          \"CONPRICDAT\": \"2020-12-14\",\n          \"CALCTYPCON\": \"A\",\n          \"CONBASEVAL\": \"10.000000000\",\n          \"CONEXCHRAT\": \"0.00000\",\n          \"NUMCONVERT\": \"0\",\n          \"DENOMINATO\": \"0\",\n          \"CONDTYPE\": \"D\",\n          \"STAT_CON\": \"X\",\n          \"SCALETYPE\": \"\",\n          \"ACCRUALS\": \"\",\n          \"CONINVOLST\": \"\",\n          \"CONDORIGIN\": \"A\",\n          \"GROUPCOND\": \"\",\n          \"COND_UPDAT\": \"\",\n          \"ACCESS_SEQ\": \"01\",\n          \"CONDCOUNT\": \"01\",\n          \"ROUNDOFFDI\": \"0.000000000\",\n          \"CONDVALUE\": \"10.000000000\",\n          \"CURRENCY_2\": \"BRL\",\n          \"CURR_ISO_2\": \"BRL\",\n          \"CONDCNTRL\": \"A\",\n          \"CONDISACTI\": \"Y\",\n          \"CONDCLASS\": \"D\",\n          \"FACTBASVAL\": \"0.0000000000000000E+00\",\n          \"SCALEBASIN\": \"\",\n          \"SCALBASVAL\": \"0.000000000\",\n          \"UNITMEASUR\": \"\",\n          \"ISO_UNIT\": \"\",\n          \"CURRENCKEY\": \"\",\n          \"CURRENISO\": \"\",\n          \"CONDINCOMP\": \"\",\n          \"CONDCONFIG\": \"\",\n          \"CONDCHAMAN\": \"\",\n          \"COND_NO\": \"0035482469\",\n          \"TAX_CODE\": \"SD\",\n          \"VARCOND\": \"\",\n          \"ACCOUNTKEY\": \"\",\n          \"ACCOUNT_KE\": \"\",\n          \"WT_WITHCD\": \"\",\n          \"STRUCTCOND\": \"\",\n          \"FACTCONBAS\": \"0.0000000000000000E+00\",\n          \"CONDCOINHD\": \"00\"\n        },\n        {\n          \"ITM_NUMBER\": \"000010\",\n          \"COND_ST_NO\": \"200\",\n          \"COND_COUNT\": \"01\",\n          \"COND_TYPE\": \"DICM\",\n          \"COND_VALUE\": \"100.000000000\",\n          \"CURRENCY\": \"\",\n          \"COND_UNIT\": \"\",\n          \"COND_P_UNT\": \"0\",\n          \"CURR_ISO\": \"\",\n          \"CD_UNT_ISO\": \"\",\n          \"REFOBJTYPE\": \"\",\n          \"REFOBJKEY\": \"\",\n          \"REFLOGSYS\": \"\",\n          \"APPLICATIO\": \"V\",\n          \"CONPRICDAT\": \"2020-12-14\",\n          \"CALCTYPCON\": \"A\",\n          \"CONBASEVAL\": \"10.000000000\",\n          \"CONEXCHRAT\": \"0.00000\",\n          \"NUMCONVERT\": \"0\",\n          \"DENOMINATO\": \"0\",\n          \"CONDTYPE\": \"D\",\n          \"STAT_CON\": \"X\",\n          \"SCALETYPE\": \"\",\n          \"ACCRUALS\": \"\",\n          \"CONINVOLST\": \"\",\n          \"CONDORIGIN\": \"A\",\n          \"GROUPCOND\": \"\",\n          \"COND_UPDAT\": \"\",\n          \"ACCESS_SEQ\": \"10\",\n          \"CONDCOUNT\": \"01\",\n          \"ROUNDOFFDI\": \"0.000000000\",\n          \"CONDVALUE\": \"10.000000000\",\n          \"CURRENCY_2\": \"BRL\",\n          \"CURR_ISO_2\": \"BRL\",\n          \"CONDCNTRL\": \"A\",\n          \"CONDISACTI\": \"Y\",\n          \"CONDCLASS\": \"D\",\n          \"FACTBASVAL\": \"0.0000000000000000E+00\",\n          \"SCALEBASIN\": \"\",\n          \"SCALBASVAL\": \"0.000000000\",\n          \"UNITMEASUR\": \"\",\n          \"ISO_UNIT\": \"\",\n          \"CURRENCKEY\": \"\",\n          \"CURRENISO\": \"\",\n          \"CONDINCOMP\": \"\",\n          \"CONDCONFIG\": \"\",\n          \"CONDCHAMAN\": \"\",\n          \"COND_NO\": \"0011142811\",\n          \"TAX_CODE\": \"SD\",\n          \"VARCOND\": \"\",\n          \"ACCOUNTKEY\": \"\",\n          \"ACCOUNT_KE\": \"\",\n          \"WT_WITHCD\": \"\",\n          \"STRUCTCOND\": \"\",\n          \"FACTCONBAS\": \"0.0000000000000000E+00\",\n          \"CONDCOINHD\": \"00\"\n        },\n        {\n          \"ITM_NUMBER\": \"000010\",\n          \"COND_ST_NO\": \"201\",\n          \"COND_COUNT\": \"01\",\n          \"COND_TYPE\": \"ICVA\",\n          \"COND_VALUE\": \"12.000000000\",\n          \"CURRENCY\": \"\",\n          \"COND_UNIT\": \"\",\n          \"COND_P_UNT\": \"0\",\n          \"CURR_ISO\": \"\",\n          \"CD_UNT_ISO\": \"\",\n          \"REFOBJTYPE\": \"\",\n          \"REFOBJKEY\": \"\",\n          \"REFLOGSYS\": \"\",\n          \"APPLICATIO\": \"V\",\n          \"CONPRICDAT\": \"2020-12-14\",\n          \"CALCTYPCON\": \"A\",\n          \"CONBASEVAL\": \"10.000000000\",\n          \"CONEXCHRAT\": \"0.00000\",\n          \"NUMCONVERT\": \"0\",\n          \"DENOMINATO\": \"0\",\n          \"CONDTYPE\": \"D\",\n          \"STAT_CON\": \"X\",\n          \"SCALETYPE\": \"\",\n          \"ACCRUALS\": \"\",\n          \"CONINVOLST\": \"\",\n          \"CONDORIGIN\": \"A\",\n          \"GROUPCOND\": \"\",\n          \"COND_UPDAT\": \"\",\n          \"ACCESS_SEQ\": \"87\",\n          \"CONDCOUNT\": \"01\",\n          \"ROUNDOFFDI\": \"0.000000000\",\n          \"CONDVALUE\": \"1.200000000\",\n          \"CURRENCY_2\": \"BRL\",\n          \"CURR_ISO_2\": \"BRL\",\n          \"CONDCNTRL\": \"A\",\n          \"CONDISACTI\": \"Y\",\n          \"CONDCLASS\": \"D\",\n          \"FACTBASVAL\": \"0.0000000000000000E+00\",\n          \"SCALEBASIN\": \"\",\n          \"SCALBASVAL\": \"0.000000000\",\n          \"UNITMEASUR\": \"\",\n          \"ISO_UNIT\": \"\",\n          \"CURRENCKEY\": \"\",\n          \"CURRENISO\": \"\",\n          \"CONDINCOMP\": \"\",\n          \"CONDCONFIG\": \"\",\n          \"CONDCHAMAN\": \"\",\n          \"COND_NO\": \"0034882128\",\n          \"TAX_CODE\": \"SD\",\n          \"VARCOND\": \"\",\n          \"ACCOUNTKEY\": \"\",\n          \"ACCOUNT_KE\": \"\",\n          \"WT_WITHCD\": \"\",\n          \"STRUCTCOND\": \"\",\n          \"FACTCONBAS\": \"0.0000000000000000E+00\",\n          \"CONDCOINHD\": \"00\"\n        },\n        {\n          \"ITM_NUMBER\": \"000010\",\n          \"COND_ST_NO\": \"202\",\n          \"COND_COUNT\": \"01\",\n          \"COND_TYPE\": \"ICBS\",\n          \"COND_VALUE\": \"100.000000000\",\n          \"CURRENCY\": \"\",\n          \"COND_UNIT\": \"\",\n          \"COND_P_UNT\": \"0\",\n          \"CURR_ISO\": \"\",\n          \"CD_UNT_ISO\": \"\",\n          \"REFOBJTYPE\": \"\",\n          \"REFOBJKEY\": \"\",\n          \"REFLOGSYS\": \"\",\n          \"APPLICATIO\": \"V\",\n          \"CONPRICDAT\": \"2020-12-14\",\n          \"CALCTYPCON\": \"A\",\n          \"CONBASEVAL\": \"10.000000000\",\n          \"CONEXCHRAT\": \"0.00000\",\n          \"NUMCONVERT\": \"0\",\n          \"DENOMINATO\": \"0\",\n          \"CONDTYPE\": \"D\",\n          \"STAT_CON\": \"X\",\n          \"SCALETYPE\": \"\",\n          \"ACCRUALS\": \"\",\n          \"CONINVOLST\": \"\",\n          \"CONDORIGIN\": \"A\",\n          \"GROUPCOND\": \"\",\n          \"COND_UPDAT\": \"\",\n          \"ACCESS_SEQ\": \"87\",\n          \"CONDCOUNT\": \"01\",\n          \"ROUNDOFFDI\": \"0.000000000\",\n          \"CONDVALUE\": \"10.000000000\",\n          \"CURRENCY_2\": \"BRL\",\n          \"CURR_ISO_2\": \"BRL\",\n          \"CONDCNTRL\": \"A\",\n          \"CONDISACTI\": \"Y\",\n          \"CONDCLASS\": \"D\",\n          \"FACTBASVAL\": \"0.0000000000000000E+00\",\n          \"SCALEBASIN\": \"\",\n          \"SCALBASVAL\": \"0.000000000\",\n          \"UNITMEASUR\": \"\",\n          \"ISO_UNIT\": \"\",\n          \"CURRENCKEY\": \"\",\n          \"CURRENISO\": \"\",\n          \"CONDINCOMP\": \"\",\n          \"CONDCONFIG\": \"\",\n          \"CONDCHAMAN\": \"\",\n          \"COND_NO\": \"0034882129\",\n          \"TAX_CODE\": \"SD\",\n          \"VARCOND\": \"\",\n          \"ACCOUNTKEY\": \"\",\n          \"ACCOUNT_KE\": \"\",\n          \"WT_WITHCD\": \"\",\n          \"STRUCTCOND\": \"\",\n          \"FACTCONBAS\": \"0.0000000000000000E+00\",\n          \"CONDCOINHD\": \"00\"\n        },\n        {\n          \"ITM_NUMBER\": \"000010\",\n          \"COND_ST_NO\": \"207\",\n          \"COND_COUNT\": \"01\",\n          \"COND_TYPE\": \"ISIC\",\n          \"COND_VALUE\": \"18.000000000\",\n          \"CURRENCY\": \"\",\n          \"COND_UNIT\": \"\",\n          \"COND_P_UNT\": \"0\",\n          \"CURR_ISO\": \"\",\n          \"CD_UNT_ISO\": \"\",\n          \"REFOBJTYPE\": \"\",\n          \"REFOBJKEY\": \"\",\n          \"REFLOGSYS\": \"\",\n          \"APPLICATIO\": \"V\",\n          \"CONPRICDAT\": \"2020-12-14\",\n          \"CALCTYPCON\": \"A\",\n          \"CONBASEVAL\": \"10.000000000\",\n          \"CONEXCHRAT\": \"0.00000\",\n          \"NUMCONVERT\": \"0\",\n          \"DENOMINATO\": \"0\",\n          \"CONDTYPE\": \"D\",\n          \"STAT_CON\": \"X\",\n          \"SCALETYPE\": \"\",\n          \"ACCRUALS\": \"\",\n          \"CONINVOLST\": \"\",\n          \"CONDORIGIN\": \"A\",\n          \"GROUPCOND\": \"\",\n          \"COND_UPDAT\": \"\",\n          \"ACCESS_SEQ\": \"53\",\n          \"CONDCOUNT\": \"01\",\n          \"ROUNDOFFDI\": \"0.000000000\",\n          \"CONDVALUE\": \"1.800000000\",\n          \"CURRENCY_2\": \"BRL\",\n          \"CURR_ISO_2\": \"BRL\",\n          \"CONDCNTRL\": \"A\",\n          \"CONDISACTI\": \"Y\",\n          \"CONDCLASS\": \"D\",\n          \"FACTBASVAL\": \"0.0000000000000000E+00\",\n          \"SCALEBASIN\": \"\",\n          \"SCALBASVAL\": \"0.000000000\",\n          \"UNITMEASUR\": \"\",\n          \"ISO_UNIT\": \"\",\n          \"CURRENCKEY\": \"\",\n          \"CURRENISO\": \"\",\n          \"CONDINCOMP\": \"\",\n          \"CONDCONFIG\": \"\",\n          \"CONDCHAMAN\": \"\",\n          \"COND_NO\": \"0035528182\",\n          \"TAX_CODE\": \"SD\",\n          \"VARCOND\": \"\",\n          \"ACCOUNTKEY\": \"\",\n          \"ACCOUNT_KE\": \"\",\n          \"WT_WITHCD\": \"\",\n          \"STRUCTCOND\": \"\",\n          \"FACTCONBAS\": \"0.0000000000000000E+00\",\n          \"CONDCOINHD\": \"00\"\n        },\n        {\n          \"ITM_NUMBER\": \"000010\",\n          \"COND_ST_NO\": \"211\",\n          \"COND_COUNT\": \"01\",\n          \"COND_TYPE\": \"ISIB\",\n          \"COND_VALUE\": \"100.000000000\",\n          \"CURRENCY\": \"\",\n          \"COND_UNIT\": \"\",\n          \"COND_P_UNT\": \"0\",\n          \"CURR_ISO\": \"\",\n          \"CD_UNT_ISO\": \"\",\n          \"REFOBJTYPE\": \"\",\n          \"REFOBJKEY\": \"\",\n          \"REFLOGSYS\": \"\",\n          \"APPLICATIO\": \"V\",\n          \"CONPRICDAT\": \"2020-12-14\",\n          \"CALCTYPCON\": \"A\",\n          \"CONBASEVAL\": \"10.000000000\",\n          \"CONEXCHRAT\": \"0.00000\",\n          \"NUMCONVERT\": \"0\",\n          \"DENOMINATO\": \"0\",\n          \"CONDTYPE\": \"D\",\n          \"STAT_CON\": \"X\",\n          \"SCALETYPE\": \"\",\n          \"ACCRUALS\": \"\",\n          \"CONINVOLST\": \"\",\n          \"CONDORIGIN\": \"A\",\n          \"GROUPCOND\": \"\",\n          \"COND_UPDAT\": \"\",\n          \"ACCESS_SEQ\": \"53\",\n          \"CONDCOUNT\": \"01\",\n          \"ROUNDOFFDI\": \"0.000000000\",\n          \"CONDVALUE\": \"10.000000000\",\n          \"CURRENCY_2\": \"BRL\",\n          \"CURR_ISO_2\": \"BRL\",\n          \"CONDCNTRL\": \"A\",\n          \"CONDISACTI\": \"Y\",\n          \"CONDCLASS\": \"D\",\n          \"FACTBASVAL\": \"0.0000000000000000E+00\",\n          \"SCALEBASIN\": \"\",\n          \"SCALBASVAL\": \"0.000000000\",\n          \"UNITMEASUR\": \"\",\n          \"ISO_UNIT\": \"\",\n          \"CURRENCKEY\": \"\",\n          \"CURRENISO\": \"\",\n          \"CONDINCOMP\": \"\",\n          \"CONDCONFIG\": \"\",\n          \"CONDCHAMAN\": \"\",\n          \"COND_NO\": \"0035528188\",\n          \"TAX_CODE\": \"SD\",\n          \"VARCOND\": \"\",\n          \"ACCOUNTKEY\": \"\",\n          \"ACCOUNT_KE\": \"\",\n          \"WT_WITHCD\": \"\",\n          \"STRUCTCOND\": \"\",\n          \"FACTCONBAS\": \"0.0000000000000000E+00\",\n          \"CONDCOINHD\": \"00\"\n        },\n        {\n          \"ITM_NUMBER\": \"000010\",\n          \"COND_ST_NO\": \"212\",\n          \"COND_COUNT\": \"01\",\n          \"COND_TYPE\": \"ISFR\",\n          \"COND_VALUE\": \"0.000000000\",\n          \"CURRENCY\": \"\",\n          \"COND_UNIT\": \"\",\n          \"COND_P_UNT\": \"0\",\n          \"CURR_ISO\": \"\",\n          \"CD_UNT_ISO\": \"\",\n          \"REFOBJTYPE\": \"\",\n          \"REFOBJKEY\": \"\",\n          \"REFLOGSYS\": \"\",\n          \"APPLICATIO\": \"V\",\n          \"CONPRICDAT\": \"2020-12-14\",\n          \"CALCTYPCON\": \"A\",\n          \"CONBASEVAL\": \"10.000000000\",\n          \"CONEXCHRAT\": \"0.00000\",\n          \"NUMCONVERT\": \"0\",\n          \"DENOMINATO\": \"0\",\n          \"CONDTYPE\": \"D\",\n          \"STAT_CON\": \"X\",\n          \"SCALETYPE\": \"\",\n          \"ACCRUALS\": \"\",\n          \"CONINVOLST\": \"\",\n          \"CONDORIGIN\": \"A\",\n          \"GROUPCOND\": \"\",\n          \"COND_UPDAT\": \"\",\n          \"ACCESS_SEQ\": \"53\",\n          \"CONDCOUNT\": \"01\",\n          \"ROUNDOFFDI\": \"0.000000000\",\n          \"CONDVALUE\": \"0.000000000\",\n          \"CURRENCY_2\": \"BRL\",\n          \"CURR_ISO_2\": \"BRL\",\n          \"CONDCNTRL\": \"A\",\n          \"CONDISACTI\": \"Y\",\n          \"CONDCLASS\": \"D\",\n          \"FACTBASVAL\": \"0.0000000000000000E+00\",\n          \"SCALEBASIN\": \"\",\n          \"SCALBASVAL\": \"0.000000000\",\n          \"UNITMEASUR\": \"\",\n          \"ISO_UNIT\": \"\",\n          \"CURRENCKEY\": \"\",\n          \"CURRENISO\": \"\",\n          \"CONDINCOMP\": \"\",\n          \"CONDCONFIG\": \"\",\n          \"CONDCHAMAN\": \"\",\n          \"COND_NO\": \"0035528189\",\n          \"TAX_CODE\": \"SD\",\n          \"VARCOND\": \"\",\n          \"ACCOUNTKEY\": \"\",\n          \"ACCOUNT_KE\": \"\",\n          \"WT_WITHCD\": \"\",\n          \"STRUCTCOND\": \"\",\n          \"FACTCONBAS\": \"0.0000000000000000E+00\",\n          \"CONDCOINHD\": \"00\"\n        },\n        {\n          \"ITM_NUMBER\": \"000010\",\n          \"COND_ST_NO\": \"213\",\n          \"COND_COUNT\": \"01\",\n          \"COND_TYPE\": \"ISFB\",\n          \"COND_VALUE\": \"0.000000000\",\n          \"CURRENCY\": \"\",\n          \"COND_UNIT\": \"\",\n          \"COND_P_UNT\": \"0\",\n          \"CURR_ISO\": \"\",\n          \"CD_UNT_ISO\": \"\",\n          \"REFOBJTYPE\": \"\",\n          \"REFOBJKEY\": \"\",\n          \"REFLOGSYS\": \"\",\n          \"APPLICATIO\": \"V\",\n          \"CONPRICDAT\": \"2020-12-14\",\n          \"CALCTYPCON\": \"A\",\n          \"CONBASEVAL\": \"10.000000000\",\n          \"CONEXCHRAT\": \"0.00000\",\n          \"NUMCONVERT\": \"0\",\n          \"DENOMINATO\": \"0\",\n          \"CONDTYPE\": \"D\",\n          \"STAT_CON\": \"X\",\n          \"SCALETYPE\": \"\",\n          \"ACCRUALS\": \"\",\n          \"CONINVOLST\": \"\",\n          \"CONDORIGIN\": \"A\",\n          \"GROUPCOND\": \"\",\n          \"COND_UPDAT\": \"\",\n          \"ACCESS_SEQ\": \"53\",\n          \"CONDCOUNT\": \"01\",\n          \"ROUNDOFFDI\": \"0.000000000\",\n          \"CONDVALUE\": \"0.000000000\",\n          \"CURRENCY_2\": \"BRL\",\n          \"CURR_ISO_2\": \"BRL\",\n          \"CONDCNTRL\": \"A\",\n          \"CONDISACTI\": \"Y\",\n          \"CONDCLASS\": \"D\",\n          \"FACTBASVAL\": \"0.0000000000000000E+00\",\n          \"SCALEBASIN\": \"\",\n          \"SCALBASVAL\": \"0.000000000\",\n          \"UNITMEASUR\": \"\",\n          \"ISO_UNIT\": \"\",\n          \"CURRENCKEY\": \"\",\n          \"CURRENISO\": \"\",\n          \"CONDINCOMP\": \"\",\n          \"CONDCONFIG\": \"\",\n          \"CONDCHAMAN\": \"\",\n          \"COND_NO\": \"0035528190\",\n          \"TAX_CODE\": \"SD\",\n          \"VARCOND\": \"\",\n          \"ACCOUNTKEY\": \"\",\n          \"ACCOUNT_KE\": \"\",\n          \"WT_WITHCD\": \"\",\n          \"STRUCTCOND\": \"\",\n          \"FACTCONBAS\": \"0.0000000000000000E+00\",\n          \"CONDCOINHD\": \"00\"\n        },\n        {\n          \"ITM_NUMBER\": \"000010\",\n          \"COND_ST_NO\": \"214\",\n          \"COND_COUNT\": \"01\",\n          \"COND_TYPE\": \"DINC\",\n          \"COND_VALUE\": \"100.000000000\",\n          \"CURRENCY\": \"\",\n          \"COND_UNIT\": \"\",\n          \"COND_P_UNT\": \"0\",\n          \"CURR_ISO\": \"\",\n          \"CD_UNT_ISO\": \"\",\n          \"REFOBJTYPE\": \"\",\n          \"REFOBJKEY\": \"\",\n          \"REFLOGSYS\": \"\",\n          \"APPLICATIO\": \"V\",\n          \"CONPRICDAT\": \"2020-12-14\",\n          \"CALCTYPCON\": \"A\",\n          \"CONBASEVAL\": \"10.000000000\",\n          \"CONEXCHRAT\": \"0.00000\",\n          \"NUMCONVERT\": \"0\",\n          \"DENOMINATO\": \"0\",\n          \"CONDTYPE\": \"1\",\n          \"STAT_CON\": \"X\",\n          \"SCALETYPE\": \"\",\n          \"ACCRUALS\": \"\",\n          \"CONINVOLST\": \"\",\n          \"CONDORIGIN\": \"A\",\n          \"GROUPCOND\": \"\",\n          \"COND_UPDAT\": \"\",\n          \"ACCESS_SEQ\": \"00\",\n          \"CONDCOUNT\": \"00\",\n          \"ROUNDOFFDI\": \"0.000000000\",\n          \"CONDVALUE\": \"10.000000000\",\n          \"CURRENCY_2\": \"BRL\",\n          \"CURR_ISO_2\": \"BRL\",\n          \"CONDCNTRL\": \"A\",\n          \"CONDISACTI\": \"Y\",\n          \"CONDCLASS\": \"A\",\n          \"FACTBASVAL\": \"0.0000000000000000E+00\",\n          \"SCALEBASIN\": \"\",\n          \"SCALBASVAL\": \"0.000000000\",\n          \"UNITMEASUR\": \"\",\n          \"ISO_UNIT\": \"\",\n          \"CURRENCKEY\": \"\",\n          \"CURRENISO\": \"\",\n          \"CONDINCOMP\": \"\",\n          \"CONDCONFIG\": \"\",\n          \"CONDCHAMAN\": \"\",\n          \"COND_NO\": \"\",\n          \"TAX_CODE\": \"\",\n          \"VARCOND\": \"\",\n          \"ACCOUNTKEY\": \"\",\n          \"ACCOUNT_KE\": \"\",\n          \"WT_WITHCD\": \"\",\n          \"STRUCTCOND\": \"\",\n          \"FACTCONBAS\": \"0.0000000000000000E+00\",\n          \"CONDCOINHD\": \"00\"\n        },\n        {\n          \"ITM_NUMBER\": \"000010\",\n          \"COND_ST_NO\": \"221\",\n          \"COND_COUNT\": \"01\",\n          \"COND_TYPE\": \"ICFR\",\n          \"COND_VALUE\": \"12.000000000\",\n          \"CURRENCY\": \"\",\n          \"COND_UNIT\": \"\",\n          \"COND_P_UNT\": \"0\",\n          \"CURR_ISO\": \"\",\n          \"CD_UNT_ISO\": \"\",\n          \"REFOBJTYPE\": \"\",\n          \"REFOBJKEY\": \"\",\n          \"REFLOGSYS\": \"\",\n          \"APPLICATIO\": \"V\",\n          \"CONPRICDAT\": \"2020-12-14\",\n          \"CALCTYPCON\": \"A\",\n          \"CONBASEVAL\": \"10.000000000\",\n          \"CONEXCHRAT\": \"0.00000\",\n          \"NUMCONVERT\": \"0\",\n          \"DENOMINATO\": \"0\",\n          \"CONDTYPE\": \"D\",\n          \"STAT_CON\": \"X\",\n          \"SCALETYPE\": \"\",\n          \"ACCRUALS\": \"\",\n          \"CONINVOLST\": \"\",\n          \"CONDORIGIN\": \"A\",\n          \"GROUPCOND\": \"\",\n          \"COND_UPDAT\": \"\",\n          \"ACCESS_SEQ\": \"98\",\n          \"CONDCOUNT\": \"01\",\n          \"ROUNDOFFDI\": \"0.000000000\",\n          \"CONDVALUE\": \"1.200000000\",\n          \"CURRENCY_2\": \"BRL\",\n          \"CURR_ISO_2\": \"BRL\",\n          \"CONDCNTRL\": \"A\",\n          \"CONDISACTI\": \"Y\",\n          \"CONDCLASS\": \"D\",\n          \"FACTBASVAL\": \"0.0000000000000000E+00\",\n          \"SCALEBASIN\": \"\",\n          \"SCALBASVAL\": \"0.000000000\",\n          \"UNITMEASUR\": \"\",\n          \"ISO_UNIT\": \"\",\n          \"CURRENCKEY\": \"\",\n          \"CURRENISO\": \"\",\n          \"CONDINCOMP\": \"\",\n          \"CONDCONFIG\": \"\",\n          \"CONDCHAMAN\": \"\",\n          \"COND_NO\": \"0035124175\",\n          \"TAX_CODE\": \"SD\",\n          \"VARCOND\": \"\",\n          \"ACCOUNTKEY\": \"\",\n          \"ACCOUNT_KE\": \"\",\n          \"WT_WITHCD\": \"\",\n          \"STRUCTCOND\": \"\",\n          \"FACTCONBAS\": \"0.0000000000000000E+00\",\n          \"CONDCOINHD\": \"00\"\n        },\n        {\n          \"ITM_NUMBER\": \"000010\",\n          \"COND_ST_NO\": \"240\",\n          \"COND_COUNT\": \"01\",\n          \"COND_TYPE\": \"DIPI\",\n          \"COND_VALUE\": \"100.000000000\",\n          \"CURRENCY\": \"\",\n          \"COND_UNIT\": \"\",\n          \"COND_P_UNT\": \"0\",\n          \"CURR_ISO\": \"\",\n          \"CD_UNT_ISO\": \"\",\n          \"REFOBJTYPE\": \"\",\n          \"REFOBJKEY\": \"\",\n          \"REFLOGSYS\": \"\",\n          \"APPLICATIO\": \"V\",\n          \"CONPRICDAT\": \"2020-12-14\",\n          \"CALCTYPCON\": \"A\",\n          \"CONBASEVAL\": \"10.000000000\",\n          \"CONEXCHRAT\": \"0.00000\",\n          \"NUMCONVERT\": \"0\",\n          \"DENOMINATO\": \"0\",\n          \"CONDTYPE\": \"D\",\n          \"STAT_CON\": \"X\",\n          \"SCALETYPE\": \"\",\n          \"ACCRUALS\": \"\",\n          \"CONINVOLST\": \"\",\n          \"CONDORIGIN\": \"A\",\n          \"GROUPCOND\": \"\",\n          \"COND_UPDAT\": \"\",\n          \"ACCESS_SEQ\": \"10\",\n          \"CONDCOUNT\": \"01\",\n          \"ROUNDOFFDI\": \"0.000000000\",\n          \"CONDVALUE\": \"10.000000000\",\n          \"CURRENCY_2\": \"BRL\",\n          \"CURR_ISO_2\": \"BRL\",\n          \"CONDCNTRL\": \"A\",\n          \"CONDISACTI\": \"Y\",\n          \"CONDCLASS\": \"D\",\n          \"FACTBASVAL\": \"0.0000000000000000E+00\",\n          \"SCALEBASIN\": \"\",\n          \"SCALBASVAL\": \"0.000000000\",\n          \"UNITMEASUR\": \"\",\n          \"ISO_UNIT\": \"\",\n          \"CURRENCKEY\": \"\",\n          \"CURRENISO\": \"\",\n          \"CONDINCOMP\": \"\",\n          \"CONDCONFIG\": \"\",\n          \"CONDCHAMAN\": \"\",\n          \"COND_NO\": \"0011149091\",\n          \"TAX_CODE\": \"SD\",\n          \"VARCOND\": \"\",\n          \"ACCOUNTKEY\": \"\",\n          \"ACCOUNT_KE\": \"\",\n          \"WT_WITHCD\": \"\",\n          \"STRUCTCOND\": \"\",\n          \"FACTCONBAS\": \"0.0000000000000000E+00\",\n          \"CONDCOINHD\": \"00\"\n        },\n        {\n          \"ITM_NUMBER\": \"000010\",\n          \"COND_ST_NO\": \"241\",\n          \"COND_COUNT\": \"01\",\n          \"COND_TYPE\": \"IPVA\",\n          \"COND_VALUE\": \"5.000000000\",\n          \"CURRENCY\": \"\",\n          \"COND_UNIT\": \"\",\n          \"COND_P_UNT\": \"0\",\n          \"CURR_ISO\": \"\",\n          \"CD_UNT_ISO\": \"\",\n          \"REFOBJTYPE\": \"\",\n          \"REFOBJKEY\": \"\",\n          \"REFLOGSYS\": \"\",\n          \"APPLICATIO\": \"V\",\n          \"CONPRICDAT\": \"2020-12-14\",\n          \"CALCTYPCON\": \"A\",\n          \"CONBASEVAL\": \"10.000000000\",\n          \"CONEXCHRAT\": \"0.00000\",\n          \"NUMCONVERT\": \"0\",\n          \"DENOMINATO\": \"0\",\n          \"CONDTYPE\": \"D\",\n          \"STAT_CON\": \"X\",\n          \"SCALETYPE\": \"\",\n          \"ACCRUALS\": \"\",\n          \"CONINVOLST\": \"\",\n          \"CONDORIGIN\": \"A\",\n          \"GROUPCOND\": \"\",\n          \"COND_UPDAT\": \"\",\n          \"ACCESS_SEQ\": \"79\",\n          \"CONDCOUNT\": \"01\",\n          \"ROUNDOFFDI\": \"0.000000000\",\n          \"CONDVALUE\": \"0.500000000\",\n          \"CURRENCY_2\": \"BRL\",\n          \"CURR_ISO_2\": \"BRL\",\n          \"CONDCNTRL\": \"A\",\n          \"CONDISACTI\": \"Y\",\n          \"CONDCLASS\": \"D\",\n          \"FACTBASVAL\": \"0.0000000000000000E+00\",\n          \"SCALEBASIN\": \"\",\n          \"SCALBASVAL\": \"0.000000000\",\n          \"UNITMEASUR\": \"\",\n          \"ISO_UNIT\": \"\",\n          \"CURRENCKEY\": \"\",\n          \"CURRENISO\": \"\",\n          \"CONDINCOMP\": \"\",\n          \"CONDCONFIG\": \"\",\n          \"CONDCHAMAN\": \"\",\n          \"COND_NO\": \"0043113081\",\n          \"TAX_CODE\": \"SD\",\n          \"VARCOND\": \"\",\n          \"ACCOUNTKEY\": \"\",\n          \"ACCOUNT_KE\": \"\",\n          \"WT_WITHCD\": \"\",\n          \"STRUCTCOND\": \"\",\n          \"FACTCONBAS\": \"0.0000000000000000E+00\",\n          \"CONDCOINHD\": \"00\"\n        },\n        {\n          \"ITM_NUMBER\": \"000010\",\n          \"COND_ST_NO\": \"242\",\n          \"COND_COUNT\": \"01\",\n          \"COND_TYPE\": \"IPBS\",\n          \"COND_VALUE\": \"100.000000000\",\n          \"CURRENCY\": \"\",\n          \"COND_UNIT\": \"\",\n          \"COND_P_UNT\": \"0\",\n          \"CURR_ISO\": \"\",\n          \"CD_UNT_ISO\": \"\",\n          \"REFOBJTYPE\": \"\",\n          \"REFOBJKEY\": \"\",\n          \"REFLOGSYS\": \"\",\n          \"APPLICATIO\": \"V\",\n          \"CONPRICDAT\": \"2020-12-14\",\n          \"CALCTYPCON\": \"A\",\n          \"CONBASEVAL\": \"10.000000000\",\n          \"CONEXCHRAT\": \"0.00000\",\n          \"NUMCONVERT\": \"0\",\n          \"DENOMINATO\": \"0\",\n          \"CONDTYPE\": \"D\",\n          \"STAT_CON\": \"X\",\n          \"SCALETYPE\": \"\",\n          \"ACCRUALS\": \"\",\n          \"CONINVOLST\": \"\",\n          \"CONDORIGIN\": \"A\",\n          \"GROUPCOND\": \"\",\n          \"COND_UPDAT\": \"\",\n          \"ACCESS_SEQ\": \"79\",\n          \"CONDCOUNT\": \"01\",\n          \"ROUNDOFFDI\": \"0.000000000\",\n          \"CONDVALUE\": \"10.000000000\",\n          \"CURRENCY_2\": \"BRL\",\n          \"CURR_ISO_2\": \"BRL\",\n          \"CONDCNTRL\": \"A\",\n          \"CONDISACTI\": \"Y\",\n          \"CONDCLASS\": \"D\",\n          \"FACTBASVAL\": \"0.0000000000000000E+00\",\n          \"SCALEBASIN\": \"\",\n          \"SCALBASVAL\": \"0.000000000\",\n          \"UNITMEASUR\": \"\",\n          \"ISO_UNIT\": \"\",\n          \"CURRENCKEY\": \"\",\n          \"CURRENISO\": \"\",\n          \"CONDINCOMP\": \"\",\n          \"CONDCONFIG\": \"\",\n          \"CONDCHAMAN\": \"\",\n          \"COND_NO\": \"0043113082\",\n          \"TAX_CODE\": \"SD\",\n          \"VARCOND\": \"\",\n          \"ACCOUNTKEY\": \"\",\n          \"ACCOUNT_KE\": \"\",\n          \"WT_WITHCD\": \"\",\n          \"STRUCTCOND\": \"\",\n          \"FACTCONBAS\": \"0.0000000000000000E+00\",\n          \"CONDCOINHD\": \"00\"\n        },\n        {\n          \"ITM_NUMBER\": \"000010\",\n          \"COND_ST_NO\": \"243\",\n          \"COND_COUNT\": \"01\",\n          \"COND_TYPE\": \"IPOB\",\n          \"COND_VALUE\": \"0.000000000\",\n          \"CURRENCY\": \"\",\n          \"COND_UNIT\": \"\",\n          \"COND_P_UNT\": \"0\",\n          \"CURR_ISO\": \"\",\n          \"CD_UNT_ISO\": \"\",\n          \"REFOBJTYPE\": \"\",\n          \"REFOBJKEY\": \"\",\n          \"REFLOGSYS\": \"\",\n          \"APPLICATIO\": \"V\",\n          \"CONPRICDAT\": \"2020-12-14\",\n          \"CALCTYPCON\": \"A\",\n          \"CONBASEVAL\": \"10.000000000\",\n          \"CONEXCHRAT\": \"0.00000\",\n          \"NUMCONVERT\": \"0\",\n          \"DENOMINATO\": \"0\",\n          \"CONDTYPE\": \"D\",\n          \"STAT_CON\": \"X\",\n          \"SCALETYPE\": \"\",\n          \"ACCRUALS\": \"\",\n          \"CONINVOLST\": \"\",\n          \"CONDORIGIN\": \"A\",\n          \"GROUPCOND\": \"\",\n          \"COND_UPDAT\": \"\",\n          \"ACCESS_SEQ\": \"79\",\n          \"CONDCOUNT\": \"01\",\n          \"ROUNDOFFDI\": \"0.000000000\",\n          \"CONDVALUE\": \"0.000000000\",\n          \"CURRENCY_2\": \"BRL\",\n          \"CURR_ISO_2\": \"BRL\",\n          \"CONDCNTRL\": \"A\",\n          \"CONDISACTI\": \"Y\",\n          \"CONDCLASS\": \"D\",\n          \"FACTBASVAL\": \"0.0000000000000000E+00\",\n          \"SCALEBASIN\": \"\",\n          \"SCALBASVAL\": \"0.000000000\",\n          \"UNITMEASUR\": \"\",\n          \"ISO_UNIT\": \"\",\n          \"CURRENCKEY\": \"\",\n          \"CURRENISO\": \"\",\n          \"CONDINCOMP\": \"\",\n          \"CONDCONFIG\": \"\",\n          \"CONDCHAMAN\": \"\",\n          \"COND_NO\": \"0043113083\",\n          \"TAX_CODE\": \"SD\",\n          \"VARCOND\": \"\",\n          \"ACCOUNTKEY\": \"\",\n          \"ACCOUNT_KE\": \"\",\n          \"WT_WITHCD\": \"\",\n          \"STRUCTCOND\": \"\",\n          \"FACTCONBAS\": \"0.0000000000000000E+00\",\n          \"CONDCOINHD\": \"00\"\n        },\n        {\n          \"ITM_NUMBER\": \"000010\",\n          \"COND_ST_NO\": \"246\",\n          \"COND_COUNT\": \"01\",\n          \"COND_TYPE\": \"IPLW\",\n          \"COND_VALUE\": \"100.000000000\",\n          \"CURRENCY\": \"\",\n          \"COND_UNIT\": \"\",\n          \"COND_P_UNT\": \"0\",\n          \"CURR_ISO\": \"\",\n          \"CD_UNT_ISO\": \"\",\n          \"REFOBJTYPE\": \"\",\n          \"REFOBJKEY\": \"\",\n          \"REFLOGSYS\": \"\",\n          \"APPLICATIO\": \"V\",\n          \"CONPRICDAT\": \"2020-12-14\",\n          \"CALCTYPCON\": \"A\",\n          \"CONBASEVAL\": \"10.000000000\",\n          \"CONEXCHRAT\": \"0.00000\",\n          \"NUMCONVERT\": \"0\",\n          \"DENOMINATO\": \"0\",\n          \"CONDTYPE\": \"D\",\n          \"STAT_CON\": \"X\",\n          \"SCALETYPE\": \"\",\n          \"ACCRUALS\": \"\",\n          \"CONINVOLST\": \"\",\n          \"CONDORIGIN\": \"A\",\n          \"GROUPCOND\": \"\",\n          \"COND_UPDAT\": \"\",\n          \"ACCESS_SEQ\": \"79\",\n          \"CONDCOUNT\": \"01\",\n          \"ROUNDOFFDI\": \"0.000000000\",\n          \"CONDVALUE\": \"10.000000000\",\n          \"CURRENCY_2\": \"BRL\",\n          \"CURR_ISO_2\": \"BRL\",\n          \"CONDCNTRL\": \"A\",\n          \"CONDISACTI\": \"Y\",\n          \"CONDCLASS\": \"D\",\n          \"FACTBASVAL\": \"0.0000000000000000E+00\",\n          \"SCALEBASIN\": \"\",\n          \"SCALBASVAL\": \"0.000000000\",\n          \"UNITMEASUR\": \"\",\n          \"ISO_UNIT\": \"\",\n          \"CURRENCKEY\": \"\",\n          \"CURRENISO\": \"\",\n          \"CONDINCOMP\": \"\",\n          \"CONDCONFIG\": \"\",\n          \"CONDCHAMAN\": \"\",\n          \"COND_NO\": \"0043113084\",\n          \"TAX_CODE\": \"SD\",\n          \"VARCOND\": \"\",\n          \"ACCOUNTKEY\": \"\",\n          \"ACCOUNT_KE\": \"\",\n          \"WT_WITHCD\": \"\",\n          \"STRUCTCOND\": \"\",\n          \"FACTCONBAS\": \"0.0000000000000000E+00\",\n          \"CONDCOINHD\": \"00\"\n        },\n        {\n          \"ITM_NUMBER\": \"000010\",\n          \"COND_ST_NO\": \"250\",\n          \"COND_COUNT\": \"01\",\n          \"COND_TYPE\": \"DCOF\",\n          \"COND_VALUE\": \"100.000000000\",\n          \"CURRENCY\": \"\",\n          \"COND_UNIT\": \"\",\n          \"COND_P_UNT\": \"0\",\n          \"CURR_ISO\": \"\",\n          \"CD_UNT_ISO\": \"\",\n          \"REFOBJTYPE\": \"\",\n          \"REFOBJKEY\": \"\",\n          \"REFLOGSYS\": \"\",\n          \"APPLICATIO\": \"V\",\n          \"CONPRICDAT\": \"2020-12-14\",\n          \"CALCTYPCON\": \"A\",\n          \"CONBASEVAL\": \"10.000000000\",\n          \"CONEXCHRAT\": \"0.00000\",\n          \"NUMCONVERT\": \"0\",\n          \"DENOMINATO\": \"0\",\n          \"CONDTYPE\": \"D\",\n          \"STAT_CON\": \"X\",\n          \"SCALETYPE\": \"\",\n          \"ACCRUALS\": \"\",\n          \"CONINVOLST\": \"\",\n          \"CONDORIGIN\": \"A\",\n          \"GROUPCOND\": \"\",\n          \"COND_UPDAT\": \"\",\n          \"ACCESS_SEQ\": \"10\",\n          \"CONDCOUNT\": \"01\",\n          \"ROUNDOFFDI\": \"0.000000000\",\n          \"CONDVALUE\": \"10.000000000\",\n          \"CURRENCY_2\": \"BRL\",\n          \"CURR_ISO_2\": \"BRL\",\n          \"CONDCNTRL\": \"A\",\n          \"CONDISACTI\": \"Y\",\n          \"CONDCLASS\": \"D\",\n          \"FACTBASVAL\": \"0.0000000000000000E+00\",\n          \"SCALEBASIN\": \"\",\n          \"SCALBASVAL\": \"0.000000000\",\n          \"UNITMEASUR\": \"\",\n          \"ISO_UNIT\": \"\",\n          \"CURRENCKEY\": \"\",\n          \"CURRENISO\": \"\",\n          \"CONDINCOMP\": \"\",\n          \"CONDCONFIG\": \"\",\n          \"CONDCHAMAN\": \"\",\n          \"COND_NO\": \"0011152508\",\n          \"TAX_CODE\": \"SD\",\n          \"VARCOND\": \"\",\n          \"ACCOUNTKEY\": \"\",\n          \"ACCOUNT_KE\": \"\",\n          \"WT_WITHCD\": \"\",\n          \"STRUCTCOND\": \"\",\n          \"FACTCONBAS\": \"0.0000000000000000E+00\",\n          \"CONDCOINHD\": \"00\"\n        },\n        {\n          \"ITM_NUMBER\": \"000010\",\n          \"COND_ST_NO\": \"251\",\n          \"COND_COUNT\": \"01\",\n          \"COND_TYPE\": \"BCO1\",\n          \"COND_VALUE\": \"7.600000000\",\n          \"CURRENCY\": \"\",\n          \"COND_UNIT\": \"\",\n          \"COND_P_UNT\": \"0\",\n          \"CURR_ISO\": \"\",\n          \"CD_UNT_ISO\": \"\",\n          \"REFOBJTYPE\": \"\",\n          \"REFOBJKEY\": \"\",\n          \"REFLOGSYS\": \"\",\n          \"APPLICATIO\": \"V\",\n          \"CONPRICDAT\": \"2020-12-14\",\n          \"CALCTYPCON\": \"A\",\n          \"CONBASEVAL\": \"10.000000000\",\n          \"CONEXCHRAT\": \"0.00000\",\n          \"NUMCONVERT\": \"0\",\n          \"DENOMINATO\": \"0\",\n          \"CONDTYPE\": \"D\",\n          \"STAT_CON\": \"X\",\n          \"SCALETYPE\": \"\",\n          \"ACCRUALS\": \"\",\n          \"CONINVOLST\": \"\",\n          \"CONDORIGIN\": \"A\",\n          \"GROUPCOND\": \"\",\n          \"COND_UPDAT\": \"\",\n          \"ACCESS_SEQ\": \"89\",\n          \"CONDCOUNT\": \"01\",\n          \"ROUNDOFFDI\": \"0.000000000\",\n          \"CONDVALUE\": \"0.760000000\",\n          \"CURRENCY_2\": \"BRL\",\n          \"CURR_ISO_2\": \"BRL\",\n          \"CONDCNTRL\": \"A\",\n          \"CONDISACTI\": \"Y\",\n          \"CONDCLASS\": \"D\",\n          \"FACTBASVAL\": \"0.0000000000000000E+00\",\n          \"SCALEBASIN\": \"\",\n          \"SCALBASVAL\": \"0.000000000\",\n          \"UNITMEASUR\": \"\",\n          \"ISO_UNIT\": \"\",\n          \"CURRENCKEY\": \"\",\n          \"CURRENISO\": \"\",\n          \"CONDINCOMP\": \"\",\n          \"CONDCONFIG\": \"\",\n          \"CONDCHAMAN\": \"\",\n          \"COND_NO\": \"0023891241\",\n          \"TAX_CODE\": \"SD\",\n          \"VARCOND\": \"\",\n          \"ACCOUNTKEY\": \"\",\n          \"ACCOUNT_KE\": \"\",\n          \"WT_WITHCD\": \"\",\n          \"STRUCTCOND\": \"\",\n          \"FACTCONBAS\": \"0.0000000000000000E+00\",\n          \"CONDCOINHD\": \"00\"\n        },\n        {\n          \"ITM_NUMBER\": \"000010\",\n          \"COND_ST_NO\": \"252\",\n          \"COND_COUNT\": \"01\",\n          \"COND_TYPE\": \"BCO2\",\n          \"COND_VALUE\": \"100.000000000\",\n          \"CURRENCY\": \"\",\n          \"COND_UNIT\": \"\",\n          \"COND_P_UNT\": \"0\",\n          \"CURR_ISO\": \"\",\n          \"CD_UNT_ISO\": \"\",\n          \"REFOBJTYPE\": \"\",\n          \"REFOBJKEY\": \"\",\n          \"REFLOGSYS\": \"\",\n          \"APPLICATIO\": \"V\",\n          \"CONPRICDAT\": \"2020-12-14\",\n          \"CALCTYPCON\": \"A\",\n          \"CONBASEVAL\": \"10.000000000\",\n          \"CONEXCHRAT\": \"0.00000\",\n          \"NUMCONVERT\": \"0\",\n          \"DENOMINATO\": \"0\",\n          \"CONDTYPE\": \"D\",\n          \"STAT_CON\": \"X\",\n          \"SCALETYPE\": \"\",\n          \"ACCRUALS\": \"\",\n          \"CONINVOLST\": \"\",\n          \"CONDORIGIN\": \"A\",\n          \"GROUPCOND\": \"\",\n          \"COND_UPDAT\": \"\",\n          \"ACCESS_SEQ\": \"89\",\n          \"CONDCOUNT\": \"01\",\n          \"ROUNDOFFDI\": \"0.000000000\",\n          \"CONDVALUE\": \"10.000000000\",\n          \"CURRENCY_2\": \"BRL\",\n          \"CURR_ISO_2\": \"BRL\",\n          \"CONDCNTRL\": \"A\",\n          \"CONDISACTI\": \"Y\",\n          \"CONDCLASS\": \"D\",\n          \"FACTBASVAL\": \"0.0000000000000000E+00\",\n          \"SCALEBASIN\": \"\",\n          \"SCALBASVAL\": \"0.000000000\",\n          \"UNITMEASUR\": \"\",\n          \"ISO_UNIT\": \"\",\n          \"CURRENCKEY\": \"\",\n          \"CURRENISO\": \"\",\n          \"CONDINCOMP\": \"\",\n          \"CONDCONFIG\": \"\",\n          \"CONDCHAMAN\": \"\",\n          \"COND_NO\": \"0023891242\",\n          \"TAX_CODE\": \"SD\",\n          \"VARCOND\": \"\",\n          \"ACCOUNTKEY\": \"\",\n          \"ACCOUNT_KE\": \"\",\n          \"WT_WITHCD\": \"\",\n          \"STRUCTCOND\": \"\",\n          \"FACTCONBAS\": \"0.0000000000000000E+00\",\n          \"CONDCOINHD\": \"00\"\n        },\n        {\n          \"ITM_NUMBER\": \"000010\",\n          \"COND_ST_NO\": \"255\",\n          \"COND_COUNT\": \"01\",\n          \"COND_TYPE\": \"DPIS\",\n          \"COND_VALUE\": \"100.000000000\",\n          \"CURRENCY\": \"\",\n          \"COND_UNIT\": \"\",\n          \"COND_P_UNT\": \"0\",\n          \"CURR_ISO\": \"\",\n          \"CD_UNT_ISO\": \"\",\n          \"REFOBJTYPE\": \"\",\n          \"REFOBJKEY\": \"\",\n          \"REFLOGSYS\": \"\",\n          \"APPLICATIO\": \"V\",\n          \"CONPRICDAT\": \"2020-12-14\",\n          \"CALCTYPCON\": \"A\",\n          \"CONBASEVAL\": \"10.000000000\",\n          \"CONEXCHRAT\": \"0.00000\",\n          \"NUMCONVERT\": \"0\",\n          \"DENOMINATO\": \"0\",\n          \"CONDTYPE\": \"D\",\n          \"STAT_CON\": \"X\",\n          \"SCALETYPE\": \"\",\n          \"ACCRUALS\": \"\",\n          \"CONINVOLST\": \"\",\n          \"CONDORIGIN\": \"A\",\n          \"GROUPCOND\": \"\",\n          \"COND_UPDAT\": \"\",\n          \"ACCESS_SEQ\": \"10\",\n          \"CONDCOUNT\": \"01\",\n          \"ROUNDOFFDI\": \"0.000000000\",\n          \"CONDVALUE\": \"10.000000000\",\n          \"CURRENCY_2\": \"BRL\",\n          \"CURR_ISO_2\": \"BRL\",\n          \"CONDCNTRL\": \"A\",\n          \"CONDISACTI\": \"Y\",\n          \"CONDCLASS\": \"D\",\n          \"FACTBASVAL\": \"0.0000000000000000E+00\",\n          \"SCALEBASIN\": \"\",\n          \"SCALBASVAL\": \"0.000000000\",\n          \"UNITMEASUR\": \"\",\n          \"ISO_UNIT\": \"\",\n          \"CURRENCKEY\": \"\",\n          \"CURRENISO\": \"\",\n          \"CONDINCOMP\": \"\",\n          \"CONDCONFIG\": \"\",\n          \"CONDCHAMAN\": \"\",\n          \"COND_NO\": \"0011153563\",\n          \"TAX_CODE\": \"SD\",\n          \"VARCOND\": \"\",\n          \"ACCOUNTKEY\": \"\",\n          \"ACCOUNT_KE\": \"\",\n          \"WT_WITHCD\": \"\",\n          \"STRUCTCOND\": \"\",\n          \"FACTCONBAS\": \"0.0000000000000000E+00\",\n          \"CONDCOINHD\": \"00\"\n        },\n        {\n          \"ITM_NUMBER\": \"000010\",\n          \"COND_ST_NO\": \"256\",\n          \"COND_COUNT\": \"01\",\n          \"COND_TYPE\": \"BPI1\",\n          \"COND_VALUE\": \"1.650000000\",\n          \"CURRENCY\": \"\",\n          \"COND_UNIT\": \"\",\n          \"COND_P_UNT\": \"0\",\n          \"CURR_ISO\": \"\",\n          \"CD_UNT_ISO\": \"\",\n          \"REFOBJTYPE\": \"\",\n          \"REFOBJKEY\": \"\",\n          \"REFLOGSYS\": \"\",\n          \"APPLICATIO\": \"V\",\n          \"CONPRICDAT\": \"2020-12-14\",\n          \"CALCTYPCON\": \"A\",\n          \"CONBASEVAL\": \"10.000000000\",\n          \"CONEXCHRAT\": \"0.00000\",\n          \"NUMCONVERT\": \"0\",\n          \"DENOMINATO\": \"0\",\n          \"CONDTYPE\": \"D\",\n          \"STAT_CON\": \"X\",\n          \"SCALETYPE\": \"\",\n          \"ACCRUALS\": \"\",\n          \"CONINVOLST\": \"\",\n          \"CONDORIGIN\": \"A\",\n          \"GROUPCOND\": \"\",\n          \"COND_UPDAT\": \"\",\n          \"ACCESS_SEQ\": \"89\",\n          \"CONDCOUNT\": \"01\",\n          \"ROUNDOFFDI\": \"0.000000000\",\n          \"CONDVALUE\": \"0.170000000\",\n          \"CURRENCY_2\": \"BRL\",\n          \"CURR_ISO_2\": \"BRL\",\n          \"CONDCNTRL\": \"A\",\n          \"CONDISACTI\": \"Y\",\n          \"CONDCLASS\": \"D\",\n          \"FACTBASVAL\": \"0.0000000000000000E+00\",\n          \"SCALEBASIN\": \"\",\n          \"SCALBASVAL\": \"0.000000000\",\n          \"UNITMEASUR\": \"\",\n          \"ISO_UNIT\": \"\",\n          \"CURRENCKEY\": \"\",\n          \"CURRENISO\": \"\",\n          \"CONDINCOMP\": \"\",\n          \"CONDCONFIG\": \"\",\n          \"CONDCHAMAN\": \"\",\n          \"COND_NO\": \"0023924157\",\n          \"TAX_CODE\": \"SD\",\n          \"VARCOND\": \"\",\n          \"ACCOUNTKEY\": \"\",\n          \"ACCOUNT_KE\": \"\",\n          \"WT_WITHCD\": \"\",\n          \"STRUCTCOND\": \"\",\n          \"FACTCONBAS\": \"0.0000000000000000E+00\",\n          \"CONDCOINHD\": \"00\"\n        },\n        {\n          \"ITM_NUMBER\": \"000010\",\n          \"COND_ST_NO\": \"257\",\n          \"COND_COUNT\": \"01\",\n          \"COND_TYPE\": \"BPI2\",\n          \"COND_VALUE\": \"100.000000000\",\n          \"CURRENCY\": \"\",\n          \"COND_UNIT\": \"\",\n          \"COND_P_UNT\": \"0\",\n          \"CURR_ISO\": \"\",\n          \"CD_UNT_ISO\": \"\",\n          \"REFOBJTYPE\": \"\",\n          \"REFOBJKEY\": \"\",\n          \"REFLOGSYS\": \"\",\n          \"APPLICATIO\": \"V\",\n          \"CONPRICDAT\": \"2020-12-14\",\n          \"CALCTYPCON\": \"A\",\n          \"CONBASEVAL\": \"10.000000000\",\n          \"CONEXCHRAT\": \"0.00000\",\n          \"NUMCONVERT\": \"0\",\n          \"DENOMINATO\": \"0\",\n          \"CONDTYPE\": \"D\",\n          \"STAT_CON\": \"X\",\n          \"SCALETYPE\": \"\",\n          \"ACCRUALS\": \"\",\n          \"CONINVOLST\": \"\",\n          \"CONDORIGIN\": \"A\",\n          \"GROUPCOND\": \"\",\n          \"COND_UPDAT\": \"\",\n          \"ACCESS_SEQ\": \"89\",\n          \"CONDCOUNT\": \"01\",\n          \"ROUNDOFFDI\": \"0.000000000\",\n          \"CONDVALUE\": \"10.000000000\",\n          \"CURRENCY_2\": \"BRL\",\n          \"CURR_ISO_2\": \"BRL\",\n          \"CONDCNTRL\": \"A\",\n          \"CONDISACTI\": \"Y\",\n          \"CONDCLASS\": \"D\",\n          \"FACTBASVAL\": \"0.0000000000000000E+00\",\n          \"SCALEBASIN\": \"\",\n          \"SCALBASVAL\": \"0.000000000\",\n          \"UNITMEASUR\": \"\",\n          \"ISO_UNIT\": \"\",\n          \"CURRENCKEY\": \"\",\n          \"CURRENISO\": \"\",\n          \"CONDINCOMP\": \"\",\n          \"CONDCONFIG\": \"\",\n          \"CONDCHAMAN\": \"\",\n          \"COND_NO\": \"0023924158\",\n          \"TAX_CODE\": \"SD\",\n          \"VARCOND\": \"\",\n          \"ACCOUNTKEY\": \"\",\n          \"ACCOUNT_KE\": \"\",\n          \"WT_WITHCD\": \"\",\n          \"STRUCTCOND\": \"\",\n          \"FACTCONBAS\": \"0.0000000000000000E+00\",\n          \"CONDCOINHD\": \"00\"\n        },\n        {\n          \"ITM_NUMBER\": \"000010\",\n          \"COND_ST_NO\": \"280\",\n          \"COND_COUNT\": \"01\",\n          \"COND_TYPE\": \"DSUB\",\n          \"COND_VALUE\": \"100.000000000\",\n          \"CURRENCY\": \"\",\n          \"COND_UNIT\": \"\",\n          \"COND_P_UNT\": \"0\",\n          \"CURR_ISO\": \"\",\n          \"CD_UNT_ISO\": \"\",\n          \"REFOBJTYPE\": \"\",\n          \"REFOBJKEY\": \"\",\n          \"REFLOGSYS\": \"\",\n          \"APPLICATIO\": \"V\",\n          \"CONPRICDAT\": \"2020-12-14\",\n          \"CALCTYPCON\": \"A\",\n          \"CONBASEVAL\": \"10.000000000\",\n          \"CONEXCHRAT\": \"0.00000\",\n          \"NUMCONVERT\": \"0\",\n          \"DENOMINATO\": \"0\",\n          \"CONDTYPE\": \"D\",\n          \"STAT_CON\": \"X\",\n          \"SCALETYPE\": \"\",\n          \"ACCRUALS\": \"\",\n          \"CONINVOLST\": \"\",\n          \"CONDORIGIN\": \"A\",\n          \"GROUPCOND\": \"\",\n          \"COND_UPDAT\": \"\",\n          \"ACCESS_SEQ\": \"10\",\n          \"CONDCOUNT\": \"01\",\n          \"ROUNDOFFDI\": \"0.000000000\",\n          \"CONDVALUE\": \"10.000000000\",\n          \"CURRENCY_2\": \"BRL\",\n          \"CURR_ISO_2\": \"BRL\",\n          \"CONDCNTRL\": \"A\",\n          \"CONDISACTI\": \"Y\",\n          \"CONDCLASS\": \"D\",\n          \"FACTBASVAL\": \"0.0000000000000000E+00\",\n          \"SCALEBASIN\": \"\",\n          \"SCALBASVAL\": \"0.000000000\",\n          \"UNITMEASUR\": \"\",\n          \"ISO_UNIT\": \"\",\n          \"CURRENCKEY\": \"\",\n          \"CURRENISO\": \"\",\n          \"CONDINCOMP\": \"\",\n          \"CONDCONFIG\": \"\",\n          \"CONDCHAMAN\": \"\",\n          \"COND_NO\": \"0011208403\",\n          \"TAX_CODE\": \"SD\",\n          \"VARCOND\": \"\",\n          \"ACCOUNTKEY\": \"\",\n          \"ACCOUNT_KE\": \"\",\n          \"WT_WITHCD\": \"\",\n          \"STRUCTCOND\": \"\",\n          \"FACTCONBAS\": \"0.0000000000000000E+00\",\n          \"CONDCOINHD\": \"00\"\n        },\n        {\n          \"ITM_NUMBER\": \"000010\",\n          \"COND_ST_NO\": \"300\",\n          \"COND_COUNT\": \"01\",\n          \"COND_TYPE\": \"ICMI\",\n          \"COND_VALUE\": \"164.690000000\",\n          \"CURRENCY\": \"BRL\",\n          \"COND_UNIT\": \"CS\",\n          \"COND_P_UNT\": \"1\",\n          \"CURR_ISO\": \"BRL\",\n          \"CD_UNT_ISO\": \"CS\",\n          \"REFOBJTYPE\": \"\",\n          \"REFOBJKEY\": \"\",\n          \"REFLOGSYS\": \"\",\n          \"APPLICATIO\": \"V\",\n          \"CONPRICDAT\": \"2020-12-14\",\n          \"CALCTYPCON\": \"C\",\n          \"CONBASEVAL\": \"1.000000000\",\n          \"CONEXCHRAT\": \"1.00000\",\n          \"NUMCONVERT\": \"1\",\n          \"DENOMINATO\": \"1\",\n          \"CONDTYPE\": \"\",\n          \"STAT_CON\": \"\",\n          \"SCALETYPE\": \"\",\n          \"ACCRUALS\": \"\",\n          \"CONINVOLST\": \"\",\n          \"CONDORIGIN\": \"A\",\n          \"GROUPCOND\": \"\",\n          \"COND_UPDAT\": \"\",\n          \"ACCESS_SEQ\": \"00\",\n          \"CONDCOUNT\": \"00\",\n          \"ROUNDOFFDI\": \"0.000000000\",\n          \"CONDVALUE\": \"164.690000000\",\n          \"CURRENCY_2\": \"BRL\",\n          \"CURR_ISO_2\": \"BRL\",\n          \"CONDCNTRL\": \"A\",\n          \"CONDISACTI\": \"\",\n          \"CONDCLASS\": \"B\",\n          \"FACTBASVAL\": \"0.0000000000000000E+00\",\n          \"SCALEBASIN\": \"\",\n          \"SCALBASVAL\": \"0.000000000\",\n          \"UNITMEASUR\": \"\",\n          \"ISO_UNIT\": \"\",\n          \"CURRENCKEY\": \"\",\n          \"CURRENISO\": \"\",\n          \"CONDINCOMP\": \"\",\n          \"CONDCONFIG\": \"\",\n          \"CONDCHAMAN\": \"\",\n          \"COND_NO\": \"\",\n          \"TAX_CODE\": \"\",\n          \"VARCOND\": \"\",\n          \"ACCOUNTKEY\": \"\",\n          \"ACCOUNT_KE\": \"\",\n          \"WT_WITHCD\": \"\",\n          \"STRUCTCOND\": \"\",\n          \"FACTCONBAS\": \"0.0000000000000000E+00\",\n          \"CONDCOINHD\": \"00\"\n        },\n        {\n          \"ITM_NUMBER\": \"000010\",\n          \"COND_ST_NO\": \"305\",\n          \"COND_COUNT\": \"01\",\n          \"COND_TYPE\": \"ZICI\",\n          \"COND_VALUE\": \"164.690000000\",\n          \"CURRENCY\": \"BRL\",\n          \"COND_UNIT\": \"CS\",\n          \"COND_P_UNT\": \"1\",\n          \"CURR_ISO\": \"BRL\",\n          \"CD_UNT_ISO\": \"CS\",\n          \"REFOBJTYPE\": \"\",\n          \"REFOBJKEY\": \"\",\n          \"REFLOGSYS\": \"\",\n          \"APPLICATIO\": \"V\",\n          \"CONPRICDAT\": \"2020-12-14\",\n          \"CALCTYPCON\": \"C\",\n          \"CONBASEVAL\": \"1.000000000\",\n          \"CONEXCHRAT\": \"1.00000\",\n          \"NUMCONVERT\": \"1\",\n          \"DENOMINATO\": \"1\",\n          \"CONDTYPE\": \"\",\n          \"STAT_CON\": \"X\",\n          \"SCALETYPE\": \"\",\n          \"ACCRUALS\": \"\",\n          \"CONINVOLST\": \"\",\n          \"CONDORIGIN\": \"A\",\n          \"GROUPCOND\": \"\",\n          \"COND_UPDAT\": \"\",\n          \"ACCESS_SEQ\": \"00\",\n          \"CONDCOUNT\": \"00\",\n          \"ROUNDOFFDI\": \"0.000000000\",\n          \"CONDVALUE\": \"164.690000000\",\n          \"CURRENCY_2\": \"BRL\",\n          \"CURR_ISO_2\": \"BRL\",\n          \"CONDCNTRL\": \"A\",\n          \"CONDISACTI\": \"\",\n          \"CONDCLASS\": \"B\",\n          \"FACTBASVAL\": \"0.0000000000000000E+00\",\n          \"SCALEBASIN\": \"\",\n          \"SCALBASVAL\": \"0.000000000\",\n          \"UNITMEASUR\": \"\",\n          \"ISO_UNIT\": \"\",\n          \"CURRENCKEY\": \"\",\n          \"CURRENISO\": \"\",\n          \"CONDINCOMP\": \"\",\n          \"CONDCONFIG\": \"\",\n          \"CONDCHAMAN\": \"\",\n          \"COND_NO\": \"\",\n          \"TAX_CODE\": \"\",\n          \"VARCOND\": \"\",\n          \"ACCOUNTKEY\": \"\",\n          \"ACCOUNT_KE\": \"\",\n          \"WT_WITHCD\": \"\",\n          \"STRUCTCOND\": \"\",\n          \"FACTCONBAS\": \"0.0000000000000000E+00\",\n          \"CONDCOINHD\": \"00\"\n        },\n        {\n          \"ITM_NUMBER\": \"000010\",\n          \"COND_ST_NO\": \"310\",\n          \"COND_COUNT\": \"01\",\n          \"COND_TYPE\": \"ZICD\",\n          \"COND_VALUE\": \"-100.000000000\",\n          \"CURRENCY\": \"\",\n          \"COND_UNIT\": \"\",\n          \"COND_P_UNT\": \"0\",\n          \"CURR_ISO\": \"\",\n          \"CD_UNT_ISO\": \"\",\n          \"REFOBJTYPE\": \"\",\n          \"REFOBJKEY\": \"\",\n          \"REFLOGSYS\": \"\",\n          \"APPLICATIO\": \"V\",\n          \"CONPRICDAT\": \"2020-12-14\",\n          \"CALCTYPCON\": \"A\",\n          \"CONBASEVAL\": \"164.690000000\",\n          \"CONEXCHRAT\": \"0.00000\",\n          \"NUMCONVERT\": \"0\",\n          \"DENOMINATO\": \"0\",\n          \"CONDTYPE\": \"D\",\n          \"STAT_CON\": \"\",\n          \"SCALETYPE\": \"\",\n          \"ACCRUALS\": \"\",\n          \"CONINVOLST\": \"\",\n          \"CONDORIGIN\": \"A\",\n          \"GROUPCOND\": \"\",\n          \"COND_UPDAT\": \"\",\n          \"ACCESS_SEQ\": \"01\",\n          \"CONDCOUNT\": \"01\",\n          \"ROUNDOFFDI\": \"0.000000000\",\n          \"CONDVALUE\": \"0.000000000\",\n          \"CURRENCY_2\": \"BRL\",\n          \"CURR_ISO_2\": \"BRL\",\n          \"CONDCNTRL\": \"A\",\n          \"CONDISACTI\": \"\",\n          \"CONDCLASS\": \"A\",\n          \"FACTBASVAL\": \"0.0000000000000000E+00\",\n          \"SCALEBASIN\": \"\",\n          \"SCALBASVAL\": \"0.000000000\",\n          \"UNITMEASUR\": \"\",\n          \"ISO_UNIT\": \"\",\n          \"CURRENCKEY\": \"\",\n          \"CURRENISO\": \"\",\n          \"CONDINCOMP\": \"\",\n          \"CONDCONFIG\": \"\",\n          \"CONDCHAMAN\": \"\",\n          \"COND_NO\": \"0011863741\",\n          \"TAX_CODE\": \"\",\n          \"VARCOND\": \"\",\n          \"ACCOUNTKEY\": \"\",\n          \"ACCOUNT_KE\": \"\",\n          \"WT_WITHCD\": \"\",\n          \"STRUCTCOND\": \"\",\n          \"FACTCONBAS\": \"0.0000000000000000E+00\",\n          \"CONDCOINHD\": \"00\"\n        },\n        {\n          \"ITM_NUMBER\": \"000010\",\n          \"COND_ST_NO\": \"340\",\n          \"COND_COUNT\": \"01\",\n          \"COND_TYPE\": \"Z060\",\n          \"COND_VALUE\": \"0.000000000\",\n          \"CURRENCY\": \"\",\n          \"COND_UNIT\": \"\",\n          \"COND_P_UNT\": \"0\",\n          \"CURR_ISO\": \"\",\n          \"CD_UNT_ISO\": \"\",\n          \"REFOBJTYPE\": \"\",\n          \"REFOBJKEY\": \"\",\n          \"REFLOGSYS\": \"\",\n          \"APPLICATIO\": \"V\",\n          \"CONPRICDAT\": \"2020-12-14\",\n          \"CALCTYPCON\": \"A\",\n          \"CONBASEVAL\": \"164.690000000\",\n          \"CONEXCHRAT\": \"0.00000\",\n          \"NUMCONVERT\": \"0\",\n          \"DENOMINATO\": \"0\",\n          \"CONDTYPE\": \"\",\n          \"STAT_CON\": \"\",\n          \"SCALETYPE\": \"\",\n          \"ACCRUALS\": \"\",\n          \"CONINVOLST\": \"\",\n          \"CONDORIGIN\": \"A\",\n          \"GROUPCOND\": \"\",\n          \"COND_UPDAT\": \"\",\n          \"ACCESS_SEQ\": \"15\",\n          \"CONDCOUNT\": \"01\",\n          \"ROUNDOFFDI\": \"0.000000000\",\n          \"CONDVALUE\": \"0.000000000\",\n          \"CURRENCY_2\": \"BRL\",\n          \"CURR_ISO_2\": \"BRL\",\n          \"CONDCNTRL\": \"A\",\n          \"CONDISACTI\": \"\",\n          \"CONDCLASS\": \"A\",\n          \"FACTBASVAL\": \"0.0000000000000000E+00\",\n          \"SCALEBASIN\": \"B\",\n          \"SCALBASVAL\": \"164.690000000\",\n          \"UNITMEASUR\": \"\",\n          \"ISO_UNIT\": \"\",\n          \"CURRENCKEY\": \"BRL\",\n          \"CURRENISO\": \"BRL\",\n          \"CONDINCOMP\": \"\",\n          \"CONDCONFIG\": \"\",\n          \"CONDCHAMAN\": \"\",\n          \"COND_NO\": \"0000741815\",\n          \"TAX_CODE\": \"\",\n          \"VARCOND\": \"\",\n          \"ACCOUNTKEY\": \"\",\n          \"ACCOUNT_KE\": \"\",\n          \"WT_WITHCD\": \"\",\n          \"STRUCTCOND\": \"\",\n          \"FACTCONBAS\": \"0.0000000000000000E+00\",\n          \"CONDCOINHD\": \"00\"\n        },\n        {\n          \"ITM_NUMBER\": \"000010\",\n          \"COND_ST_NO\": \"600\",\n          \"COND_COUNT\": \"01\",\n          \"COND_TYPE\": \"IBRX\",\n          \"COND_VALUE\": \"100.000000000\",\n          \"CURRENCY\": \"\",\n          \"COND_UNIT\": \"\",\n          \"COND_P_UNT\": \"0\",\n          \"CURR_ISO\": \"\",\n          \"CD_UNT_ISO\": \"\",\n          \"REFOBJTYPE\": \"\",\n          \"REFOBJKEY\": \"\",\n          \"REFLOGSYS\": \"\",\n          \"APPLICATIO\": \"V\",\n          \"CONPRICDAT\": \"2020-12-14\",\n          \"CALCTYPCON\": \"A\",\n          \"CONBASEVAL\": \"164.690000000\",\n          \"CONEXCHRAT\": \"0.00000\",\n          \"NUMCONVERT\": \"0\",\n          \"DENOMINATO\": \"0\",\n          \"CONDTYPE\": \"1\",\n          \"STAT_CON\": \"X\",\n          \"SCALETYPE\": \"\",\n          \"ACCRUALS\": \"\",\n          \"CONINVOLST\": \"\",\n          \"CONDORIGIN\": \"A\",\n          \"GROUPCOND\": \"\",\n          \"COND_UPDAT\": \"\",\n          \"ACCESS_SEQ\": \"01\",\n          \"CONDCOUNT\": \"01\",\n          \"ROUNDOFFDI\": \"0.000000000\",\n          \"CONDVALUE\": \"164.690000000\",\n          \"CURRENCY_2\": \"BRL\",\n          \"CURR_ISO_2\": \"BRL\",\n          \"CONDCNTRL\": \"A\",\n          \"CONDISACTI\": \"\",\n          \"CONDCLASS\": \"D\",\n          \"FACTBASVAL\": \"0.0000000000000000E+00\",\n          \"SCALEBASIN\": \"\",\n          \"SCALBASVAL\": \"0.000000000\",\n          \"UNITMEASUR\": \"\",\n          \"ISO_UNIT\": \"\",\n          \"CURRENCKEY\": \"\",\n          \"CURRENISO\": \"\",\n          \"CONDINCOMP\": \"\",\n          \"CONDCONFIG\": \"\",\n          \"CONDCHAMAN\": \"\",\n          \"COND_NO\": \"0035482469\",\n          \"TAX_CODE\": \"SD\",\n          \"VARCOND\": \"\",\n          \"ACCOUNTKEY\": \"\",\n          \"ACCOUNT_KE\": \"\",\n          \"WT_WITHCD\": \"\",\n          \"STRUCTCOND\": \"\",\n          \"FACTCONBAS\": \"0.0000000000000000E+00\",\n          \"CONDCOINHD\": \"00\"\n        },\n        {\n          \"ITM_NUMBER\": \"000010\",\n          \"COND_ST_NO\": \"610\",\n          \"COND_COUNT\": \"01\",\n          \"COND_TYPE\": \"BX10\",\n          \"COND_VALUE\": \"0.000000000\",\n          \"CURRENCY\": \"BRL\",\n          \"COND_UNIT\": \"\",\n          \"COND_P_UNT\": \"0\",\n          \"CURR_ISO\": \"BRL\",\n          \"CD_UNT_ISO\": \"\",\n          \"REFOBJTYPE\": \"\",\n          \"REFOBJKEY\": \"\",\n          \"REFLOGSYS\": \"\",\n          \"APPLICATIO\": \"V\",\n          \"CONPRICDAT\": \"2020-12-14\",\n          \"CALCTYPCON\": \"B\",\n          \"CONBASEVAL\": \"329.380000000\",\n          \"CONEXCHRAT\": \"1.00000\",\n          \"NUMCONVERT\": \"0\",\n          \"DENOMINATO\": \"0\",\n          \"CONDTYPE\": \"1\",\n          \"STAT_CON\": \"X\",\n          \"SCALETYPE\": \"\",\n          \"ACCRUALS\": \"\",\n          \"CONINVOLST\": \"\",\n          \"CONDORIGIN\": \"A\",\n          \"GROUPCOND\": \"\",\n          \"COND_UPDAT\": \"\",\n          \"ACCESS_SEQ\": \"00\",\n          \"CONDCOUNT\": \"00\",\n          \"ROUNDOFFDI\": \"0.000000000\",\n          \"CONDVALUE\": \"172.920000000\",\n          \"CURRENCY_2\": \"BRL\",\n          \"CURR_ISO_2\": \"BRL\",\n          \"CONDCNTRL\": \"A\",\n          \"CONDISACTI\": \"\",\n          \"CONDCLASS\": \"A\",\n          \"FACTBASVAL\": \"0.0000000000000000E+00\",\n          \"SCALEBASIN\": \"\",\n          \"SCALBASVAL\": \"0.000000000\",\n          \"UNITMEASUR\": \"\",\n          \"ISO_UNIT\": \"\",\n          \"CURRENCKEY\": \"\",\n          \"CURRENISO\": \"\",\n          \"CONDINCOMP\": \"\",\n          \"CONDCONFIG\": \"\",\n          \"CONDCHAMAN\": \"\",\n          \"COND_NO\": \"\",\n          \"TAX_CODE\": \"\",\n          \"VARCOND\": \"\",\n          \"ACCOUNTKEY\": \"\",\n          \"ACCOUNT_KE\": \"\",\n          \"WT_WITHCD\": \"\",\n          \"STRUCTCOND\": \"\",\n          \"FACTCONBAS\": \"0.0000000000000000E+00\",\n          \"CONDCOINHD\": \"00\"\n        },\n        {\n          \"ITM_NUMBER\": \"000010\",\n          \"COND_ST_NO\": \"612\",\n          \"COND_COUNT\": \"01\",\n          \"COND_TYPE\": \"BX11\",\n          \"COND_VALUE\": \"0.000000000\",\n          \"CURRENCY\": \"BRL\",\n          \"COND_UNIT\": \"\",\n          \"COND_P_UNT\": \"0\",\n          \"CURR_ISO\": \"BRL\",\n          \"CD_UNT_ISO\": \"\",\n          \"REFOBJTYPE\": \"\",\n          \"REFOBJKEY\": \"\",\n          \"REFLOGSYS\": \"\",\n          \"APPLICATIO\": \"V\",\n          \"CONPRICDAT\": \"2020-12-14\",\n          \"CALCTYPCON\": \"B\",\n          \"CONBASEVAL\": \"502.300000000\",\n          \"CONEXCHRAT\": \"1.00000\",\n          \"NUMCONVERT\": \"0\",\n          \"DENOMINATO\": \"0\",\n          \"CONDTYPE\": \"1\",\n          \"STAT_CON\": \"X\",\n          \"SCALETYPE\": \"\",\n          \"ACCRUALS\": \"\",\n          \"CONINVOLST\": \"\",\n          \"CONDORIGIN\": \"A\",\n          \"GROUPCOND\": \"\",\n          \"COND_UPDAT\": \"\",\n          \"ACCESS_SEQ\": \"00\",\n          \"CONDCOUNT\": \"00\",\n          \"ROUNDOFFDI\": \"0.000000000\",\n          \"CONDVALUE\": \"0.000000000\",\n          \"CURRENCY_2\": \"BRL\",\n          \"CURR_ISO_2\": \"BRL\",\n          \"CONDCNTRL\": \"A\",\n          \"CONDISACTI\": \"\",\n          \"CONDCLASS\": \"A\",\n          \"FACTBASVAL\": \"0.0000000000000000E+00\",\n          \"SCALEBASIN\": \"\",\n          \"SCALBASVAL\": \"0.000000000\",\n          \"UNITMEASUR\": \"\",\n          \"ISO_UNIT\": \"\",\n          \"CURRENCKEY\": \"\",\n          \"CURRENISO\": \"\",\n          \"CONDINCOMP\": \"\",\n          \"CONDCONFIG\": \"\",\n          \"CONDCHAMAN\": \"\",\n          \"COND_NO\": \"\",\n          \"TAX_CODE\": \"\",\n          \"VARCOND\": \"\",\n          \"ACCOUNTKEY\": \"\",\n          \"ACCOUNT_KE\": \"\",\n          \"WT_WITHCD\": \"\",\n          \"STRUCTCOND\": \"\",\n          \"FACTCONBAS\": \"0.0000000000000000E+00\",\n          \"CONDCOINHD\": \"00\"\n        },\n        {\n          \"ITM_NUMBER\": \"000010\",\n          \"COND_ST_NO\": \"614\",\n          \"COND_COUNT\": \"01\",\n          \"COND_TYPE\": \"BX12\",\n          \"COND_VALUE\": \"0.000000000\",\n          \"CURRENCY\": \"BRL\",\n          \"COND_UNIT\": \"\",\n          \"COND_P_UNT\": \"0\",\n          \"CURR_ISO\": \"BRL\",\n          \"CD_UNT_ISO\": \"\",\n          \"REFOBJTYPE\": \"\",\n          \"REFOBJKEY\": \"\",\n          \"REFLOGSYS\": \"\",\n          \"APPLICATIO\": \"V\",\n          \"CONPRICDAT\": \"2020-12-14\",\n          \"CALCTYPCON\": \"B\",\n          \"CONBASEVAL\": \"502.300000000\",\n          \"CONEXCHRAT\": \"1.00000\",\n          \"NUMCONVERT\": \"0\",\n          \"DENOMINATO\": \"0\",\n          \"CONDTYPE\": \"1\",\n          \"STAT_CON\": \"X\",\n          \"SCALETYPE\": \"\",\n          \"ACCRUALS\": \"\",\n          \"CONINVOLST\": \"\",\n          \"CONDORIGIN\": \"A\",\n          \"GROUPCOND\": \"\",\n          \"COND_UPDAT\": \"\",\n          \"ACCESS_SEQ\": \"00\",\n          \"CONDCOUNT\": \"00\",\n          \"ROUNDOFFDI\": \"0.000000000\",\n          \"CONDVALUE\": \"0.000000000\",\n          \"CURRENCY_2\": \"BRL\",\n          \"CURR_ISO_2\": \"BRL\",\n          \"CONDCNTRL\": \"A\",\n          \"CONDISACTI\": \"\",\n          \"CONDCLASS\": \"A\",\n          \"FACTBASVAL\": \"0.0000000000000000E+00\",\n          \"SCALEBASIN\": \"\",\n          \"SCALBASVAL\": \"0.000000000\",\n          \"UNITMEASUR\": \"\",\n          \"ISO_UNIT\": \"\",\n          \"CURRENCKEY\": \"\",\n          \"CURRENISO\": \"\",\n          \"CONDINCOMP\": \"\",\n          \"CONDCONFIG\": \"\",\n          \"CONDCHAMAN\": \"\",\n          \"COND_NO\": \"\",\n          \"TAX_CODE\": \"\",\n          \"VARCOND\": \"\",\n          \"ACCOUNTKEY\": \"\",\n          \"ACCOUNT_KE\": \"\",\n          \"WT_WITHCD\": \"\",\n          \"STRUCTCOND\": \"\",\n          \"FACTCONBAS\": \"0.0000000000000000E+00\",\n          \"CONDCOINHD\": \"00\"\n        },\n        {\n          \"ITM_NUMBER\": \"000010\",\n          \"COND_ST_NO\": \"616\",\n          \"COND_COUNT\": \"01\",\n          \"COND_TYPE\": \"BX13\",\n          \"COND_VALUE\": \"12.000000000\",\n          \"CURRENCY\": \"\",\n          \"COND_UNIT\": \"\",\n          \"COND_P_UNT\": \"0\",\n          \"CURR_ISO\": \"\",\n          \"CD_UNT_ISO\": \"\",\n          \"REFOBJTYPE\": \"\",\n          \"REFOBJKEY\": \"\",\n          \"REFLOGSYS\": \"\",\n          \"APPLICATIO\": \"V\",\n          \"CONPRICDAT\": \"2020-12-14\",\n          \"CALCTYPCON\": \"A\",\n          \"CONBASEVAL\": \"172.920000000\",\n          \"CONEXCHRAT\": \"0.00000\",\n          \"NUMCONVERT\": \"0\",\n          \"DENOMINATO\": \"0\",\n          \"CONDTYPE\": \"D\",\n          \"STAT_CON\": \"\",\n          \"SCALETYPE\": \"\",\n          \"ACCRUALS\": \"\",\n          \"CONINVOLST\": \"\",\n          \"CONDORIGIN\": \"A\",\n          \"GROUPCOND\": \"\",\n          \"COND_UPDAT\": \"\",\n          \"ACCESS_SEQ\": \"01\",\n          \"CONDCOUNT\": \"01\",\n          \"ROUNDOFFDI\": \"0.000000000\",\n          \"CONDVALUE\": \"20.750000000\",\n          \"CURRENCY_2\": \"BRL\",\n          \"CURR_ISO_2\": \"BRL\",\n          \"CONDCNTRL\": \"A\",\n          \"CONDISACTI\": \"\",\n          \"CONDCLASS\": \"D\",\n          \"FACTBASVAL\": \"0.0000000000000000E+00\",\n          \"SCALEBASIN\": \"\",\n          \"SCALBASVAL\": \"0.000000000\",\n          \"UNITMEASUR\": \"\",\n          \"ISO_UNIT\": \"\",\n          \"CURRENCKEY\": \"\",\n          \"CURRENISO\": \"\",\n          \"CONDINCOMP\": \"\",\n          \"CONDCONFIG\": \"\",\n          \"CONDCHAMAN\": \"\",\n          \"COND_NO\": \"0035482469\",\n          \"TAX_CODE\": \"SD\",\n          \"VARCOND\": \"\",\n          \"ACCOUNTKEY\": \"\",\n          \"ACCOUNT_KE\": \"\",\n          \"WT_WITHCD\": \"\",\n          \"STRUCTCOND\": \"\",\n          \"FACTCONBAS\": \"0.0000000000000000E+00\",\n          \"CONDCOINHD\": \"00\"\n        },\n        {\n          \"ITM_NUMBER\": \"000010\",\n          \"COND_ST_NO\": \"617\",\n          \"COND_COUNT\": \"01\",\n          \"COND_TYPE\": \"BXZF\",\n          \"COND_VALUE\": \"0.000000000\",\n          \"CURRENCY\": \"\",\n          \"COND_UNIT\": \"\",\n          \"COND_P_UNT\": \"0\",\n          \"CURR_ISO\": \"\",\n          \"CD_UNT_ISO\": \"\",\n          \"REFOBJTYPE\": \"\",\n          \"REFOBJKEY\": \"\",\n          \"REFLOGSYS\": \"\",\n          \"APPLICATIO\": \"V\",\n          \"CONPRICDAT\": \"2020-12-14\",\n          \"CALCTYPCON\": \"A\",\n          \"CONBASEVAL\": \"0.000000000\",\n          \"CONEXCHRAT\": \"0.00000\",\n          \"NUMCONVERT\": \"0\",\n          \"DENOMINATO\": \"0\",\n          \"CONDTYPE\": \"D\",\n          \"STAT_CON\": \"\",\n          \"SCALETYPE\": \"\",\n          \"ACCRUALS\": \"\",\n          \"CONINVOLST\": \"\",\n          \"CONDORIGIN\": \"A\",\n          \"GROUPCOND\": \"\",\n          \"COND_UPDAT\": \"\",\n          \"ACCESS_SEQ\": \"01\",\n          \"CONDCOUNT\": \"01\",\n          \"ROUNDOFFDI\": \"0.000000000\",\n          \"CONDVALUE\": \"0.000000000\",\n          \"CURRENCY_2\": \"BRL\",\n          \"CURR_ISO_2\": \"BRL\",\n          \"CONDCNTRL\": \"A\",\n          \"CONDISACTI\": \"\",\n          \"CONDCLASS\": \"D\",\n          \"FACTBASVAL\": \"0.0000000000000000E+00\",\n          \"SCALEBASIN\": \"\",\n          \"SCALBASVAL\": \"0.000000000\",\n          \"UNITMEASUR\": \"\",\n          \"ISO_UNIT\": \"\",\n          \"CURRENCKEY\": \"\",\n          \"CURRENISO\": \"\",\n          \"CONDINCOMP\": \"\",\n          \"CONDCONFIG\": \"\",\n          \"CONDCHAMAN\": \"\",\n          \"COND_NO\": \"0035482469\",\n          \"TAX_CODE\": \"SD\",\n          \"VARCOND\": \"\",\n          \"ACCOUNTKEY\": \"\",\n          \"ACCOUNT_KE\": \"\",\n          \"WT_WITHCD\": \"\",\n          \"STRUCTCOND\": \"\",\n          \"FACTCONBAS\": \"0.0000000000000000E+00\",\n          \"CONDCOINHD\": \"00\"\n        },\n        {\n          \"ITM_NUMBER\": \"000010\",\n          \"COND_ST_NO\": \"618\",\n          \"COND_COUNT\": \"01\",\n          \"COND_TYPE\": \"BX14\",\n          \"COND_VALUE\": \"0.000000000\",\n          \"CURRENCY\": \"BRL\",\n          \"COND_UNIT\": \"\",\n          \"COND_P_UNT\": \"0\",\n          \"CURR_ISO\": \"BRL\",\n          \"CD_UNT_ISO\": \"\",\n          \"REFOBJTYPE\": \"\",\n          \"REFOBJKEY\": \"\",\n          \"REFLOGSYS\": \"\",\n          \"APPLICATIO\": \"V\",\n          \"CONPRICDAT\": \"2020-12-14\",\n          \"CALCTYPCON\": \"B\",\n          \"CONBASEVAL\": \"523.050000000\",\n          \"CONEXCHRAT\": \"1.00000\",\n          \"NUMCONVERT\": \"0\",\n          \"DENOMINATO\": \"0\",\n          \"CONDTYPE\": \"1\",\n          \"STAT_CON\": \"X\",\n          \"SCALETYPE\": \"\",\n          \"ACCRUALS\": \"\",\n          \"CONINVOLST\": \"\",\n          \"CONDORIGIN\": \"A\",\n          \"GROUPCOND\": \"\",\n          \"COND_UPDAT\": \"\",\n          \"ACCESS_SEQ\": \"00\",\n          \"CONDCOUNT\": \"00\",\n          \"ROUNDOFFDI\": \"0.000000000\",\n          \"CONDVALUE\": \"0.000000000\",\n          \"CURRENCY_2\": \"BRL\",\n          \"CURR_ISO_2\": \"BRL\",\n          \"CONDCNTRL\": \"A\",\n          \"CONDISACTI\": \"\",\n          \"CONDCLASS\": \"A\",\n          \"FACTBASVAL\": \"0.0000000000000000E+00\",\n          \"SCALEBASIN\": \"\",\n          \"SCALBASVAL\": \"0.000000000\",\n          \"UNITMEASUR\": \"\",\n          \"ISO_UNIT\": \"\",\n          \"CURRENCKEY\": \"\",\n          \"CURRENISO\": \"\",\n          \"CONDINCOMP\": \"\",\n          \"CONDCONFIG\": \"\",\n          \"CONDCHAMAN\": \"\",\n          \"COND_NO\": \"\",\n          \"TAX_CODE\": \"\",\n          \"VARCOND\": \"\",\n          \"ACCOUNTKEY\": \"\",\n          \"ACCOUNT_KE\": \"\",\n          \"WT_WITHCD\": \"\",\n          \"STRUCTCOND\": \"\",\n          \"FACTCONBAS\": \"0.0000000000000000E+00\",\n          \"CONDCOINHD\": \"00\"\n        },\n        {\n          \"ITM_NUMBER\": \"000010\",\n          \"COND_ST_NO\": \"620\",\n          \"COND_COUNT\": \"01\",\n          \"COND_TYPE\": \"BX15\",\n          \"COND_VALUE\": \"100.000000000\",\n          \"CURRENCY\": \"\",\n          \"COND_UNIT\": \"\",\n          \"COND_P_UNT\": \"0\",\n          \"CURR_ISO\": \"\",\n          \"CD_UNT_ISO\": \"\",\n          \"REFOBJTYPE\": \"\",\n          \"REFOBJKEY\": \"\",\n          \"REFLOGSYS\": \"\",\n          \"APPLICATIO\": \"V\",\n          \"CONPRICDAT\": \"2020-12-14\",\n          \"CALCTYPCON\": \"A\",\n          \"CONBASEVAL\": \"523.050000000\",\n          \"CONEXCHRAT\": \"0.00000\",\n          \"NUMCONVERT\": \"0\",\n          \"DENOMINATO\": \"0\",\n          \"CONDTYPE\": \"D\",\n          \"STAT_CON\": \"X\",\n          \"SCALETYPE\": \"\",\n          \"ACCRUALS\": \"\",\n          \"CONINVOLST\": \"\",\n          \"CONDORIGIN\": \"A\",\n          \"GROUPCOND\": \"\",\n          \"COND_UPDAT\": \"\",\n          \"ACCESS_SEQ\": \"01\",\n          \"CONDCOUNT\": \"01\",\n          \"ROUNDOFFDI\": \"0.000000000\",\n          \"CONDVALUE\": \"0.000000000\",\n          \"CURRENCY_2\": \"BRL\",\n          \"CURR_ISO_2\": \"BRL\",\n          \"CONDCNTRL\": \"A\",\n          \"CONDISACTI\": \"\",\n          \"CONDCLASS\": \"D\",\n          \"FACTBASVAL\": \"0.0000000000000000E+00\",\n          \"SCALEBASIN\": \"\",\n          \"SCALBASVAL\": \"0.000000000\",\n          \"UNITMEASUR\": \"\",\n          \"ISO_UNIT\": \"\",\n          \"CURRENCKEY\": \"\",\n          \"CURRENISO\": \"\",\n          \"CONDINCOMP\": \"\",\n          \"CONDCONFIG\": \"\",\n          \"CONDCHAMAN\": \"\",\n          \"COND_NO\": \"0035482469\",\n          \"TAX_CODE\": \"SD\",\n          \"VARCOND\": \"\",\n          \"ACCOUNTKEY\": \"\",\n          \"ACCOUNT_KE\": \"\",\n          \"WT_WITHCD\": \"\",\n          \"STRUCTCOND\": \"\",\n          \"FACTCONBAS\": \"0.0000000000000000E+00\",\n          \"CONDCOINHD\": \"00\"\n        },\n        {\n          \"ITM_NUMBER\": \"000010\",\n          \"COND_ST_NO\": \"622\",\n          \"COND_COUNT\": \"01\",\n          \"COND_TYPE\": \"BX16\",\n          \"COND_VALUE\": \"0.000000000\",\n          \"CURRENCY\": \"BRL\",\n          \"COND_UNIT\": \"\",\n          \"COND_P_UNT\": \"0\",\n          \"CURR_ISO\": \"BRL\",\n          \"CD_UNT_ISO\": \"\",\n          \"REFOBJTYPE\": \"\",\n          \"REFOBJKEY\": \"\",\n          \"REFLOGSYS\": \"\",\n          \"APPLICATIO\": \"V\",\n          \"CONPRICDAT\": \"2020-12-14\",\n          \"CALCTYPCON\": \"B\",\n          \"CONBASEVAL\": \"523.050000000\",\n          \"CONEXCHRAT\": \"1.00000\",\n          \"NUMCONVERT\": \"0\",\n          \"DENOMINATO\": \"0\",\n          \"CONDTYPE\": \"1\",\n          \"STAT_CON\": \"X\",\n          \"SCALETYPE\": \"\",\n          \"ACCRUALS\": \"\",\n          \"CONINVOLST\": \"\",\n          \"CONDORIGIN\": \"A\",\n          \"GROUPCOND\": \"\",\n          \"COND_UPDAT\": \"\",\n          \"ACCESS_SEQ\": \"00\",\n          \"CONDCOUNT\": \"00\",\n          \"ROUNDOFFDI\": \"0.000000000\",\n          \"CONDVALUE\": \"120.000000000\",\n          \"CURRENCY_2\": \"BRL\",\n          \"CURR_ISO_2\": \"BRL\",\n          \"CONDCNTRL\": \"A\",\n          \"CONDISACTI\": \"\",\n          \"CONDCLASS\": \"A\",\n          \"FACTBASVAL\": \"0.0000000000000000E+00\",\n          \"SCALEBASIN\": \"\",\n          \"SCALBASVAL\": \"0.000000000\",\n          \"UNITMEASUR\": \"\",\n          \"ISO_UNIT\": \"\",\n          \"CURRENCKEY\": \"\",\n          \"CURRENISO\": \"\",\n          \"CONDINCOMP\": \"\",\n          \"CONDCONFIG\": \"\",\n          \"CONDCHAMAN\": \"\",\n          \"COND_NO\": \"\",\n          \"TAX_CODE\": \"\",\n          \"VARCOND\": \"\",\n          \"ACCOUNTKEY\": \"\",\n          \"ACCOUNT_KE\": \"\",\n          \"WT_WITHCD\": \"\",\n          \"STRUCTCOND\": \"\",\n          \"FACTCONBAS\": \"0.0000000000000000E+00\",\n          \"CONDCOINHD\": \"00\"\n        },\n        {\n          \"ITM_NUMBER\": \"000010\",\n          \"COND_ST_NO\": \"623\",\n          \"COND_COUNT\": \"01\",\n          \"COND_TYPE\": \"BX17\",\n          \"COND_VALUE\": \"-100.000000000\",\n          \"CURRENCY\": \"\",\n          \"COND_UNIT\": \"\",\n          \"COND_P_UNT\": \"0\",\n          \"CURR_ISO\": \"\",\n          \"CD_UNT_ISO\": \"\",\n          \"REFOBJTYPE\": \"\",\n          \"REFOBJKEY\": \"\",\n          \"REFLOGSYS\": \"\",\n          \"APPLICATIO\": \"V\",\n          \"CONPRICDAT\": \"2020-12-14\",\n          \"CALCTYPCON\": \"A\",\n          \"CONBASEVAL\": \"20.750000000\",\n          \"CONEXCHRAT\": \"0.00000\",\n          \"NUMCONVERT\": \"0\",\n          \"DENOMINATO\": \"0\",\n          \"CONDTYPE\": \"\",\n          \"STAT_CON\": \"\",\n          \"SCALETYPE\": \"\",\n          \"ACCRUALS\": \"\",\n          \"CONINVOLST\": \"\",\n          \"CONDORIGIN\": \"A\",\n          \"GROUPCOND\": \"\",\n          \"COND_UPDAT\": \"\",\n          \"ACCESS_SEQ\": \"01\",\n          \"CONDCOUNT\": \"01\",\n          \"ROUNDOFFDI\": \"0.000000000\",\n          \"CONDVALUE\": \"-20.750000000\",\n          \"CURRENCY_2\": \"BRL\",\n          \"CURR_ISO_2\": \"BRL\",\n          \"CONDCNTRL\": \"A\",\n          \"CONDISACTI\": \"\",\n          \"CONDCLASS\": \"A\",\n          \"FACTBASVAL\": \"0.0000000000000000E+00\",\n          \"SCALEBASIN\": \"\",\n          \"SCALBASVAL\": \"0.000000000\",\n          \"UNITMEASUR\": \"\",\n          \"ISO_UNIT\": \"\",\n          \"CURRENCKEY\": \"\",\n          \"CURRENISO\": \"\",\n          \"CONDINCOMP\": \"\",\n          \"CONDCONFIG\": \"\",\n          \"CONDCHAMAN\": \"\",\n          \"COND_NO\": \"0011401268\",\n          \"TAX_CODE\": \"\",\n          \"VARCOND\": \"\",\n          \"ACCOUNTKEY\": \"\",\n          \"ACCOUNT_KE\": \"\",\n          \"WT_WITHCD\": \"\",\n          \"STRUCTCOND\": \"\",\n          \"FACTCONBAS\": \"0.0000000000000000E+00\",\n          \"CONDCOINHD\": \"00\"\n        },\n        {\n          \"ITM_NUMBER\": \"000010\",\n          \"COND_ST_NO\": \"624\",\n          \"COND_COUNT\": \"01\",\n          \"COND_TYPE\": \"BX20\",\n          \"COND_VALUE\": \"0.000000000\",\n          \"CURRENCY\": \"BRL\",\n          \"COND_UNIT\": \"\",\n          \"COND_P_UNT\": \"0\",\n          \"CURR_ISO\": \"BRL\",\n          \"CD_UNT_ISO\": \"\",\n          \"REFOBJTYPE\": \"\",\n          \"REFOBJKEY\": \"\",\n          \"REFLOGSYS\": \"\",\n          \"APPLICATIO\": \"V\",\n          \"CONPRICDAT\": \"2020-12-14\",\n          \"CALCTYPCON\": \"B\",\n          \"CONBASEVAL\": \"622.300000000\",\n          \"CONEXCHRAT\": \"1.00000\",\n          \"NUMCONVERT\": \"0\",\n          \"DENOMINATO\": \"0\",\n          \"CONDTYPE\": \"1\",\n          \"STAT_CON\": \"X\",\n          \"SCALETYPE\": \"\",\n          \"ACCRUALS\": \"\",\n          \"CONINVOLST\": \"\",\n          \"CONDORIGIN\": \"A\",\n          \"GROUPCOND\": \"\",\n          \"COND_UPDAT\": \"\",\n          \"ACCESS_SEQ\": \"00\",\n          \"CONDCOUNT\": \"00\",\n          \"ROUNDOFFDI\": \"0.000000000\",\n          \"CONDVALUE\": \"164.690000000\",\n          \"CURRENCY_2\": \"BRL\",\n          \"CURR_ISO_2\": \"BRL\",\n          \"CONDCNTRL\": \"A\",\n          \"CONDISACTI\": \"\",\n          \"CONDCLASS\": \"A\",\n          \"FACTBASVAL\": \"0.0000000000000000E+00\",\n          \"SCALEBASIN\": \"\",\n          \"SCALBASVAL\": \"0.000000000\",\n          \"UNITMEASUR\": \"\",\n          \"ISO_UNIT\": \"\",\n          \"CURRENCKEY\": \"\",\n          \"CURRENISO\": \"\",\n          \"CONDINCOMP\": \"\",\n          \"CONDCONFIG\": \"\",\n          \"CONDCHAMAN\": \"\",\n          \"COND_NO\": \"\",\n          \"TAX_CODE\": \"\",\n          \"VARCOND\": \"\",\n          \"ACCOUNTKEY\": \"\",\n          \"ACCOUNT_KE\": \"\",\n          \"WT_WITHCD\": \"\",\n          \"STRUCTCOND\": \"\",\n          \"FACTCONBAS\": \"0.0000000000000000E+00\",\n          \"CONDCOINHD\": \"00\"\n        },\n        {\n          \"ITM_NUMBER\": \"000010\",\n          \"COND_ST_NO\": \"626\",\n          \"COND_COUNT\": \"01\",\n          \"COND_TYPE\": \"BX21\",\n          \"COND_VALUE\": \"0.000000000\",\n          \"CURRENCY\": \"BRL\",\n          \"COND_UNIT\": \"\",\n          \"COND_P_UNT\": \"0\",\n          \"CURR_ISO\": \"BRL\",\n          \"CD_UNT_ISO\": \"\",\n          \"REFOBJTYPE\": \"\",\n          \"REFOBJKEY\": \"\",\n          \"REFLOGSYS\": \"\",\n          \"APPLICATIO\": \"V\",\n          \"CONPRICDAT\": \"2020-12-14\",\n          \"CALCTYPCON\": \"B\",\n          \"CONBASEVAL\": \"786.990000000\",\n          \"CONEXCHRAT\": \"1.00000\",\n          \"NUMCONVERT\": \"0\",\n          \"DENOMINATO\": \"0\",\n          \"CONDTYPE\": \"1\",\n          \"STAT_CON\": \"X\",\n          \"SCALETYPE\": \"\",\n          \"ACCRUALS\": \"\",\n          \"CONINVOLST\": \"\",\n          \"CONDORIGIN\": \"A\",\n          \"GROUPCOND\": \"\",\n          \"COND_UPDAT\": \"\",\n          \"ACCESS_SEQ\": \"00\",\n          \"CONDCOUNT\": \"00\",\n          \"ROUNDOFFDI\": \"0.000000000\",\n          \"CONDVALUE\": \"0.000000000\",\n          \"CURRENCY_2\": \"BRL\",\n          \"CURR_ISO_2\": \"BRL\",\n          \"CONDCNTRL\": \"A\",\n          \"CONDISACTI\": \"\",\n          \"CONDCLASS\": \"A\",\n          \"FACTBASVAL\": \"0.0000000000000000E+00\",\n          \"SCALEBASIN\": \"\",\n          \"SCALBASVAL\": \"0.000000000\",\n          \"UNITMEASUR\": \"\",\n          \"ISO_UNIT\": \"\",\n          \"CURRENCKEY\": \"\",\n          \"CURRENISO\": \"\",\n          \"CONDINCOMP\": \"\",\n          \"CONDCONFIG\": \"\",\n          \"CONDCHAMAN\": \"\",\n          \"COND_NO\": \"\",\n          \"TAX_CODE\": \"\",\n          \"VARCOND\": \"\",\n          \"ACCOUNTKEY\": \"\",\n          \"ACCOUNT_KE\": \"\",\n          \"WT_WITHCD\": \"\",\n          \"STRUCTCOND\": \"\",\n          \"FACTCONBAS\": \"0.0000000000000000E+00\",\n          \"CONDCOINHD\": \"00\"\n        },\n        {\n          \"ITM_NUMBER\": \"000010\",\n          \"COND_ST_NO\": \"628\",\n          \"COND_COUNT\": \"01\",\n          \"COND_TYPE\": \"BX22\",\n          \"COND_VALUE\": \"0.000000000\",\n          \"CURRENCY\": \"BRL\",\n          \"COND_UNIT\": \"\",\n          \"COND_P_UNT\": \"0\",\n          \"CURR_ISO\": \"BRL\",\n          \"CD_UNT_ISO\": \"\",\n          \"REFOBJTYPE\": \"\",\n          \"REFOBJKEY\": \"\",\n          \"REFLOGSYS\": \"\",\n          \"APPLICATIO\": \"V\",\n          \"CONPRICDAT\": \"2020-12-14\",\n          \"CALCTYPCON\": \"B\",\n          \"CONBASEVAL\": \"786.990000000\",\n          \"CONEXCHRAT\": \"1.00000\",\n          \"NUMCONVERT\": \"0\",\n          \"DENOMINATO\": \"0\",\n          \"CONDTYPE\": \"1\",\n          \"STAT_CON\": \"X\",\n          \"SCALETYPE\": \"\",\n          \"ACCRUALS\": \"\",\n          \"CONINVOLST\": \"\",\n          \"CONDORIGIN\": \"A\",\n          \"GROUPCOND\": \"\",\n          \"COND_UPDAT\": \"\",\n          \"ACCESS_SEQ\": \"00\",\n          \"CONDCOUNT\": \"00\",\n          \"ROUNDOFFDI\": \"0.000000000\",\n          \"CONDVALUE\": \"0.000000000\",\n          \"CURRENCY_2\": \"BRL\",\n          \"CURR_ISO_2\": \"BRL\",\n          \"CONDCNTRL\": \"A\",\n          \"CONDISACTI\": \"\",\n          \"CONDCLASS\": \"A\",\n          \"FACTBASVAL\": \"0.0000000000000000E+00\",\n          \"SCALEBASIN\": \"\",\n          \"SCALBASVAL\": \"0.000000000\",\n          \"UNITMEASUR\": \"\",\n          \"ISO_UNIT\": \"\",\n          \"CURRENCKEY\": \"\",\n          \"CURRENISO\": \"\",\n          \"CONDINCOMP\": \"\",\n          \"CONDCONFIG\": \"\",\n          \"CONDCHAMAN\": \"\",\n          \"COND_NO\": \"\",\n          \"TAX_CODE\": \"\",\n          \"VARCOND\": \"\",\n          \"ACCOUNTKEY\": \"\",\n          \"ACCOUNT_KE\": \"\",\n          \"WT_WITHCD\": \"\",\n          \"STRUCTCOND\": \"\",\n          \"FACTCONBAS\": \"0.0000000000000000E+00\",\n          \"CONDCOINHD\": \"00\"\n        },\n        {\n          \"ITM_NUMBER\": \"000010\",\n          \"COND_ST_NO\": \"630\",\n          \"COND_COUNT\": \"01\",\n          \"COND_TYPE\": \"BX23\",\n          \"COND_VALUE\": \"100.000000000\",\n          \"CURRENCY\": \"\",\n          \"COND_UNIT\": \"\",\n          \"COND_P_UNT\": \"0\",\n          \"CURR_ISO\": \"\",\n          \"CD_UNT_ISO\": \"\",\n          \"REFOBJTYPE\": \"\",\n          \"REFOBJKEY\": \"\",\n          \"REFLOGSYS\": \"\",\n          \"APPLICATIO\": \"V\",\n          \"CONPRICDAT\": \"2020-12-14\",\n          \"CALCTYPCON\": \"A\",\n          \"CONBASEVAL\": \"786.990000000\",\n          \"CONEXCHRAT\": \"0.00000\",\n          \"NUMCONVERT\": \"0\",\n          \"DENOMINATO\": \"0\",\n          \"CONDTYPE\": \"D\",\n          \"STAT_CON\": \"\",\n          \"SCALETYPE\": \"\",\n          \"ACCRUALS\": \"\",\n          \"CONINVOLST\": \"\",\n          \"CONDORIGIN\": \"A\",\n          \"GROUPCOND\": \"\",\n          \"COND_UPDAT\": \"\",\n          \"ACCESS_SEQ\": \"01\",\n          \"CONDCOUNT\": \"01\",\n          \"ROUNDOFFDI\": \"0.000000000\",\n          \"CONDVALUE\": \"8.230000000\",\n          \"CURRENCY_2\": \"BRL\",\n          \"CURR_ISO_2\": \"BRL\",\n          \"CONDCNTRL\": \"A\",\n          \"CONDISACTI\": \"\",\n          \"CONDCLASS\": \"D\",\n          \"FACTBASVAL\": \"0.0000000000000000E+00\",\n          \"SCALEBASIN\": \"\",\n          \"SCALBASVAL\": \"0.000000000\",\n          \"UNITMEASUR\": \"\",\n          \"ISO_UNIT\": \"\",\n          \"CURRENCKEY\": \"\",\n          \"CURRENISO\": \"\",\n          \"CONDINCOMP\": \"\",\n          \"CONDCONFIG\": \"\",\n          \"CONDCHAMAN\": \"\",\n          \"COND_NO\": \"0035482469\",\n          \"TAX_CODE\": \"SD\",\n          \"VARCOND\": \"\",\n          \"ACCOUNTKEY\": \"\",\n          \"ACCOUNT_KE\": \"\",\n          \"WT_WITHCD\": \"\",\n          \"STRUCTCOND\": \"\",\n          \"FACTCONBAS\": \"0.0000000000000000E+00\",\n          \"CONDCOINHD\": \"00\"\n        },\n        {\n          \"ITM_NUMBER\": \"000010\",\n          \"COND_ST_NO\": \"632\",\n          \"COND_COUNT\": \"01\",\n          \"COND_TYPE\": \"BX24\",\n          \"COND_VALUE\": \"0.000000000\",\n          \"CURRENCY\": \"BRL\",\n          \"COND_UNIT\": \"\",\n          \"COND_P_UNT\": \"0\",\n          \"CURR_ISO\": \"BRL\",\n          \"CD_UNT_ISO\": \"\",\n          \"REFOBJTYPE\": \"\",\n          \"REFOBJKEY\": \"\",\n          \"REFLOGSYS\": \"\",\n          \"APPLICATIO\": \"V\",\n          \"CONPRICDAT\": \"2020-12-14\",\n          \"CALCTYPCON\": \"B\",\n          \"CONBASEVAL\": \"795.220000000\",\n          \"CONEXCHRAT\": \"1.00000\",\n          \"NUMCONVERT\": \"0\",\n          \"DENOMINATO\": \"0\",\n          \"CONDTYPE\": \"1\",\n          \"STAT_CON\": \"X\",\n          \"SCALETYPE\": \"\",\n          \"ACCRUALS\": \"\",\n          \"CONINVOLST\": \"\",\n          \"CONDORIGIN\": \"A\",\n          \"GROUPCOND\": \"\",\n          \"COND_UPDAT\": \"\",\n          \"ACCESS_SEQ\": \"00\",\n          \"CONDCOUNT\": \"00\",\n          \"ROUNDOFFDI\": \"0.000000000\",\n          \"CONDVALUE\": \"0.000000000\",\n          \"CURRENCY_2\": \"BRL\",\n          \"CURR_ISO_2\": \"BRL\",\n          \"CONDCNTRL\": \"A\",\n          \"CONDISACTI\": \"\",\n          \"CONDCLASS\": \"A\",\n          \"FACTBASVAL\": \"0.0000000000000000E+00\",\n          \"SCALEBASIN\": \"\",\n          \"SCALBASVAL\": \"0.000000000\",\n          \"UNITMEASUR\": \"\",\n          \"ISO_UNIT\": \"\",\n          \"CURRENCKEY\": \"\",\n          \"CURRENISO\": \"\",\n          \"CONDINCOMP\": \"\",\n          \"CONDCONFIG\": \"\",\n          \"CONDCHAMAN\": \"\",\n          \"COND_NO\": \"\",\n          \"TAX_CODE\": \"\",\n          \"VARCOND\": \"\",\n          \"ACCOUNTKEY\": \"\",\n          \"ACCOUNT_KE\": \"\",\n          \"WT_WITHCD\": \"\",\n          \"STRUCTCOND\": \"\",\n          \"FACTCONBAS\": \"0.0000000000000000E+00\",\n          \"CONDCOINHD\": \"00\"\n        },\n        {\n          \"ITM_NUMBER\": \"000010\",\n          \"COND_ST_NO\": \"634\",\n          \"COND_COUNT\": \"01\",\n          \"COND_TYPE\": \"BX25\",\n          \"COND_VALUE\": \"-100.000000000\",\n          \"CURRENCY\": \"\",\n          \"COND_UNIT\": \"\",\n          \"COND_P_UNT\": \"0\",\n          \"CURR_ISO\": \"\",\n          \"CD_UNT_ISO\": \"\",\n          \"REFOBJTYPE\": \"\",\n          \"REFOBJKEY\": \"\",\n          \"REFLOGSYS\": \"\",\n          \"APPLICATIO\": \"V\",\n          \"CONPRICDAT\": \"2020-12-14\",\n          \"CALCTYPCON\": \"A\",\n          \"CONBASEVAL\": \"8.230000000\",\n          \"CONEXCHRAT\": \"0.00000\",\n          \"NUMCONVERT\": \"0\",\n          \"DENOMINATO\": \"0\",\n          \"CONDTYPE\": \"\",\n          \"STAT_CON\": \"\",\n          \"SCALETYPE\": \"\",\n          \"ACCRUALS\": \"\",\n          \"CONINVOLST\": \"\",\n          \"CONDORIGIN\": \"A\",\n          \"GROUPCOND\": \"\",\n          \"COND_UPDAT\": \"\",\n          \"ACCESS_SEQ\": \"01\",\n          \"CONDCOUNT\": \"01\",\n          \"ROUNDOFFDI\": \"0.000000000\",\n          \"CONDVALUE\": \"-8.230000000\",\n          \"CURRENCY_2\": \"BRL\",\n          \"CURR_ISO_2\": \"BRL\",\n          \"CONDCNTRL\": \"A\",\n          \"CONDISACTI\": \"\",\n          \"CONDCLASS\": \"A\",\n          \"FACTBASVAL\": \"0.0000000000000000E+00\",\n          \"SCALEBASIN\": \"\",\n          \"SCALBASVAL\": \"0.000000000\",\n          \"UNITMEASUR\": \"\",\n          \"ISO_UNIT\": \"\",\n          \"CURRENCKEY\": \"\",\n          \"CURRENISO\": \"\",\n          \"CONDINCOMP\": \"\",\n          \"CONDCONFIG\": \"\",\n          \"CONDCHAMAN\": \"\",\n          \"COND_NO\": \"0000006853\",\n          \"TAX_CODE\": \"\",\n          \"VARCOND\": \"\",\n          \"ACCOUNTKEY\": \"\",\n          \"ACCOUNT_KE\": \"\",\n          \"WT_WITHCD\": \"\",\n          \"STRUCTCOND\": \"\",\n          \"FACTCONBAS\": \"0.0000000000000000E+00\",\n          \"CONDCOINHD\": \"00\"\n        },\n        {\n          \"ITM_NUMBER\": \"000010\",\n          \"COND_ST_NO\": \"636\",\n          \"COND_COUNT\": \"01\",\n          \"COND_TYPE\": \"BX40\",\n          \"COND_VALUE\": \"0.000000000\",\n          \"CURRENCY\": \"BRL\",\n          \"COND_UNIT\": \"\",\n          \"COND_P_UNT\": \"0\",\n          \"CURR_ISO\": \"BRL\",\n          \"CD_UNT_ISO\": \"\",\n          \"REFOBJTYPE\": \"\",\n          \"REFOBJKEY\": \"\",\n          \"REFLOGSYS\": \"\",\n          \"APPLICATIO\": \"V\",\n          \"CONPRICDAT\": \"2020-12-14\",\n          \"CALCTYPCON\": \"B\",\n          \"CONBASEVAL\": \"786.990000000\",\n          \"CONEXCHRAT\": \"1.00000\",\n          \"NUMCONVERT\": \"0\",\n          \"DENOMINATO\": \"0\",\n          \"CONDTYPE\": \"1\",\n          \"STAT_CON\": \"X\",\n          \"SCALETYPE\": \"\",\n          \"ACCRUALS\": \"\",\n          \"CONINVOLST\": \"\",\n          \"CONDORIGIN\": \"A\",\n          \"GROUPCOND\": \"\",\n          \"COND_UPDAT\": \"\",\n          \"ACCESS_SEQ\": \"00\",\n          \"CONDCOUNT\": \"00\",\n          \"ROUNDOFFDI\": \"0.000000000\",\n          \"CONDVALUE\": \"0.000000000\",\n          \"CURRENCY_2\": \"BRL\",\n          \"CURR_ISO_2\": \"BRL\",\n          \"CONDCNTRL\": \"A\",\n          \"CONDISACTI\": \"\",\n          \"CONDCLASS\": \"A\",\n          \"FACTBASVAL\": \"0.0000000000000000E+00\",\n          \"SCALEBASIN\": \"\",\n          \"SCALBASVAL\": \"0.000000000\",\n          \"UNITMEASUR\": \"\",\n          \"ISO_UNIT\": \"\",\n          \"CURRENCKEY\": \"\",\n          \"CURRENISO\": \"\",\n          \"CONDINCOMP\": \"\",\n          \"CONDCONFIG\": \"\",\n          \"CONDCHAMAN\": \"\",\n          \"COND_NO\": \"\",\n          \"TAX_CODE\": \"\",\n          \"VARCOND\": \"\",\n          \"ACCOUNTKEY\": \"\",\n          \"ACCOUNT_KE\": \"\",\n          \"WT_WITHCD\": \"\",\n          \"STRUCTCOND\": \"\",\n          \"FACTCONBAS\": \"0.0000000000000000E+00\",\n          \"CONDCOINHD\": \"00\"\n        },\n        {\n          \"ITM_NUMBER\": \"000010\",\n          \"COND_ST_NO\": \"638\",\n          \"COND_COUNT\": \"01\",\n          \"COND_TYPE\": \"BX41\",\n          \"COND_VALUE\": \"100.000000000\",\n          \"CURRENCY\": \"\",\n          \"COND_UNIT\": \"\",\n          \"COND_P_UNT\": \"0\",\n          \"CURR_ISO\": \"\",\n          \"CD_UNT_ISO\": \"\",\n          \"REFOBJTYPE\": \"\",\n          \"REFOBJKEY\": \"\",\n          \"REFLOGSYS\": \"\",\n          \"APPLICATIO\": \"V\",\n          \"CONPRICDAT\": \"2020-12-14\",\n          \"CALCTYPCON\": \"A\",\n          \"CONBASEVAL\": \"786.990000000\",\n          \"CONEXCHRAT\": \"0.00000\",\n          \"NUMCONVERT\": \"0\",\n          \"DENOMINATO\": \"0\",\n          \"CONDTYPE\": \"D\",\n          \"STAT_CON\": \"\",\n          \"SCALETYPE\": \"\",\n          \"ACCRUALS\": \"\",\n          \"CONINVOLST\": \"\",\n          \"CONDORIGIN\": \"A\",\n          \"GROUPCOND\": \"\",\n          \"COND_UPDAT\": \"\",\n          \"ACCESS_SEQ\": \"01\",\n          \"CONDCOUNT\": \"01\",\n          \"ROUNDOFFDI\": \"0.000000000\",\n          \"CONDVALUE\": \"0.000000000\",\n          \"CURRENCY_2\": \"BRL\",\n          \"CURR_ISO_2\": \"BRL\",\n          \"CONDCNTRL\": \"A\",\n          \"CONDISACTI\": \"\",\n          \"CONDCLASS\": \"D\",\n          \"FACTBASVAL\": \"0.0000000000000000E+00\",\n          \"SCALEBASIN\": \"\",\n          \"SCALBASVAL\": \"0.000000000\",\n          \"UNITMEASUR\": \"\",\n          \"ISO_UNIT\": \"\",\n          \"CURRENCKEY\": \"\",\n          \"CURRENISO\": \"\",\n          \"CONDINCOMP\": \"\",\n          \"CONDCONFIG\": \"\",\n          \"CONDCHAMAN\": \"\",\n          \"COND_NO\": \"0035482469\",\n          \"TAX_CODE\": \"SD\",\n          \"VARCOND\": \"\",\n          \"ACCOUNTKEY\": \"\",\n          \"ACCOUNT_KE\": \"\",\n          \"WT_WITHCD\": \"\",\n          \"STRUCTCOND\": \"\",\n          \"FACTCONBAS\": \"0.0000000000000000E+00\",\n          \"CONDCOINHD\": \"00\"\n        },\n        {\n          \"ITM_NUMBER\": \"000010\",\n          \"COND_ST_NO\": \"640\",\n          \"COND_COUNT\": \"01\",\n          \"COND_TYPE\": \"BX42\",\n          \"COND_VALUE\": \"0.000000000\",\n          \"CURRENCY\": \"BRL\",\n          \"COND_UNIT\": \"\",\n          \"COND_P_UNT\": \"0\",\n          \"CURR_ISO\": \"BRL\",\n          \"CD_UNT_ISO\": \"\",\n          \"REFOBJTYPE\": \"\",\n          \"REFOBJKEY\": \"\",\n          \"REFLOGSYS\": \"\",\n          \"APPLICATIO\": \"V\",\n          \"CONPRICDAT\": \"2020-12-14\",\n          \"CALCTYPCON\": \"B\",\n          \"CONBASEVAL\": \"786.990000000\",\n          \"CONEXCHRAT\": \"1.00000\",\n          \"NUMCONVERT\": \"0\",\n          \"DENOMINATO\": \"0\",\n          \"CONDTYPE\": \"1\",\n          \"STAT_CON\": \"X\",\n          \"SCALETYPE\": \"\",\n          \"ACCRUALS\": \"\",\n          \"CONINVOLST\": \"\",\n          \"CONDORIGIN\": \"A\",\n          \"GROUPCOND\": \"\",\n          \"COND_UPDAT\": \"\",\n          \"ACCESS_SEQ\": \"00\",\n          \"CONDCOUNT\": \"00\",\n          \"ROUNDOFFDI\": \"0.000000000\",\n          \"CONDVALUE\": \"0.000000000\",\n          \"CURRENCY_2\": \"BRL\",\n          \"CURR_ISO_2\": \"BRL\",\n          \"CONDCNTRL\": \"A\",\n          \"CONDISACTI\": \"\",\n          \"CONDCLASS\": \"A\",\n          \"FACTBASVAL\": \"0.0000000000000000E+00\",\n          \"SCALEBASIN\": \"\",\n          \"SCALBASVAL\": \"0.000000000\",\n          \"UNITMEASUR\": \"\",\n          \"ISO_UNIT\": \"\",\n          \"CURRENCKEY\": \"\",\n          \"CURRENISO\": \"\",\n          \"CONDINCOMP\": \"\",\n          \"CONDCONFIG\": \"\",\n          \"CONDCHAMAN\": \"\",\n          \"COND_NO\": \"\",\n          \"TAX_CODE\": \"\",\n          \"VARCOND\": \"\",\n          \"ACCOUNTKEY\": \"\",\n          \"ACCOUNT_KE\": \"\",\n          \"WT_WITHCD\": \"\",\n          \"STRUCTCOND\": \"\",\n          \"FACTCONBAS\": \"0.0000000000000000E+00\",\n          \"CONDCOINHD\": \"00\"\n        },\n        {\n          \"ITM_NUMBER\": \"000010\",\n          \"COND_ST_NO\": \"642\",\n          \"COND_COUNT\": \"01\",\n          \"COND_TYPE\": \"BX43\",\n          \"COND_VALUE\": \"100.000000000\",\n          \"CURRENCY\": \"\",\n          \"COND_UNIT\": \"\",\n          \"COND_P_UNT\": \"0\",\n          \"CURR_ISO\": \"\",\n          \"CD_UNT_ISO\": \"\",\n          \"REFOBJTYPE\": \"\",\n          \"REFOBJKEY\": \"\",\n          \"REFLOGSYS\": \"\",\n          \"APPLICATIO\": \"V\",\n          \"CONPRICDAT\": \"2020-12-14\",\n          \"CALCTYPCON\": \"A\",\n          \"CONBASEVAL\": \"786.990000000\",\n          \"CONEXCHRAT\": \"0.00000\",\n          \"NUMCONVERT\": \"0\",\n          \"DENOMINATO\": \"0\",\n          \"CONDTYPE\": \"D\",\n          \"STAT_CON\": \"X\",\n          \"SCALETYPE\": \"\",\n          \"ACCRUALS\": \"\",\n          \"CONINVOLST\": \"\",\n          \"CONDORIGIN\": \"A\",\n          \"GROUPCOND\": \"\",\n          \"COND_UPDAT\": \"\",\n          \"ACCESS_SEQ\": \"01\",\n          \"CONDCOUNT\": \"01\",\n          \"ROUNDOFFDI\": \"0.000000000\",\n          \"CONDVALUE\": \"0.000000000\",\n          \"CURRENCY_2\": \"BRL\",\n          \"CURR_ISO_2\": \"BRL\",\n          \"CONDCNTRL\": \"A\",\n          \"CONDISACTI\": \"\",\n          \"CONDCLASS\": \"D\",\n          \"FACTBASVAL\": \"0.0000000000000000E+00\",\n          \"SCALEBASIN\": \"\",\n          \"SCALBASVAL\": \"0.000000000\",\n          \"UNITMEASUR\": \"\",\n          \"ISO_UNIT\": \"\",\n          \"CURRENCKEY\": \"\",\n          \"CURRENISO\": \"\",\n          \"CONDINCOMP\": \"\",\n          \"CONDCONFIG\": \"\",\n          \"CONDCHAMAN\": \"\",\n          \"COND_NO\": \"0035482469\",\n          \"TAX_CODE\": \"SD\",\n          \"VARCOND\": \"\",\n          \"ACCOUNTKEY\": \"\",\n          \"ACCOUNT_KE\": \"\",\n          \"WT_WITHCD\": \"\",\n          \"STRUCTCOND\": \"\",\n          \"FACTCONBAS\": \"0.0000000000000000E+00\",\n          \"CONDCOINHD\": \"00\"\n        },\n        {\n          \"ITM_NUMBER\": \"000010\",\n          \"COND_ST_NO\": \"644\",\n          \"COND_COUNT\": \"01\",\n          \"COND_TYPE\": \"BX44\",\n          \"COND_VALUE\": \"0.000000000\",\n          \"CURRENCY\": \"BRL\",\n          \"COND_UNIT\": \"\",\n          \"COND_P_UNT\": \"0\",\n          \"CURR_ISO\": \"BRL\",\n          \"CD_UNT_ISO\": \"\",\n          \"REFOBJTYPE\": \"\",\n          \"REFOBJKEY\": \"\",\n          \"REFLOGSYS\": \"\",\n          \"APPLICATIO\": \"V\",\n          \"CONPRICDAT\": \"2020-12-14\",\n          \"CALCTYPCON\": \"B\",\n          \"CONBASEVAL\": \"786.990000000\",\n          \"CONEXCHRAT\": \"1.00000\",\n          \"NUMCONVERT\": \"0\",\n          \"DENOMINATO\": \"0\",\n          \"CONDTYPE\": \"1\",\n          \"STAT_CON\": \"X\",\n          \"SCALETYPE\": \"\",\n          \"ACCRUALS\": \"\",\n          \"CONINVOLST\": \"\",\n          \"CONDORIGIN\": \"A\",\n          \"GROUPCOND\": \"\",\n          \"COND_UPDAT\": \"\",\n          \"ACCESS_SEQ\": \"00\",\n          \"CONDCOUNT\": \"00\",\n          \"ROUNDOFFDI\": \"0.000000000\",\n          \"CONDVALUE\": \"180.000000000\",\n          \"CURRENCY_2\": \"BRL\",\n          \"CURR_ISO_2\": \"BRL\",\n          \"CONDCNTRL\": \"A\",\n          \"CONDISACTI\": \"\",\n          \"CONDCLASS\": \"A\",\n          \"FACTBASVAL\": \"0.0000000000000000E+00\",\n          \"SCALEBASIN\": \"\",\n          \"SCALBASVAL\": \"0.000000000\",\n          \"UNITMEASUR\": \"\",\n          \"ISO_UNIT\": \"\",\n          \"CURRENCKEY\": \"\",\n          \"CURRENISO\": \"\",\n          \"CONDINCOMP\": \"\",\n          \"CONDCONFIG\": \"\",\n          \"CONDCHAMAN\": \"\",\n          \"COND_NO\": \"\",\n          \"TAX_CODE\": \"\",\n          \"VARCOND\": \"\",\n          \"ACCOUNTKEY\": \"\",\n          \"ACCOUNT_KE\": \"\",\n          \"WT_WITHCD\": \"\",\n          \"STRUCTCOND\": \"\",\n          \"FACTCONBAS\": \"0.0000000000000000E+00\",\n          \"CONDCOINHD\": \"00\"\n        },\n        {\n          \"ITM_NUMBER\": \"000010\",\n          \"COND_ST_NO\": \"645\",\n          \"COND_COUNT\": \"01\",\n          \"COND_TYPE\": \"BX45\",\n          \"COND_VALUE\": \"0.000000000\",\n          \"CURRENCY\": \"BRL\",\n          \"COND_UNIT\": \"\",\n          \"COND_P_UNT\": \"0\",\n          \"CURR_ISO\": \"BRL\",\n          \"CD_UNT_ISO\": \"\",\n          \"REFOBJTYPE\": \"\",\n          \"REFOBJKEY\": \"\",\n          \"REFLOGSYS\": \"\",\n          \"APPLICATIO\": \"V\",\n          \"CONPRICDAT\": \"2020-12-14\",\n          \"CALCTYPCON\": \"B\",\n          \"CONBASEVAL\": \"966.990000000\",\n          \"CONEXCHRAT\": \"1.00000\",\n          \"NUMCONVERT\": \"0\",\n          \"DENOMINATO\": \"0\",\n          \"CONDTYPE\": \"1\",\n          \"STAT_CON\": \"X\",\n          \"SCALETYPE\": \"\",\n          \"ACCRUALS\": \"\",\n          \"CONINVOLST\": \"\",\n          \"CONDORIGIN\": \"A\",\n          \"GROUPCOND\": \"\",\n          \"COND_UPDAT\": \"\",\n          \"ACCESS_SEQ\": \"00\",\n          \"CONDCOUNT\": \"00\",\n          \"ROUNDOFFDI\": \"0.000000000\",\n          \"CONDVALUE\": \"0.000000000\",\n          \"CURRENCY_2\": \"BRL\",\n          \"CURR_ISO_2\": \"BRL\",\n          \"CONDCNTRL\": \"A\",\n          \"CONDISACTI\": \"\",\n          \"CONDCLASS\": \"A\",\n          \"FACTBASVAL\": \"0.0000000000000000E+00\",\n          \"SCALEBASIN\": \"\",\n          \"SCALBASVAL\": \"0.000000000\",\n          \"UNITMEASUR\": \"\",\n          \"ISO_UNIT\": \"\",\n          \"CURRENCKEY\": \"\",\n          \"CURRENISO\": \"\",\n          \"CONDINCOMP\": \"\",\n          \"CONDCONFIG\": \"\",\n          \"CONDCHAMAN\": \"\",\n          \"COND_NO\": \"\",\n          \"TAX_CODE\": \"\",\n          \"VARCOND\": \"\",\n          \"ACCOUNTKEY\": \"\",\n          \"ACCOUNT_KE\": \"\",\n          \"WT_WITHCD\": \"\",\n          \"STRUCTCOND\": \"\",\n          \"FACTCONBAS\": \"0.0000000000000000E+00\",\n          \"CONDCOINHD\": \"00\"\n        },\n        {\n          \"ITM_NUMBER\": \"000010\",\n          \"COND_ST_NO\": \"646\",\n          \"COND_COUNT\": \"01\",\n          \"COND_TYPE\": \"BX46\",\n          \"COND_VALUE\": \"0.000000000\",\n          \"CURRENCY\": \"BRL\",\n          \"COND_UNIT\": \"\",\n          \"COND_P_UNT\": \"0\",\n          \"CURR_ISO\": \"BRL\",\n          \"CD_UNT_ISO\": \"\",\n          \"REFOBJTYPE\": \"\",\n          \"REFOBJKEY\": \"\",\n          \"REFLOGSYS\": \"\",\n          \"APPLICATIO\": \"V\",\n          \"CONPRICDAT\": \"2020-12-14\",\n          \"CALCTYPCON\": \"B\",\n          \"CONBASEVAL\": \"966.990000000\",\n          \"CONEXCHRAT\": \"1.00000\",\n          \"NUMCONVERT\": \"0\",\n          \"DENOMINATO\": \"0\",\n          \"CONDTYPE\": \"1\",\n          \"STAT_CON\": \"X\",\n          \"SCALETYPE\": \"\",\n          \"ACCRUALS\": \"\",\n          \"CONINVOLST\": \"\",\n          \"CONDORIGIN\": \"A\",\n          \"GROUPCOND\": \"\",\n          \"COND_UPDAT\": \"\",\n          \"ACCESS_SEQ\": \"00\",\n          \"CONDCOUNT\": \"00\",\n          \"ROUNDOFFDI\": \"0.000000000\",\n          \"CONDVALUE\": \"0.000000000\",\n          \"CURRENCY_2\": \"BRL\",\n          \"CURR_ISO_2\": \"BRL\",\n          \"CONDCNTRL\": \"A\",\n          \"CONDISACTI\": \"\",\n          \"CONDCLASS\": \"A\",\n          \"FACTBASVAL\": \"0.0000000000000000E+00\",\n          \"SCALEBASIN\": \"\",\n          \"SCALBASVAL\": \"0.000000000\",\n          \"UNITMEASUR\": \"\",\n          \"ISO_UNIT\": \"\",\n          \"CURRENCKEY\": \"\",\n          \"CURRENISO\": \"\",\n          \"CONDINCOMP\": \"\",\n          \"CONDCONFIG\": \"\",\n          \"CONDCHAMAN\": \"\",\n          \"COND_NO\": \"\",\n          \"TAX_CODE\": \"\",\n          \"VARCOND\": \"\",\n          \"ACCOUNTKEY\": \"\",\n          \"ACCOUNT_KE\": \"\",\n          \"WT_WITHCD\": \"\",\n          \"STRUCTCOND\": \"\",\n          \"FACTCONBAS\": \"0.0000000000000000E+00\",\n          \"CONDCOINHD\": \"00\"\n        },\n        {\n          \"ITM_NUMBER\": \"000010\",\n          \"COND_ST_NO\": \"650\",\n          \"COND_COUNT\": \"01\",\n          \"COND_TYPE\": \"BXPA\",\n          \"COND_VALUE\": \"0.000000000\",\n          \"CURRENCY\": \"BRL\",\n          \"COND_UNIT\": \"\",\n          \"COND_P_UNT\": \"0\",\n          \"CURR_ISO\": \"BRL\",\n          \"CD_UNT_ISO\": \"\",\n          \"REFOBJTYPE\": \"\",\n          \"REFOBJKEY\": \"\",\n          \"REFLOGSYS\": \"\",\n          \"APPLICATIO\": \"V\",\n          \"CONPRICDAT\": \"2020-12-14\",\n          \"CALCTYPCON\": \"B\",\n          \"CONBASEVAL\": \"966.990000000\",\n          \"CONEXCHRAT\": \"1.00000\",\n          \"NUMCONVERT\": \"0\",\n          \"DENOMINATO\": \"0\",\n          \"CONDTYPE\": \"1\",\n          \"STAT_CON\": \"\",\n          \"SCALETYPE\": \"\",\n          \"ACCRUALS\": \"\",\n          \"CONINVOLST\": \"\",\n          \"CONDORIGIN\": \"A\",\n          \"GROUPCOND\": \"\",\n          \"COND_UPDAT\": \"\",\n          \"ACCESS_SEQ\": \"00\",\n          \"CONDCOUNT\": \"00\",\n          \"ROUNDOFFDI\": \"0.000000000\",\n          \"CONDVALUE\": \"0.000000000\",\n          \"CURRENCY_2\": \"BRL\",\n          \"CURR_ISO_2\": \"BRL\",\n          \"CONDCNTRL\": \"A\",\n          \"CONDISACTI\": \"\",\n          \"CONDCLASS\": \"A\",\n          \"FACTBASVAL\": \"0.0000000000000000E+00\",\n          \"SCALEBASIN\": \"\",\n          \"SCALBASVAL\": \"0.000000000\",\n          \"UNITMEASUR\": \"\",\n          \"ISO_UNIT\": \"\",\n          \"CURRENCKEY\": \"\",\n          \"CURRENISO\": \"\",\n          \"CONDINCOMP\": \"\",\n          \"CONDCONFIG\": \"\",\n          \"CONDCHAMAN\": \"\",\n          \"COND_NO\": \"\",\n          \"TAX_CODE\": \"\",\n          \"VARCOND\": \"\",\n          \"ACCOUNTKEY\": \"\",\n          \"ACCOUNT_KE\": \"\",\n          \"WT_WITHCD\": \"\",\n          \"STRUCTCOND\": \"\",\n          \"FACTCONBAS\": \"0.0000000000000000E+00\",\n          \"CONDCOINHD\": \"00\"\n        },\n        {\n          \"ITM_NUMBER\": \"000010\",\n          \"COND_ST_NO\": \"666\",\n          \"COND_COUNT\": \"01\",\n          \"COND_TYPE\": \"BX70\",\n          \"COND_VALUE\": \"0.000000000\",\n          \"CURRENCY\": \"BRL\",\n          \"COND_UNIT\": \"\",\n          \"COND_P_UNT\": \"0\",\n          \"CURR_ISO\": \"BRL\",\n          \"CD_UNT_ISO\": \"\",\n          \"REFOBJTYPE\": \"\",\n          \"REFOBJKEY\": \"\",\n          \"REFLOGSYS\": \"\",\n          \"APPLICATIO\": \"V\",\n          \"CONPRICDAT\": \"2020-12-14\",\n          \"CALCTYPCON\": \"B\",\n          \"CONBASEVAL\": \"966.990000000\",\n          \"CONEXCHRAT\": \"1.00000\",\n          \"NUMCONVERT\": \"0\",\n          \"DENOMINATO\": \"0\",\n          \"CONDTYPE\": \"1\",\n          \"STAT_CON\": \"X\",\n          \"SCALETYPE\": \"\",\n          \"ACCRUALS\": \"\",\n          \"CONINVOLST\": \"\",\n          \"CONDORIGIN\": \"A\",\n          \"GROUPCOND\": \"\",\n          \"COND_UPDAT\": \"\",\n          \"ACCESS_SEQ\": \"00\",\n          \"CONDCOUNT\": \"00\",\n          \"ROUNDOFFDI\": \"0.000000000\",\n          \"CONDVALUE\": \"164.690000000\",\n          \"CURRENCY_2\": \"BRL\",\n          \"CURR_ISO_2\": \"BRL\",\n          \"CONDCNTRL\": \"A\",\n          \"CONDISACTI\": \"\",\n          \"CONDCLASS\": \"A\",\n          \"FACTBASVAL\": \"0.0000000000000000E+00\",\n          \"SCALEBASIN\": \"\",\n          \"SCALBASVAL\": \"0.000000000\",\n          \"UNITMEASUR\": \"\",\n          \"ISO_UNIT\": \"\",\n          \"CURRENCKEY\": \"\",\n          \"CURRENISO\": \"\",\n          \"CONDINCOMP\": \"\",\n          \"CONDCONFIG\": \"\",\n          \"CONDCHAMAN\": \"\",\n          \"COND_NO\": \"\",\n          \"TAX_CODE\": \"\",\n          \"VARCOND\": \"\",\n          \"ACCOUNTKEY\": \"\",\n          \"ACCOUNT_KE\": \"\",\n          \"WT_WITHCD\": \"\",\n          \"STRUCTCOND\": \"\",\n          \"FACTCONBAS\": \"0.0000000000000000E+00\",\n          \"CONDCOINHD\": \"00\"\n        },\n        {\n          \"ITM_NUMBER\": \"000010\",\n          \"COND_ST_NO\": \"667\",\n          \"COND_COUNT\": \"01\",\n          \"COND_TYPE\": \"BX71\",\n          \"COND_VALUE\": \"0.000000000\",\n          \"CURRENCY\": \"BRL\",\n          \"COND_UNIT\": \"\",\n          \"COND_P_UNT\": \"0\",\n          \"CURR_ISO\": \"BRL\",\n          \"CD_UNT_ISO\": \"\",\n          \"REFOBJTYPE\": \"\",\n          \"REFOBJKEY\": \"\",\n          \"REFLOGSYS\": \"\",\n          \"APPLICATIO\": \"V\",\n          \"CONPRICDAT\": \"2020-12-14\",\n          \"CALCTYPCON\": \"B\",\n          \"CONBASEVAL\": \"1131.680000000\",\n          \"CONEXCHRAT\": \"1.00000\",\n          \"NUMCONVERT\": \"0\",\n          \"DENOMINATO\": \"0\",\n          \"CONDTYPE\": \"1\",\n          \"STAT_CON\": \"X\",\n          \"SCALETYPE\": \"\",\n          \"ACCRUALS\": \"\",\n          \"CONINVOLST\": \"\",\n          \"CONDORIGIN\": \"A\",\n          \"GROUPCOND\": \"\",\n          \"COND_UPDAT\": \"\",\n          \"ACCESS_SEQ\": \"00\",\n          \"CONDCOUNT\": \"00\",\n          \"ROUNDOFFDI\": \"0.000000000\",\n          \"CONDVALUE\": \"0.000000000\",\n          \"CURRENCY_2\": \"BRL\",\n          \"CURR_ISO_2\": \"BRL\",\n          \"CONDCNTRL\": \"A\",\n          \"CONDISACTI\": \"\",\n          \"CONDCLASS\": \"A\",\n          \"FACTBASVAL\": \"0.0000000000000000E+00\",\n          \"SCALEBASIN\": \"\",\n          \"SCALBASVAL\": \"0.000000000\",\n          \"UNITMEASUR\": \"\",\n          \"ISO_UNIT\": \"\",\n          \"CURRENCKEY\": \"\",\n          \"CURRENISO\": \"\",\n          \"CONDINCOMP\": \"\",\n          \"CONDCONFIG\": \"\",\n          \"CONDCHAMAN\": \"\",\n          \"COND_NO\": \"\",\n          \"TAX_CODE\": \"\",\n          \"VARCOND\": \"\",\n          \"ACCOUNTKEY\": \"\",\n          \"ACCOUNT_KE\": \"\",\n          \"WT_WITHCD\": \"\",\n          \"STRUCTCOND\": \"\",\n          \"FACTCONBAS\": \"0.0000000000000000E+00\",\n          \"CONDCOINHD\": \"00\"\n        },\n        {\n          \"ITM_NUMBER\": \"000010\",\n          \"COND_ST_NO\": \"668\",\n          \"COND_COUNT\": \"01\",\n          \"COND_TYPE\": \"BX72\",\n          \"COND_VALUE\": \"100.000000000\",\n          \"CURRENCY\": \"\",\n          \"COND_UNIT\": \"\",\n          \"COND_P_UNT\": \"0\",\n          \"CURR_ISO\": \"\",\n          \"CD_UNT_ISO\": \"\",\n          \"REFOBJTYPE\": \"\",\n          \"REFOBJKEY\": \"\",\n          \"REFLOGSYS\": \"\",\n          \"APPLICATIO\": \"V\",\n          \"CONPRICDAT\": \"2020-12-14\",\n          \"CALCTYPCON\": \"A\",\n          \"CONBASEVAL\": \"1131.680000000\",\n          \"CONEXCHRAT\": \"0.00000\",\n          \"NUMCONVERT\": \"0\",\n          \"DENOMINATO\": \"0\",\n          \"CONDTYPE\": \"D\",\n          \"STAT_CON\": \"\",\n          \"SCALETYPE\": \"\",\n          \"ACCRUALS\": \"\",\n          \"CONINVOLST\": \"\",\n          \"CONDORIGIN\": \"A\",\n          \"GROUPCOND\": \"\",\n          \"COND_UPDAT\": \"\",\n          \"ACCESS_SEQ\": \"01\",\n          \"CONDCOUNT\": \"01\",\n          \"ROUNDOFFDI\": \"0.000000000\",\n          \"CONDVALUE\": \"12.520000000\",\n          \"CURRENCY_2\": \"BRL\",\n          \"CURR_ISO_2\": \"BRL\",\n          \"CONDCNTRL\": \"A\",\n          \"CONDISACTI\": \"\",\n          \"CONDCLASS\": \"D\",\n          \"FACTBASVAL\": \"0.0000000000000000E+00\",\n          \"SCALEBASIN\": \"\",\n          \"SCALBASVAL\": \"0.000000000\",\n          \"UNITMEASUR\": \"\",\n          \"ISO_UNIT\": \"\",\n          \"CURRENCKEY\": \"\",\n          \"CURRENISO\": \"\",\n          \"CONDINCOMP\": \"\",\n          \"CONDCONFIG\": \"\",\n          \"CONDCHAMAN\": \"\",\n          \"COND_NO\": \"0035482469\",\n          \"TAX_CODE\": \"SD\",\n          \"VARCOND\": \"\",\n          \"ACCOUNTKEY\": \"\",\n          \"ACCOUNT_KE\": \"\",\n          \"WT_WITHCD\": \"\",\n          \"STRUCTCOND\": \"\",\n          \"FACTCONBAS\": \"0.0000000000000000E+00\",\n          \"CONDCOINHD\": \"00\"\n        },\n        {\n          \"ITM_NUMBER\": \"000010\",\n          \"COND_ST_NO\": \"669\",\n          \"COND_COUNT\": \"01\",\n          \"COND_TYPE\": \"BX7P\",\n          \"COND_VALUE\": \"0.000000000\",\n          \"CURRENCY\": \"BRL\",\n          \"COND_UNIT\": \"\",\n          \"COND_P_UNT\": \"0\",\n          \"CURR_ISO\": \"BRL\",\n          \"CD_UNT_ISO\": \"\",\n          \"REFOBJTYPE\": \"\",\n          \"REFOBJKEY\": \"\",\n          \"REFLOGSYS\": \"\",\n          \"APPLICATIO\": \"V\",\n          \"CONPRICDAT\": \"2020-12-14\",\n          \"CALCTYPCON\": \"B\",\n          \"CONBASEVAL\": \"1144.200000000\",\n          \"CONEXCHRAT\": \"1.00000\",\n          \"NUMCONVERT\": \"0\",\n          \"DENOMINATO\": \"0\",\n          \"CONDTYPE\": \"1\",\n          \"STAT_CON\": \"X\",\n          \"SCALETYPE\": \"\",\n          \"ACCRUALS\": \"\",\n          \"CONINVOLST\": \"\",\n          \"CONDORIGIN\": \"A\",\n          \"GROUPCOND\": \"\",\n          \"COND_UPDAT\": \"\",\n          \"ACCESS_SEQ\": \"00\",\n          \"CONDCOUNT\": \"00\",\n          \"ROUNDOFFDI\": \"0.000000000\",\n          \"CONDVALUE\": \"0.000000000\",\n          \"CURRENCY_2\": \"BRL\",\n          \"CURR_ISO_2\": \"BRL\",\n          \"CONDCNTRL\": \"A\",\n          \"CONDISACTI\": \"\",\n          \"CONDCLASS\": \"A\",\n          \"FACTBASVAL\": \"0.0000000000000000E+00\",\n          \"SCALEBASIN\": \"\",\n          \"SCALBASVAL\": \"0.000000000\",\n          \"UNITMEASUR\": \"\",\n          \"ISO_UNIT\": \"\",\n          \"CURRENCKEY\": \"\",\n          \"CURRENISO\": \"\",\n          \"CONDINCOMP\": \"\",\n          \"CONDCONFIG\": \"\",\n          \"CONDCHAMAN\": \"\",\n          \"COND_NO\": \"\",\n          \"TAX_CODE\": \"\",\n          \"VARCOND\": \"\",\n          \"ACCOUNTKEY\": \"\",\n          \"ACCOUNT_KE\": \"\",\n          \"WT_WITHCD\": \"\",\n          \"STRUCTCOND\": \"\",\n          \"FACTCONBAS\": \"0.0000000000000000E+00\",\n          \"CONDCOINHD\": \"00\"\n        },\n        {\n          \"ITM_NUMBER\": \"000010\",\n          \"COND_ST_NO\": \"672\",\n          \"COND_COUNT\": \"01\",\n          \"COND_TYPE\": \"BX7O\",\n          \"COND_VALUE\": \"-100.000000000\",\n          \"CURRENCY\": \"\",\n          \"COND_UNIT\": \"\",\n          \"COND_P_UNT\": \"0\",\n          \"CURR_ISO\": \"\",\n          \"CD_UNT_ISO\": \"\",\n          \"REFOBJTYPE\": \"\",\n          \"REFOBJKEY\": \"\",\n          \"REFLOGSYS\": \"\",\n          \"APPLICATIO\": \"V\",\n          \"CONPRICDAT\": \"2020-12-14\",\n          \"CALCTYPCON\": \"A\",\n          \"CONBASEVAL\": \"12.520000000\",\n          \"CONEXCHRAT\": \"0.00000\",\n          \"NUMCONVERT\": \"0\",\n          \"DENOMINATO\": \"0\",\n          \"CONDTYPE\": \"\",\n          \"STAT_CON\": \"\",\n          \"SCALETYPE\": \"\",\n          \"ACCRUALS\": \"\",\n          \"CONINVOLST\": \"\",\n          \"CONDORIGIN\": \"A\",\n          \"GROUPCOND\": \"\",\n          \"COND_UPDAT\": \"\",\n          \"ACCESS_SEQ\": \"01\",\n          \"CONDCOUNT\": \"01\",\n          \"ROUNDOFFDI\": \"0.000000000\",\n          \"CONDVALUE\": \"-12.520000000\",\n          \"CURRENCY_2\": \"BRL\",\n          \"CURR_ISO_2\": \"BRL\",\n          \"CONDCNTRL\": \"A\",\n          \"CONDISACTI\": \"\",\n          \"CONDCLASS\": \"A\",\n          \"FACTBASVAL\": \"0.0000000000000000E+00\",\n          \"SCALEBASIN\": \"\",\n          \"SCALBASVAL\": \"0.000000000\",\n          \"UNITMEASUR\": \"\",\n          \"ISO_UNIT\": \"\",\n          \"CURRENCKEY\": \"\",\n          \"CURRENISO\": \"\",\n          \"CONDINCOMP\": \"\",\n          \"CONDCONFIG\": \"\",\n          \"CONDCHAMAN\": \"\",\n          \"COND_NO\": \"0000006853\",\n          \"TAX_CODE\": \"\",\n          \"VARCOND\": \"\",\n          \"ACCOUNTKEY\": \"\",\n          \"ACCOUNT_KE\": \"\",\n          \"WT_WITHCD\": \"\",\n          \"STRUCTCOND\": \"\",\n          \"FACTCONBAS\": \"0.0000000000000000E+00\",\n          \"CONDCOINHD\": \"00\"\n        },\n        {\n          \"ITM_NUMBER\": \"000010\",\n          \"COND_ST_NO\": \"675\",\n          \"COND_COUNT\": \"01\",\n          \"COND_TYPE\": \"BX80\",\n          \"COND_VALUE\": \"0.000000000\",\n          \"CURRENCY\": \"BRL\",\n          \"COND_UNIT\": \"\",\n          \"COND_P_UNT\": \"0\",\n          \"CURR_ISO\": \"BRL\",\n          \"CD_UNT_ISO\": \"\",\n          \"REFOBJTYPE\": \"\",\n          \"REFOBJKEY\": \"\",\n          \"REFLOGSYS\": \"\",\n          \"APPLICATIO\": \"V\",\n          \"CONPRICDAT\": \"2020-12-14\",\n          \"CALCTYPCON\": \"B\",\n          \"CONBASEVAL\": \"1131.680000000\",\n          \"CONEXCHRAT\": \"1.00000\",\n          \"NUMCONVERT\": \"0\",\n          \"DENOMINATO\": \"0\",\n          \"CONDTYPE\": \"1\",\n          \"STAT_CON\": \"X\",\n          \"SCALETYPE\": \"\",\n          \"ACCRUALS\": \"\",\n          \"CONINVOLST\": \"\",\n          \"CONDORIGIN\": \"A\",\n          \"GROUPCOND\": \"\",\n          \"COND_UPDAT\": \"\",\n          \"ACCESS_SEQ\": \"00\",\n          \"CONDCOUNT\": \"00\",\n          \"ROUNDOFFDI\": \"0.000000000\",\n          \"CONDVALUE\": \"164.690000000\",\n          \"CURRENCY_2\": \"BRL\",\n          \"CURR_ISO_2\": \"BRL\",\n          \"CONDCNTRL\": \"A\",\n          \"CONDISACTI\": \"\",\n          \"CONDCLASS\": \"A\",\n          \"FACTBASVAL\": \"0.0000000000000000E+00\",\n          \"SCALEBASIN\": \"\",\n          \"SCALBASVAL\": \"0.000000000\",\n          \"UNITMEASUR\": \"\",\n          \"ISO_UNIT\": \"\",\n          \"CURRENCKEY\": \"\",\n          \"CURRENISO\": \"\",\n          \"CONDINCOMP\": \"\",\n          \"CONDCONFIG\": \"\",\n          \"CONDCHAMAN\": \"\",\n          \"COND_NO\": \"\",\n          \"TAX_CODE\": \"\",\n          \"VARCOND\": \"\",\n          \"ACCOUNTKEY\": \"\",\n          \"ACCOUNT_KE\": \"\",\n          \"WT_WITHCD\": \"\",\n          \"STRUCTCOND\": \"\",\n          \"FACTCONBAS\": \"0.0000000000000000E+00\",\n          \"CONDCOINHD\": \"00\"\n        },\n        {\n          \"ITM_NUMBER\": \"000010\",\n          \"COND_ST_NO\": \"677\",\n          \"COND_COUNT\": \"01\",\n          \"COND_TYPE\": \"BX81\",\n          \"COND_VALUE\": \"0.000000000\",\n          \"CURRENCY\": \"BRL\",\n          \"COND_UNIT\": \"\",\n          \"COND_P_UNT\": \"0\",\n          \"CURR_ISO\": \"BRL\",\n          \"CD_UNT_ISO\": \"\",\n          \"REFOBJTYPE\": \"\",\n          \"REFOBJKEY\": \"\",\n          \"REFLOGSYS\": \"\",\n          \"APPLICATIO\": \"V\",\n          \"CONPRICDAT\": \"2020-12-14\",\n          \"CALCTYPCON\": \"B\",\n          \"CONBASEVAL\": \"1296.370000000\",\n          \"CONEXCHRAT\": \"1.00000\",\n          \"NUMCONVERT\": \"0\",\n          \"DENOMINATO\": \"0\",\n          \"CONDTYPE\": \"1\",\n          \"STAT_CON\": \"X\",\n          \"SCALETYPE\": \"\",\n          \"ACCRUALS\": \"\",\n          \"CONINVOLST\": \"\",\n          \"CONDORIGIN\": \"A\",\n          \"GROUPCOND\": \"\",\n          \"COND_UPDAT\": \"\",\n          \"ACCESS_SEQ\": \"00\",\n          \"CONDCOUNT\": \"00\",\n          \"ROUNDOFFDI\": \"0.000000000\",\n          \"CONDVALUE\": \"0.000000000\",\n          \"CURRENCY_2\": \"BRL\",\n          \"CURR_ISO_2\": \"BRL\",\n          \"CONDCNTRL\": \"A\",\n          \"CONDISACTI\": \"\",\n          \"CONDCLASS\": \"A\",\n          \"FACTBASVAL\": \"0.0000000000000000E+00\",\n          \"SCALEBASIN\": \"\",\n          \"SCALBASVAL\": \"0.000000000\",\n          \"UNITMEASUR\": \"\",\n          \"ISO_UNIT\": \"\",\n          \"CURRENCKEY\": \"\",\n          \"CURRENISO\": \"\",\n          \"CONDINCOMP\": \"\",\n          \"CONDCONFIG\": \"\",\n          \"CONDCHAMAN\": \"\",\n          \"COND_NO\": \"\",\n          \"TAX_CODE\": \"\",\n          \"VARCOND\": \"\",\n          \"ACCOUNTKEY\": \"\",\n          \"ACCOUNT_KE\": \"\",\n          \"WT_WITHCD\": \"\",\n          \"STRUCTCOND\": \"\",\n          \"FACTCONBAS\": \"0.0000000000000000E+00\",\n          \"CONDCOINHD\": \"00\"\n        },\n        {\n          \"ITM_NUMBER\": \"000010\",\n          \"COND_ST_NO\": \"679\",\n          \"COND_COUNT\": \"01\",\n          \"COND_TYPE\": \"BX82\",\n          \"COND_VALUE\": \"100.000000000\",\n          \"CURRENCY\": \"\",\n          \"COND_UNIT\": \"\",\n          \"COND_P_UNT\": \"0\",\n          \"CURR_ISO\": \"\",\n          \"CD_UNT_ISO\": \"\",\n          \"REFOBJTYPE\": \"\",\n          \"REFOBJKEY\": \"\",\n          \"REFLOGSYS\": \"\",\n          \"APPLICATIO\": \"V\",\n          \"CONPRICDAT\": \"2020-12-14\",\n          \"CALCTYPCON\": \"A\",\n          \"CONBASEVAL\": \"1296.370000000\",\n          \"CONEXCHRAT\": \"0.00000\",\n          \"NUMCONVERT\": \"0\",\n          \"DENOMINATO\": \"0\",\n          \"CONDTYPE\": \"D\",\n          \"STAT_CON\": \"\",\n          \"SCALETYPE\": \"\",\n          \"ACCRUALS\": \"\",\n          \"CONINVOLST\": \"\",\n          \"CONDORIGIN\": \"A\",\n          \"GROUPCOND\": \"\",\n          \"COND_UPDAT\": \"\",\n          \"ACCESS_SEQ\": \"01\",\n          \"CONDCOUNT\": \"01\",\n          \"ROUNDOFFDI\": \"0.000000000\",\n          \"CONDVALUE\": \"2.720000000\",\n          \"CURRENCY_2\": \"BRL\",\n          \"CURR_ISO_2\": \"BRL\",\n          \"CONDCNTRL\": \"A\",\n          \"CONDISACTI\": \"\",\n          \"CONDCLASS\": \"D\",\n          \"FACTBASVAL\": \"0.0000000000000000E+00\",\n          \"SCALEBASIN\": \"\",\n          \"SCALBASVAL\": \"0.000000000\",\n          \"UNITMEASUR\": \"\",\n          \"ISO_UNIT\": \"\",\n          \"CURRENCKEY\": \"\",\n          \"CURRENISO\": \"\",\n          \"CONDINCOMP\": \"\",\n          \"CONDCONFIG\": \"\",\n          \"CONDCHAMAN\": \"\",\n          \"COND_NO\": \"0035482469\",\n          \"TAX_CODE\": \"SD\",\n          \"VARCOND\": \"\",\n          \"ACCOUNTKEY\": \"\",\n          \"ACCOUNT_KE\": \"\",\n          \"WT_WITHCD\": \"\",\n          \"STRUCTCOND\": \"\",\n          \"FACTCONBAS\": \"0.0000000000000000E+00\",\n          \"CONDCOINHD\": \"00\"\n        },\n        {\n          \"ITM_NUMBER\": \"000010\",\n          \"COND_ST_NO\": \"680\",\n          \"COND_COUNT\": \"01\",\n          \"COND_TYPE\": \"BX8P\",\n          \"COND_VALUE\": \"0.000000000\",\n          \"CURRENCY\": \"BRL\",\n          \"COND_UNIT\": \"\",\n          \"COND_P_UNT\": \"0\",\n          \"CURR_ISO\": \"BRL\",\n          \"CD_UNT_ISO\": \"\",\n          \"REFOBJTYPE\": \"\",\n          \"REFOBJKEY\": \"\",\n          \"REFLOGSYS\": \"\",\n          \"APPLICATIO\": \"V\",\n          \"CONPRICDAT\": \"2020-12-14\",\n          \"CALCTYPCON\": \"B\",\n          \"CONBASEVAL\": \"1299.090000000\",\n          \"CONEXCHRAT\": \"1.00000\",\n          \"NUMCONVERT\": \"0\",\n          \"DENOMINATO\": \"0\",\n          \"CONDTYPE\": \"1\",\n          \"STAT_CON\": \"\",\n          \"SCALETYPE\": \"\",\n          \"ACCRUALS\": \"\",\n          \"CONINVOLST\": \"\",\n          \"CONDORIGIN\": \"A\",\n          \"GROUPCOND\": \"\",\n          \"COND_UPDAT\": \"\",\n          \"ACCESS_SEQ\": \"00\",\n          \"CONDCOUNT\": \"00\",\n          \"ROUNDOFFDI\": \"0.000000000\",\n          \"CONDVALUE\": \"0.000000000\",\n          \"CURRENCY_2\": \"BRL\",\n          \"CURR_ISO_2\": \"BRL\",\n          \"CONDCNTRL\": \"A\",\n          \"CONDISACTI\": \"\",\n          \"CONDCLASS\": \"A\",\n          \"FACTBASVAL\": \"0.0000000000000000E+00\",\n          \"SCALEBASIN\": \"\",\n          \"SCALBASVAL\": \"0.000000000\",\n          \"UNITMEASUR\": \"\",\n          \"ISO_UNIT\": \"\",\n          \"CURRENCKEY\": \"\",\n          \"CURRENISO\": \"\",\n          \"CONDINCOMP\": \"\",\n          \"CONDCONFIG\": \"\",\n          \"CONDCHAMAN\": \"\",\n          \"COND_NO\": \"\",\n          \"TAX_CODE\": \"\",\n          \"VARCOND\": \"\",\n          \"ACCOUNTKEY\": \"\",\n          \"ACCOUNT_KE\": \"\",\n          \"WT_WITHCD\": \"\",\n          \"STRUCTCOND\": \"\",\n          \"FACTCONBAS\": \"0.0000000000000000E+00\",\n          \"CONDCOINHD\": \"00\"\n        },\n        {\n          \"ITM_NUMBER\": \"000010\",\n          \"COND_ST_NO\": \"683\",\n          \"COND_COUNT\": \"01\",\n          \"COND_TYPE\": \"BX8O\",\n          \"COND_VALUE\": \"-100.000000000\",\n          \"CURRENCY\": \"\",\n          \"COND_UNIT\": \"\",\n          \"COND_P_UNT\": \"0\",\n          \"CURR_ISO\": \"\",\n          \"CD_UNT_ISO\": \"\",\n          \"REFOBJTYPE\": \"\",\n          \"REFOBJKEY\": \"\",\n          \"REFLOGSYS\": \"\",\n          \"APPLICATIO\": \"V\",\n          \"CONPRICDAT\": \"2020-12-14\",\n          \"CALCTYPCON\": \"A\",\n          \"CONBASEVAL\": \"2.720000000\",\n          \"CONEXCHRAT\": \"0.00000\",\n          \"NUMCONVERT\": \"0\",\n          \"DENOMINATO\": \"0\",\n          \"CONDTYPE\": \"\",\n          \"STAT_CON\": \"\",\n          \"SCALETYPE\": \"\",\n          \"ACCRUALS\": \"\",\n          \"CONINVOLST\": \"\",\n          \"CONDORIGIN\": \"A\",\n          \"GROUPCOND\": \"\",\n          \"COND_UPDAT\": \"\",\n          \"ACCESS_SEQ\": \"01\",\n          \"CONDCOUNT\": \"01\",\n          \"ROUNDOFFDI\": \"0.000000000\",\n          \"CONDVALUE\": \"-2.720000000\",\n          \"CURRENCY_2\": \"BRL\",\n          \"CURR_ISO_2\": \"BRL\",\n          \"CONDCNTRL\": \"A\",\n          \"CONDISACTI\": \"\",\n          \"CONDCLASS\": \"A\",\n          \"FACTBASVAL\": \"0.0000000000000000E+00\",\n          \"SCALEBASIN\": \"\",\n          \"SCALBASVAL\": \"0.000000000\",\n          \"UNITMEASUR\": \"\",\n          \"ISO_UNIT\": \"\",\n          \"CURRENCKEY\": \"\",\n          \"CURRENISO\": \"\",\n          \"CONDINCOMP\": \"\",\n          \"CONDCONFIG\": \"\",\n          \"CONDCHAMAN\": \"\",\n          \"COND_NO\": \"0000006853\",\n          \"TAX_CODE\": \"\",\n          \"VARCOND\": \"\",\n          \"ACCOUNTKEY\": \"\",\n          \"ACCOUNT_KE\": \"\",\n          \"WT_WITHCD\": \"\",\n          \"STRUCTCOND\": \"\",\n          \"FACTCONBAS\": \"0.0000000000000000E+00\",\n          \"CONDCOINHD\": \"00\"\n        },\n        {\n          \"ITM_NUMBER\": \"000010\",\n          \"COND_ST_NO\": \"702\",\n          \"COND_COUNT\": \"01\",\n          \"COND_TYPE\": \"IPI3\",\n          \"COND_VALUE\": \"100.000000000\",\n          \"CURRENCY\": \"\",\n          \"COND_UNIT\": \"\",\n          \"COND_P_UNT\": \"0\",\n          \"CURR_ISO\": \"\",\n          \"CD_UNT_ISO\": \"\",\n          \"REFOBJTYPE\": \"\",\n          \"REFOBJKEY\": \"\",\n          \"REFLOGSYS\": \"\",\n          \"APPLICATIO\": \"TX\",\n          \"CONPRICDAT\": \"2020-12-14\",\n          \"CALCTYPCON\": \"A\",\n          \"CONBASEVAL\": \"0.000000000\",\n          \"CONEXCHRAT\": \"0.00000\",\n          \"NUMCONVERT\": \"0\",\n          \"DENOMINATO\": \"0\",\n          \"CONDTYPE\": \"1\",\n          \"STAT_CON\": \"\",\n          \"SCALETYPE\": \"\",\n          \"ACCRUALS\": \"\",\n          \"CONINVOLST\": \"\",\n          \"CONDORIGIN\": \"A\",\n          \"GROUPCOND\": \"\",\n          \"COND_UPDAT\": \"\",\n          \"ACCESS_SEQ\": \"10\",\n          \"CONDCOUNT\": \"01\",\n          \"ROUNDOFFDI\": \"0.000000000\",\n          \"CONDVALUE\": \"0.000000000\",\n          \"CURRENCY_2\": \"BRL\",\n          \"CURR_ISO_2\": \"BRL\",\n          \"CONDCNTRL\": \"A\",\n          \"CONDISACTI\": \"\",\n          \"CONDCLASS\": \"D\",\n          \"FACTBASVAL\": \"0.0000000000000000E+00\",\n          \"SCALEBASIN\": \"\",\n          \"SCALBASVAL\": \"0.000000000\",\n          \"UNITMEASUR\": \"\",\n          \"ISO_UNIT\": \"\",\n          \"CURRENCKEY\": \"\",\n          \"CURRENISO\": \"\",\n          \"CONDINCOMP\": \"\",\n          \"CONDCONFIG\": \"\",\n          \"CONDCHAMAN\": \"\",\n          \"COND_NO\": \"0000006899\",\n          \"TAX_CODE\": \"SD\",\n          \"VARCOND\": \"\",\n          \"ACCOUNTKEY\": \"\",\n          \"ACCOUNT_KE\": \"\",\n          \"WT_WITHCD\": \"\",\n          \"STRUCTCOND\": \"\",\n          \"FACTCONBAS\": \"0.0000000000000000E+00\",\n          \"CONDCOINHD\": \"00\"\n        },\n        {\n          \"ITM_NUMBER\": \"000010\",\n          \"COND_ST_NO\": \"704\",\n          \"COND_COUNT\": \"01\",\n          \"COND_TYPE\": \"ICM3\",\n          \"COND_VALUE\": \"100.000000000\",\n          \"CURRENCY\": \"\",\n          \"COND_UNIT\": \"\",\n          \"COND_P_UNT\": \"0\",\n          \"CURR_ISO\": \"\",\n          \"CD_UNT_ISO\": \"\",\n          \"REFOBJTYPE\": \"\",\n          \"REFOBJKEY\": \"\",\n          \"REFLOGSYS\": \"\",\n          \"APPLICATIO\": \"TX\",\n          \"CONPRICDAT\": \"2020-12-14\",\n          \"CALCTYPCON\": \"A\",\n          \"CONBASEVAL\": \"0.000000000\",\n          \"CONEXCHRAT\": \"0.00000\",\n          \"NUMCONVERT\": \"0\",\n          \"DENOMINATO\": \"0\",\n          \"CONDTYPE\": \"1\",\n          \"STAT_CON\": \"\",\n          \"SCALETYPE\": \"\",\n          \"ACCRUALS\": \"\",\n          \"CONINVOLST\": \"\",\n          \"CONDORIGIN\": \"A\",\n          \"GROUPCOND\": \"\",\n          \"COND_UPDAT\": \"\",\n          \"ACCESS_SEQ\": \"10\",\n          \"CONDCOUNT\": \"01\",\n          \"ROUNDOFFDI\": \"0.000000000\",\n          \"CONDVALUE\": \"0.000000000\",\n          \"CURRENCY_2\": \"BRL\",\n          \"CURR_ISO_2\": \"BRL\",\n          \"CONDCNTRL\": \"A\",\n          \"CONDISACTI\": \"\",\n          \"CONDCLASS\": \"D\",\n          \"FACTBASVAL\": \"0.0000000000000000E+00\",\n          \"SCALEBASIN\": \"\",\n          \"SCALBASVAL\": \"0.000000000\",\n          \"UNITMEASUR\": \"\",\n          \"ISO_UNIT\": \"\",\n          \"CURRENCKEY\": \"\",\n          \"CURRENISO\": \"\",\n          \"CONDINCOMP\": \"\",\n          \"CONDCONFIG\": \"\",\n          \"CONDCHAMAN\": \"\",\n          \"COND_NO\": \"0000006900\",\n          \"TAX_CODE\": \"SD\",\n          \"VARCOND\": \"\",\n          \"ACCOUNTKEY\": \"\",\n          \"ACCOUNT_KE\": \"\",\n          \"WT_WITHCD\": \"\",\n          \"STRUCTCOND\": \"\",\n          \"FACTCONBAS\": \"0.0000000000000000E+00\",\n          \"CONDCOINHD\": \"00\"\n        },\n        {\n          \"ITM_NUMBER\": \"000010\",\n          \"COND_ST_NO\": \"706\",\n          \"COND_COUNT\": \"01\",\n          \"COND_TYPE\": \"ICS3\",\n          \"COND_VALUE\": \"100.000000000\",\n          \"CURRENCY\": \"\",\n          \"COND_UNIT\": \"\",\n          \"COND_P_UNT\": \"0\",\n          \"CURR_ISO\": \"\",\n          \"CD_UNT_ISO\": \"\",\n          \"REFOBJTYPE\": \"\",\n          \"REFOBJKEY\": \"\",\n          \"REFLOGSYS\": \"\",\n          \"APPLICATIO\": \"TX\",\n          \"CONPRICDAT\": \"2020-12-14\",\n          \"CALCTYPCON\": \"A\",\n          \"CONBASEVAL\": \"0.000000000\",\n          \"CONEXCHRAT\": \"0.00000\",\n          \"NUMCONVERT\": \"0\",\n          \"DENOMINATO\": \"0\",\n          \"CONDTYPE\": \"1\",\n          \"STAT_CON\": \"\",\n          \"SCALETYPE\": \"\",\n          \"ACCRUALS\": \"\",\n          \"CONINVOLST\": \"\",\n          \"CONDORIGIN\": \"A\",\n          \"GROUPCOND\": \"\",\n          \"COND_UPDAT\": \"\",\n          \"ACCESS_SEQ\": \"10\",\n          \"CONDCOUNT\": \"01\",\n          \"ROUNDOFFDI\": \"0.000000000\",\n          \"CONDVALUE\": \"0.000000000\",\n          \"CURRENCY_2\": \"BRL\",\n          \"CURR_ISO_2\": \"BRL\",\n          \"CONDCNTRL\": \"A\",\n          \"CONDISACTI\": \"\",\n          \"CONDCLASS\": \"D\",\n          \"FACTBASVAL\": \"0.0000000000000000E+00\",\n          \"SCALEBASIN\": \"\",\n          \"SCALBASVAL\": \"0.000000000\",\n          \"UNITMEASUR\": \"\",\n          \"ISO_UNIT\": \"\",\n          \"CURRENCKEY\": \"\",\n          \"CURRENISO\": \"\",\n          \"CONDINCOMP\": \"\",\n          \"CONDCONFIG\": \"\",\n          \"CONDCHAMAN\": \"\",\n          \"COND_NO\": \"0000006901\",\n          \"TAX_CODE\": \"SD\",\n          \"VARCOND\": \"\",\n          \"ACCOUNTKEY\": \"\",\n          \"ACCOUNT_KE\": \"\",\n          \"WT_WITHCD\": \"\",\n          \"STRUCTCOND\": \"\",\n          \"FACTCONBAS\": \"0.0000000000000000E+00\",\n          \"CONDCOINHD\": \"00\"\n        },\n        {\n          \"ITM_NUMBER\": \"000010\",\n          \"COND_ST_NO\": \"770\",\n          \"COND_COUNT\": \"01\",\n          \"COND_TYPE\": \"VPRS\",\n          \"COND_VALUE\": \"45.400000000\",\n          \"CURRENCY\": \"BRL\",\n          \"COND_UNIT\": \"CS\",\n          \"COND_P_UNT\": \"1\",\n          \"CURR_ISO\": \"BRL\",\n          \"CD_UNT_ISO\": \"CS\",\n          \"REFOBJTYPE\": \"\",\n          \"REFOBJKEY\": \"\",\n          \"REFLOGSYS\": \"\",\n          \"APPLICATIO\": \"V\",\n          \"CONPRICDAT\": \"2020-12-14\",\n          \"CALCTYPCON\": \"C\",\n          \"CONBASEVAL\": \"1.000000000\",\n          \"CONEXCHRAT\": \"1.00000\",\n          \"NUMCONVERT\": \"1\",\n          \"DENOMINATO\": \"1\",\n          \"CONDTYPE\": \"G\",\n          \"STAT_CON\": \"X\",\n          \"SCALETYPE\": \"\",\n          \"ACCRUALS\": \"\",\n          \"CONINVOLST\": \"\",\n          \"CONDORIGIN\": \"A\",\n          \"GROUPCOND\": \"\",\n          \"COND_UPDAT\": \"\",\n          \"ACCESS_SEQ\": \"00\",\n          \"CONDCOUNT\": \"00\",\n          \"ROUNDOFFDI\": \"0.000000000\",\n          \"CONDVALUE\": \"45.400000000\",\n          \"CURRENCY_2\": \"BRL\",\n          \"CURR_ISO_2\": \"BRL\",\n          \"CONDCNTRL\": \"A\",\n          \"CONDISACTI\": \"\",\n          \"CONDCLASS\": \"B\",\n          \"FACTBASVAL\": \"0.0000000000000000E+00\",\n          \"SCALEBASIN\": \"\",\n          \"SCALBASVAL\": \"0.000000000\",\n          \"UNITMEASUR\": \"\",\n          \"ISO_UNIT\": \"\",\n          \"CURRENCKEY\": \"\",\n          \"CURRENISO\": \"\",\n          \"CONDINCOMP\": \"\",\n          \"CONDCONFIG\": \"\",\n          \"CONDCHAMAN\": \"\",\n          \"COND_NO\": \"\",\n          \"TAX_CODE\": \"\",\n          \"VARCOND\": \"\",\n          \"ACCOUNTKEY\": \"\",\n          \"ACCOUNT_KE\": \"\",\n          \"WT_WITHCD\": \"\",\n          \"STRUCTCOND\": \"\",\n          \"FACTCONBAS\": \"0.0000000000000000E+00\",\n          \"CONDCOINHD\": \"00\"\n        },\n        {\n          \"ITM_NUMBER\": \"000010\",\n          \"COND_ST_NO\": \"780\",\n          \"COND_COUNT\": \"01\",\n          \"COND_TYPE\": \"BX9M\",\n          \"COND_VALUE\": \"0.000000000\",\n          \"CURRENCY\": \"BRL\",\n          \"COND_UNIT\": \"\",\n          \"COND_P_UNT\": \"0\",\n          \"CURR_ISO\": \"BRL\",\n          \"CD_UNT_ISO\": \"\",\n          \"REFOBJTYPE\": \"\",\n          \"REFOBJKEY\": \"\",\n          \"REFLOGSYS\": \"\",\n          \"APPLICATIO\": \"V\",\n          \"CONPRICDAT\": \"2020-12-14\",\n          \"CALCTYPCON\": \"B\",\n          \"CONBASEVAL\": \"45.400000000\",\n          \"CONEXCHRAT\": \"1.00000\",\n          \"NUMCONVERT\": \"0\",\n          \"DENOMINATO\": \"0\",\n          \"CONDTYPE\": \"1\",\n          \"STAT_CON\": \"X\",\n          \"SCALETYPE\": \"\",\n          \"ACCRUALS\": \"\",\n          \"CONINVOLST\": \"\",\n          \"CONDORIGIN\": \"A\",\n          \"GROUPCOND\": \"\",\n          \"COND_UPDAT\": \"\",\n          \"ACCESS_SEQ\": \"00\",\n          \"CONDCOUNT\": \"00\",\n          \"ROUNDOFFDI\": \"0.000000000\",\n          \"CONDVALUE\": \"0.000000000\",\n          \"CURRENCY_2\": \"BRL\",\n          \"CURR_ISO_2\": \"BRL\",\n          \"CONDCNTRL\": \"A\",\n          \"CONDISACTI\": \"\",\n          \"CONDCLASS\": \"A\",\n          \"FACTBASVAL\": \"0.0000000000000000E+00\",\n          \"SCALEBASIN\": \"\",\n          \"SCALBASVAL\": \"0.000000000\",\n          \"UNITMEASUR\": \"\",\n          \"ISO_UNIT\": \"\",\n          \"CURRENCKEY\": \"\",\n          \"CURRENISO\": \"\",\n          \"CONDINCOMP\": \"\",\n          \"CONDCONFIG\": \"\",\n          \"CONDCHAMAN\": \"\",\n          \"COND_NO\": \"\",\n          \"TAX_CODE\": \"\",\n          \"VARCOND\": \"\",\n          \"ACCOUNTKEY\": \"\",\n          \"ACCOUNT_KE\": \"\",\n          \"WT_WITHCD\": \"\",\n          \"STRUCTCOND\": \"\",\n          \"FACTCONBAS\": \"0.0000000000000000E+00\",\n          \"CONDCOINHD\": \"00\"\n        },\n        {\n          \"ITM_NUMBER\": \"000010\",\n          \"COND_ST_NO\": \"780\",\n          \"COND_COUNT\": \"02\",\n          \"COND_TYPE\": \"BX9L\",\n          \"COND_VALUE\": \"0.000000000\",\n          \"CURRENCY\": \"BRL\",\n          \"COND_UNIT\": \"\",\n          \"COND_P_UNT\": \"0\",\n          \"CURR_ISO\": \"BRL\",\n          \"CD_UNT_ISO\": \"\",\n          \"REFOBJTYPE\": \"\",\n          \"REFOBJKEY\": \"\",\n          \"REFLOGSYS\": \"\",\n          \"APPLICATIO\": \"V\",\n          \"CONPRICDAT\": \"2020-12-14\",\n          \"CALCTYPCON\": \"B\",\n          \"CONBASEVAL\": \"45.400000000\",\n          \"CONEXCHRAT\": \"1.00000\",\n          \"NUMCONVERT\": \"0\",\n          \"DENOMINATO\": \"0\",\n          \"CONDTYPE\": \"1\",\n          \"STAT_CON\": \"X\",\n          \"SCALETYPE\": \"\",\n          \"ACCRUALS\": \"\",\n          \"CONINVOLST\": \"\",\n          \"CONDORIGIN\": \"A\",\n          \"GROUPCOND\": \"\",\n          \"COND_UPDAT\": \"\",\n          \"ACCESS_SEQ\": \"00\",\n          \"CONDCOUNT\": \"00\",\n          \"ROUNDOFFDI\": \"0.000000000\",\n          \"CONDVALUE\": \"0.000000000\",\n          \"CURRENCY_2\": \"BRL\",\n          \"CURR_ISO_2\": \"BRL\",\n          \"CONDCNTRL\": \"A\",\n          \"CONDISACTI\": \"\",\n          \"CONDCLASS\": \"A\",\n          \"FACTBASVAL\": \"0.0000000000000000E+00\",\n          \"SCALEBASIN\": \"\",\n          \"SCALBASVAL\": \"0.000000000\",\n          \"UNITMEASUR\": \"\",\n          \"ISO_UNIT\": \"\",\n          \"CURRENCKEY\": \"\",\n          \"CURRENISO\": \"\",\n          \"CONDINCOMP\": \"\",\n          \"CONDCONFIG\": \"\",\n          \"CONDCHAMAN\": \"\",\n          \"COND_NO\": \"\",\n          \"TAX_CODE\": \"\",\n          \"VARCOND\": \"\",\n          \"ACCOUNTKEY\": \"\",\n          \"ACCOUNT_KE\": \"\",\n          \"WT_WITHCD\": \"\",\n          \"STRUCTCOND\": \"\",\n          \"FACTCONBAS\": \"0.0000000000000000E+00\",\n          \"CONDCOINHD\": \"00\"\n        },\n        {\n          \"ITM_NUMBER\": \"000010\",\n          \"COND_ST_NO\": \"780\",\n          \"COND_COUNT\": \"03\",\n          \"COND_TYPE\": \"BX9H\",\n          \"COND_VALUE\": \"0.000000000\",\n          \"CURRENCY\": \"BRL\",\n          \"COND_UNIT\": \"\",\n          \"COND_P_UNT\": \"0\",\n          \"CURR_ISO\": \"BRL\",\n          \"CD_UNT_ISO\": \"\",\n          \"REFOBJTYPE\": \"\",\n          \"REFOBJKEY\": \"\",\n          \"REFLOGSYS\": \"\",\n          \"APPLICATIO\": \"V\",\n          \"CONPRICDAT\": \"2020-12-14\",\n          \"CALCTYPCON\": \"B\",\n          \"CONBASEVAL\": \"45.400000000\",\n          \"CONEXCHRAT\": \"1.00000\",\n          \"NUMCONVERT\": \"0\",\n          \"DENOMINATO\": \"0\",\n          \"CONDTYPE\": \"1\",\n          \"STAT_CON\": \"X\",\n          \"SCALETYPE\": \"\",\n          \"ACCRUALS\": \"\",\n          \"CONINVOLST\": \"\",\n          \"CONDORIGIN\": \"A\",\n          \"GROUPCOND\": \"\",\n          \"COND_UPDAT\": \"\",\n          \"ACCESS_SEQ\": \"00\",\n          \"CONDCOUNT\": \"00\",\n          \"ROUNDOFFDI\": \"0.000000000\",\n          \"CONDVALUE\": \"0.000000000\",\n          \"CURRENCY_2\": \"BRL\",\n          \"CURR_ISO_2\": \"BRL\",\n          \"CONDCNTRL\": \"A\",\n          \"CONDISACTI\": \"\",\n          \"CONDCLASS\": \"A\",\n          \"FACTBASVAL\": \"0.0000000000000000E+00\",\n          \"SCALEBASIN\": \"\",\n          \"SCALBASVAL\": \"0.000000000\",\n          \"UNITMEASUR\": \"\",\n          \"ISO_UNIT\": \"\",\n          \"CURRENCKEY\": \"\",\n          \"CURRENISO\": \"\",\n          \"CONDINCOMP\": \"\",\n          \"CONDCONFIG\": \"\",\n          \"CONDCHAMAN\": \"\",\n          \"COND_NO\": \"\",\n          \"TAX_CODE\": \"\",\n          \"VARCOND\": \"\",\n          \"ACCOUNTKEY\": \"\",\n          \"ACCOUNT_KE\": \"\",\n          \"WT_WITHCD\": \"\",\n          \"STRUCTCOND\": \"\",\n          \"FACTCONBAS\": \"0.0000000000000000E+00\",\n          \"CONDCOINHD\": \"00\"\n        },\n        {\n          \"ITM_NUMBER\": \"000010\",\n          \"COND_ST_NO\": \"780\",\n          \"COND_COUNT\": \"04\",\n          \"COND_TYPE\": \"BX90\",\n          \"COND_VALUE\": \"0.000000000\",\n          \"CURRENCY\": \"BRL\",\n          \"COND_UNIT\": \"\",\n          \"COND_P_UNT\": \"0\",\n          \"CURR_ISO\": \"BRL\",\n          \"CD_UNT_ISO\": \"\",\n          \"REFOBJTYPE\": \"\",\n          \"REFOBJKEY\": \"\",\n          \"REFLOGSYS\": \"\",\n          \"APPLICATIO\": \"V\",\n          \"CONPRICDAT\": \"2020-12-14\",\n          \"CALCTYPCON\": \"B\",\n          \"CONBASEVAL\": \"45.400000000\",\n          \"CONEXCHRAT\": \"1.00000\",\n          \"NUMCONVERT\": \"0\",\n          \"DENOMINATO\": \"0\",\n          \"CONDTYPE\": \"1\",\n          \"STAT_CON\": \"X\",\n          \"SCALETYPE\": \"\",\n          \"ACCRUALS\": \"\",\n          \"CONINVOLST\": \"\",\n          \"CONDORIGIN\": \"A\",\n          \"GROUPCOND\": \"\",\n          \"COND_UPDAT\": \"\",\n          \"ACCESS_SEQ\": \"00\",\n          \"CONDCOUNT\": \"00\",\n          \"ROUNDOFFDI\": \"0.000000000\",\n          \"CONDVALUE\": \"0.000000000\",\n          \"CURRENCY_2\": \"BRL\",\n          \"CURR_ISO_2\": \"BRL\",\n          \"CONDCNTRL\": \"A\",\n          \"CONDISACTI\": \"\",\n          \"CONDCLASS\": \"A\",\n          \"FACTBASVAL\": \"0.0000000000000000E+00\",\n          \"SCALEBASIN\": \"\",\n          \"SCALBASVAL\": \"0.000000000\",\n          \"UNITMEASUR\": \"\",\n          \"ISO_UNIT\": \"\",\n          \"CURRENCKEY\": \"\",\n          \"CURRENISO\": \"\",\n          \"CONDINCOMP\": \"\",\n          \"CONDCONFIG\": \"\",\n          \"CONDCHAMAN\": \"\",\n          \"COND_NO\": \"\",\n          \"TAX_CODE\": \"\",\n          \"VARCOND\": \"\",\n          \"ACCOUNTKEY\": \"\",\n          \"ACCOUNT_KE\": \"\",\n          \"WT_WITHCD\": \"\",\n          \"STRUCTCOND\": \"\",\n          \"FACTCONBAS\": \"0.0000000000000000E+00\",\n          \"CONDCOINHD\": \"00\"\n        },\n        {\n          \"ITM_NUMBER\": \"000010\",\n          \"COND_ST_NO\": \"780\",\n          \"COND_COUNT\": \"05\",\n          \"COND_TYPE\": \"BX9A\",\n          \"COND_VALUE\": \"0.000000000\",\n          \"CURRENCY\": \"BRL\",\n          \"COND_UNIT\": \"\",\n          \"COND_P_UNT\": \"0\",\n          \"CURR_ISO\": \"BRL\",\n          \"CD_UNT_ISO\": \"\",\n          \"REFOBJTYPE\": \"\",\n          \"REFOBJKEY\": \"\",\n          \"REFLOGSYS\": \"\",\n          \"APPLICATIO\": \"V\",\n          \"CONPRICDAT\": \"2020-12-14\",\n          \"CALCTYPCON\": \"B\",\n          \"CONBASEVAL\": \"45.400000000\",\n          \"CONEXCHRAT\": \"1.00000\",\n          \"NUMCONVERT\": \"0\",\n          \"DENOMINATO\": \"0\",\n          \"CONDTYPE\": \"1\",\n          \"STAT_CON\": \"X\",\n          \"SCALETYPE\": \"\",\n          \"ACCRUALS\": \"\",\n          \"CONINVOLST\": \"\",\n          \"CONDORIGIN\": \"A\",\n          \"GROUPCOND\": \"\",\n          \"COND_UPDAT\": \"\",\n          \"ACCESS_SEQ\": \"00\",\n          \"CONDCOUNT\": \"00\",\n          \"ROUNDOFFDI\": \"0.000000000\",\n          \"CONDVALUE\": \"172.920000000\",\n          \"CURRENCY_2\": \"BRL\",\n          \"CURR_ISO_2\": \"BRL\",\n          \"CONDCNTRL\": \"A\",\n          \"CONDISACTI\": \"\",\n          \"CONDCLASS\": \"A\",\n          \"FACTBASVAL\": \"0.0000000000000000E+00\",\n          \"SCALEBASIN\": \"\",\n          \"SCALBASVAL\": \"0.000000000\",\n          \"UNITMEASUR\": \"\",\n          \"ISO_UNIT\": \"\",\n          \"CURRENCKEY\": \"\",\n          \"CURRENISO\": \"\",\n          \"CONDINCOMP\": \"\",\n          \"CONDCONFIG\": \"\",\n          \"CONDCHAMAN\": \"\",\n          \"COND_NO\": \"\",\n          \"TAX_CODE\": \"\",\n          \"VARCOND\": \"\",\n          \"ACCOUNTKEY\": \"\",\n          \"ACCOUNT_KE\": \"\",\n          \"WT_WITHCD\": \"\",\n          \"STRUCTCOND\": \"\",\n          \"FACTCONBAS\": \"0.0000000000000000E+00\",\n          \"CONDCOINHD\": \"00\"\n        },\n        {\n          \"ITM_NUMBER\": \"000010\",\n          \"COND_ST_NO\": \"781\",\n          \"COND_COUNT\": \"01\",\n          \"COND_TYPE\": \"BX92\",\n          \"COND_VALUE\": \"0.000000000\",\n          \"CURRENCY\": \"BRL\",\n          \"COND_UNIT\": \"\",\n          \"COND_P_UNT\": \"0\",\n          \"CURR_ISO\": \"BRL\",\n          \"CD_UNT_ISO\": \"\",\n          \"REFOBJTYPE\": \"\",\n          \"REFOBJKEY\": \"\",\n          \"REFLOGSYS\": \"\",\n          \"APPLICATIO\": \"V\",\n          \"CONPRICDAT\": \"2020-12-14\",\n          \"CALCTYPCON\": \"B\",\n          \"CONBASEVAL\": \"218.320000000\",\n          \"CONEXCHRAT\": \"1.00000\",\n          \"NUMCONVERT\": \"0\",\n          \"DENOMINATO\": \"0\",\n          \"CONDTYPE\": \"1\",\n          \"STAT_CON\": \"X\",\n          \"SCALETYPE\": \"\",\n          \"ACCRUALS\": \"\",\n          \"CONINVOLST\": \"\",\n          \"CONDORIGIN\": \"A\",\n          \"GROUPCOND\": \"\",\n          \"COND_UPDAT\": \"\",\n          \"ACCESS_SEQ\": \"00\",\n          \"CONDCOUNT\": \"00\",\n          \"ROUNDOFFDI\": \"0.000000000\",\n          \"CONDVALUE\": \"180.000000000\",\n          \"CURRENCY_2\": \"BRL\",\n          \"CURR_ISO_2\": \"BRL\",\n          \"CONDCNTRL\": \"A\",\n          \"CONDISACTI\": \"\",\n          \"CONDCLASS\": \"A\",\n          \"FACTBASVAL\": \"0.0000000000000000E+00\",\n          \"SCALEBASIN\": \"\",\n          \"SCALBASVAL\": \"0.000000000\",\n          \"UNITMEASUR\": \"\",\n          \"ISO_UNIT\": \"\",\n          \"CURRENCKEY\": \"\",\n          \"CURRENISO\": \"\",\n          \"CONDINCOMP\": \"\",\n          \"CONDCONFIG\": \"\",\n          \"CONDCHAMAN\": \"\",\n          \"COND_NO\": \"\",\n          \"TAX_CODE\": \"\",\n          \"VARCOND\": \"\",\n          \"ACCOUNTKEY\": \"\",\n          \"ACCOUNT_KE\": \"\",\n          \"WT_WITHCD\": \"\",\n          \"STRUCTCOND\": \"\",\n          \"FACTCONBAS\": \"0.0000000000000000E+00\",\n          \"CONDCOINHD\": \"00\"\n        },\n        {\n          \"ITM_NUMBER\": \"000010\",\n          \"COND_ST_NO\": \"782\",\n          \"COND_COUNT\": \"01\",\n          \"COND_TYPE\": \"BX94\",\n          \"COND_VALUE\": \"100.000000000\",\n          \"CURRENCY\": \"\",\n          \"COND_UNIT\": \"\",\n          \"COND_P_UNT\": \"0\",\n          \"CURR_ISO\": \"\",\n          \"CD_UNT_ISO\": \"\",\n          \"REFOBJTYPE\": \"\",\n          \"REFOBJKEY\": \"\",\n          \"REFLOGSYS\": \"\",\n          \"APPLICATIO\": \"V\",\n          \"CONPRICDAT\": \"2020-12-14\",\n          \"CALCTYPCON\": \"A\",\n          \"CONBASEVAL\": \"398.320000000\",\n          \"CONEXCHRAT\": \"0.00000\",\n          \"NUMCONVERT\": \"0\",\n          \"DENOMINATO\": \"0\",\n          \"CONDTYPE\": \"D\",\n          \"STAT_CON\": \"\",\n          \"SCALETYPE\": \"\",\n          \"ACCRUALS\": \"\",\n          \"CONINVOLST\": \"\",\n          \"CONDORIGIN\": \"A\",\n          \"GROUPCOND\": \"\",\n          \"COND_UPDAT\": \"\",\n          \"ACCESS_SEQ\": \"01\",\n          \"CONDCOUNT\": \"01\",\n          \"ROUNDOFFDI\": \"0.000000000\",\n          \"CONDVALUE\": \"0.000000000\",\n          \"CURRENCY_2\": \"BRL\",\n          \"CURR_ISO_2\": \"BRL\",\n          \"CONDCNTRL\": \"A\",\n          \"CONDISACTI\": \"\",\n          \"CONDCLASS\": \"D\",\n          \"FACTBASVAL\": \"0.0000000000000000E+00\",\n          \"SCALEBASIN\": \"\",\n          \"SCALBASVAL\": \"0.000000000\",\n          \"UNITMEASUR\": \"\",\n          \"ISO_UNIT\": \"\",\n          \"CURRENCKEY\": \"\",\n          \"CURRENISO\": \"\",\n          \"CONDINCOMP\": \"\",\n          \"CONDCONFIG\": \"\",\n          \"CONDCHAMAN\": \"\",\n          \"COND_NO\": \"0035482469\",\n          \"TAX_CODE\": \"SD\",\n          \"VARCOND\": \"\",\n          \"ACCOUNTKEY\": \"\",\n          \"ACCOUNT_KE\": \"\",\n          \"WT_WITHCD\": \"\",\n          \"STRUCTCOND\": \"\",\n          \"FACTCONBAS\": \"0.0000000000000000E+00\",\n          \"CONDCOINHD\": \"00\"\n        },\n        {\n          \"ITM_NUMBER\": \"000010\",\n          \"COND_ST_NO\": \"783\",\n          \"COND_COUNT\": \"01\",\n          \"COND_TYPE\": \"BX91\",\n          \"COND_VALUE\": \"0.000000000\",\n          \"CURRENCY\": \"BRL\",\n          \"COND_UNIT\": \"\",\n          \"COND_P_UNT\": \"0\",\n          \"CURR_ISO\": \"BRL\",\n          \"CD_UNT_ISO\": \"\",\n          \"REFOBJTYPE\": \"\",\n          \"REFOBJKEY\": \"\",\n          \"REFLOGSYS\": \"\",\n          \"APPLICATIO\": \"V\",\n          \"CONPRICDAT\": \"2020-12-14\",\n          \"CALCTYPCON\": \"B\",\n          \"CONBASEVAL\": \"398.320000000\",\n          \"CONEXCHRAT\": \"1.00000\",\n          \"NUMCONVERT\": \"0\",\n          \"DENOMINATO\": \"0\",\n          \"CONDTYPE\": \"1\",\n          \"STAT_CON\": \"X\",\n          \"SCALETYPE\": \"\",\n          \"ACCRUALS\": \"\",\n          \"CONINVOLST\": \"\",\n          \"CONDORIGIN\": \"A\",\n          \"GROUPCOND\": \"\",\n          \"COND_UPDAT\": \"\",\n          \"ACCESS_SEQ\": \"00\",\n          \"CONDCOUNT\": \"00\",\n          \"ROUNDOFFDI\": \"0.000000000\",\n          \"CONDVALUE\": \"172.920000000\",\n          \"CURRENCY_2\": \"BRL\",\n          \"CURR_ISO_2\": \"BRL\",\n          \"CONDCNTRL\": \"A\",\n          \"CONDISACTI\": \"\",\n          \"CONDCLASS\": \"A\",\n          \"FACTBASVAL\": \"0.0000000000000000E+00\",\n          \"SCALEBASIN\": \"\",\n          \"SCALBASVAL\": \"0.000000000\",\n          \"UNITMEASUR\": \"\",\n          \"ISO_UNIT\": \"\",\n          \"CURRENCKEY\": \"\",\n          \"CURRENISO\": \"\",\n          \"CONDINCOMP\": \"\",\n          \"CONDCONFIG\": \"\",\n          \"CONDCHAMAN\": \"\",\n          \"COND_NO\": \"\",\n          \"TAX_CODE\": \"\",\n          \"VARCOND\": \"\",\n          \"ACCOUNTKEY\": \"\",\n          \"ACCOUNT_KE\": \"\",\n          \"WT_WITHCD\": \"\",\n          \"STRUCTCOND\": \"\",\n          \"FACTCONBAS\": \"0.0000000000000000E+00\",\n          \"CONDCOINHD\": \"00\"\n        },\n        {\n          \"ITM_NUMBER\": \"000010\",\n          \"COND_ST_NO\": \"783\",\n          \"COND_COUNT\": \"02\",\n          \"COND_TYPE\": \"BX9B\",\n          \"COND_VALUE\": \"0.000000000\",\n          \"CURRENCY\": \"BRL\",\n          \"COND_UNIT\": \"\",\n          \"COND_P_UNT\": \"0\",\n          \"CURR_ISO\": \"BRL\",\n          \"CD_UNT_ISO\": \"\",\n          \"REFOBJTYPE\": \"\",\n          \"REFOBJKEY\": \"\",\n          \"REFLOGSYS\": \"\",\n          \"APPLICATIO\": \"V\",\n          \"CONPRICDAT\": \"2020-12-14\",\n          \"CALCTYPCON\": \"B\",\n          \"CONBASEVAL\": \"571.240000000\",\n          \"CONEXCHRAT\": \"1.00000\",\n          \"NUMCONVERT\": \"0\",\n          \"DENOMINATO\": \"0\",\n          \"CONDTYPE\": \"1\",\n          \"STAT_CON\": \"X\",\n          \"SCALETYPE\": \"\",\n          \"ACCRUALS\": \"\",\n          \"CONINVOLST\": \"\",\n          \"CONDORIGIN\": \"A\",\n          \"GROUPCOND\": \"\",\n          \"COND_UPDAT\": \"\",\n          \"ACCESS_SEQ\": \"00\",\n          \"CONDCOUNT\": \"00\",\n          \"ROUNDOFFDI\": \"0.000000000\",\n          \"CONDVALUE\": \"0.000000000\",\n          \"CURRENCY_2\": \"BRL\",\n          \"CURR_ISO_2\": \"BRL\",\n          \"CONDCNTRL\": \"A\",\n          \"CONDISACTI\": \"\",\n          \"CONDCLASS\": \"A\",\n          \"FACTBASVAL\": \"0.0000000000000000E+00\",\n          \"SCALEBASIN\": \"\",\n          \"SCALBASVAL\": \"0.000000000\",\n          \"UNITMEASUR\": \"\",\n          \"ISO_UNIT\": \"\",\n          \"CURRENCKEY\": \"\",\n          \"CURRENISO\": \"\",\n          \"CONDINCOMP\": \"\",\n          \"CONDCONFIG\": \"\",\n          \"CONDCHAMAN\": \"\",\n          \"COND_NO\": \"\",\n          \"TAX_CODE\": \"\",\n          \"VARCOND\": \"\",\n          \"ACCOUNTKEY\": \"\",\n          \"ACCOUNT_KE\": \"\",\n          \"WT_WITHCD\": \"\",\n          \"STRUCTCOND\": \"\",\n          \"FACTCONBAS\": \"0.0000000000000000E+00\",\n          \"CONDCOINHD\": \"00\"\n        },\n        {\n          \"ITM_NUMBER\": \"000010\",\n          \"COND_ST_NO\": \"784\",\n          \"COND_COUNT\": \"01\",\n          \"COND_TYPE\": \"BX93\",\n          \"COND_VALUE\": \"0.000000000\",\n          \"CURRENCY\": \"BRL\",\n          \"COND_UNIT\": \"\",\n          \"COND_P_UNT\": \"0\",\n          \"CURR_ISO\": \"BRL\",\n          \"CD_UNT_ISO\": \"\",\n          \"REFOBJTYPE\": \"\",\n          \"REFOBJKEY\": \"\",\n          \"REFLOGSYS\": \"\",\n          \"APPLICATIO\": \"V\",\n          \"CONPRICDAT\": \"2020-12-14\",\n          \"CALCTYPCON\": \"B\",\n          \"CONBASEVAL\": \"571.240000000\",\n          \"CONEXCHRAT\": \"1.00000\",\n          \"NUMCONVERT\": \"0\",\n          \"DENOMINATO\": \"0\",\n          \"CONDTYPE\": \"1\",\n          \"STAT_CON\": \"X\",\n          \"SCALETYPE\": \"\",\n          \"ACCRUALS\": \"\",\n          \"CONINVOLST\": \"\",\n          \"CONDORIGIN\": \"A\",\n          \"GROUPCOND\": \"\",\n          \"COND_UPDAT\": \"\",\n          \"ACCESS_SEQ\": \"00\",\n          \"CONDCOUNT\": \"00\",\n          \"ROUNDOFFDI\": \"0.000000000\",\n          \"CONDVALUE\": \"180.000000000\",\n          \"CURRENCY_2\": \"BRL\",\n          \"CURR_ISO_2\": \"BRL\",\n          \"CONDCNTRL\": \"A\",\n          \"CONDISACTI\": \"\",\n          \"CONDCLASS\": \"A\",\n          \"FACTBASVAL\": \"0.0000000000000000E+00\",\n          \"SCALEBASIN\": \"\",\n          \"SCALBASVAL\": \"0.000000000\",\n          \"UNITMEASUR\": \"\",\n          \"ISO_UNIT\": \"\",\n          \"CURRENCKEY\": \"\",\n          \"CURRENISO\": \"\",\n          \"CONDINCOMP\": \"\",\n          \"CONDCONFIG\": \"\",\n          \"CONDCHAMAN\": \"\",\n          \"COND_NO\": \"\",\n          \"TAX_CODE\": \"\",\n          \"VARCOND\": \"\",\n          \"ACCOUNTKEY\": \"\",\n          \"ACCOUNT_KE\": \"\",\n          \"WT_WITHCD\": \"\",\n          \"STRUCTCOND\": \"\",\n          \"FACTCONBAS\": \"0.0000000000000000E+00\",\n          \"CONDCOINHD\": \"00\"\n        },\n        {\n          \"ITM_NUMBER\": \"000010\",\n          \"COND_ST_NO\": \"786\",\n          \"COND_COUNT\": \"01\",\n          \"COND_TYPE\": \"BX95\",\n          \"COND_VALUE\": \"100.000000000\",\n          \"CURRENCY\": \"\",\n          \"COND_UNIT\": \"\",\n          \"COND_P_UNT\": \"0\",\n          \"CURR_ISO\": \"\",\n          \"CD_UNT_ISO\": \"\",\n          \"REFOBJTYPE\": \"\",\n          \"REFOBJKEY\": \"\",\n          \"REFLOGSYS\": \"\",\n          \"APPLICATIO\": \"V\",\n          \"CONPRICDAT\": \"2020-12-14\",\n          \"CALCTYPCON\": \"A\",\n          \"CONBASEVAL\": \"751.240000000\",\n          \"CONEXCHRAT\": \"0.00000\",\n          \"NUMCONVERT\": \"0\",\n          \"DENOMINATO\": \"0\",\n          \"CONDTYPE\": \"D\",\n          \"STAT_CON\": \"\",\n          \"SCALETYPE\": \"\",\n          \"ACCRUALS\": \"\",\n          \"CONINVOLST\": \"\",\n          \"CONDORIGIN\": \"A\",\n          \"GROUPCOND\": \"\",\n          \"COND_UPDAT\": \"\",\n          \"ACCESS_SEQ\": \"01\",\n          \"CONDCOUNT\": \"01\",\n          \"ROUNDOFFDI\": \"0.000000000\",\n          \"CONDVALUE\": \"10.380000000\",\n          \"CURRENCY_2\": \"BRL\",\n          \"CURR_ISO_2\": \"BRL\",\n          \"CONDCNTRL\": \"A\",\n          \"CONDISACTI\": \"\",\n          \"CONDCLASS\": \"D\",\n          \"FACTBASVAL\": \"0.0000000000000000E+00\",\n          \"SCALEBASIN\": \"\",\n          \"SCALBASVAL\": \"0.000000000\",\n          \"UNITMEASUR\": \"\",\n          \"ISO_UNIT\": \"\",\n          \"CURRENCKEY\": \"\",\n          \"CURRENISO\": \"\",\n          \"CONDINCOMP\": \"\",\n          \"CONDCONFIG\": \"\",\n          \"CONDCHAMAN\": \"\",\n          \"COND_NO\": \"0035482469\",\n          \"TAX_CODE\": \"SD\",\n          \"VARCOND\": \"\",\n          \"ACCOUNTKEY\": \"\",\n          \"ACCOUNT_KE\": \"\",\n          \"WT_WITHCD\": \"\",\n          \"STRUCTCOND\": \"\",\n          \"FACTCONBAS\": \"0.0000000000000000E+00\",\n          \"CONDCOINHD\": \"00\"\n        },\n        {\n          \"ITM_NUMBER\": \"000010\",\n          \"COND_ST_NO\": \"787\",\n          \"COND_COUNT\": \"01\",\n          \"COND_TYPE\": \"BX98\",\n          \"COND_VALUE\": \"0.000000000\",\n          \"CURRENCY\": \"BRL\",\n          \"COND_UNIT\": \"\",\n          \"COND_P_UNT\": \"0\",\n          \"CURR_ISO\": \"BRL\",\n          \"CD_UNT_ISO\": \"\",\n          \"REFOBJTYPE\": \"\",\n          \"REFOBJKEY\": \"\",\n          \"REFLOGSYS\": \"\",\n          \"APPLICATIO\": \"V\",\n          \"CONPRICDAT\": \"2020-12-14\",\n          \"CALCTYPCON\": \"B\",\n          \"CONBASEVAL\": \"761.620000000\",\n          \"CONEXCHRAT\": \"1.00000\",\n          \"NUMCONVERT\": \"0\",\n          \"DENOMINATO\": \"0\",\n          \"CONDTYPE\": \"1\",\n          \"STAT_CON\": \"X\",\n          \"SCALETYPE\": \"\",\n          \"ACCRUALS\": \"\",\n          \"CONINVOLST\": \"\",\n          \"CONDORIGIN\": \"A\",\n          \"GROUPCOND\": \"\",\n          \"COND_UPDAT\": \"\",\n          \"ACCESS_SEQ\": \"00\",\n          \"CONDCOUNT\": \"00\",\n          \"ROUNDOFFDI\": \"0.000000000\",\n          \"CONDVALUE\": \"0.000000000\",\n          \"CURRENCY_2\": \"BRL\",\n          \"CURR_ISO_2\": \"BRL\",\n          \"CONDCNTRL\": \"A\",\n          \"CONDISACTI\": \"\",\n          \"CONDCLASS\": \"A\",\n          \"FACTBASVAL\": \"0.0000000000000000E+00\",\n          \"SCALEBASIN\": \"\",\n          \"SCALBASVAL\": \"0.000000000\",\n          \"UNITMEASUR\": \"\",\n          \"ISO_UNIT\": \"\",\n          \"CURRENCKEY\": \"\",\n          \"CURRENISO\": \"\",\n          \"CONDINCOMP\": \"\",\n          \"CONDCONFIG\": \"\",\n          \"CONDCHAMAN\": \"\",\n          \"COND_NO\": \"\",\n          \"TAX_CODE\": \"\",\n          \"VARCOND\": \"\",\n          \"ACCOUNTKEY\": \"\",\n          \"ACCOUNT_KE\": \"\",\n          \"WT_WITHCD\": \"\",\n          \"STRUCTCOND\": \"\",\n          \"FACTCONBAS\": \"0.0000000000000000E+00\",\n          \"CONDCOINHD\": \"00\"\n        },\n        {\n          \"ITM_NUMBER\": \"000010\",\n          \"COND_ST_NO\": \"787\",\n          \"COND_COUNT\": \"02\",\n          \"COND_TYPE\": \"BX9C\",\n          \"COND_VALUE\": \"0.000000000\",\n          \"CURRENCY\": \"BRL\",\n          \"COND_UNIT\": \"\",\n          \"COND_P_UNT\": \"0\",\n          \"CURR_ISO\": \"BRL\",\n          \"CD_UNT_ISO\": \"\",\n          \"REFOBJTYPE\": \"\",\n          \"REFOBJKEY\": \"\",\n          \"REFLOGSYS\": \"\",\n          \"APPLICATIO\": \"V\",\n          \"CONPRICDAT\": \"2020-12-14\",\n          \"CALCTYPCON\": \"B\",\n          \"CONBASEVAL\": \"761.620000000\",\n          \"CONEXCHRAT\": \"1.00000\",\n          \"NUMCONVERT\": \"0\",\n          \"DENOMINATO\": \"0\",\n          \"CONDTYPE\": \"1\",\n          \"STAT_CON\": \"X\",\n          \"SCALETYPE\": \"\",\n          \"ACCRUALS\": \"\",\n          \"CONINVOLST\": \"\",\n          \"CONDORIGIN\": \"A\",\n          \"GROUPCOND\": \"\",\n          \"COND_UPDAT\": \"\",\n          \"ACCESS_SEQ\": \"00\",\n          \"CONDCOUNT\": \"00\",\n          \"ROUNDOFFDI\": \"0.000000000\",\n          \"CONDVALUE\": \"172.920000000\",\n          \"CURRENCY_2\": \"BRL\",\n          \"CURR_ISO_2\": \"BRL\",\n          \"CONDCNTRL\": \"A\",\n          \"CONDISACTI\": \"\",\n          \"CONDCLASS\": \"A\",\n          \"FACTBASVAL\": \"0.0000000000000000E+00\",\n          \"SCALEBASIN\": \"\",\n          \"SCALBASVAL\": \"0.000000000\",\n          \"UNITMEASUR\": \"\",\n          \"ISO_UNIT\": \"\",\n          \"CURRENCKEY\": \"\",\n          \"CURRENISO\": \"\",\n          \"CONDINCOMP\": \"\",\n          \"CONDCONFIG\": \"\",\n          \"CONDCHAMAN\": \"\",\n          \"COND_NO\": \"\",\n          \"TAX_CODE\": \"\",\n          \"VARCOND\": \"\",\n          \"ACCOUNTKEY\": \"\",\n          \"ACCOUNT_KE\": \"\",\n          \"WT_WITHCD\": \"\",\n          \"STRUCTCOND\": \"\",\n          \"FACTCONBAS\": \"0.0000000000000000E+00\",\n          \"CONDCOINHD\": \"00\"\n        },\n        {\n          \"ITM_NUMBER\": \"000010\",\n          \"COND_ST_NO\": \"788\",\n          \"COND_COUNT\": \"01\",\n          \"COND_TYPE\": \"BX97\",\n          \"COND_VALUE\": \"0.000000000\",\n          \"CURRENCY\": \"BRL\",\n          \"COND_UNIT\": \"\",\n          \"COND_P_UNT\": \"0\",\n          \"CURR_ISO\": \"BRL\",\n          \"CD_UNT_ISO\": \"\",\n          \"REFOBJTYPE\": \"\",\n          \"REFOBJKEY\": \"\",\n          \"REFLOGSYS\": \"\",\n          \"APPLICATIO\": \"V\",\n          \"CONPRICDAT\": \"2020-12-14\",\n          \"CALCTYPCON\": \"B\",\n          \"CONBASEVAL\": \"934.540000000\",\n          \"CONEXCHRAT\": \"1.00000\",\n          \"NUMCONVERT\": \"0\",\n          \"DENOMINATO\": \"0\",\n          \"CONDTYPE\": \"1\",\n          \"STAT_CON\": \"X\",\n          \"SCALETYPE\": \"\",\n          \"ACCRUALS\": \"\",\n          \"CONINVOLST\": \"\",\n          \"CONDORIGIN\": \"A\",\n          \"GROUPCOND\": \"\",\n          \"COND_UPDAT\": \"\",\n          \"ACCESS_SEQ\": \"00\",\n          \"CONDCOUNT\": \"00\",\n          \"ROUNDOFFDI\": \"0.000000000\",\n          \"CONDVALUE\": \"0.000000000\",\n          \"CURRENCY_2\": \"BRL\",\n          \"CURR_ISO_2\": \"BRL\",\n          \"CONDCNTRL\": \"A\",\n          \"CONDISACTI\": \"\",\n          \"CONDCLASS\": \"A\",\n          \"FACTBASVAL\": \"0.0000000000000000E+00\",\n          \"SCALEBASIN\": \"\",\n          \"SCALBASVAL\": \"0.000000000\",\n          \"UNITMEASUR\": \"\",\n          \"ISO_UNIT\": \"\",\n          \"CURRENCKEY\": \"\",\n          \"CURRENISO\": \"\",\n          \"CONDINCOMP\": \"\",\n          \"CONDCONFIG\": \"\",\n          \"CONDCHAMAN\": \"\",\n          \"COND_NO\": \"\",\n          \"TAX_CODE\": \"\",\n          \"VARCOND\": \"\",\n          \"ACCOUNTKEY\": \"\",\n          \"ACCOUNT_KE\": \"\",\n          \"WT_WITHCD\": \"\",\n          \"STRUCTCOND\": \"\",\n          \"FACTCONBAS\": \"0.0000000000000000E+00\",\n          \"CONDCOINHD\": \"00\"\n        },\n        {\n          \"ITM_NUMBER\": \"000010\",\n          \"COND_ST_NO\": \"789\",\n          \"COND_COUNT\": \"01\",\n          \"COND_TYPE\": \"BX96\",\n          \"COND_VALUE\": \"100.000000000\",\n          \"CURRENCY\": \"\",\n          \"COND_UNIT\": \"\",\n          \"COND_P_UNT\": \"0\",\n          \"CURR_ISO\": \"\",\n          \"CD_UNT_ISO\": \"\",\n          \"REFOBJTYPE\": \"\",\n          \"REFOBJKEY\": \"\",\n          \"REFLOGSYS\": \"\",\n          \"APPLICATIO\": \"V\",\n          \"CONPRICDAT\": \"2020-12-14\",\n          \"CALCTYPCON\": \"A\",\n          \"CONBASEVAL\": \"934.540000000\",\n          \"CONEXCHRAT\": \"0.00000\",\n          \"NUMCONVERT\": \"0\",\n          \"DENOMINATO\": \"0\",\n          \"CONDTYPE\": \"D\",\n          \"STAT_CON\": \"\",\n          \"SCALETYPE\": \"\",\n          \"ACCRUALS\": \"\",\n          \"CONINVOLST\": \"\",\n          \"CONDORIGIN\": \"A\",\n          \"GROUPCOND\": \"\",\n          \"COND_UPDAT\": \"\",\n          \"ACCESS_SEQ\": \"01\",\n          \"CONDCOUNT\": \"01\",\n          \"ROUNDOFFDI\": \"0.000000000\",\n          \"CONDVALUE\": \"0.000000000\",\n          \"CURRENCY_2\": \"BRL\",\n          \"CURR_ISO_2\": \"BRL\",\n          \"CONDCNTRL\": \"A\",\n          \"CONDISACTI\": \"\",\n          \"CONDCLASS\": \"D\",\n          \"FACTBASVAL\": \"0.0000000000000000E+00\",\n          \"SCALEBASIN\": \"\",\n          \"SCALBASVAL\": \"0.000000000\",\n          \"UNITMEASUR\": \"\",\n          \"ISO_UNIT\": \"\",\n          \"CURRENCKEY\": \"\",\n          \"CURRENISO\": \"\",\n          \"CONDINCOMP\": \"\",\n          \"CONDCONFIG\": \"\",\n          \"CONDCHAMAN\": \"\",\n          \"COND_NO\": \"0035482469\",\n          \"TAX_CODE\": \"SD\",\n          \"VARCOND\": \"\",\n          \"ACCOUNTKEY\": \"\",\n          \"ACCOUNT_KE\": \"\",\n          \"WT_WITHCD\": \"\",\n          \"STRUCTCOND\": \"\",\n          \"FACTCONBAS\": \"0.0000000000000000E+00\",\n          \"CONDCOINHD\": \"00\"\n        },\n        {\n          \"ITM_NUMBER\": \"000010\",\n          \"COND_ST_NO\": \"789\",\n          \"COND_COUNT\": \"02\",\n          \"COND_TYPE\": \"BX9I\",\n          \"COND_VALUE\": \"100.000000000\",\n          \"CURRENCY\": \"\",\n          \"COND_UNIT\": \"\",\n          \"COND_P_UNT\": \"0\",\n          \"CURR_ISO\": \"\",\n          \"CD_UNT_ISO\": \"\",\n          \"REFOBJTYPE\": \"\",\n          \"REFOBJKEY\": \"\",\n          \"REFLOGSYS\": \"\",\n          \"APPLICATIO\": \"V\",\n          \"CONPRICDAT\": \"2020-12-14\",\n          \"CALCTYPCON\": \"A\",\n          \"CONBASEVAL\": \"934.540000000\",\n          \"CONEXCHRAT\": \"0.00000\",\n          \"NUMCONVERT\": \"0\",\n          \"DENOMINATO\": \"0\",\n          \"CONDTYPE\": \"D\",\n          \"STAT_CON\": \"\",\n          \"SCALETYPE\": \"\",\n          \"ACCRUALS\": \"\",\n          \"CONINVOLST\": \"\",\n          \"CONDORIGIN\": \"A\",\n          \"GROUPCOND\": \"\",\n          \"COND_UPDAT\": \"\",\n          \"ACCESS_SEQ\": \"01\",\n          \"CONDCOUNT\": \"01\",\n          \"ROUNDOFFDI\": \"0.000000000\",\n          \"CONDVALUE\": \"0.000000000\",\n          \"CURRENCY_2\": \"BRL\",\n          \"CURR_ISO_2\": \"BRL\",\n          \"CONDCNTRL\": \"A\",\n          \"CONDISACTI\": \"\",\n          \"CONDCLASS\": \"D\",\n          \"FACTBASVAL\": \"0.0000000000000000E+00\",\n          \"SCALEBASIN\": \"\",\n          \"SCALBASVAL\": \"0.000000000\",\n          \"UNITMEASUR\": \"\",\n          \"ISO_UNIT\": \"\",\n          \"CURRENCKEY\": \"\",\n          \"CURRENISO\": \"\",\n          \"CONDINCOMP\": \"\",\n          \"CONDCONFIG\": \"\",\n          \"CONDCHAMAN\": \"\",\n          \"COND_NO\": \"0035482469\",\n          \"TAX_CODE\": \"SD\",\n          \"VARCOND\": \"\",\n          \"ACCOUNTKEY\": \"\",\n          \"ACCOUNT_KE\": \"\",\n          \"WT_WITHCD\": \"\",\n          \"STRUCTCOND\": \"\",\n          \"FACTCONBAS\": \"0.0000000000000000E+00\",\n          \"CONDCOINHD\": \"00\"\n        },\n        {\n          \"ITM_NUMBER\": \"000010\",\n          \"COND_ST_NO\": \"790\",\n          \"COND_COUNT\": \"01\",\n          \"COND_TYPE\": \"BX9O\",\n          \"COND_VALUE\": \"-100.000000000\",\n          \"CURRENCY\": \"\",\n          \"COND_UNIT\": \"\",\n          \"COND_P_UNT\": \"0\",\n          \"CURR_ISO\": \"\",\n          \"CD_UNT_ISO\": \"\",\n          \"REFOBJTYPE\": \"\",\n          \"REFOBJKEY\": \"\",\n          \"REFLOGSYS\": \"\",\n          \"APPLICATIO\": \"V\",\n          \"CONPRICDAT\": \"2020-12-14\",\n          \"CALCTYPCON\": \"A\",\n          \"CONBASEVAL\": \"0.000000000\",\n          \"CONEXCHRAT\": \"0.00000\",\n          \"NUMCONVERT\": \"0\",\n          \"DENOMINATO\": \"0\",\n          \"CONDTYPE\": \"H\",\n          \"STAT_CON\": \"\",\n          \"SCALETYPE\": \"\",\n          \"ACCRUALS\": \"\",\n          \"CONINVOLST\": \"\",\n          \"CONDORIGIN\": \"A\",\n          \"GROUPCOND\": \"\",\n          \"COND_UPDAT\": \"\",\n          \"ACCESS_SEQ\": \"01\",\n          \"CONDCOUNT\": \"01\",\n          \"ROUNDOFFDI\": \"0.000000000\",\n          \"CONDVALUE\": \"0.000000000\",\n          \"CURRENCY_2\": \"BRL\",\n          \"CURR_ISO_2\": \"BRL\",\n          \"CONDCNTRL\": \"A\",\n          \"CONDISACTI\": \"\",\n          \"CONDCLASS\": \"A\",\n          \"FACTBASVAL\": \"0.0000000000000000E+00\",\n          \"SCALEBASIN\": \"\",\n          \"SCALBASVAL\": \"0.000000000\",\n          \"UNITMEASUR\": \"\",\n          \"ISO_UNIT\": \"\",\n          \"CURRENCKEY\": \"\",\n          \"CURRENISO\": \"\",\n          \"CONDINCOMP\": \"\",\n          \"CONDCONFIG\": \"\",\n          \"CONDCHAMAN\": \"\",\n          \"COND_NO\": \"0035054234\",\n          \"TAX_CODE\": \"\",\n          \"VARCOND\": \"\",\n          \"ACCOUNTKEY\": \"\",\n          \"ACCOUNT_KE\": \"\",\n          \"WT_WITHCD\": \"\",\n          \"STRUCTCOND\": \"\",\n          \"FACTCONBAS\": \"0.0000000000000000E+00\",\n          \"CONDCOINHD\": \"00\"\n        },\n        {\n          \"ITM_NUMBER\": \"000010\",\n          \"COND_ST_NO\": \"790\",\n          \"COND_COUNT\": \"02\",\n          \"COND_TYPE\": \"BX9P\",\n          \"COND_VALUE\": \"-100.000000000\",\n          \"CURRENCY\": \"\",\n          \"COND_UNIT\": \"\",\n          \"COND_P_UNT\": \"0\",\n          \"CURR_ISO\": \"\",\n          \"CD_UNT_ISO\": \"\",\n          \"REFOBJTYPE\": \"\",\n          \"REFOBJKEY\": \"\",\n          \"REFLOGSYS\": \"\",\n          \"APPLICATIO\": \"V\",\n          \"CONPRICDAT\": \"2020-12-14\",\n          \"CALCTYPCON\": \"A\",\n          \"CONBASEVAL\": \"0.000000000\",\n          \"CONEXCHRAT\": \"0.00000\",\n          \"NUMCONVERT\": \"0\",\n          \"DENOMINATO\": \"0\",\n          \"CONDTYPE\": \"H\",\n          \"STAT_CON\": \"\",\n          \"SCALETYPE\": \"\",\n          \"ACCRUALS\": \"\",\n          \"CONINVOLST\": \"\",\n          \"CONDORIGIN\": \"A\",\n          \"GROUPCOND\": \"\",\n          \"COND_UPDAT\": \"\",\n          \"ACCESS_SEQ\": \"01\",\n          \"CONDCOUNT\": \"01\",\n          \"ROUNDOFFDI\": \"0.000000000\",\n          \"CONDVALUE\": \"0.000000000\",\n          \"CURRENCY_2\": \"BRL\",\n          \"CURR_ISO_2\": \"BRL\",\n          \"CONDCNTRL\": \"A\",\n          \"CONDISACTI\": \"\",\n          \"CONDCLASS\": \"A\",\n          \"FACTBASVAL\": \"0.0000000000000000E+00\",\n          \"SCALEBASIN\": \"\",\n          \"SCALBASVAL\": \"0.000000000\",\n          \"UNITMEASUR\": \"\",\n          \"ISO_UNIT\": \"\",\n          \"CURRENCKEY\": \"\",\n          \"CURRENISO\": \"\",\n          \"CONDINCOMP\": \"\",\n          \"CONDCONFIG\": \"\",\n          \"CONDCHAMAN\": \"\",\n          \"COND_NO\": \"0035054235\",\n          \"TAX_CODE\": \"\",\n          \"VARCOND\": \"\",\n          \"ACCOUNTKEY\": \"\",\n          \"ACCOUNT_KE\": \"\",\n          \"WT_WITHCD\": \"\",\n          \"STRUCTCOND\": \"\",\n          \"FACTCONBAS\": \"0.0000000000000000E+00\",\n          \"CONDCOINHD\": \"00\"\n        },\n        {\n          \"ITM_NUMBER\": \"000010\",\n          \"COND_ST_NO\": \"790\",\n          \"COND_COUNT\": \"03\",\n          \"COND_TYPE\": \"BX9D\",\n          \"COND_VALUE\": \"-100.000000000\",\n          \"CURRENCY\": \"\",\n          \"COND_UNIT\": \"\",\n          \"COND_P_UNT\": \"0\",\n          \"CURR_ISO\": \"\",\n          \"CD_UNT_ISO\": \"\",\n          \"REFOBJTYPE\": \"\",\n          \"REFOBJKEY\": \"\",\n          \"REFLOGSYS\": \"\",\n          \"APPLICATIO\": \"V\",\n          \"CONPRICDAT\": \"2020-12-14\",\n          \"CALCTYPCON\": \"A\",\n          \"CONBASEVAL\": \"10.380000000\",\n          \"CONEXCHRAT\": \"0.00000\",\n          \"NUMCONVERT\": \"0\",\n          \"DENOMINATO\": \"0\",\n          \"CONDTYPE\": \"H\",\n          \"STAT_CON\": \"\",\n          \"SCALETYPE\": \"\",\n          \"ACCRUALS\": \"\",\n          \"CONINVOLST\": \"\",\n          \"CONDORIGIN\": \"A\",\n          \"GROUPCOND\": \"\",\n          \"COND_UPDAT\": \"\",\n          \"ACCESS_SEQ\": \"01\",\n          \"CONDCOUNT\": \"01\",\n          \"ROUNDOFFDI\": \"0.000000000\",\n          \"CONDVALUE\": \"-10.380000000\",\n          \"CURRENCY_2\": \"BRL\",\n          \"CURR_ISO_2\": \"BRL\",\n          \"CONDCNTRL\": \"A\",\n          \"CONDISACTI\": \"\",\n          \"CONDCLASS\": \"A\",\n          \"FACTBASVAL\": \"0.0000000000000000E+00\",\n          \"SCALEBASIN\": \"\",\n          \"SCALBASVAL\": \"0.000000000\",\n          \"UNITMEASUR\": \"\",\n          \"ISO_UNIT\": \"\",\n          \"CURRENCKEY\": \"\",\n          \"CURRENISO\": \"\",\n          \"CONDINCOMP\": \"\",\n          \"CONDCONFIG\": \"\",\n          \"CONDCHAMAN\": \"\",\n          \"COND_NO\": \"0035054236\",\n          \"TAX_CODE\": \"\",\n          \"VARCOND\": \"\",\n          \"ACCOUNTKEY\": \"\",\n          \"ACCOUNT_KE\": \"\",\n          \"WT_WITHCD\": \"\",\n          \"STRUCTCOND\": \"\",\n          \"FACTCONBAS\": \"0.0000000000000000E+00\",\n          \"CONDCOINHD\": \"00\"\n        },\n        {\n          \"ITM_NUMBER\": \"000010\",\n          \"COND_ST_NO\": \"791\",\n          \"COND_COUNT\": \"01\",\n          \"COND_TYPE\": \"BX4B\",\n          \"COND_VALUE\": \"0.000000000\",\n          \"CURRENCY\": \"BRL\",\n          \"COND_UNIT\": \"\",\n          \"COND_P_UNT\": \"0\",\n          \"CURR_ISO\": \"BRL\",\n          \"CD_UNT_ISO\": \"\",\n          \"REFOBJTYPE\": \"\",\n          \"REFOBJKEY\": \"\",\n          \"REFLOGSYS\": \"\",\n          \"APPLICATIO\": \"V\",\n          \"CONPRICDAT\": \"2020-12-14\",\n          \"CALCTYPCON\": \"B\",\n          \"CONBASEVAL\": \"924.160000000\",\n          \"CONEXCHRAT\": \"1.00000\",\n          \"NUMCONVERT\": \"0\",\n          \"DENOMINATO\": \"0\",\n          \"CONDTYPE\": \"1\",\n          \"STAT_CON\": \"X\",\n          \"SCALETYPE\": \"\",\n          \"ACCRUALS\": \"\",\n          \"CONINVOLST\": \"\",\n          \"CONDORIGIN\": \"A\",\n          \"GROUPCOND\": \"\",\n          \"COND_UPDAT\": \"\",\n          \"ACCESS_SEQ\": \"00\",\n          \"CONDCOUNT\": \"00\",\n          \"ROUNDOFFDI\": \"0.000000000\",\n          \"CONDVALUE\": \"0.000000000\",\n          \"CURRENCY_2\": \"BRL\",\n          \"CURR_ISO_2\": \"BRL\",\n          \"CONDCNTRL\": \"A\",\n          \"CONDISACTI\": \"\",\n          \"CONDCLASS\": \"A\",\n          \"FACTBASVAL\": \"0.0000000000000000E+00\",\n          \"SCALEBASIN\": \"\",\n          \"SCALBASVAL\": \"0.000000000\",\n          \"UNITMEASUR\": \"\",\n          \"ISO_UNIT\": \"\",\n          \"CURRENCKEY\": \"\",\n          \"CURRENISO\": \"\",\n          \"CONDINCOMP\": \"\",\n          \"CONDCONFIG\": \"\",\n          \"CONDCHAMAN\": \"\",\n          \"COND_NO\": \"\",\n          \"TAX_CODE\": \"\",\n          \"VARCOND\": \"\",\n          \"ACCOUNTKEY\": \"\",\n          \"ACCOUNT_KE\": \"\",\n          \"WT_WITHCD\": \"\",\n          \"STRUCTCOND\": \"\",\n          \"FACTCONBAS\": \"0.0000000000000000E+00\",\n          \"CONDCOINHD\": \"00\"\n        },\n        {\n          \"ITM_NUMBER\": \"000010\",\n          \"COND_ST_NO\": \"792\",\n          \"COND_COUNT\": \"01\",\n          \"COND_TYPE\": \"BX4C\",\n          \"COND_VALUE\": \"0.000000000\",\n          \"CURRENCY\": \"BRL\",\n          \"COND_UNIT\": \"\",\n          \"COND_P_UNT\": \"0\",\n          \"CURR_ISO\": \"BRL\",\n          \"CD_UNT_ISO\": \"\",\n          \"REFOBJTYPE\": \"\",\n          \"REFOBJKEY\": \"\",\n          \"REFLOGSYS\": \"\",\n          \"APPLICATIO\": \"V\",\n          \"CONPRICDAT\": \"2020-12-14\",\n          \"CALCTYPCON\": \"B\",\n          \"CONBASEVAL\": \"924.160000000\",\n          \"CONEXCHRAT\": \"1.00000\",\n          \"NUMCONVERT\": \"0\",\n          \"DENOMINATO\": \"0\",\n          \"CONDTYPE\": \"1\",\n          \"STAT_CON\": \"X\",\n          \"SCALETYPE\": \"\",\n          \"ACCRUALS\": \"\",\n          \"CONINVOLST\": \"\",\n          \"CONDORIGIN\": \"A\",\n          \"GROUPCOND\": \"\",\n          \"COND_UPDAT\": \"\",\n          \"ACCESS_SEQ\": \"00\",\n          \"CONDCOUNT\": \"00\",\n          \"ROUNDOFFDI\": \"0.000000000\",\n          \"CONDVALUE\": \"0.000000000\",\n          \"CURRENCY_2\": \"BRL\",\n          \"CURR_ISO_2\": \"BRL\",\n          \"CONDCNTRL\": \"A\",\n          \"CONDISACTI\": \"\",\n          \"CONDCLASS\": \"A\",\n          \"FACTBASVAL\": \"0.0000000000000000E+00\",\n          \"SCALEBASIN\": \"\",\n          \"SCALBASVAL\": \"0.000000000\",\n          \"UNITMEASUR\": \"\",\n          \"ISO_UNIT\": \"\",\n          \"CURRENCKEY\": \"\",\n          \"CURRENISO\": \"\",\n          \"CONDINCOMP\": \"\",\n          \"CONDCONFIG\": \"\",\n          \"CONDCHAMAN\": \"\",\n          \"COND_NO\": \"\",\n          \"TAX_CODE\": \"\",\n          \"VARCOND\": \"\",\n          \"ACCOUNTKEY\": \"\",\n          \"ACCOUNT_KE\": \"\",\n          \"WT_WITHCD\": \"\",\n          \"STRUCTCOND\": \"\",\n          \"FACTCONBAS\": \"0.0000000000000000E+00\",\n          \"CONDCOINHD\": \"00\"\n        },\n        {\n          \"ITM_NUMBER\": \"000010\",\n          \"COND_ST_NO\": \"793\",\n          \"COND_COUNT\": \"01\",\n          \"COND_TYPE\": \"BX4A\",\n          \"COND_VALUE\": \"100.000000000\",\n          \"CURRENCY\": \"\",\n          \"COND_UNIT\": \"\",\n          \"COND_P_UNT\": \"0\",\n          \"CURR_ISO\": \"\",\n          \"CD_UNT_ISO\": \"\",\n          \"REFOBJTYPE\": \"\",\n          \"REFOBJKEY\": \"\",\n          \"REFLOGSYS\": \"\",\n          \"APPLICATIO\": \"V\",\n          \"CONPRICDAT\": \"2020-12-14\",\n          \"CALCTYPCON\": \"A\",\n          \"CONBASEVAL\": \"924.160000000\",\n          \"CONEXCHRAT\": \"0.00000\",\n          \"NUMCONVERT\": \"0\",\n          \"DENOMINATO\": \"0\",\n          \"CONDTYPE\": \"D\",\n          \"STAT_CON\": \"\",\n          \"SCALETYPE\": \"\",\n          \"ACCRUALS\": \"\",\n          \"CONINVOLST\": \"\",\n          \"CONDORIGIN\": \"A\",\n          \"GROUPCOND\": \"\",\n          \"COND_UPDAT\": \"\",\n          \"ACCESS_SEQ\": \"01\",\n          \"CONDCOUNT\": \"01\",\n          \"ROUNDOFFDI\": \"0.000000000\",\n          \"CONDVALUE\": \"0.000000000\",\n          \"CURRENCY_2\": \"BRL\",\n          \"CURR_ISO_2\": \"BRL\",\n          \"CONDCNTRL\": \"A\",\n          \"CONDISACTI\": \"\",\n          \"CONDCLASS\": \"D\",\n          \"FACTBASVAL\": \"0.0000000000000000E+00\",\n          \"SCALEBASIN\": \"\",\n          \"SCALBASVAL\": \"0.000000000\",\n          \"UNITMEASUR\": \"\",\n          \"ISO_UNIT\": \"\",\n          \"CURRENCKEY\": \"\",\n          \"CURRENISO\": \"\",\n          \"CONDINCOMP\": \"\",\n          \"CONDCONFIG\": \"\",\n          \"CONDCHAMAN\": \"\",\n          \"COND_NO\": \"0035482469\",\n          \"TAX_CODE\": \"SD\",\n          \"VARCOND\": \"\",\n          \"ACCOUNTKEY\": \"\",\n          \"ACCOUNT_KE\": \"\",\n          \"WT_WITHCD\": \"\",\n          \"STRUCTCOND\": \"\",\n          \"FACTCONBAS\": \"0.0000000000000000E+00\",\n          \"CONDCOINHD\": \"00\"\n        },\n        {\n          \"ITM_NUMBER\": \"000010\",\n          \"COND_ST_NO\": \"880\",\n          \"COND_COUNT\": \"01\",\n          \"COND_TYPE\": \"ZBDC\",\n          \"COND_VALUE\": \"100.000000000\",\n          \"CURRENCY\": \"\",\n          \"COND_UNIT\": \"\",\n          \"COND_P_UNT\": \"0\",\n          \"CURR_ISO\": \"\",\n          \"CD_UNT_ISO\": \"\",\n          \"REFOBJTYPE\": \"\",\n          \"REFOBJKEY\": \"\",\n          \"REFLOGSYS\": \"\",\n          \"APPLICATIO\": \"V\",\n          \"CONPRICDAT\": \"2020-12-14\",\n          \"CALCTYPCON\": \"A\",\n          \"CONBASEVAL\": \"0.000000000\",\n          \"CONEXCHRAT\": \"0.00000\",\n          \"NUMCONVERT\": \"0\",\n          \"DENOMINATO\": \"0\",\n          \"CONDTYPE\": \"\",\n          \"STAT_CON\": \"\",\n          \"SCALETYPE\": \"\",\n          \"ACCRUALS\": \"\",\n          \"CONINVOLST\": \"\",\n          \"CONDORIGIN\": \"A\",\n          \"GROUPCOND\": \"\",\n          \"COND_UPDAT\": \"\",\n          \"ACCESS_SEQ\": \"10\",\n          \"CONDCOUNT\": \"01\",\n          \"ROUNDOFFDI\": \"0.000000000\",\n          \"CONDVALUE\": \"0.000000000\",\n          \"CURRENCY_2\": \"BRL\",\n          \"CURR_ISO_2\": \"BRL\",\n          \"CONDCNTRL\": \"A\",\n          \"CONDISACTI\": \"\",\n          \"CONDCLASS\": \"A\",\n          \"FACTBASVAL\": \"0.0000000000000000E+00\",\n          \"SCALEBASIN\": \"\",\n          \"SCALBASVAL\": \"0.000000000\",\n          \"UNITMEASUR\": \"\",\n          \"ISO_UNIT\": \"\",\n          \"CURRENCKEY\": \"\",\n          \"CURRENISO\": \"\",\n          \"CONDINCOMP\": \"\",\n          \"CONDCONFIG\": \"\",\n          \"CONDCHAMAN\": \"\",\n          \"COND_NO\": \"0011028355\",\n          \"TAX_CODE\": \"\",\n          \"VARCOND\": \"\",\n          \"ACCOUNTKEY\": \"\",\n          \"ACCOUNT_KE\": \"\",\n          \"WT_WITHCD\": \"\",\n          \"STRUCTCOND\": \"\",\n          \"FACTCONBAS\": \"0.0000000000000000E+00\",\n          \"CONDCOINHD\": \"00\"\n        },\n        {\n          \"ITM_NUMBER\": \"000010\",\n          \"COND_ST_NO\": \"880\",\n          \"COND_COUNT\": \"03\",\n          \"COND_TYPE\": \"ZBD4\",\n          \"COND_VALUE\": \"100.000000000\",\n          \"CURRENCY\": \"\",\n          \"COND_UNIT\": \"\",\n          \"COND_P_UNT\": \"0\",\n          \"CURR_ISO\": \"\",\n          \"CD_UNT_ISO\": \"\",\n          \"REFOBJTYPE\": \"\",\n          \"REFOBJKEY\": \"\",\n          \"REFLOGSYS\": \"\",\n          \"APPLICATIO\": \"V\",\n          \"CONPRICDAT\": \"2020-12-14\",\n          \"CALCTYPCON\": \"A\",\n          \"CONBASEVAL\": \"0.000000000\",\n          \"CONEXCHRAT\": \"0.00000\",\n          \"NUMCONVERT\": \"0\",\n          \"DENOMINATO\": \"0\",\n          \"CONDTYPE\": \"\",\n          \"STAT_CON\": \"\",\n          \"SCALETYPE\": \"\",\n          \"ACCRUALS\": \"\",\n          \"CONINVOLST\": \"\",\n          \"CONDORIGIN\": \"A\",\n          \"GROUPCOND\": \"\",\n          \"COND_UPDAT\": \"\",\n          \"ACCESS_SEQ\": \"10\",\n          \"CONDCOUNT\": \"01\",\n          \"ROUNDOFFDI\": \"0.000000000\",\n          \"CONDVALUE\": \"0.000000000\",\n          \"CURRENCY_2\": \"BRL\",\n          \"CURR_ISO_2\": \"BRL\",\n          \"CONDCNTRL\": \"A\",\n          \"CONDISACTI\": \"\",\n          \"CONDCLASS\": \"A\",\n          \"FACTBASVAL\": \"0.0000000000000000E+00\",\n          \"SCALEBASIN\": \"\",\n          \"SCALBASVAL\": \"0.000000000\",\n          \"UNITMEASUR\": \"\",\n          \"ISO_UNIT\": \"\",\n          \"CURRENCKEY\": \"\",\n          \"CURRENISO\": \"\",\n          \"CONDINCOMP\": \"\",\n          \"CONDCONFIG\": \"\",\n          \"CONDCHAMAN\": \"\",\n          \"COND_NO\": \"0011028355\",\n          \"TAX_CODE\": \"\",\n          \"VARCOND\": \"\",\n          \"ACCOUNTKEY\": \"\",\n          \"ACCOUNT_KE\": \"\",\n          \"WT_WITHCD\": \"\",\n          \"STRUCTCOND\": \"\",\n          \"FACTCONBAS\": \"0.0000000000000000E+00\",\n          \"CONDCOINHD\": \"00\"\n        },\n        {\n          \"ITM_NUMBER\": \"000010\",\n          \"COND_ST_NO\": \"880\",\n          \"COND_COUNT\": \"04\",\n          \"COND_TYPE\": \"ZBDS\",\n          \"COND_VALUE\": \"100.000000000\",\n          \"CURRENCY\": \"\",\n          \"COND_UNIT\": \"\",\n          \"COND_P_UNT\": \"0\",\n          \"CURR_ISO\": \"\",\n          \"CD_UNT_ISO\": \"\",\n          \"REFOBJTYPE\": \"\",\n          \"REFOBJKEY\": \"\",\n          \"REFLOGSYS\": \"\",\n          \"APPLICATIO\": \"V\",\n          \"CONPRICDAT\": \"2020-12-14\",\n          \"CALCTYPCON\": \"A\",\n          \"CONBASEVAL\": \"0.000000000\",\n          \"CONEXCHRAT\": \"0.00000\",\n          \"NUMCONVERT\": \"0\",\n          \"DENOMINATO\": \"0\",\n          \"CONDTYPE\": \"\",\n          \"STAT_CON\": \"\",\n          \"SCALETYPE\": \"\",\n          \"ACCRUALS\": \"\",\n          \"CONINVOLST\": \"\",\n          \"CONDORIGIN\": \"A\",\n          \"GROUPCOND\": \"\",\n          \"COND_UPDAT\": \"\",\n          \"ACCESS_SEQ\": \"10\",\n          \"CONDCOUNT\": \"01\",\n          \"ROUNDOFFDI\": \"0.000000000\",\n          \"CONDVALUE\": \"0.000000000\",\n          \"CURRENCY_2\": \"BRL\",\n          \"CURR_ISO_2\": \"BRL\",\n          \"CONDCNTRL\": \"A\",\n          \"CONDISACTI\": \"\",\n          \"CONDCLASS\": \"A\",\n          \"FACTBASVAL\": \"0.0000000000000000E+00\",\n          \"SCALEBASIN\": \"\",\n          \"SCALBASVAL\": \"0.000000000\",\n          \"UNITMEASUR\": \"\",\n          \"ISO_UNIT\": \"\",\n          \"CURRENCKEY\": \"\",\n          \"CURRENISO\": \"\",\n          \"CONDINCOMP\": \"\",\n          \"CONDCONFIG\": \"\",\n          \"CONDCHAMAN\": \"\",\n          \"COND_NO\": \"0011028355\",\n          \"TAX_CODE\": \"\",\n          \"VARCOND\": \"\",\n          \"ACCOUNTKEY\": \"\",\n          \"ACCOUNT_KE\": \"\",\n          \"WT_WITHCD\": \"\",\n          \"STRUCTCOND\": \"\",\n          \"FACTCONBAS\": \"0.0000000000000000E+00\",\n          \"CONDCOINHD\": \"00\"\n        },\n        {\n          \"ITM_NUMBER\": \"000010\",\n          \"COND_ST_NO\": \"880\",\n          \"COND_COUNT\": \"05\",\n          \"COND_TYPE\": \"ZBD5\",\n          \"COND_VALUE\": \"100.000000000\",\n          \"CURRENCY\": \"\",\n          \"COND_UNIT\": \"\",\n          \"COND_P_UNT\": \"0\",\n          \"CURR_ISO\": \"\",\n          \"CD_UNT_ISO\": \"\",\n          \"REFOBJTYPE\": \"\",\n          \"REFOBJKEY\": \"\",\n          \"REFLOGSYS\": \"\",\n          \"APPLICATIO\": \"V\",\n          \"CONPRICDAT\": \"2020-12-14\",\n          \"CALCTYPCON\": \"A\",\n          \"CONBASEVAL\": \"0.000000000\",\n          \"CONEXCHRAT\": \"0.00000\",\n          \"NUMCONVERT\": \"0\",\n          \"DENOMINATO\": \"0\",\n          \"CONDTYPE\": \"\",\n          \"STAT_CON\": \"\",\n          \"SCALETYPE\": \"\",\n          \"ACCRUALS\": \"\",\n          \"CONINVOLST\": \"\",\n          \"CONDORIGIN\": \"A\",\n          \"GROUPCOND\": \"\",\n          \"COND_UPDAT\": \"\",\n          \"ACCESS_SEQ\": \"10\",\n          \"CONDCOUNT\": \"01\",\n          \"ROUNDOFFDI\": \"0.000000000\",\n          \"CONDVALUE\": \"0.000000000\",\n          \"CURRENCY_2\": \"BRL\",\n          \"CURR_ISO_2\": \"BRL\",\n          \"CONDCNTRL\": \"A\",\n          \"CONDISACTI\": \"\",\n          \"CONDCLASS\": \"A\",\n          \"FACTBASVAL\": \"0.0000000000000000E+00\",\n          \"SCALEBASIN\": \"\",\n          \"SCALBASVAL\": \"0.000000000\",\n          \"UNITMEASUR\": \"\",\n          \"ISO_UNIT\": \"\",\n          \"CURRENCKEY\": \"\",\n          \"CURRENISO\": \"\",\n          \"CONDINCOMP\": \"\",\n          \"CONDCONFIG\": \"\",\n          \"CONDCHAMAN\": \"\",\n          \"COND_NO\": \"0011028355\",\n          \"TAX_CODE\": \"\",\n          \"VARCOND\": \"\",\n          \"ACCOUNTKEY\": \"\",\n          \"ACCOUNT_KE\": \"\",\n          \"WT_WITHCD\": \"\",\n          \"STRUCTCOND\": \"\",\n          \"FACTCONBAS\": \"0.0000000000000000E+00\",\n          \"CONDCOINHD\": \"00\"\n        },\n        {\n          \"ITM_NUMBER\": \"000010\",\n          \"COND_ST_NO\": \"880\",\n          \"COND_COUNT\": \"06\",\n          \"COND_TYPE\": \"ZBD6\",\n          \"COND_VALUE\": \"100.000000000\",\n          \"CURRENCY\": \"\",\n          \"COND_UNIT\": \"\",\n          \"COND_P_UNT\": \"0\",\n          \"CURR_ISO\": \"\",\n          \"CD_UNT_ISO\": \"\",\n          \"REFOBJTYPE\": \"\",\n          \"REFOBJKEY\": \"\",\n          \"REFLOGSYS\": \"\",\n          \"APPLICATIO\": \"V\",\n          \"CONPRICDAT\": \"2020-12-14\",\n          \"CALCTYPCON\": \"A\",\n          \"CONBASEVAL\": \"0.000000000\",\n          \"CONEXCHRAT\": \"0.00000\",\n          \"NUMCONVERT\": \"0\",\n          \"DENOMINATO\": \"0\",\n          \"CONDTYPE\": \"\",\n          \"STAT_CON\": \"\",\n          \"SCALETYPE\": \"\",\n          \"ACCRUALS\": \"\",\n          \"CONINVOLST\": \"\",\n          \"CONDORIGIN\": \"A\",\n          \"GROUPCOND\": \"\",\n          \"COND_UPDAT\": \"\",\n          \"ACCESS_SEQ\": \"10\",\n          \"CONDCOUNT\": \"01\",\n          \"ROUNDOFFDI\": \"0.000000000\",\n          \"CONDVALUE\": \"0.000000000\",\n          \"CURRENCY_2\": \"BRL\",\n          \"CURR_ISO_2\": \"BRL\",\n          \"CONDCNTRL\": \"A\",\n          \"CONDISACTI\": \"\",\n          \"CONDCLASS\": \"A\",\n          \"FACTBASVAL\": \"0.0000000000000000E+00\",\n          \"SCALEBASIN\": \"\",\n          \"SCALBASVAL\": \"0.000000000\",\n          \"UNITMEASUR\": \"\",\n          \"ISO_UNIT\": \"\",\n          \"CURRENCKEY\": \"\",\n          \"CURRENISO\": \"\",\n          \"CONDINCOMP\": \"\",\n          \"CONDCONFIG\": \"\",\n          \"CONDCHAMAN\": \"\",\n          \"COND_NO\": \"0011028355\",\n          \"TAX_CODE\": \"\",\n          \"VARCOND\": \"\",\n          \"ACCOUNTKEY\": \"\",\n          \"ACCOUNT_KE\": \"\",\n          \"WT_WITHCD\": \"\",\n          \"STRUCTCOND\": \"\",\n          \"FACTCONBAS\": \"0.0000000000000000E+00\",\n          \"CONDCOINHD\": \"00\"\n        },\n        {\n          \"ITM_NUMBER\": \"000010\",\n          \"COND_ST_NO\": \"880\",\n          \"COND_COUNT\": \"07\",\n          \"COND_TYPE\": \"ZBDA\",\n          \"COND_VALUE\": \"100.000000000\",\n          \"CURRENCY\": \"\",\n          \"COND_UNIT\": \"\",\n          \"COND_P_UNT\": \"0\",\n          \"CURR_ISO\": \"\",\n          \"CD_UNT_ISO\": \"\",\n          \"REFOBJTYPE\": \"\",\n          \"REFOBJKEY\": \"\",\n          \"REFLOGSYS\": \"\",\n          \"APPLICATIO\": \"V\",\n          \"CONPRICDAT\": \"2020-12-14\",\n          \"CALCTYPCON\": \"A\",\n          \"CONBASEVAL\": \"0.000000000\",\n          \"CONEXCHRAT\": \"0.00000\",\n          \"NUMCONVERT\": \"0\",\n          \"DENOMINATO\": \"0\",\n          \"CONDTYPE\": \"\",\n          \"STAT_CON\": \"\",\n          \"SCALETYPE\": \"\",\n          \"ACCRUALS\": \"\",\n          \"CONINVOLST\": \"\",\n          \"CONDORIGIN\": \"A\",\n          \"GROUPCOND\": \"\",\n          \"COND_UPDAT\": \"\",\n          \"ACCESS_SEQ\": \"10\",\n          \"CONDCOUNT\": \"01\",\n          \"ROUNDOFFDI\": \"0.000000000\",\n          \"CONDVALUE\": \"0.000000000\",\n          \"CURRENCY_2\": \"BRL\",\n          \"CURR_ISO_2\": \"BRL\",\n          \"CONDCNTRL\": \"A\",\n          \"CONDISACTI\": \"\",\n          \"CONDCLASS\": \"A\",\n          \"FACTBASVAL\": \"0.0000000000000000E+00\",\n          \"SCALEBASIN\": \"\",\n          \"SCALBASVAL\": \"0.000000000\",\n          \"UNITMEASUR\": \"\",\n          \"ISO_UNIT\": \"\",\n          \"CURRENCKEY\": \"\",\n          \"CURRENISO\": \"\",\n          \"CONDINCOMP\": \"\",\n          \"CONDCONFIG\": \"\",\n          \"CONDCHAMAN\": \"\",\n          \"COND_NO\": \"0011028355\",\n          \"TAX_CODE\": \"\",\n          \"VARCOND\": \"\",\n          \"ACCOUNTKEY\": \"\",\n          \"ACCOUNT_KE\": \"\",\n          \"WT_WITHCD\": \"\",\n          \"STRUCTCOND\": \"\",\n          \"FACTCONBAS\": \"0.0000000000000000E+00\",\n          \"CONDCOINHD\": \"00\"\n        },\n        {\n          \"ITM_NUMBER\": \"000010\",\n          \"COND_ST_NO\": \"880\",\n          \"COND_COUNT\": \"08\",\n          \"COND_TYPE\": \"ZBD8\",\n          \"COND_VALUE\": \"100.000000000\",\n          \"CURRENCY\": \"\",\n          \"COND_UNIT\": \"\",\n          \"COND_P_UNT\": \"0\",\n          \"CURR_ISO\": \"\",\n          \"CD_UNT_ISO\": \"\",\n          \"REFOBJTYPE\": \"\",\n          \"REFOBJKEY\": \"\",\n          \"REFLOGSYS\": \"\",\n          \"APPLICATIO\": \"V\",\n          \"CONPRICDAT\": \"2020-12-14\",\n          \"CALCTYPCON\": \"A\",\n          \"CONBASEVAL\": \"0.000000000\",\n          \"CONEXCHRAT\": \"0.00000\",\n          \"NUMCONVERT\": \"0\",\n          \"DENOMINATO\": \"0\",\n          \"CONDTYPE\": \"\",\n          \"STAT_CON\": \"\",\n          \"SCALETYPE\": \"\",\n          \"ACCRUALS\": \"\",\n          \"CONINVOLST\": \"\",\n          \"CONDORIGIN\": \"A\",\n          \"GROUPCOND\": \"\",\n          \"COND_UPDAT\": \"\",\n          \"ACCESS_SEQ\": \"10\",\n          \"CONDCOUNT\": \"01\",\n          \"ROUNDOFFDI\": \"0.000000000\",\n          \"CONDVALUE\": \"0.000000000\",\n          \"CURRENCY_2\": \"BRL\",\n          \"CURR_ISO_2\": \"BRL\",\n          \"CONDCNTRL\": \"A\",\n          \"CONDISACTI\": \"\",\n          \"CONDCLASS\": \"A\",\n          \"FACTBASVAL\": \"0.0000000000000000E+00\",\n          \"SCALEBASIN\": \"\",\n          \"SCALBASVAL\": \"0.000000000\",\n          \"UNITMEASUR\": \"\",\n          \"ISO_UNIT\": \"\",\n          \"CURRENCKEY\": \"\",\n          \"CURRENISO\": \"\",\n          \"CONDINCOMP\": \"\",\n          \"CONDCONFIG\": \"\",\n          \"CONDCHAMAN\": \"\",\n          \"COND_NO\": \"0011028355\",\n          \"TAX_CODE\": \"\",\n          \"VARCOND\": \"\",\n          \"ACCOUNTKEY\": \"\",\n          \"ACCOUNT_KE\": \"\",\n          \"WT_WITHCD\": \"\",\n          \"STRUCTCOND\": \"\",\n          \"FACTCONBAS\": \"0.0000000000000000E+00\",\n          \"CONDCOINHD\": \"00\"\n        },\n        {\n          \"ITM_NUMBER\": \"000010\",\n          \"COND_ST_NO\": \"880\",\n          \"COND_COUNT\": \"09\",\n          \"COND_TYPE\": \"ZBDB\",\n          \"COND_VALUE\": \"100.000000000\",\n          \"CURRENCY\": \"\",\n          \"COND_UNIT\": \"\",\n          \"COND_P_UNT\": \"0\",\n          \"CURR_ISO\": \"\",\n          \"CD_UNT_ISO\": \"\",\n          \"REFOBJTYPE\": \"\",\n          \"REFOBJKEY\": \"\",\n          \"REFLOGSYS\": \"\",\n          \"APPLICATIO\": \"V\",\n          \"CONPRICDAT\": \"2020-12-14\",\n          \"CALCTYPCON\": \"A\",\n          \"CONBASEVAL\": \"0.000000000\",\n          \"CONEXCHRAT\": \"0.00000\",\n          \"NUMCONVERT\": \"0\",\n          \"DENOMINATO\": \"0\",\n          \"CONDTYPE\": \"\",\n          \"STAT_CON\": \"\",\n          \"SCALETYPE\": \"\",\n          \"ACCRUALS\": \"\",\n          \"CONINVOLST\": \"\",\n          \"CONDORIGIN\": \"A\",\n          \"GROUPCOND\": \"\",\n          \"COND_UPDAT\": \"\",\n          \"ACCESS_SEQ\": \"10\",\n          \"CONDCOUNT\": \"01\",\n          \"ROUNDOFFDI\": \"0.000000000\",\n          \"CONDVALUE\": \"0.000000000\",\n          \"CURRENCY_2\": \"BRL\",\n          \"CURR_ISO_2\": \"BRL\",\n          \"CONDCNTRL\": \"A\",\n          \"CONDISACTI\": \"\",\n          \"CONDCLASS\": \"A\",\n          \"FACTBASVAL\": \"0.0000000000000000E+00\",\n          \"SCALEBASIN\": \"\",\n          \"SCALBASVAL\": \"0.000000000\",\n          \"UNITMEASUR\": \"\",\n          \"ISO_UNIT\": \"\",\n          \"CURRENCKEY\": \"\",\n          \"CURRENISO\": \"\",\n          \"CONDINCOMP\": \"\",\n          \"CONDCONFIG\": \"\",\n          \"CONDCHAMAN\": \"\",\n          \"COND_NO\": \"0011028355\",\n          \"TAX_CODE\": \"\",\n          \"VARCOND\": \"\",\n          \"ACCOUNTKEY\": \"\",\n          \"ACCOUNT_KE\": \"\",\n          \"WT_WITHCD\": \"\",\n          \"STRUCTCOND\": \"\",\n          \"FACTCONBAS\": \"0.0000000000000000E+00\",\n          \"CONDCOINHD\": \"00\"\n        },\n        {\n          \"ITM_NUMBER\": \"000010\",\n          \"COND_ST_NO\": \"885\",\n          \"COND_COUNT\": \"01\",\n          \"COND_TYPE\": \"ZBDI\",\n          \"COND_VALUE\": \"-100.000000000\",\n          \"CURRENCY\": \"\",\n          \"COND_UNIT\": \"\",\n          \"COND_P_UNT\": \"0\",\n          \"CURR_ISO\": \"\",\n          \"CD_UNT_ISO\": \"\",\n          \"REFOBJTYPE\": \"\",\n          \"REFOBJKEY\": \"\",\n          \"REFLOGSYS\": \"\",\n          \"APPLICATIO\": \"V\",\n          \"CONPRICDAT\": \"2020-12-14\",\n          \"CALCTYPCON\": \"A\",\n          \"CONBASEVAL\": \"-160.380000000\",\n          \"CONEXCHRAT\": \"0.00000\",\n          \"NUMCONVERT\": \"0\",\n          \"DENOMINATO\": \"0\",\n          \"CONDTYPE\": \"\",\n          \"STAT_CON\": \"\",\n          \"SCALETYPE\": \"\",\n          \"ACCRUALS\": \"\",\n          \"CONINVOLST\": \"\",\n          \"CONDORIGIN\": \"A\",\n          \"GROUPCOND\": \"\",\n          \"COND_UPDAT\": \"\",\n          \"ACCESS_SEQ\": \"10\",\n          \"CONDCOUNT\": \"01\",\n          \"ROUNDOFFDI\": \"0.000000000\",\n          \"CONDVALUE\": \"160.380000000\",\n          \"CURRENCY_2\": \"BRL\",\n          \"CURR_ISO_2\": \"BRL\",\n          \"CONDCNTRL\": \"A\",\n          \"CONDISACTI\": \"\",\n          \"CONDCLASS\": \"A\",\n          \"FACTBASVAL\": \"0.0000000000000000E+00\",\n          \"SCALEBASIN\": \"\",\n          \"SCALBASVAL\": \"0.000000000\",\n          \"UNITMEASUR\": \"\",\n          \"ISO_UNIT\": \"\",\n          \"CURRENCKEY\": \"\",\n          \"CURRENISO\": \"\",\n          \"CONDINCOMP\": \"\",\n          \"CONDCONFIG\": \"\",\n          \"CONDCHAMAN\": \"\",\n          \"COND_NO\": \"0000716933\",\n          \"TAX_CODE\": \"\",\n          \"VARCOND\": \"\",\n          \"ACCOUNTKEY\": \"\",\n          \"ACCOUNT_KE\": \"\",\n          \"WT_WITHCD\": \"\",\n          \"STRUCTCOND\": \"\",\n          \"FACTCONBAS\": \"0.0000000000000000E+00\",\n          \"CONDCOINHD\": \"00\"\n        },\n        {\n          \"ITM_NUMBER\": \"000010\",\n          \"COND_ST_NO\": \"890\",\n          \"COND_COUNT\": \"01\",\n          \"COND_TYPE\": \"ZBIP\",\n          \"COND_VALUE\": \"-100.000000000\",\n          \"CURRENCY\": \"\",\n          \"COND_UNIT\": \"\",\n          \"COND_P_UNT\": \"0\",\n          \"CURR_ISO\": \"\",\n          \"CD_UNT_ISO\": \"\",\n          \"REFOBJTYPE\": \"\",\n          \"REFOBJKEY\": \"\",\n          \"REFLOGSYS\": \"\",\n          \"APPLICATIO\": \"V\",\n          \"CONPRICDAT\": \"2020-12-14\",\n          \"CALCTYPCON\": \"A\",\n          \"CONBASEVAL\": \"-8.230000000\",\n          \"CONEXCHRAT\": \"0.00000\",\n          \"NUMCONVERT\": \"0\",\n          \"DENOMINATO\": \"0\",\n          \"CONDTYPE\": \"\",\n          \"STAT_CON\": \"\",\n          \"SCALETYPE\": \"\",\n          \"ACCRUALS\": \"\",\n          \"CONINVOLST\": \"\",\n          \"CONDORIGIN\": \"A\",\n          \"GROUPCOND\": \"\",\n          \"COND_UPDAT\": \"\",\n          \"ACCESS_SEQ\": \"10\",\n          \"CONDCOUNT\": \"01\",\n          \"ROUNDOFFDI\": \"0.000000000\",\n          \"CONDVALUE\": \"8.230000000\",\n          \"CURRENCY_2\": \"BRL\",\n          \"CURR_ISO_2\": \"BRL\",\n          \"CONDCNTRL\": \"A\",\n          \"CONDISACTI\": \"\",\n          \"CONDCLASS\": \"A\",\n          \"FACTBASVAL\": \"0.0000000000000000E+00\",\n          \"SCALEBASIN\": \"\",\n          \"SCALBASVAL\": \"0.000000000\",\n          \"UNITMEASUR\": \"\",\n          \"ISO_UNIT\": \"\",\n          \"CURRENCKEY\": \"\",\n          \"CURRENISO\": \"\",\n          \"CONDINCOMP\": \"\",\n          \"CONDCONFIG\": \"\",\n          \"CONDCHAMAN\": \"\",\n          \"COND_NO\": \"0000716933\",\n          \"TAX_CODE\": \"\",\n          \"VARCOND\": \"\",\n          \"ACCOUNTKEY\": \"\",\n          \"ACCOUNT_KE\": \"\",\n          \"WT_WITHCD\": \"\",\n          \"STRUCTCOND\": \"\",\n          \"FACTCONBAS\": \"0.0000000000000000E+00\",\n          \"CONDCOINHD\": \"00\"\n        },\n        {\n          \"ITM_NUMBER\": \"000010\",\n          \"COND_ST_NO\": \"894\",\n          \"COND_COUNT\": \"01\",\n          \"COND_TYPE\": \"ZBTB\",\n          \"COND_VALUE\": \"0.000000000\",\n          \"CURRENCY\": \"BRL\",\n          \"COND_UNIT\": \"\",\n          \"COND_P_UNT\": \"0\",\n          \"CURR_ISO\": \"BRL\",\n          \"CD_UNT_ISO\": \"\",\n          \"REFOBJTYPE\": \"\",\n          \"REFOBJKEY\": \"\",\n          \"REFLOGSYS\": \"\",\n          \"APPLICATIO\": \"V\",\n          \"CONPRICDAT\": \"2020-12-14\",\n          \"CALCTYPCON\": \"B\",\n          \"CONBASEVAL\": \"0.000000000\",\n          \"CONEXCHRAT\": \"1.00000\",\n          \"NUMCONVERT\": \"0\",\n          \"DENOMINATO\": \"0\",\n          \"CONDTYPE\": \"\",\n          \"STAT_CON\": \"X\",\n          \"SCALETYPE\": \"\",\n          \"ACCRUALS\": \"\",\n          \"CONINVOLST\": \"\",\n          \"CONDORIGIN\": \"A\",\n          \"GROUPCOND\": \"\",\n          \"COND_UPDAT\": \"\",\n          \"ACCESS_SEQ\": \"00\",\n          \"CONDCOUNT\": \"00\",\n          \"ROUNDOFFDI\": \"0.000000000\",\n          \"CONDVALUE\": \"128.700000000\",\n          \"CURRENCY_2\": \"BRL\",\n          \"CURR_ISO_2\": \"BRL\",\n          \"CONDCNTRL\": \"A\",\n          \"CONDISACTI\": \"\",\n          \"CONDCLASS\": \"A\",\n          \"FACTBASVAL\": \"0.0000000000000000E+00\",\n          \"SCALEBASIN\": \"\",\n          \"SCALBASVAL\": \"0.000000000\",\n          \"UNITMEASUR\": \"\",\n          \"ISO_UNIT\": \"\",\n          \"CURRENCKEY\": \"\",\n          \"CURRENISO\": \"\",\n          \"CONDINCOMP\": \"\",\n          \"CONDCONFIG\": \"\",\n          \"CONDCHAMAN\": \"\",\n          \"COND_NO\": \"\",\n          \"TAX_CODE\": \"\",\n          \"VARCOND\": \"\",\n          \"ACCOUNTKEY\": \"\",\n          \"ACCOUNT_KE\": \"\",\n          \"WT_WITHCD\": \"\",\n          \"STRUCTCOND\": \"\",\n          \"FACTCONBAS\": \"0.0000000000000000E+00\",\n          \"CONDCOINHD\": \"00\"\n        },\n        {\n          \"ITM_NUMBER\": \"000010\",\n          \"COND_ST_NO\": \"896\",\n          \"COND_COUNT\": \"01\",\n          \"COND_TYPE\": \"ZBTR\",\n          \"COND_VALUE\": \"-100.000000000\",\n          \"CURRENCY\": \"\",\n          \"COND_UNIT\": \"\",\n          \"COND_P_UNT\": \"0\",\n          \"CURR_ISO\": \"\",\n          \"CD_UNT_ISO\": \"\",\n          \"REFOBJTYPE\": \"\",\n          \"REFOBJKEY\": \"\",\n          \"REFLOGSYS\": \"\",\n          \"APPLICATIO\": \"V\",\n          \"CONPRICDAT\": \"2020-12-14\",\n          \"CALCTYPCON\": \"A\",\n          \"CONBASEVAL\": \"128.700000000\",\n          \"CONEXCHRAT\": \"0.00000\",\n          \"NUMCONVERT\": \"0\",\n          \"DENOMINATO\": \"0\",\n          \"CONDTYPE\": \"\",\n          \"STAT_CON\": \"X\",\n          \"SCALETYPE\": \"\",\n          \"ACCRUALS\": \"\",\n          \"CONINVOLST\": \"\",\n          \"CONDORIGIN\": \"A\",\n          \"GROUPCOND\": \"\",\n          \"COND_UPDAT\": \"\",\n          \"ACCESS_SEQ\": \"10\",\n          \"CONDCOUNT\": \"01\",\n          \"ROUNDOFFDI\": \"0.000000000\",\n          \"CONDVALUE\": \"-128.700000000\",\n          \"CURRENCY_2\": \"BRL\",\n          \"CURR_ISO_2\": \"BRL\",\n          \"CONDCNTRL\": \"A\",\n          \"CONDISACTI\": \"\",\n          \"CONDCLASS\": \"A\",\n          \"FACTBASVAL\": \"0.0000000000000000E+00\",\n          \"SCALEBASIN\": \"\",\n          \"SCALBASVAL\": \"0.000000000\",\n          \"UNITMEASUR\": \"\",\n          \"ISO_UNIT\": \"\",\n          \"CURRENCKEY\": \"\",\n          \"CURRENISO\": \"\",\n          \"CONDINCOMP\": \"\",\n          \"CONDCONFIG\": \"\",\n          \"CONDCHAMAN\": \"\",\n          \"COND_NO\": \"0000716933\",\n          \"TAX_CODE\": \"\",\n          \"VARCOND\": \"\",\n          \"ACCOUNTKEY\": \"\",\n          \"ACCOUNT_KE\": \"\",\n          \"WT_WITHCD\": \"\",\n          \"STRUCTCOND\": \"\",\n          \"FACTCONBAS\": \"0.0000000000000000E+00\",\n          \"CONDCOINHD\": \"00\"\n        },\n        {\n          \"ITM_NUMBER\": \"000010\",\n          \"COND_ST_NO\": \"904\",\n          \"COND_COUNT\": \"01\",\n          \"COND_TYPE\": \"ZTOT\",\n          \"COND_VALUE\": \"172.920000000\",\n          \"CURRENCY\": \"BRL\",\n          \"COND_UNIT\": \"CS\",\n          \"COND_P_UNT\": \"1\",\n          \"CURR_ISO\": \"BRL\",\n          \"CD_UNT_ISO\": \"CS\",\n          \"REFOBJTYPE\": \"\",\n          \"REFOBJKEY\": \"\",\n          \"REFLOGSYS\": \"\",\n          \"APPLICATIO\": \"V\",\n          \"CONPRICDAT\": \"2020-12-14\",\n          \"CALCTYPCON\": \"C\",\n          \"CONBASEVAL\": \"1.000000000\",\n          \"CONEXCHRAT\": \"1.00000\",\n          \"NUMCONVERT\": \"1\",\n          \"DENOMINATO\": \"1\",\n          \"CONDTYPE\": \"\",\n          \"STAT_CON\": \"X\",\n          \"SCALETYPE\": \"\",\n          \"ACCRUALS\": \"\",\n          \"CONINVOLST\": \"\",\n          \"CONDORIGIN\": \"A\",\n          \"GROUPCOND\": \"\",\n          \"COND_UPDAT\": \"\",\n          \"ACCESS_SEQ\": \"00\",\n          \"CONDCOUNT\": \"00\",\n          \"ROUNDOFFDI\": \"0.000000000\",\n          \"CONDVALUE\": \"172.920000000\",\n          \"CURRENCY_2\": \"BRL\",\n          \"CURR_ISO_2\": \"BRL\",\n          \"CONDCNTRL\": \"A\",\n          \"CONDISACTI\": \"\",\n          \"CONDCLASS\": \"B\",\n          \"FACTBASVAL\": \"0.0000000000000000E+00\",\n          \"SCALEBASIN\": \"\",\n          \"SCALBASVAL\": \"0.000000000\",\n          \"UNITMEASUR\": \"\",\n          \"ISO_UNIT\": \"\",\n          \"CURRENCKEY\": \"\",\n          \"CURRENISO\": \"\",\n          \"CONDINCOMP\": \"\",\n          \"CONDCONFIG\": \"\",\n          \"CONDCHAMAN\": \"\",\n          \"COND_NO\": \"\",\n          \"TAX_CODE\": \"\",\n          \"VARCOND\": \"\",\n          \"ACCOUNTKEY\": \"\",\n          \"ACCOUNT_KE\": \"\",\n          \"WT_WITHCD\": \"\",\n          \"STRUCTCOND\": \"\",\n          \"FACTCONBAS\": \"0.0000000000000000E+00\",\n          \"CONDCOINHD\": \"00\"\n        },\n        {\n          \"ITM_NUMBER\": \"000010\",\n          \"COND_ST_NO\": \"977\",\n          \"COND_COUNT\": \"01\",\n          \"COND_TYPE\": \"ZVC2\",\n          \"COND_VALUE\": \"-100.000000000\",\n          \"CURRENCY\": \"\",\n          \"COND_UNIT\": \"\",\n          \"COND_P_UNT\": \"0\",\n          \"CURR_ISO\": \"\",\n          \"CD_UNT_ISO\": \"\",\n          \"REFOBJTYPE\": \"\",\n          \"REFOBJKEY\": \"\",\n          \"REFLOGSYS\": \"\",\n          \"APPLICATIO\": \"V\",\n          \"CONPRICDAT\": \"2020-12-14\",\n          \"CALCTYPCON\": \"A\",\n          \"CONBASEVAL\": \"0.000000000\",\n          \"CONEXCHRAT\": \"0.00000\",\n          \"NUMCONVERT\": \"0\",\n          \"DENOMINATO\": \"0\",\n          \"CONDTYPE\": \"\",\n          \"STAT_CON\": \"\",\n          \"SCALETYPE\": \"\",\n          \"ACCRUALS\": \"\",\n          \"CONINVOLST\": \"\",\n          \"CONDORIGIN\": \"A\",\n          \"GROUPCOND\": \"\",\n          \"COND_UPDAT\": \"\",\n          \"ACCESS_SEQ\": \"10\",\n          \"CONDCOUNT\": \"01\",\n          \"ROUNDOFFDI\": \"0.000000000\",\n          \"CONDVALUE\": \"0.000000000\",\n          \"CURRENCY_2\": \"BRL\",\n          \"CURR_ISO_2\": \"BRL\",\n          \"CONDCNTRL\": \"A\",\n          \"CONDISACTI\": \"\",\n          \"CONDCLASS\": \"E\",\n          \"FACTBASVAL\": \"0.0000000000000000E+00\",\n          \"SCALEBASIN\": \"\",\n          \"SCALBASVAL\": \"0.000000000\",\n          \"UNITMEASUR\": \"\",\n          \"ISO_UNIT\": \"\",\n          \"CURRENCKEY\": \"\",\n          \"CURRENISO\": \"\",\n          \"CONDINCOMP\": \"\",\n          \"CONDCONFIG\": \"\",\n          \"CONDCHAMAN\": \"\",\n          \"COND_NO\": \"0000716941\",\n          \"TAX_CODE\": \"\",\n          \"VARCOND\": \"\",\n          \"ACCOUNTKEY\": \"\",\n          \"ACCOUNT_KE\": \"\",\n          \"WT_WITHCD\": \"\",\n          \"STRUCTCOND\": \"\",\n          \"FACTCONBAS\": \"0.0000000000000000E+00\",\n          \"CONDCOINHD\": \"00\"\n        },\n        {\n          \"ITM_NUMBER\": \"000010\",\n          \"COND_ST_NO\": \"979\",\n          \"COND_COUNT\": \"01\",\n          \"COND_TYPE\": \"ZVC4\",\n          \"COND_VALUE\": \"-100.000000000\",\n          \"CURRENCY\": \"\",\n          \"COND_UNIT\": \"\",\n          \"COND_P_UNT\": \"0\",\n          \"CURR_ISO\": \"\",\n          \"CD_UNT_ISO\": \"\",\n          \"REFOBJTYPE\": \"\",\n          \"REFOBJKEY\": \"\",\n          \"REFLOGSYS\": \"\",\n          \"APPLICATIO\": \"V\",\n          \"CONPRICDAT\": \"2020-12-14\",\n          \"CALCTYPCON\": \"A\",\n          \"CONBASEVAL\": \"0.000000000\",\n          \"CONEXCHRAT\": \"0.00000\",\n          \"NUMCONVERT\": \"0\",\n          \"DENOMINATO\": \"0\",\n          \"CONDTYPE\": \"\",\n          \"STAT_CON\": \"\",\n          \"SCALETYPE\": \"\",\n          \"ACCRUALS\": \"\",\n          \"CONINVOLST\": \"\",\n          \"CONDORIGIN\": \"A\",\n          \"GROUPCOND\": \"\",\n          \"COND_UPDAT\": \"\",\n          \"ACCESS_SEQ\": \"10\",\n          \"CONDCOUNT\": \"01\",\n          \"ROUNDOFFDI\": \"0.000000000\",\n          \"CONDVALUE\": \"0.000000000\",\n          \"CURRENCY_2\": \"BRL\",\n          \"CURR_ISO_2\": \"BRL\",\n          \"CONDCNTRL\": \"A\",\n          \"CONDISACTI\": \"\",\n          \"CONDCLASS\": \"E\",\n          \"FACTBASVAL\": \"0.0000000000000000E+00\",\n          \"SCALEBASIN\": \"\",\n          \"SCALBASVAL\": \"0.000000000\",\n          \"UNITMEASUR\": \"\",\n          \"ISO_UNIT\": \"\",\n          \"CURRENCKEY\": \"\",\n          \"CURRENISO\": \"\",\n          \"CONDINCOMP\": \"\",\n          \"CONDCONFIG\": \"\",\n          \"CONDCHAMAN\": \"\",\n          \"COND_NO\": \"0000716945\",\n          \"TAX_CODE\": \"\",\n          \"VARCOND\": \"\",\n          \"ACCOUNTKEY\": \"\",\n          \"ACCOUNT_KE\": \"\",\n          \"WT_WITHCD\": \"\",\n          \"STRUCTCOND\": \"\",\n          \"FACTCONBAS\": \"0.0000000000000000E+00\",\n          \"CONDCOINHD\": \"00\"\n        }\n      ]\n    },\n    \"ETB_EXTENSION\": {\n      \"item\": [\n        \n      ]\n    },\n    \"ETB_INCOMPLETE_LOG\": {\n      \"item\": [\n        {\n          \"DOC_NUMBER\": \"\",\n          \"ITM_NUMBER\": \"000000\",\n          \"SCHED_LINE\": \"0000\",\n          \"PARTN_ROLE\": \"\",\n          \"TABLE_NAME\": \"VBKD\",\n          \"FIELD_NAME\": \"BSTDK\",\n          \"FIELD_TEXT\": \"Purchase order date\"\n        },\n        {\n          \"DOC_NUMBER\": \"\",\n          \"ITM_NUMBER\": \"000000\",\n          \"SCHED_LINE\": \"0000\",\n          \"PARTN_ROLE\": \"\",\n          \"TABLE_NAME\": \"VBKD\",\n          \"FIELD_NAME\": \"BSTKD\",\n          \"FIELD_TEXT\": \"PO number\"\n        }\n      ]\n    },\n    \"ETB_ITEMS\": {\n      \"item\": [\n        {\n          \"OPERATION\": \"\",\n          \"DOC_NUMBER\": \"\",\n          \"ITM_NUMBER\": \"000010\",\n          \"MATERIAL\": \"000000000030197119\",\n          \"MAT_ENTRD\": \"000000000030197119\",\n          \"PR_REF_MAT\": \"\",\n          \"BATCH\": \"\",\n          \"MATL_GROUP\": \"048\",\n          \"SHORT_TEXT\": \"KCP SCOTT SPRAY ANTISSEPTICO 300ML 6X1\",\n          \"ITEM_CATEG\": \"ZTBN\",\n          \"ITEM_TYPE\": \"\",\n          \"REL_FOR_DE\": \"\",\n          \"REL_FOR_BI\": \"H\",\n          \"HG_LV_ITEM\": \"000000\",\n          \"ALTERN_ITM\": \"000000\",\n          \"REA_FOR_RE\": \"\",\n          \"PROD_HIER\": \"28004002001001\",\n          \"OUT_AGR_TA\": \"0.000000000\",\n          \"TARGET_QTY\": \"0.000\",\n          \"TARGET_QU\": \"CS\",\n          \"T_UNIT_ISO\": \"CS\",\n          \"TARG_QTY_N\": \"1\",\n          \"TARG_QTY_D\": \"1\",\n          \"BASE_UOM\": \"CS\",\n          \"T_BAS_UNIT\": \"CS\",\n          \"SCALE_QUAN\": \"0.000\",\n          \"ROUND_DLV\": \"0.000\",\n          \"RECON_DATE\": \"0000-00-00\",\n          \"MAX_DEVIAT\": \"0.000\",\n          \"PO_ITM_NO\": \"\",\n          \"CUST_MAT22\": \"\",\n          \"MAX_DEV_PE\": \"0\",\n          \"MAX_DEV_DA\": \"0\",\n          \"REPAIR_PRO\": \"\",\n          \"DLVSCHEDUS\": \"\",\n          \"DLV_GROUP\": \"000\",\n          \"FIXED_QUAN\": \"\",\n          \"DELI_UNLIM\": \"\",\n          \"OVER_DLV_T\": \"0.0\",\n          \"UNDER_DLV\": \"0.0\",\n          \"BILL_BLOCK\": \"\",\n          \"REPLACE_PT\": \"\",\n          \"METH_BILL\": \"\",\n          \"DIVISION\": \"02\",\n          \"BUS_AREA\": \"\",\n          \"NET_VALUE\": \"118.320000000\",\n          \"CURRENCY\": \"BRL\",\n          \"CURREN_ISO\": \"BRL\",\n          \"MAX_PL_DLV\": \"1\",\n          \"PART_DLV\": \"B\",\n          \"BTCH_SPLIT\": \"\",\n          \"REQ_QTY\": \"1.000\",\n          \"CUM_REQ_DE\": \"1.000\",\n          \"CUM_CF_QTY\": \"0.000\",\n          \"CUM_CON_QU\": \"0.000\",\n          \"SALES_UNIT\": \"CS\",\n          \"ISOCODUNIT\": \"CS\",\n          \"SALES_QTY1\": \"1\",\n          \"SALES_QTY2\": \"1\",\n          \"GROSS_WEIG\": \"1.797\",\n          \"NET_WEIGHT\": \"1.572\",\n          \"UNIT_OF_WT\": \"KG\",\n          \"UNIT_WTISO\": \"KGM\",\n          \"VOLUME\": \"5.736\",\n          \"VOLUMEUNIT\": \"CDM\",\n          \"VOLUNITISO\": \"DMQ\",\n          \"CAU_VBELN\": \"\",\n          \"CAU_POSNR\": \"000000\",\n          \"REF_DOC\": \"\",\n          \"POSNR_VOR\": \"000000\",\n          \"OBJ_COPY\": \"\",\n          \"UPDAT_FLAG\": \"\",\n          \"END_RULE\": \"\",\n          \"DLV_PRIO\": \"02\",\n          \"PLANT\": \"7026\",\n          \"STGE_LOC\": \"\",\n          \"SHIP_POINT\": \"BR27\",\n          \"ROUTE\": \"BRK120\",\n          \"KEY_ST\": \"\",\n          \"DATE_ST\": \"0000-00-00\",\n          \"NBR_ST\": \"\",\n          \"STPOS_VBAP\": \"0\",\n          \"ORDER_PROB\": \"100\",\n          \"CREAT_DATE\": \"2020-12-14\",\n          \"CREATED_BY\": \"APISALES0001\",\n          \"REC_TIME\": \"15:28:08\",\n          \"TAX_CLASS1\": \"1\",\n          \"TAX_CLASS2\": \"\",\n          \"TAX_CLASS3\": \"\",\n          \"TAX_CLASS4\": \"\",\n          \"TAX_CLASS5\": \"\",\n          \"TAX_CLASS6\": \"\",\n          \"TAX_CLASS7\": \"\",\n          \"TAX_CLASS8\": \"\",\n          \"TAX_CLASS9\": \"\",\n          \"FIX_SP_DAY\": \"0.00\",\n          \"VAR_SP_DAY\": \"0.00\",\n          \"PREC_DOC\": \"\",\n          \"NET_PRICE\": \"118.320000000\",\n          \"COND_P_UNT\": \"1\",\n          \"COND_UNIT\": \"CS\",\n          \"CONISOUNIT\": \"CS\",\n          \"RETOURE\": \"\",\n          \"CASH_DISC\": \"\",\n          \"AVAILCHECK\": \"Z2\",\n          \"SUM_REQUIR\": \"A\",\n          \"MAT_PR_GRP\": \"\",\n          \"ACCT_ASSGT\": \"M1\",\n          \"REBATE_GRP\": \"\",\n          \"COMM_GROUP\": \"\",\n          \"EUR_ART_NR\": \"\",\n          \"PRICE_OK\": \"X\",\n          \"VAL_TYPE\": \"\",\n          \"SEP_VALUAT\": \"\",\n          \"BATCH_MGMT\": \"\",\n          \"IND_BTCH\": \"\",\n          \"MIN_DELY\": \"0.000\",\n          \"UPDATE_GRP\": \"000001\",\n          \"COST_DOC_C\": \"45.400000000\",\n          \"SUBTOT_PP1\": \"128.710000000\",\n          \"SUBTOT_PP2\": \"0.000000000\",\n          \"SUBTOT_PP3\": \"0.000000000\",\n          \"SUBTOT_PP4\": \"0.000000000\",\n          \"SUBTOT_PP5\": \"128.700000000\",\n          \"SUBTOT_PP6\": \"0.000000000\",\n          \"EXCH_RATE\": \"5.02614\",\n          \"CH_ON\": \"0000-00-00\",\n          \"EAN_UPC\": \"17891172001298\",\n          \"FIX_DATE\": \"\",\n          \"PROFIT_CTR\": \"P141200005\",\n          \"PRC_GROUP1\": \"\",\n          \"PRC_GROUP2\": \"\",\n          \"PRC_GROUP3\": \"\",\n          \"PRC_GROUP4\": \"\",\n          \"PRC_GROUP5\": \"\",\n          \"COMPON_QTY\": \"0.000\",\n          \"SUBSTREASO\": \"\",\n          \"SPEC_STOCK\": \"\",\n          \"ALLOC_INDI\": \"1\",\n          \"PROFIT_SEG\": \"0732969666\",\n          \"WBS_ELEM\": \"00000000\",\n          \"ORDERID\": \"\",\n          \"PLNG_MATL\": \"\",\n          \"PLNG_PLANT\": \"\",\n          \"BASE_UNIT\": \"\",\n          \"ISOBASUNIT\": \"\",\n          \"CONV_FACT\": \"0.0000000000000000E+00\",\n          \"ACCTASSCAT\": \"\",\n          \"CONSUMPT\": \"\",\n          \"BOMEXPLNO\": \"\",\n          \"OBJ_NR_IT\": \"\",\n          \"RES_ANAL\": \"\",\n          \"REQMTSTYP\": \"KSV\",\n          \"CREDPRICIT\": \"172.920000000\",\n          \"PARTRELID\": \"\",\n          \"ACTCREDID\": \"X\",\n          \"CR_EXCHRAT\": \"1.00000\",\n          \"CONFIG\": \"000000000000000000\",\n          \"CHCLASS_IN\": \"000000000000000000\",\n          \"STAT_PRICE\": \"\",\n          \"COND_UPDAT\": \"X\",\n          \"SERNO_PROF\": \"\",\n          \"NO_OF_SERI\": \"0\",\n          \"NOGRPOSTED\": \"\",\n          \"MAT_GRP_SM\": \"\",\n          \"MAN_PR_CH\": \"\",\n          \"DOC_CAT_SD\": \"\",\n          \"MATDETERID\": \"\",\n          \"ITUSAGEID\": \"\",\n          \"COSTESTNR\": \"000000000000\",\n          \"CSTG_VRNT\": \"\",\n          \"BOMITEMNR\": \"\",\n          \"STAT_VAL\": \"\",\n          \"STAT_DATE\": \"0000-00-00\",\n          \"BUS_TRANST\": \"\",\n          \"PREF_INDIC\": \"\",\n          \"NRCONDREC\": \"\",\n          \"INTCLASSNR\": \"0000000000\",\n          \"BATCH_EXIT\": \"000\",\n          \"BOM_CATEGO\": \"\",\n          \"BOM_IT_NR\": \"00000000\",\n          \"COUNTER\": \"00000000\",\n          \"INCONSCONF\": \"\",\n          \"OVERH_KEY\": \"\",\n          \"CSTG_SHEET\": \"\",\n          \"CSTG_VRNT1\": \"\",\n          \"PROD_ALLOC\": \"\",\n          \"PRICE_REF\": \"\",\n          \"MATPRICGRP\": \"\",\n          \"MATFRGTGRP\": \"\",\n          \"PLANDLVSCH\": \"\",\n          \"SEQUENCENO\": \"\",\n          \"CREDPRIC\": \"1.7291999999999999E+02\",\n          \"PAY_GUARAN\": \"\",\n          \"GURANTEED\": \"0.0000000000000000E+00\",\n          \"CFOP_CODE\": \"\",\n          \"TAXLAWICMS\": \"IC0\",\n          \"TAXLAWIPI\": \"IP0\",\n          \"SD_TAXCODE\": \"C4\",\n          \"VALCONTRNR\": \"\",\n          \"VALCONTRIT\": \"000000\",\n          \"ASSORT_MOD\": \"\",\n          \"VALSPECSTO\": \"\",\n          \"MATGRHIE1\": \"\",\n          \"MATGRHIE2\": \"\",\n          \"PROMOTION\": \"\",\n          \"SALES_DEAL\": \"\",\n          \"FLGLEADUNI\": \"\",\n          \"FREE_GOODS\": \"\",\n          \"VALID_OBJ\": \"\",\n          \"TAX_AMOUNT\": \"54.600000000\",\n          \"MRP_AREA\": \"7026\",\n          \"CUST_MAT35\": \"\",\n          \"CR_EXCHRAT_V\": \"0.00000\",\n          \"EXCHRATEST_V\": \"0.00000\",\n          \"ITM_TYPE_USAGE\": \"\",\n          \"CFOP_LONG\": \"6108AA\",\n          \"GROSS_VAL\": \"0.000000000\",\n          \"LOG_SYSTEM_OWN\": \"QL3400\",\n          \"TAXLAWISS\": \"\",\n          \"TAXLAWCOFINS\": \"C01\",\n          \"TAXLAWPIS\": \"P01\"\n        }\n      ]\n    },\n    \"ETB_RETURN\": {\n      \"item\": [\n        {\n          \"TYPE\": \"S\",\n          \"ID\": \"V4\",\n          \"NUMBER\": \"233\",\n          \"MESSAGE\": \"SALES_HEADER_IN has been processed successfully\",\n          \"LOG_NO\": \"\",\n          \"LOG_MSG_NO\": \"000000\",\n          \"MESSAGE_V1\": \"VBAKKOM\",\n          \"MESSAGE_V2\": \"14.12.2020\",\n          \"MESSAGE_V3\": \"15:28:08\",\n          \"MESSAGE_V4\": \"\",\n          \"PARAMETER\": \"SALES_HEADER_IN\",\n          \"ROW\": \"0\",\n          \"FIELD\": \"\",\n          \"SYSTEM\": \"QL3400\"\n        },\n        {\n          \"TYPE\": \"S\",\n          \"ID\": \"V4\",\n          \"NUMBER\": \"233\",\n          \"MESSAGE\": \"SALES_ITEM_IN has been processed successfully\",\n          \"LOG_NO\": \"\",\n          \"LOG_MSG_NO\": \"000000\",\n          \"MESSAGE_V1\": \"VBAPKOM\",\n          \"MESSAGE_V2\": \"000010\",\n          \"MESSAGE_V3\": \"\",\n          \"MESSAGE_V4\": \"\",\n          \"PARAMETER\": \"SALES_ITEM_IN\",\n          \"ROW\": \"1\",\n          \"FIELD\": \"\",\n          \"SYSTEM\": \"QL3400\"\n        },\n        {\n          \"TYPE\": \"W\",\n          \"ID\": \"V1\",\n          \"NUMBER\": \"555\",\n          \"MESSAGE\": \"The sales document is not yet complete: Edit data\",\n          \"LOG_NO\": \"\",\n          \"LOG_MSG_NO\": \"000000\",\n          \"MESSAGE_V1\": \"VBAPKOM\",\n          \"MESSAGE_V2\": \"000010\",\n          \"MESSAGE_V3\": \"\",\n          \"MESSAGE_V4\": \"\",\n          \"PARAMETER\": \"VBUVKOM\",\n          \"ROW\": \"0\",\n          \"FIELD\": \"\",\n          \"SYSTEM\": \"QL3400\"\n        }\n      ]\n    },\n    \"EWA_SALES_HEADER_OUT\": {\n      \"OPERATION\": \"\",\n      \"DOC_NUMBER\": \"\",\n      \"REC_DATE\": \"2020-12-14\",\n      \"REC_TIME\": \"15:28:08\",\n      \"CREATED_BY\": \"APISALES0001\",\n      \"QT_VALID_F\": \"0000-00-00\",\n      \"QT_VALID_T\": \"0000-00-00\",\n      \"DOC_DATE\": \"2020-12-14\",\n      \"SD_DOC_CAT\": \"C\",\n      \"TRAN_GROUP\": \"0\",\n      \"DOC_TYPE\": \"ZSMP\",\n      \"ORD_REASON\": \"\",\n      \"WAR_DATE\": \"0000-00-00\",\n      \"SD_COL_NUM\": \"\",\n      \"DLV_BLOCK\": \"\",\n      \"BILL_BLOCK\": \"\",\n      \"NET_VAL_HD\": \"118.320000000\",\n      \"CURRENCY\": \"BRL\",\n      \"CURREN_ISO\": \"BRL\",\n      \"SALES_ORG\": \"7024\",\n      \"DISTR_CHAN\": \"50\",\n      \"DIVISION\": \"02\",\n      \"SALES_GRP\": \"BMF\",\n      \"SALES_OFF\": \"BR70\",\n      \"BUS_AREA\": \"\",\n      \"CT_AREA\": \"\",\n      \"CT_VALID_F\": \"0000-00-00\",\n      \"CT_VALID_T\": \"0000-00-00\",\n      \"CONDITIONS\": \"\",\n      \"REQ_DATE_H\": \"2020-12-22\",\n      \"DATE_TYPE\": \"1\",\n      \"COMPL_DLV\": \"X\",\n      \"DOC_CLASS\": \"\",\n      \"DOC_INDIC\": \"\",\n      \"SD_PRIC_PR\": \"ZBRABV\",\n      \"SHIP_COND\": \"10\",\n      \"ORDBILLTYP\": \"ZF2B\",\n      \"ORD_PROBAB\": \"100\",\n      \"SEAR_PRPR\": \"\",\n      \"PURCH_NO\": \"\",\n      \"PO_METHOD\": \"\",\n      \"PURCH_DATE\": \"0000-00-00\",\n      \"PO_SUPPLEM\": \"\",\n      \"REF_1\": \"\",\n      \"ORDERER_NA\": \"\",\n      \"TELEPHONE\": \"(45) 2102-7500\",\n      \"DUN_COUNT\": \"0\",\n      \"DUN_DATE\": \"0000-00-00\",\n      \"SOLD_TO\": \"0042026019\",\n      \"COSTCENTER\": \"\",\n      \"UPDATE_GRP\": \"\",\n      \"STAT_CURR\": \"USD\",\n      \"ISOSTATCUR\": \"USD\",\n      \"CH_ON\": \"0000-00-00\",\n      \"CUST_GRP1\": \"10\",\n      \"CUST_GRP2\": \"101\",\n      \"CUST_GRP3\": \"\",\n      \"CUST_GRP4\": \"02\",\n      \"CUST_GRP5\": \"B3H\",\n      \"AGREE_COND\": \"\",\n      \"CO_AREA\": \"LA01\",\n      \"WBS_ELEM\": \"00000000\",\n      \"EXCHG_RATE\": \"\",\n      \"C_CTR_AREA\": \"BR02\",\n      \"CRED_ACCNT\": \"0042026019\",\n      \"CRED_GROUP\": \"\",\n      \"REPR_GROUP\": \"\",\n      \"RISK_CATEG\": \"C\",\n      \"CURR_CRED\": \"BRL\",\n      \"ISOCURRCRE\": \"BRL\",\n      \"REL_DAT_DD\": \"0000-00-00\",\n      \"NEXT_CHDAT\": \"0000-00-00\",\n      \"NEXT_DATE\": \"2020-12-14\",\n      \"REL_CREDIT\": \"0.000000000\",\n      \"HI_TYPE_PR\": \"A\",\n      \"DLVSCHEDUS\": \"\",\n      \"PLAN_DLV\": \"\",\n      \"REF_DOC\": \"\",\n      \"OB_JNR_HD\": \"\",\n      \"COMP_CODE\": \"0545\",\n      \"ALT_TAX_CL\": \"\",\n      \"TAX_CLASS2\": \"\",\n      \"TAX_CLASS3\": \"\",\n      \"TAX_CLASS4\": \"\",\n      \"TAX_CLASS5\": \"\",\n      \"TAX_CLASS6\": \"\",\n      \"TAX_CLASS7\": \"\",\n      \"TAX_CLASS8\": \"\",\n      \"TAX_CLASS9\": \"\",\n      \"REF_DOC_L\": \"\",\n      \"ASS_NUMBER\": \"\",\n      \"DOC_CAT_SD\": \"\",\n      \"KALSM_CH\": \"\",\n      \"ACC_PERIOD\": \"00\",\n      \"ORDERID\": \"\",\n      \"NOTIF_NO\": \"\",\n      \"MASTER_CON\": \"\",\n      \"REF_PROC\": \"\",\n      \"CHECK_PART\": \"\",\n      \"PICK_UP_DA\": \"0000-00-00\",\n      \"PICK_UP_T1\": \"00:00:00\",\n      \"PICK_UP_T2\": \"00:00:00\",\n      \"NUM_PAY_CA\": \"\",\n      \"LINE_TIME\": \"00:00:00\",\n      \"TAX_DEST_CT\": \"\",\n      \"ISOTAXDEST\": \"\",\n      \"TAX_DEPART\": \"\",\n      \"ISOTAXDEPA\": \"\",\n      \"EU_TRIANG\": \"\",\n      \"MAST_CONTR\": \"\",\n      \"CML_QTY_DA\": \"0000-00-00\",\n      \"MS_DATE\": \"0000-00-00\",\n      \"VERSION\": \"\",\n      \"REF_DOC_L_LONG\": \"\",\n      \"CRM_GUID\": \"\"\n    },\n    \"EWA_SALES_HEADER_STATUS\": {\n      \"OPERATION\": \"\",\n      \"SD_DOC\": \"\",\n      \"REFDOCHDST\": \"\",\n      \"TOTREFSTAT\": \"\",\n      \"CONFIRSTAT\": \"A\",\n      \"DELIV_STAT\": \"A\",\n      \"DLV_STAT_H\": \"A\",\n      \"TOTGOODSMV\": \"\",\n      \"BILLSTATUS\": \"\",\n      \"BILLINGSTA\": \"\",\n      \"ACCOUNTSTA\": \"\",\n      \"OVERALLREJ\": \"A\",\n      \"PRC_STAT_H\": \"B\",\n      \"OVERALLPIC\": \"\",\n      \"OVERALL_WM\": \"\",\n      \"TOTINCOMPL\": \"C\",\n      \"TOTINCOMIT\": \"C\",\n      \"TOTINCOMBI\": \"C\",\n      \"GENINCOMHD\": \"A\",\n      \"HDIMCOMDEL\": \"C\",\n      \"HDINCOMBIL\": \"C\",\n      \"DOCIMCOMPR\": \"C\",\n      \"SD_DOC_CAT\": \"C\",\n      \"SDDOCOBJ\": \"A\",\n      \"CH_ON\": \"0000-00-00\",\n      \"BILTOTSTAT\": \"\",\n      \"INVOICSTAT\": \"\",\n      \"CUSTRESHD1\": \"\",\n      \"CUSTRESHD2\": \"\",\n      \"CUSTRESHD3\": \"\",\n      \"CUSTRESHD4\": \"\",\n      \"CUSTRESHD5\": \"\",\n      \"CUSTRESIT1\": \"\",\n      \"CUSTRESIT2\": \"\",\n      \"CUSTRESIT3\": \"\",\n      \"CUSTRESIT4\": \"\",\n      \"CUSTRESIT5\": \"\",\n      \"TOTSTATIT\": \"\",\n      \"STATSTACLC\": \"\",\n      \"STATDYNCLC\": \"B\",\n      \"STATCREDCH\": \"\",\n      \"STATCRECH1\": \"\",\n      \"STATCRECH2\": \"\",\n      \"STATCRECH3\": \"\",\n      \"STATCRECH4\": \"\",\n      \"STATCRECH5\": \"\",\n      \"STATCRECH6\": \"\",\n      \"STATCRECH7\": \"\",\n      \"STATCRECH8\": \"\",\n      \"STATCRECH9\": \"\",\n      \"STATCRECHA\": \"\",\n      \"STATCRECHB\": \"B\",\n      \"STATCRECHC\": \"\",\n      \"TOTSTATCCH\": \"B\",\n      \"TRNSPLANST\": \"\",\n      \"QUITTSTAT\": \"\",\n      \"CONFIRMSTA\": \"\",\n      \"SAPRELEASE\": \"740\",\n      \"TOTINCOMI\": \"\",\n      \"TOTINCOMI1\": \"\",\n      \"TOTINCOMI2\": \"\",\n      \"HDINCOMPL\": \"\",\n      \"HDINCOMPL1\": \"\",\n      \"HDINCOMPL2\": \"\",\n      \"HDINCOMPL3\": \"\",\n      \"CREDCHECK\": \"\",\n      \"DELAYSTAT\": \"\",\n      \"SHIPPUNIT\": \"\",\n      \"DISTRISTAT\": \"\",\n      \"REVDETSTAT\": \"\",\n      \"INDIDOCACH\": \"\",\n      \"TOBILBLOST\": \"\",\n      \"TODELBLOST\": \"\",\n      \"TOBLOCKSTA\": \"C\",\n      \"LEBHEADSTA\": \"\",\n      \"FMSTATUS\": \"\"\n    },\n    \"EW_SALESDOCUMENT\": \"\",\n    \"ETB_SCALES\": {\n      \"item\": [\n        \n      ]\n    },\n    \"ETB_BUSINESS_EX\": {\n      \"item\": [\n        \n      ]\n    }\n  }\n}"}],"start":1607959699221,"stop":1607959699221}],"attachments":[],"parameters":[{"name":"sheetName","value":"SPARTA_API"},{"name":"domain","value":"https://kcc-oc-saledocuments-api-qa.cloudhub.io"},{"name":"requestMethod","value":"POST"},{"name":"parameterType","value":"JSON"},{"name":"header","value":"{client_secret=79d902E6DC5e447a845737AC15Dcc453, client_id=7fdecc3621a24de7bd1ae68085662fb2, Content-Type=application/json}"},{"name":"path","value":"/api/createSalesOrder"},{"name":"params","value":"{}"},{"name":"body","value":"{Z_YYKC_SALES_ORDER_CREATE={ITB_ITEMS={item=[{TARGET_QTY=1, ITM_NUMBER=000010, MATERIAL=000000000030197119}]}, IW_APPNAME=SFDC_KCP_DIGTRANSF, ITB_PARTNER={item=[{PARTN_ROLE=AG, PARTN_NUMB=0042026019, ITM_NUMBER=000000}, {PARTN_ROLE=WE, PARTN_NUMB=0042026019, ITM_NUMBER=000000}]}, IW_TESTRUN=X, IWA_HEADER={DOC_TYPE=ZSMP, SALES_ORG=7024, DIVISION=02, DISTR_CHAN=50}}, region=1}"},{"name":"expectedStatus","value":"200"},{"name":"paramsQuery","value":"{}"}],"start":1607959687829,"stop":1607959699221},{"name":"Verify API Good Request for Google_TestAPI1","status":"passed","stage":"finished","steps":[{"name":"Response Status is HTTP/1.1 200 OK\n Response Body {\"id\":4,\"token\":\"QpwL5tke4Pnpja7X4\"}","status":"passed","stage":"finished","steps":[],"attachments":[],"parameters":[{"name":"responseStatus","value":"HTTP/1.1 200 OK"},{"name":"responseBody","value":"{\"id\":4,\"token\":\"QpwL5tke4Pnpja7X4\"}"}],"start":1607959699922,"stop":1607959699922}],"attachments":[],"parameters":[{"name":"sheetName","value":"Google_TestAPI1"},{"name":"domain","value":"https://reqres.in/"},{"name":"requestMethod","value":"POST"},{"name":"parameterType","value":"JSON"},{"name":"header","value":"{Content-Type=application/json}"},{"name":"path","value":"/api/register"},{"name":"params","value":"{}"},{"name":"body","value":"{password=cityslicka, email=eve.holt@reqres.in}"},{"name":"expectedStatus","value":"200"},{"name":"paramsQuery","value":"{}"}],"start":1607959699225,"stop":1607959699922},{"name":"Generating a Alpha string Sequence, the lenght of String is a Random length between 1 and 5","status":"passed","stage":"finished","steps":[{"name":"Generating a single Random Number between 1 and 5","status":"passed","stage":"finished","steps":[],"attachments":[],"parameters":[{"name":"boundStart","value":"1"},{"name":"boundEnd","value":"5"}],"start":1607959699926,"stop":1607959699926},{"name":"Generating a Alphabetic string Sequence of lenght 4","status":"passed","stage":"finished","steps":[],"attachments":[],"parameters":[{"name":"randomStrLen","value":"4"}],"start":1607959699928,"stop":1607959699928}],"attachments":[{"name":"SingleNumber_BetBounds","source":"c1ba2973-c101-497f-83a0-7f33ff1bf9b9-attachment"},{"name":"String_Sequence","source":"c234881f-16ad-4552-8b86-40f4df54f6c9-attachment"}],"parameters":[{"name":"boundStart","value":"1"},{"name":"boundEnd","value":"5"}],"start":1607959699926,"stop":1607959699929},{"name":"Verify API Good Request for Google_TestAPI4","status":"passed","stage":"finished","steps":[{"name":"Response Status is HTTP/1.1 200 OK\n Response Body {\"id\":4,\"token\":\"QpwL5tke4Pnpja7X4\"}","status":"passed","stage":"finished","steps":[],"attachments":[],"parameters":[{"name":"responseStatus","value":"HTTP/1.1 200 OK"},{"name":"responseBody","value":"{\"id\":4,\"token\":\"QpwL5tke4Pnpja7X4\"}"}],"start":1607959700607,"stop":1607959700607}],"attachments":[],"parameters":[{"name":"sheetName","value":"Google_TestAPI4"},{"name":"domain","value":"https://reqres.in/"},{"name":"requestMethod","value":"POST"},{"name":"parameterType","value":"NormalParameter"},{"name":"header","value":"{Content-Type=application/json}"},{"name":"path","value":"/api/register"},{"name":"params","value":"{}"},{"name":"body","value":"{email=eve.holt@reqres.in, password=mBzl}"},{"name":"expectedStatus","value":"200"},{"name":"paramsQuery","value":"{}"}],"start":1607959699930,"stop":1607959700607},{"name":"Generating a Alphanumeric string Sequence, the lenght of String is a Random length between 1 and 5","status":"passed","stage":"finished","steps":[{"name":"Generating a single Random Number between 1 and 5","status":"passed","stage":"finished","steps":[],"attachments":[],"parameters":[{"name":"boundStart","value":"1"},{"name":"boundEnd","value":"5"}],"start":1607959700611,"stop":1607959700611},{"name":"Generating a Alphanumeric string Sequence of lenght 4","status":"passed","stage":"finished","steps":[],"attachments":[],"parameters":[{"name":"randomStrLen","value":"4"}],"start":1607959700612,"stop":1607959700612}],"attachments":[{"name":"SingleNumber_BetBounds","source":"b64173c1-6cdc-46bc-90ea-56942c75a515-attachment"},{"name":"AlphaNumericString_Sequence","source":"9a5ab080-e478-4082-9273-fff24dea53e9-attachment"}],"parameters":[{"name":"boundStart","value":"1"},{"name":"boundEnd","value":"5"}],"start":1607959700610,"stop":1607959700613},{"name":"Verify API Good Request for Google_TestAPI5","status":"passed","stage":"finished","steps":[{"name":"Response Status is HTTP/1.1 200 OK\n Response Body {\"id\":4,\"token\":\"QpwL5tke4Pnpja7X4\"}","status":"passed","stage":"finished","steps":[],"attachments":[],"parameters":[{"name":"responseStatus","value":"HTTP/1.1 200 OK"},{"name":"responseBody","value":"{\"id\":4,\"token\":\"QpwL5tke4Pnpja7X4\"}"}],"start":1607959701378,"stop":1607959701378}],"attachments":[],"parameters":[{"name":"sheetName","value":"Google_TestAPI5"},{"name":"domain","value":"https://reqres.in/"},{"name":"requestMethod","value":"POST"},{"name":"parameterType","value":"NormalParameter"},{"name":"header","value":"{Content-Type=application/json}"},{"name":"path","value":"/api/register"},{"name":"params","value":"{}"},{"name":"body","value":"{email=eve.holt@reqres.in, password=G4I7}"},{"name":"expectedStatus","value":"200"},{"name":"paramsQuery","value":"{}"}],"start":1607959700614,"stop":1607959701378}],"attachments":[{"name":"NumberSequence_BetBounds","source":"439896b7-592e-44b6-b5d8-f9275fda036c-attachment"},{"name":"AlphaString_Sequence_BetBounds","source":"171b8816-80b2-479f-86bf-30e1cb9e0329-attachment"},{"name":"AlphaNumericString_Sequence_BetBounds","source":"c3e747c8-0a67-47d5-90d1-ace56e39443a-attachment"}],"parameters":[],"start":1607959680267,"stop":1607959701378,"uuid":"537dfef8-dded-43ef-aefe-eee899ca7761","historyId":"d02bb21bc76744dbe173b65e21d6e1ed","fullName":"Hackathon_Test.APITest.testGoodRequest","labels":[{"name":"package","value":"Hackathon_Test.APITest"},{"name":"testClass","value":"Hackathon_Test.APITest"},{"name":"testMethod","value":"testGoodRequest"},{"name":"parentSuite","value":"Suite"},{"name":"suite","value":"Test"},{"name":"subSuite","value":"Hackathon_Test.APITest"},{"name":"host","value":"kc-spartans"},{"name":"thread","value":"6352@kc-spartans.TestNG-test=Test-2(10)"},{"name":"framework","value":"testng"},{"name":"language","value":"java"},{"name":"epic","value":"Ep0001"},{"name":"feature","value":"Feature1"},{"name":"story","value":"UserStory1"},{"name":"severity","value":"normal"}],"links":[]}